package com.google.android.gms.internal;

import java.io.OutputStream;

final class zzacw implements Runnable {
  zzacw(zzacv paramzzacv, OutputStream paramOutputStream, byte[] paramArrayOfbyte) {}
  
  public final void run() {
    // Byte code:
    //   0: new java/io/DataOutputStream
    //   3: dup
    //   4: aload_0
    //   5: getfield zzcus : Ljava/io/OutputStream;
    //   8: invokespecial <init> : (Ljava/io/OutputStream;)V
    //   11: astore_2
    //   12: aload_2
    //   13: astore_1
    //   14: aload_2
    //   15: aload_0
    //   16: getfield zzcut : [B
    //   19: arraylength
    //   20: invokevirtual writeInt : (I)V
    //   23: aload_2
    //   24: astore_1
    //   25: aload_2
    //   26: aload_0
    //   27: getfield zzcut : [B
    //   30: invokevirtual write : ([B)V
    //   33: aload_2
    //   34: invokestatic closeQuietly : (Ljava/io/Closeable;)V
    //   37: return
    //   38: astore_3
    //   39: goto -> 51
    //   42: astore_2
    //   43: aconst_null
    //   44: astore_1
    //   45: goto -> 88
    //   48: astore_3
    //   49: aconst_null
    //   50: astore_2
    //   51: aload_2
    //   52: astore_1
    //   53: ldc 'Error transporting the ad response'
    //   55: aload_3
    //   56: invokestatic zzb : (Ljava/lang/String;Ljava/lang/Throwable;)V
    //   59: aload_2
    //   60: astore_1
    //   61: invokestatic zzep : ()Lcom/google/android/gms/internal/zzahi;
    //   64: aload_3
    //   65: ldc 'LargeParcelTeleporter.pipeData.1'
    //   67: invokevirtual zza : (Ljava/lang/Throwable;Ljava/lang/String;)V
    //   70: aload_2
    //   71: ifnonnull -> 82
    //   74: aload_0
    //   75: getfield zzcus : Ljava/io/OutputStream;
    //   78: invokestatic closeQuietly : (Ljava/io/Closeable;)V
    //   81: return
    //   82: aload_2
    //   83: invokestatic closeQuietly : (Ljava/io/Closeable;)V
    //   86: return
    //   87: astore_2
    //   88: aload_1
    //   89: astore_3
    //   90: aload_1
    //   91: ifnonnull -> 99
    //   94: aload_0
    //   95: getfield zzcus : Ljava/io/OutputStream;
    //   98: astore_3
    //   99: aload_3
    //   100: invokestatic closeQuietly : (Ljava/io/Closeable;)V
    //   103: aload_2
    //   104: athrow
    // Exception table:
    //   from	to	target	type
    //   0	12	48	java/io/IOException
    //   0	12	42	finally
    //   14	23	38	java/io/IOException
    //   14	23	87	finally
    //   25	33	38	java/io/IOException
    //   25	33	87	finally
    //   53	59	87	finally
    //   61	70	87	finally
  }
}


/* Location:              /home/egaebel/Programs/sony-headphones-hack/base-dex2jar.jar!/com/google/android/gms/internal/zzacw.class
 * Java compiler version: 6 (50.0)
 * JD-Core Version:       1.1.3
 */