package com.google.android.gms.internal;

import com.google.android.gms.common.internal.Hide;
import java.util.Arrays;
import java.util.List;
import java.util.Map;

@zzabh
@Hide
public final class zzadx {
  private int mOrientation = -1;
  
  private zzacl zzaoq;
  
  private String zzbxx;
  
  private boolean zzciv = false;
  
  private final zzacf zzcjk;
  
  private List<String> zzcpa;
  
  private String zzcwq;
  
  private String zzcwr;
  
  private List<String> zzcws;
  
  private String zzcwt;
  
  private String zzcwu;
  
  private String zzcwv;
  
  private List<String> zzcww;
  
  private long zzcwx = -1L;
  
  private boolean zzcwy = false;
  
  private final long zzcwz = -1L;
  
  private long zzcxa = -1L;
  
  private boolean zzcxb = false;
  
  private boolean zzcxc = false;
  
  private boolean zzcxd = false;
  
  private boolean zzcxe = true;
  
  private boolean zzcxf = true;
  
  private String zzcxg = "";
  
  private boolean zzcxh = false;
  
  private zzagd zzcxi;
  
  private List<String> zzcxj;
  
  private List<String> zzcxk;
  
  private boolean zzcxl = false;
  
  private boolean zzcxm = false;
  
  private String zzcxn;
  
  private List<String> zzcxo;
  
  private boolean zzcxp;
  
  private String zzcxq;
  
  private zzagn zzcxr;
  
  private boolean zzcxs;
  
  private boolean zzcxt;
  
  public zzadx(zzacf paramzzacf, String paramString) {
    this.zzcwr = paramString;
    this.zzcjk = paramzzacf;
  }
  
  private static String zza(Map<String, List<String>> paramMap, String paramString) {
    List<String> list = paramMap.get(paramString);
    return (list != null && !list.isEmpty()) ? list.get(0) : null;
  }
  
  private static long zzb(Map<String, List<String>> paramMap, String paramString) {
    List<String> list = paramMap.get(paramString);
    if (list != null && !list.isEmpty()) {
      String str = list.get(0);
      try {
        float f = Float.parseFloat(str);
        return (long)(f * 1000.0F);
      } catch (NumberFormatException numberFormatException) {
        StringBuilder stringBuilder = new StringBuilder(String.valueOf(paramString).length() + 36 + String.valueOf(str).length());
        stringBuilder.append("Could not parse float from ");
        stringBuilder.append(paramString);
        stringBuilder.append(" header: ");
        stringBuilder.append(str);
        zzahw.zzcz(stringBuilder.toString());
      } 
    } 
    return -1L;
  }
  
  private static List<String> zzc(Map<String, List<String>> paramMap, String paramString) {
    List<String> list = paramMap.get(paramString);
    if (list != null && !list.isEmpty()) {
      String str = list.get(0);
      if (str != null)
        return Arrays.asList(str.trim().split("\\s+")); 
    } 
    return null;
  }
  
  private static boolean zzd(Map<String, List<String>> paramMap, String paramString) {
    List<String> list = paramMap.get(paramString);
    return (list != null) ? (list.isEmpty() ? false : Boolean.valueOf(list.get(0)).booleanValue()) : false;
  }
  
  public final zzacj zza(long paramLong, boolean paramBoolean) {
    boolean bool;
    zzacf zzacf1 = this.zzcjk;
    String str1 = this.zzcwr;
    String str2 = this.zzbxx;
    List<String> list1 = this.zzcws;
    List<String> list2 = this.zzcww;
    long l1 = this.zzcwx;
    boolean bool1 = this.zzcwy;
    List<String> list3 = this.zzcpa;
    long l2 = this.zzcxa;
    int i = this.mOrientation;
    String str3 = this.zzcwq;
    String str4 = this.zzcwu;
    String str5 = this.zzcwv;
    boolean bool2 = this.zzcxb;
    boolean bool3 = this.zzcxc;
    boolean bool4 = this.zzcxd;
    boolean bool5 = this.zzcxe;
    String str6 = this.zzcxg;
    boolean bool6 = this.zzcxh;
    boolean bool7 = this.zzciv;
    zzagd zzagd1 = this.zzcxi;
    List<String> list4 = this.zzcxj;
    List<String> list5 = this.zzcxk;
    boolean bool8 = this.zzcxl;
    zzacl zzacl1 = this.zzaoq;
    boolean bool9 = this.zzcxm;
    String str7 = this.zzcxn;
    List<String> list6 = this.zzcxo;
    boolean bool10 = this.zzcxp;
    String str8 = this.zzcxq;
    zzagn zzagn1 = this.zzcxr;
    String str9 = this.zzcwt;
    boolean bool11 = this.zzcxf;
    boolean bool12 = this.zzcxs;
    boolean bool13 = this.zzcxt;
    if (paramBoolean) {
      bool = true;
    } else {
      bool = true;
    } 
    return new zzacj(zzacf1, str1, str2, list1, list2, l1, bool1, -1L, list3, l2, i, str3, paramLong, str4, str5, bool2, bool3, bool4, bool5, false, str6, bool6, bool7, zzagd1, list4, list5, bool8, zzacl1, bool9, str7, list6, bool10, str8, zzagn1, str9, bool11, bool12, bool13, bool);
  }
  
  public final void zza(String paramString1, Map<String, List<String>> paramMap, String paramString2) {
    this.zzbxx = paramString2;
    zzo(paramMap);
  }
  
  public final void zzo(Map<String, List<String>> paramMap) {
    // Byte code:
    //   0: aload_0
    //   1: aload_1
    //   2: ldc 'X-Afma-Ad-Size'
    //   4: invokestatic zza : (Ljava/util/Map;Ljava/lang/String;)Ljava/lang/String;
    //   7: putfield zzcwq : Ljava/lang/String;
    //   10: aload_0
    //   11: aload_1
    //   12: ldc 'X-Afma-Ad-Slot-Size'
    //   14: invokestatic zza : (Ljava/util/Map;Ljava/lang/String;)Ljava/lang/String;
    //   17: putfield zzcxq : Ljava/lang/String;
    //   20: aload_1
    //   21: ldc 'X-Afma-Click-Tracking-Urls'
    //   23: invokestatic zzc : (Ljava/util/Map;Ljava/lang/String;)Ljava/util/List;
    //   26: astore #6
    //   28: aload #6
    //   30: ifnull -> 39
    //   33: aload_0
    //   34: aload #6
    //   36: putfield zzcws : Ljava/util/List;
    //   39: aload_0
    //   40: aload_1
    //   41: ldc 'X-Afma-Debug-Signals'
    //   43: invokestatic zza : (Ljava/util/Map;Ljava/lang/String;)Ljava/lang/String;
    //   46: putfield zzcwt : Ljava/lang/String;
    //   49: aload_1
    //   50: ldc 'X-Afma-Debug-Dialog'
    //   52: invokeinterface get : (Ljava/lang/Object;)Ljava/lang/Object;
    //   57: checkcast java/util/List
    //   60: astore #6
    //   62: aload #6
    //   64: ifnull -> 92
    //   67: aload #6
    //   69: invokeinterface isEmpty : ()Z
    //   74: ifne -> 92
    //   77: aload_0
    //   78: aload #6
    //   80: iconst_0
    //   81: invokeinterface get : (I)Ljava/lang/Object;
    //   86: checkcast java/lang/String
    //   89: putfield zzcwu : Ljava/lang/String;
    //   92: aload_1
    //   93: ldc_w 'X-Afma-Tracking-Urls'
    //   96: invokestatic zzc : (Ljava/util/Map;Ljava/lang/String;)Ljava/util/List;
    //   99: astore #6
    //   101: aload #6
    //   103: ifnull -> 112
    //   106: aload_0
    //   107: aload #6
    //   109: putfield zzcww : Ljava/util/List;
    //   112: aload_1
    //   113: ldc_w 'X-Afma-Interstitial-Timeout'
    //   116: invokestatic zzb : (Ljava/util/Map;Ljava/lang/String;)J
    //   119: lstore_3
    //   120: lload_3
    //   121: ldc2_w -1
    //   124: lcmp
    //   125: ifeq -> 133
    //   128: aload_0
    //   129: lload_3
    //   130: putfield zzcwx : J
    //   133: aload_0
    //   134: aload_0
    //   135: getfield zzcwy : Z
    //   138: aload_1
    //   139: ldc_w 'X-Afma-Mediation'
    //   142: invokestatic zzd : (Ljava/util/Map;Ljava/lang/String;)Z
    //   145: ior
    //   146: putfield zzcwy : Z
    //   149: aload_1
    //   150: ldc_w 'X-Afma-Manual-Tracking-Urls'
    //   153: invokestatic zzc : (Ljava/util/Map;Ljava/lang/String;)Ljava/util/List;
    //   156: astore #6
    //   158: aload #6
    //   160: ifnull -> 169
    //   163: aload_0
    //   164: aload #6
    //   166: putfield zzcpa : Ljava/util/List;
    //   169: aload_1
    //   170: ldc_w 'X-Afma-Refresh-Rate'
    //   173: invokestatic zzb : (Ljava/util/Map;Ljava/lang/String;)J
    //   176: lstore_3
    //   177: lload_3
    //   178: ldc2_w -1
    //   181: lcmp
    //   182: ifeq -> 190
    //   185: aload_0
    //   186: lload_3
    //   187: putfield zzcxa : J
    //   190: aload_1
    //   191: ldc_w 'X-Afma-Orientation'
    //   194: invokeinterface get : (Ljava/lang/Object;)Ljava/lang/Object;
    //   199: checkcast java/util/List
    //   202: astore #6
    //   204: aload #6
    //   206: ifnull -> 279
    //   209: aload #6
    //   211: invokeinterface isEmpty : ()Z
    //   216: ifne -> 279
    //   219: aload #6
    //   221: iconst_0
    //   222: invokeinterface get : (I)Ljava/lang/Object;
    //   227: checkcast java/lang/String
    //   230: astore #6
    //   232: ldc_w 'portrait'
    //   235: aload #6
    //   237: invokevirtual equalsIgnoreCase : (Ljava/lang/String;)Z
    //   240: ifeq -> 258
    //   243: invokestatic zzen : ()Lcom/google/android/gms/internal/zzaip;
    //   246: invokevirtual zzrh : ()I
    //   249: istore_2
    //   250: aload_0
    //   251: iload_2
    //   252: putfield mOrientation : I
    //   255: goto -> 279
    //   258: ldc_w 'landscape'
    //   261: aload #6
    //   263: invokevirtual equalsIgnoreCase : (Ljava/lang/String;)Z
    //   266: ifeq -> 279
    //   269: invokestatic zzen : ()Lcom/google/android/gms/internal/zzaip;
    //   272: invokevirtual zzrg : ()I
    //   275: istore_2
    //   276: goto -> 250
    //   279: aload_0
    //   280: aload_1
    //   281: ldc_w 'X-Afma-ActiveView'
    //   284: invokestatic zza : (Ljava/util/Map;Ljava/lang/String;)Ljava/lang/String;
    //   287: putfield zzcwv : Ljava/lang/String;
    //   290: aload_1
    //   291: ldc_w 'X-Afma-Use-HTTPS'
    //   294: invokeinterface get : (Ljava/lang/Object;)Ljava/lang/Object;
    //   299: checkcast java/util/List
    //   302: astore #6
    //   304: aload #6
    //   306: ifnull -> 340
    //   309: aload #6
    //   311: invokeinterface isEmpty : ()Z
    //   316: ifne -> 340
    //   319: aload_0
    //   320: aload #6
    //   322: iconst_0
    //   323: invokeinterface get : (I)Ljava/lang/Object;
    //   328: checkcast java/lang/String
    //   331: invokestatic valueOf : (Ljava/lang/String;)Ljava/lang/Boolean;
    //   334: invokevirtual booleanValue : ()Z
    //   337: putfield zzcxd : Z
    //   340: aload_0
    //   341: aload_0
    //   342: getfield zzcxb : Z
    //   345: aload_1
    //   346: ldc_w 'X-Afma-Custom-Rendering-Allowed'
    //   349: invokestatic zzd : (Ljava/util/Map;Ljava/lang/String;)Z
    //   352: ior
    //   353: putfield zzcxb : Z
    //   356: aload_0
    //   357: ldc_w 'native'
    //   360: aload_1
    //   361: ldc_w 'X-Afma-Ad-Format'
    //   364: invokestatic zza : (Ljava/util/Map;Ljava/lang/String;)Ljava/lang/String;
    //   367: invokevirtual equals : (Ljava/lang/Object;)Z
    //   370: putfield zzcxc : Z
    //   373: aload_1
    //   374: ldc_w 'X-Afma-Content-Url-Opted-Out'
    //   377: invokeinterface get : (Ljava/lang/Object;)Ljava/lang/Object;
    //   382: checkcast java/util/List
    //   385: astore #6
    //   387: aload #6
    //   389: ifnull -> 423
    //   392: aload #6
    //   394: invokeinterface isEmpty : ()Z
    //   399: ifne -> 423
    //   402: aload_0
    //   403: aload #6
    //   405: iconst_0
    //   406: invokeinterface get : (I)Ljava/lang/Object;
    //   411: checkcast java/lang/String
    //   414: invokestatic valueOf : (Ljava/lang/String;)Ljava/lang/Boolean;
    //   417: invokevirtual booleanValue : ()Z
    //   420: putfield zzcxe : Z
    //   423: aload_1
    //   424: ldc_w 'X-Afma-Content-Vertical-Opted-Out'
    //   427: invokeinterface get : (Ljava/lang/Object;)Ljava/lang/Object;
    //   432: checkcast java/util/List
    //   435: astore #6
    //   437: aload #6
    //   439: ifnull -> 473
    //   442: aload #6
    //   444: invokeinterface isEmpty : ()Z
    //   449: ifne -> 473
    //   452: aload_0
    //   453: aload #6
    //   455: iconst_0
    //   456: invokeinterface get : (I)Ljava/lang/Object;
    //   461: checkcast java/lang/String
    //   464: invokestatic valueOf : (Ljava/lang/String;)Ljava/lang/Boolean;
    //   467: invokevirtual booleanValue : ()Z
    //   470: putfield zzcxf : Z
    //   473: aload_1
    //   474: ldc_w 'X-Afma-Gws-Query-Id'
    //   477: invokeinterface get : (Ljava/lang/Object;)Ljava/lang/Object;
    //   482: checkcast java/util/List
    //   485: astore #6
    //   487: aload #6
    //   489: ifnull -> 517
    //   492: aload #6
    //   494: invokeinterface isEmpty : ()Z
    //   499: ifne -> 517
    //   502: aload_0
    //   503: aload #6
    //   505: iconst_0
    //   506: invokeinterface get : (I)Ljava/lang/Object;
    //   511: checkcast java/lang/String
    //   514: putfield zzcxg : Ljava/lang/String;
    //   517: aload_1
    //   518: ldc_w 'X-Afma-Fluid'
    //   521: invokestatic zza : (Ljava/util/Map;Ljava/lang/String;)Ljava/lang/String;
    //   524: astore #6
    //   526: aload #6
    //   528: ifnull -> 547
    //   531: aload #6
    //   533: ldc_w 'height'
    //   536: invokevirtual equals : (Ljava/lang/Object;)Z
    //   539: ifeq -> 547
    //   542: aload_0
    //   543: iconst_1
    //   544: putfield zzcxh : Z
    //   547: aload_0
    //   548: ldc_w 'native_express'
    //   551: aload_1
    //   552: ldc_w 'X-Afma-Ad-Format'
    //   555: invokestatic zza : (Ljava/util/Map;Ljava/lang/String;)Ljava/lang/String;
    //   558: invokevirtual equals : (Ljava/lang/Object;)Z
    //   561: putfield zzciv : Z
    //   564: aload_0
    //   565: aload_1
    //   566: ldc_w 'X-Afma-Rewards'
    //   569: invokestatic zza : (Ljava/util/Map;Ljava/lang/String;)Ljava/lang/String;
    //   572: invokestatic zzbu : (Ljava/lang/String;)Lcom/google/android/gms/internal/zzagd;
    //   575: putfield zzcxi : Lcom/google/android/gms/internal/zzagd;
    //   578: aload_0
    //   579: getfield zzcxj : Ljava/util/List;
    //   582: ifnonnull -> 596
    //   585: aload_0
    //   586: aload_1
    //   587: ldc_w 'X-Afma-Reward-Video-Start-Urls'
    //   590: invokestatic zzc : (Ljava/util/Map;Ljava/lang/String;)Ljava/util/List;
    //   593: putfield zzcxj : Ljava/util/List;
    //   596: aload_0
    //   597: getfield zzcxk : Ljava/util/List;
    //   600: ifnonnull -> 614
    //   603: aload_0
    //   604: aload_1
    //   605: ldc_w 'X-Afma-Reward-Video-Complete-Urls'
    //   608: invokestatic zzc : (Ljava/util/Map;Ljava/lang/String;)Ljava/util/List;
    //   611: putfield zzcxk : Ljava/util/List;
    //   614: aload_0
    //   615: aload_0
    //   616: getfield zzcxl : Z
    //   619: aload_1
    //   620: ldc_w 'X-Afma-Use-Displayed-Impression'
    //   623: invokestatic zzd : (Ljava/util/Map;Ljava/lang/String;)Z
    //   626: ior
    //   627: putfield zzcxl : Z
    //   630: aload_0
    //   631: aload_0
    //   632: getfield zzcxm : Z
    //   635: aload_1
    //   636: ldc_w 'X-Afma-Auto-Collect-Location'
    //   639: invokestatic zzd : (Ljava/util/Map;Ljava/lang/String;)Z
    //   642: ior
    //   643: putfield zzcxm : Z
    //   646: aload_0
    //   647: aload_1
    //   648: ldc_w 'Set-Cookie'
    //   651: invokestatic zza : (Ljava/util/Map;Ljava/lang/String;)Ljava/lang/String;
    //   654: putfield zzcxn : Ljava/lang/String;
    //   657: aload_1
    //   658: ldc_w 'X-Afma-Auto-Protection-Configuration'
    //   661: invokestatic zza : (Ljava/util/Map;Ljava/lang/String;)Ljava/lang/String;
    //   664: astore #6
    //   666: aload #6
    //   668: ifnull -> 725
    //   671: aload #6
    //   673: invokestatic isEmpty : (Ljava/lang/CharSequence;)Z
    //   676: ifeq -> 682
    //   679: goto -> 725
    //   682: aload_0
    //   683: new org/json/JSONObject
    //   686: dup
    //   687: aload #6
    //   689: invokespecial <init> : (Ljava/lang/String;)V
    //   692: invokestatic zzk : (Lorg/json/JSONObject;)Lcom/google/android/gms/internal/zzacl;
    //   695: putfield zzaoq : Lcom/google/android/gms/internal/zzacl;
    //   698: goto -> 864
    //   701: astore #6
    //   703: ldc_w 'Error parsing configuration JSON'
    //   706: aload #6
    //   708: invokestatic zzc : (Ljava/lang/String;Ljava/lang/Throwable;)V
    //   711: aload_0
    //   712: new com/google/android/gms/internal/zzacl
    //   715: dup
    //   716: invokespecial <init> : ()V
    //   719: putfield zzaoq : Lcom/google/android/gms/internal/zzacl;
    //   722: goto -> 864
    //   725: ldc_w 'https://pagead2.googlesyndication.com/pagead/gen_204'
    //   728: invokestatic parse : (Ljava/lang/String;)Landroid/net/Uri;
    //   731: invokevirtual buildUpon : ()Landroid/net/Uri$Builder;
    //   734: astore #6
    //   736: aload #6
    //   738: ldc_w 'id'
    //   741: ldc_w 'gmob-apps-blocked-navigation'
    //   744: invokevirtual appendQueryParameter : (Ljava/lang/String;Ljava/lang/String;)Landroid/net/Uri$Builder;
    //   747: pop
    //   748: aload_0
    //   749: getfield zzcwu : Ljava/lang/String;
    //   752: invokestatic isEmpty : (Ljava/lang/CharSequence;)Z
    //   755: ifne -> 771
    //   758: aload #6
    //   760: ldc_w 'debugDialog'
    //   763: aload_0
    //   764: getfield zzcwu : Ljava/lang/String;
    //   767: invokevirtual appendQueryParameter : (Ljava/lang/String;Ljava/lang/String;)Landroid/net/Uri$Builder;
    //   770: pop
    //   771: getstatic com/google/android/gms/internal/zzoi.zzbll : Lcom/google/android/gms/internal/zzny;
    //   774: astore #7
    //   776: invokestatic zzio : ()Lcom/google/android/gms/internal/zzog;
    //   779: aload #7
    //   781: invokevirtual zzd : (Lcom/google/android/gms/internal/zzny;)Ljava/lang/Object;
    //   784: checkcast java/lang/Boolean
    //   787: invokevirtual booleanValue : ()Z
    //   790: istore #5
    //   792: aload #6
    //   794: invokevirtual toString : ()Ljava/lang/String;
    //   797: astore #6
    //   799: new java/lang/StringBuilder
    //   802: dup
    //   803: aload #6
    //   805: invokestatic valueOf : (Ljava/lang/Object;)Ljava/lang/String;
    //   808: invokevirtual length : ()I
    //   811: bipush #31
    //   813: iadd
    //   814: invokespecial <init> : (I)V
    //   817: astore #7
    //   819: aload #7
    //   821: aload #6
    //   823: invokevirtual append : (Ljava/lang/String;)Ljava/lang/StringBuilder;
    //   826: pop
    //   827: aload #7
    //   829: ldc_w '&navigationURL={NAVIGATION_URL}'
    //   832: invokevirtual append : (Ljava/lang/String;)Ljava/lang/StringBuilder;
    //   835: pop
    //   836: aload_0
    //   837: new com/google/android/gms/internal/zzacl
    //   840: dup
    //   841: iload #5
    //   843: iconst_1
    //   844: anewarray java/lang/String
    //   847: dup
    //   848: iconst_0
    //   849: aload #7
    //   851: invokevirtual toString : ()Ljava/lang/String;
    //   854: aastore
    //   855: invokestatic asList : ([Ljava/lang/Object;)Ljava/util/List;
    //   858: invokespecial <init> : (ZLjava/util/List;)V
    //   861: putfield zzaoq : Lcom/google/android/gms/internal/zzacl;
    //   864: aload_1
    //   865: ldc_w 'X-Afma-Remote-Ping-Urls'
    //   868: invokestatic zzc : (Ljava/util/Map;Ljava/lang/String;)Ljava/util/List;
    //   871: astore #6
    //   873: aload #6
    //   875: ifnull -> 884
    //   878: aload_0
    //   879: aload #6
    //   881: putfield zzcxo : Ljava/util/List;
    //   884: aload_1
    //   885: ldc_w 'X-Afma-Safe-Browsing'
    //   888: invokestatic zza : (Ljava/util/Map;Ljava/lang/String;)Ljava/lang/String;
    //   891: astore #6
    //   893: aload #6
    //   895: invokestatic isEmpty : (Ljava/lang/CharSequence;)Z
    //   898: ifne -> 930
    //   901: aload_0
    //   902: new org/json/JSONObject
    //   905: dup
    //   906: aload #6
    //   908: invokespecial <init> : (Ljava/lang/String;)V
    //   911: invokestatic zzn : (Lorg/json/JSONObject;)Lcom/google/android/gms/internal/zzagn;
    //   914: putfield zzcxr : Lcom/google/android/gms/internal/zzagn;
    //   917: goto -> 930
    //   920: astore #6
    //   922: ldc_w 'Error parsing safe browsing header'
    //   925: aload #6
    //   927: invokestatic zzc : (Ljava/lang/String;Ljava/lang/Throwable;)V
    //   930: aload_0
    //   931: aload_0
    //   932: getfield zzcxp : Z
    //   935: aload_1
    //   936: ldc_w 'X-Afma-Render-In-Browser'
    //   939: invokestatic zzd : (Ljava/util/Map;Ljava/lang/String;)Z
    //   942: ior
    //   943: putfield zzcxp : Z
    //   946: aload_1
    //   947: ldc_w 'X-Afma-Pool'
    //   950: invokestatic zza : (Ljava/util/Map;Ljava/lang/String;)Ljava/lang/String;
    //   953: astore #6
    //   955: aload #6
    //   957: invokestatic isEmpty : (Ljava/lang/CharSequence;)Z
    //   960: ifne -> 995
    //   963: aload_0
    //   964: new org/json/JSONObject
    //   967: dup
    //   968: aload #6
    //   970: invokespecial <init> : (Ljava/lang/String;)V
    //   973: ldc_w 'never_pool'
    //   976: invokevirtual getBoolean : (Ljava/lang/String;)Z
    //   979: putfield zzcxs : Z
    //   982: goto -> 995
    //   985: astore #6
    //   987: ldc_w 'Error parsing interstitial pool header'
    //   990: aload #6
    //   992: invokestatic zzc : (Ljava/lang/String;Ljava/lang/Throwable;)V
    //   995: aload_0
    //   996: aload_1
    //   997: ldc_w 'X-Afma-Custom-Close-Blocked'
    //   1000: invokestatic zzd : (Ljava/util/Map;Ljava/lang/String;)Z
    //   1003: putfield zzcxt : Z
    //   1006: return
    // Exception table:
    //   from	to	target	type
    //   682	698	701	org/json/JSONException
    //   901	917	920	org/json/JSONException
    //   963	982	985	org/json/JSONException
  }
}


/* Location:              /home/egaebel/Programs/sony-headphones-hack/base-dex2jar.jar!/com/google/android/gms/internal/zzadx.class
 * Java compiler version: 6 (50.0)
 * JD-Core Version:       1.1.3
 */