package com.google.android.gms.internal;

import com.google.android.gms.common.internal.Hide;
import java.math.BigInteger;

@zzabh
@Hide
public final class zzaho {
  private BigInteger zzdej = BigInteger.ONE;
  
  public final String zzqg() {
    // Byte code:
    //   0: aload_0
    //   1: monitorenter
    //   2: aload_0
    //   3: getfield zzdej : Ljava/math/BigInteger;
    //   6: invokevirtual toString : ()Ljava/lang/String;
    //   9: astore_1
    //   10: aload_0
    //   11: aload_0
    //   12: getfield zzdej : Ljava/math/BigInteger;
    //   15: getstatic java/math/BigInteger.ONE : Ljava/math/BigInteger;
    //   18: invokevirtual add : (Ljava/math/BigInteger;)Ljava/math/BigInteger;
    //   21: putfield zzdej : Ljava/math/BigInteger;
    //   24: aload_0
    //   25: monitorexit
    //   26: aload_1
    //   27: areturn
    //   28: astore_1
    //   29: aload_0
    //   30: monitorexit
    //   31: aload_1
    //   32: athrow
    // Exception table:
    //   from	to	target	type
    //   2	24	28	finally
  }
}


/* Location:              /home/egaebel/Programs/sony-headphones-hack/base-dex2jar.jar!/com/google/android/gms/internal/zzaho.class
 * Java compiler version: 6 (50.0)
 * JD-Core Version:       1.1.3
 */