package com.google.android.gms.internal;

public final class zzba extends zzflm<zzba> {
  public String zzcu = null;
  
  public String zzcv = null;
  
  public String zzcx = null;
  
  public String zzcy = null;
  
  public String zzcz = null;
  
  public String zzda = null;
  
  public Long zzdb = null;
  
  private Long zzdc = null;
  
  public Long zzdd = null;
  
  public Long zzde = null;
  
  private Long zzdf = null;
  
  private Long zzdg = null;
  
  private Long zzdh = null;
  
  private Long zzdi = null;
  
  private Long zzdj = null;
  
  public Long zzdk = null;
  
  private String zzdl = null;
  
  public Long zzdm = null;
  
  public Long zzdn = null;
  
  public Long zzdo = null;
  
  public Long zzdp = null;
  
  private Long zzdq = null;
  
  private Long zzdr = null;
  
  public Long zzds = null;
  
  public Long zzdt = null;
  
  public Long zzdu = null;
  
  public String zzdv = null;
  
  public Long zzdw = null;
  
  public Long zzdx = null;
  
  public Long zzdy = null;
  
  public Long zzdz = null;
  
  public Long zzea = null;
  
  public Long zzeb = null;
  
  private zzbd zzec = null;
  
  public Long zzed = null;
  
  public Long zzee = null;
  
  public Long zzef = null;
  
  public Long zzeg = null;
  
  public Long zzeh = null;
  
  public Long zzei = null;
  
  public Integer zzej;
  
  public Integer zzek;
  
  public Long zzel = null;
  
  public Long zzem = null;
  
  public Long zzen = null;
  
  private Long zzeo = null;
  
  private Long zzep = null;
  
  public Integer zzeq;
  
  public zzbb zzer = null;
  
  public zzbb[] zzes = zzbb.zzr();
  
  public zzbc zzet = null;
  
  private Long zzeu = null;
  
  public Long zzev = null;
  
  public Long zzew = null;
  
  public Long zzex = null;
  
  public Long zzey = null;
  
  public Long zzez = null;
  
  private Long zzfa = null;
  
  private Long zzfb = null;
  
  public String zzfc = null;
  
  public Integer zzfd;
  
  public Boolean zzfe = null;
  
  private String zzff = null;
  
  public Long zzfg = null;
  
  public zzbf zzfh = null;
  
  private final zzba zzb(zzflj paramzzflj) {
    // Byte code:
    //   0: aload_1
    //   1: invokevirtual zzcxx : ()I
    //   4: istore #4
    //   6: iload #4
    //   8: lookupswitch default -> 548, 0 -> 1756, 10 -> 1745, 18 -> 1734, 24 -> 1720, 32 -> 1706, 40 -> 1692, 48 -> 1678, 56 -> 1664, 64 -> 1650, 72 -> 1636, 80 -> 1622, 88 -> 1608, 96 -> 1594, 106 -> 1583, 112 -> 1569, 120 -> 1555, 128 -> 1541, 136 -> 1527, 144 -> 1513, 152 -> 1499, 160 -> 1485, 168 -> 1471, 176 -> 1457, 184 -> 1443, 194 -> 1432, 200 -> 1418, 208 -> 1280, 218 -> 1269, 224 -> 1255, 234 -> 1244, 242 -> 1233, 248 -> 1219, 256 -> 1205, 264 -> 1191, 274 -> 1180, 280 -> 1166, 288 -> 1152, 296 -> 1138, 306 -> 1105, 312 -> 1091, 320 -> 1077, 328 -> 1063, 336 -> 1049, 346 -> 925, 352 -> 911, 360 -> 897, 370 -> 886, 378 -> 875, 384 -> 853, 392 -> 831, 402 -> 804, 408 -> 790, 416 -> 776, 424 -> 762, 432 -> 748, 440 -> 734, 448 -> 712, 458 -> 685, 464 -> 671, 472 -> 657, 480 -> 643, 488 -> 629, 496 -> 615, 504 -> 601, 512 -> 587, 1610 -> 560
    //   548: aload_0
    //   549: aload_1
    //   550: iload #4
    //   552: invokespecial zza : (Lcom/google/android/gms/internal/zzflj;I)Z
    //   555: ifne -> 0
    //   558: aload_0
    //   559: areturn
    //   560: aload_0
    //   561: getfield zzfh : Lcom/google/android/gms/internal/zzbf;
    //   564: ifnonnull -> 578
    //   567: aload_0
    //   568: new com/google/android/gms/internal/zzbf
    //   571: dup
    //   572: invokespecial <init> : ()V
    //   575: putfield zzfh : Lcom/google/android/gms/internal/zzbf;
    //   578: aload_0
    //   579: getfield zzfh : Lcom/google/android/gms/internal/zzbf;
    //   582: astore #6
    //   584: goto -> 1129
    //   587: aload_0
    //   588: aload_1
    //   589: invokevirtual zzcyr : ()J
    //   592: invokestatic valueOf : (J)Ljava/lang/Long;
    //   595: putfield zzfa : Ljava/lang/Long;
    //   598: goto -> 0
    //   601: aload_0
    //   602: aload_1
    //   603: invokevirtual zzcyr : ()J
    //   606: invokestatic valueOf : (J)Ljava/lang/Long;
    //   609: putfield zzez : Ljava/lang/Long;
    //   612: goto -> 0
    //   615: aload_0
    //   616: aload_1
    //   617: invokevirtual zzcyr : ()J
    //   620: invokestatic valueOf : (J)Ljava/lang/Long;
    //   623: putfield zzey : Ljava/lang/Long;
    //   626: goto -> 0
    //   629: aload_0
    //   630: aload_1
    //   631: invokevirtual zzcyr : ()J
    //   634: invokestatic valueOf : (J)Ljava/lang/Long;
    //   637: putfield zzex : Ljava/lang/Long;
    //   640: goto -> 0
    //   643: aload_0
    //   644: aload_1
    //   645: invokevirtual zzcyr : ()J
    //   648: invokestatic valueOf : (J)Ljava/lang/Long;
    //   651: putfield zzew : Ljava/lang/Long;
    //   654: goto -> 0
    //   657: aload_0
    //   658: aload_1
    //   659: invokevirtual zzcyr : ()J
    //   662: invokestatic valueOf : (J)Ljava/lang/Long;
    //   665: putfield zzev : Ljava/lang/Long;
    //   668: goto -> 0
    //   671: aload_0
    //   672: aload_1
    //   673: invokevirtual zzcyr : ()J
    //   676: invokestatic valueOf : (J)Ljava/lang/Long;
    //   679: putfield zzeu : Ljava/lang/Long;
    //   682: goto -> 0
    //   685: aload_0
    //   686: getfield zzet : Lcom/google/android/gms/internal/zzbc;
    //   689: ifnonnull -> 703
    //   692: aload_0
    //   693: new com/google/android/gms/internal/zzbc
    //   696: dup
    //   697: invokespecial <init> : ()V
    //   700: putfield zzet : Lcom/google/android/gms/internal/zzbc;
    //   703: aload_0
    //   704: getfield zzet : Lcom/google/android/gms/internal/zzbc;
    //   707: astore #6
    //   709: goto -> 1129
    //   712: aload_1
    //   713: invokevirtual getPosition : ()I
    //   716: istore_2
    //   717: aload_0
    //   718: aload_1
    //   719: invokevirtual zzcym : ()I
    //   722: invokestatic zzd : (I)I
    //   725: invokestatic valueOf : (I)Ljava/lang/Integer;
    //   728: putfield zzeq : Ljava/lang/Integer;
    //   731: goto -> 0
    //   734: aload_0
    //   735: aload_1
    //   736: invokevirtual zzcyr : ()J
    //   739: invokestatic valueOf : (J)Ljava/lang/Long;
    //   742: putfield zzep : Ljava/lang/Long;
    //   745: goto -> 0
    //   748: aload_0
    //   749: aload_1
    //   750: invokevirtual zzcyr : ()J
    //   753: invokestatic valueOf : (J)Ljava/lang/Long;
    //   756: putfield zzeo : Ljava/lang/Long;
    //   759: goto -> 0
    //   762: aload_0
    //   763: aload_1
    //   764: invokevirtual zzcyr : ()J
    //   767: invokestatic valueOf : (J)Ljava/lang/Long;
    //   770: putfield zzen : Ljava/lang/Long;
    //   773: goto -> 0
    //   776: aload_0
    //   777: aload_1
    //   778: invokevirtual zzcyr : ()J
    //   781: invokestatic valueOf : (J)Ljava/lang/Long;
    //   784: putfield zzem : Ljava/lang/Long;
    //   787: goto -> 0
    //   790: aload_0
    //   791: aload_1
    //   792: invokevirtual zzcyr : ()J
    //   795: invokestatic valueOf : (J)Ljava/lang/Long;
    //   798: putfield zzel : Ljava/lang/Long;
    //   801: goto -> 0
    //   804: aload_0
    //   805: getfield zzer : Lcom/google/android/gms/internal/zzbb;
    //   808: ifnonnull -> 822
    //   811: aload_0
    //   812: new com/google/android/gms/internal/zzbb
    //   815: dup
    //   816: invokespecial <init> : ()V
    //   819: putfield zzer : Lcom/google/android/gms/internal/zzbb;
    //   822: aload_0
    //   823: getfield zzer : Lcom/google/android/gms/internal/zzbb;
    //   826: astore #6
    //   828: goto -> 1129
    //   831: aload_1
    //   832: invokevirtual getPosition : ()I
    //   835: istore_2
    //   836: aload_0
    //   837: aload_1
    //   838: invokevirtual zzcym : ()I
    //   841: invokestatic zzd : (I)I
    //   844: invokestatic valueOf : (I)Ljava/lang/Integer;
    //   847: putfield zzek : Ljava/lang/Integer;
    //   850: goto -> 0
    //   853: aload_1
    //   854: invokevirtual getPosition : ()I
    //   857: istore_2
    //   858: aload_0
    //   859: aload_1
    //   860: invokevirtual zzcym : ()I
    //   863: invokestatic zzd : (I)I
    //   866: invokestatic valueOf : (I)Ljava/lang/Integer;
    //   869: putfield zzej : Ljava/lang/Integer;
    //   872: goto -> 0
    //   875: aload_0
    //   876: aload_1
    //   877: invokevirtual readString : ()Ljava/lang/String;
    //   880: putfield zzcz : Ljava/lang/String;
    //   883: goto -> 0
    //   886: aload_0
    //   887: aload_1
    //   888: invokevirtual readString : ()Ljava/lang/String;
    //   891: putfield zzcy : Ljava/lang/String;
    //   894: goto -> 0
    //   897: aload_0
    //   898: aload_1
    //   899: invokevirtual zzcyr : ()J
    //   902: invokestatic valueOf : (J)Ljava/lang/Long;
    //   905: putfield zzei : Ljava/lang/Long;
    //   908: goto -> 0
    //   911: aload_0
    //   912: aload_1
    //   913: invokevirtual zzcyr : ()J
    //   916: invokestatic valueOf : (J)Ljava/lang/Long;
    //   919: putfield zzeh : Ljava/lang/Long;
    //   922: goto -> 0
    //   925: aload_1
    //   926: sipush #346
    //   929: invokestatic zzb : (Lcom/google/android/gms/internal/zzflj;I)I
    //   932: istore_3
    //   933: aload_0
    //   934: getfield zzes : [Lcom/google/android/gms/internal/zzbb;
    //   937: astore #6
    //   939: aload #6
    //   941: ifnonnull -> 949
    //   944: iconst_0
    //   945: istore_2
    //   946: goto -> 953
    //   949: aload #6
    //   951: arraylength
    //   952: istore_2
    //   953: iload_3
    //   954: iload_2
    //   955: iadd
    //   956: anewarray com/google/android/gms/internal/zzbb
    //   959: astore #6
    //   961: iload_2
    //   962: istore_3
    //   963: iload_2
    //   964: ifeq -> 981
    //   967: aload_0
    //   968: getfield zzes : [Lcom/google/android/gms/internal/zzbb;
    //   971: iconst_0
    //   972: aload #6
    //   974: iconst_0
    //   975: iload_2
    //   976: invokestatic arraycopy : (Ljava/lang/Object;ILjava/lang/Object;II)V
    //   979: iload_2
    //   980: istore_3
    //   981: iload_3
    //   982: aload #6
    //   984: arraylength
    //   985: iconst_1
    //   986: isub
    //   987: if_icmpge -> 1021
    //   990: aload #6
    //   992: iload_3
    //   993: new com/google/android/gms/internal/zzbb
    //   996: dup
    //   997: invokespecial <init> : ()V
    //   1000: aastore
    //   1001: aload_1
    //   1002: aload #6
    //   1004: iload_3
    //   1005: aaload
    //   1006: invokevirtual zza : (Lcom/google/android/gms/internal/zzfls;)V
    //   1009: aload_1
    //   1010: invokevirtual zzcxx : ()I
    //   1013: pop
    //   1014: iload_3
    //   1015: iconst_1
    //   1016: iadd
    //   1017: istore_3
    //   1018: goto -> 981
    //   1021: aload #6
    //   1023: iload_3
    //   1024: new com/google/android/gms/internal/zzbb
    //   1027: dup
    //   1028: invokespecial <init> : ()V
    //   1031: aastore
    //   1032: aload_1
    //   1033: aload #6
    //   1035: iload_3
    //   1036: aaload
    //   1037: invokevirtual zza : (Lcom/google/android/gms/internal/zzfls;)V
    //   1040: aload_0
    //   1041: aload #6
    //   1043: putfield zzes : [Lcom/google/android/gms/internal/zzbb;
    //   1046: goto -> 0
    //   1049: aload_0
    //   1050: aload_1
    //   1051: invokevirtual zzcyr : ()J
    //   1054: invokestatic valueOf : (J)Ljava/lang/Long;
    //   1057: putfield zzeg : Ljava/lang/Long;
    //   1060: goto -> 0
    //   1063: aload_0
    //   1064: aload_1
    //   1065: invokevirtual zzcyr : ()J
    //   1068: invokestatic valueOf : (J)Ljava/lang/Long;
    //   1071: putfield zzef : Ljava/lang/Long;
    //   1074: goto -> 0
    //   1077: aload_0
    //   1078: aload_1
    //   1079: invokevirtual zzcyr : ()J
    //   1082: invokestatic valueOf : (J)Ljava/lang/Long;
    //   1085: putfield zzee : Ljava/lang/Long;
    //   1088: goto -> 0
    //   1091: aload_0
    //   1092: aload_1
    //   1093: invokevirtual zzcyr : ()J
    //   1096: invokestatic valueOf : (J)Ljava/lang/Long;
    //   1099: putfield zzed : Ljava/lang/Long;
    //   1102: goto -> 0
    //   1105: aload_0
    //   1106: getfield zzec : Lcom/google/android/gms/internal/zzbd;
    //   1109: ifnonnull -> 1123
    //   1112: aload_0
    //   1113: new com/google/android/gms/internal/zzbd
    //   1116: dup
    //   1117: invokespecial <init> : ()V
    //   1120: putfield zzec : Lcom/google/android/gms/internal/zzbd;
    //   1123: aload_0
    //   1124: getfield zzec : Lcom/google/android/gms/internal/zzbd;
    //   1127: astore #6
    //   1129: aload_1
    //   1130: aload #6
    //   1132: invokevirtual zza : (Lcom/google/android/gms/internal/zzfls;)V
    //   1135: goto -> 0
    //   1138: aload_0
    //   1139: aload_1
    //   1140: invokevirtual zzcyr : ()J
    //   1143: invokestatic valueOf : (J)Ljava/lang/Long;
    //   1146: putfield zzeb : Ljava/lang/Long;
    //   1149: goto -> 0
    //   1152: aload_0
    //   1153: aload_1
    //   1154: invokevirtual zzcyr : ()J
    //   1157: invokestatic valueOf : (J)Ljava/lang/Long;
    //   1160: putfield zzea : Ljava/lang/Long;
    //   1163: goto -> 0
    //   1166: aload_0
    //   1167: aload_1
    //   1168: invokevirtual zzcyr : ()J
    //   1171: invokestatic valueOf : (J)Ljava/lang/Long;
    //   1174: putfield zzdz : Ljava/lang/Long;
    //   1177: goto -> 0
    //   1180: aload_0
    //   1181: aload_1
    //   1182: invokevirtual readString : ()Ljava/lang/String;
    //   1185: putfield zzcx : Ljava/lang/String;
    //   1188: goto -> 0
    //   1191: aload_0
    //   1192: aload_1
    //   1193: invokevirtual zzcyr : ()J
    //   1196: invokestatic valueOf : (J)Ljava/lang/Long;
    //   1199: putfield zzdy : Ljava/lang/Long;
    //   1202: goto -> 0
    //   1205: aload_0
    //   1206: aload_1
    //   1207: invokevirtual zzcyr : ()J
    //   1210: invokestatic valueOf : (J)Ljava/lang/Long;
    //   1213: putfield zzdx : Ljava/lang/Long;
    //   1216: goto -> 0
    //   1219: aload_0
    //   1220: aload_1
    //   1221: invokevirtual zzcyr : ()J
    //   1224: invokestatic valueOf : (J)Ljava/lang/Long;
    //   1227: putfield zzdw : Ljava/lang/Long;
    //   1230: goto -> 0
    //   1233: aload_0
    //   1234: aload_1
    //   1235: invokevirtual readString : ()Ljava/lang/String;
    //   1238: putfield zzff : Ljava/lang/String;
    //   1241: goto -> 0
    //   1244: aload_0
    //   1245: aload_1
    //   1246: invokevirtual readString : ()Ljava/lang/String;
    //   1249: putfield zzdv : Ljava/lang/String;
    //   1252: goto -> 0
    //   1255: aload_0
    //   1256: aload_1
    //   1257: invokevirtual zzcyd : ()Z
    //   1260: invokestatic valueOf : (Z)Ljava/lang/Boolean;
    //   1263: putfield zzfe : Ljava/lang/Boolean;
    //   1266: goto -> 0
    //   1269: aload_0
    //   1270: aload_1
    //   1271: invokevirtual readString : ()Ljava/lang/String;
    //   1274: putfield zzcv : Ljava/lang/String;
    //   1277: goto -> 0
    //   1280: aload_1
    //   1281: invokevirtual getPosition : ()I
    //   1284: istore_3
    //   1285: iload_3
    //   1286: istore_2
    //   1287: aload_1
    //   1288: invokevirtual zzcym : ()I
    //   1291: istore #5
    //   1293: iload #5
    //   1295: tableswitch default -> 1763, 0 -> 1339, 1 -> 1339, 2 -> 1339, 3 -> 1339, 4 -> 1339, 5 -> 1339, 6 -> 1339
    //   1336: goto -> 1353
    //   1339: iload_3
    //   1340: istore_2
    //   1341: aload_0
    //   1342: iload #5
    //   1344: invokestatic valueOf : (I)Ljava/lang/Integer;
    //   1347: putfield zzfd : Ljava/lang/Integer;
    //   1350: goto -> 0
    //   1353: iload_3
    //   1354: istore_2
    //   1355: new java/lang/StringBuilder
    //   1358: dup
    //   1359: bipush #44
    //   1361: invokespecial <init> : (I)V
    //   1364: astore #6
    //   1366: iload_3
    //   1367: istore_2
    //   1368: aload #6
    //   1370: iload #5
    //   1372: invokevirtual append : (I)Ljava/lang/StringBuilder;
    //   1375: pop
    //   1376: iload_3
    //   1377: istore_2
    //   1378: aload #6
    //   1380: ldc_w ' is not a valid enum DeviceIdType'
    //   1383: invokevirtual append : (Ljava/lang/String;)Ljava/lang/StringBuilder;
    //   1386: pop
    //   1387: iload_3
    //   1388: istore_2
    //   1389: new java/lang/IllegalArgumentException
    //   1392: dup
    //   1393: aload #6
    //   1395: invokevirtual toString : ()Ljava/lang/String;
    //   1398: invokespecial <init> : (Ljava/lang/String;)V
    //   1401: athrow
    //   1402: aload_1
    //   1403: iload_2
    //   1404: invokevirtual zzmw : (I)V
    //   1407: aload_0
    //   1408: aload_1
    //   1409: iload #4
    //   1411: invokevirtual zza : (Lcom/google/android/gms/internal/zzflj;I)Z
    //   1414: pop
    //   1415: goto -> 0
    //   1418: aload_0
    //   1419: aload_1
    //   1420: invokevirtual zzcyr : ()J
    //   1423: invokestatic valueOf : (J)Ljava/lang/Long;
    //   1426: putfield zzfg : Ljava/lang/Long;
    //   1429: goto -> 0
    //   1432: aload_0
    //   1433: aload_1
    //   1434: invokevirtual readString : ()Ljava/lang/String;
    //   1437: putfield zzfc : Ljava/lang/String;
    //   1440: goto -> 0
    //   1443: aload_0
    //   1444: aload_1
    //   1445: invokevirtual zzcyr : ()J
    //   1448: invokestatic valueOf : (J)Ljava/lang/Long;
    //   1451: putfield zzdu : Ljava/lang/Long;
    //   1454: goto -> 0
    //   1457: aload_0
    //   1458: aload_1
    //   1459: invokevirtual zzcyr : ()J
    //   1462: invokestatic valueOf : (J)Ljava/lang/Long;
    //   1465: putfield zzdt : Ljava/lang/Long;
    //   1468: goto -> 0
    //   1471: aload_0
    //   1472: aload_1
    //   1473: invokevirtual zzcyr : ()J
    //   1476: invokestatic valueOf : (J)Ljava/lang/Long;
    //   1479: putfield zzfb : Ljava/lang/Long;
    //   1482: goto -> 0
    //   1485: aload_0
    //   1486: aload_1
    //   1487: invokevirtual zzcyr : ()J
    //   1490: invokestatic valueOf : (J)Ljava/lang/Long;
    //   1493: putfield zzds : Ljava/lang/Long;
    //   1496: goto -> 0
    //   1499: aload_0
    //   1500: aload_1
    //   1501: invokevirtual zzcyr : ()J
    //   1504: invokestatic valueOf : (J)Ljava/lang/Long;
    //   1507: putfield zzdr : Ljava/lang/Long;
    //   1510: goto -> 0
    //   1513: aload_0
    //   1514: aload_1
    //   1515: invokevirtual zzcyr : ()J
    //   1518: invokestatic valueOf : (J)Ljava/lang/Long;
    //   1521: putfield zzdq : Ljava/lang/Long;
    //   1524: goto -> 0
    //   1527: aload_0
    //   1528: aload_1
    //   1529: invokevirtual zzcyr : ()J
    //   1532: invokestatic valueOf : (J)Ljava/lang/Long;
    //   1535: putfield zzdp : Ljava/lang/Long;
    //   1538: goto -> 0
    //   1541: aload_0
    //   1542: aload_1
    //   1543: invokevirtual zzcyr : ()J
    //   1546: invokestatic valueOf : (J)Ljava/lang/Long;
    //   1549: putfield zzdo : Ljava/lang/Long;
    //   1552: goto -> 0
    //   1555: aload_0
    //   1556: aload_1
    //   1557: invokevirtual zzcyr : ()J
    //   1560: invokestatic valueOf : (J)Ljava/lang/Long;
    //   1563: putfield zzdn : Ljava/lang/Long;
    //   1566: goto -> 0
    //   1569: aload_0
    //   1570: aload_1
    //   1571: invokevirtual zzcyr : ()J
    //   1574: invokestatic valueOf : (J)Ljava/lang/Long;
    //   1577: putfield zzdm : Ljava/lang/Long;
    //   1580: goto -> 0
    //   1583: aload_0
    //   1584: aload_1
    //   1585: invokevirtual readString : ()Ljava/lang/String;
    //   1588: putfield zzdl : Ljava/lang/String;
    //   1591: goto -> 0
    //   1594: aload_0
    //   1595: aload_1
    //   1596: invokevirtual zzcyr : ()J
    //   1599: invokestatic valueOf : (J)Ljava/lang/Long;
    //   1602: putfield zzdk : Ljava/lang/Long;
    //   1605: goto -> 0
    //   1608: aload_0
    //   1609: aload_1
    //   1610: invokevirtual zzcyr : ()J
    //   1613: invokestatic valueOf : (J)Ljava/lang/Long;
    //   1616: putfield zzdj : Ljava/lang/Long;
    //   1619: goto -> 0
    //   1622: aload_0
    //   1623: aload_1
    //   1624: invokevirtual zzcyr : ()J
    //   1627: invokestatic valueOf : (J)Ljava/lang/Long;
    //   1630: putfield zzdi : Ljava/lang/Long;
    //   1633: goto -> 0
    //   1636: aload_0
    //   1637: aload_1
    //   1638: invokevirtual zzcyr : ()J
    //   1641: invokestatic valueOf : (J)Ljava/lang/Long;
    //   1644: putfield zzdh : Ljava/lang/Long;
    //   1647: goto -> 0
    //   1650: aload_0
    //   1651: aload_1
    //   1652: invokevirtual zzcyr : ()J
    //   1655: invokestatic valueOf : (J)Ljava/lang/Long;
    //   1658: putfield zzdg : Ljava/lang/Long;
    //   1661: goto -> 0
    //   1664: aload_0
    //   1665: aload_1
    //   1666: invokevirtual zzcyr : ()J
    //   1669: invokestatic valueOf : (J)Ljava/lang/Long;
    //   1672: putfield zzdf : Ljava/lang/Long;
    //   1675: goto -> 0
    //   1678: aload_0
    //   1679: aload_1
    //   1680: invokevirtual zzcyr : ()J
    //   1683: invokestatic valueOf : (J)Ljava/lang/Long;
    //   1686: putfield zzde : Ljava/lang/Long;
    //   1689: goto -> 0
    //   1692: aload_0
    //   1693: aload_1
    //   1694: invokevirtual zzcyr : ()J
    //   1697: invokestatic valueOf : (J)Ljava/lang/Long;
    //   1700: putfield zzdd : Ljava/lang/Long;
    //   1703: goto -> 0
    //   1706: aload_0
    //   1707: aload_1
    //   1708: invokevirtual zzcyr : ()J
    //   1711: invokestatic valueOf : (J)Ljava/lang/Long;
    //   1714: putfield zzdc : Ljava/lang/Long;
    //   1717: goto -> 0
    //   1720: aload_0
    //   1721: aload_1
    //   1722: invokevirtual zzcyr : ()J
    //   1725: invokestatic valueOf : (J)Ljava/lang/Long;
    //   1728: putfield zzdb : Ljava/lang/Long;
    //   1731: goto -> 0
    //   1734: aload_0
    //   1735: aload_1
    //   1736: invokevirtual readString : ()Ljava/lang/String;
    //   1739: putfield zzcu : Ljava/lang/String;
    //   1742: goto -> 0
    //   1745: aload_0
    //   1746: aload_1
    //   1747: invokevirtual readString : ()Ljava/lang/String;
    //   1750: putfield zzda : Ljava/lang/String;
    //   1753: goto -> 0
    //   1756: aload_0
    //   1757: areturn
    //   1758: astore #6
    //   1760: goto -> 1402
    //   1763: goto -> 1336
    // Exception table:
    //   from	to	target	type
    //   717	731	1758	java/lang/IllegalArgumentException
    //   836	850	1758	java/lang/IllegalArgumentException
    //   858	872	1758	java/lang/IllegalArgumentException
    //   1287	1293	1758	java/lang/IllegalArgumentException
    //   1341	1350	1758	java/lang/IllegalArgumentException
    //   1355	1366	1758	java/lang/IllegalArgumentException
    //   1368	1376	1758	java/lang/IllegalArgumentException
    //   1378	1387	1758	java/lang/IllegalArgumentException
    //   1389	1402	1758	java/lang/IllegalArgumentException
  }
  
  public final void zza(zzflk paramzzflk) {
    String str7 = this.zzda;
    if (str7 != null)
      paramzzflk.zzp(1, str7); 
    str7 = this.zzcu;
    if (str7 != null)
      paramzzflk.zzp(2, str7); 
    Long long_9 = this.zzdb;
    if (long_9 != null)
      paramzzflk.zzf(3, long_9.longValue()); 
    long_9 = this.zzdc;
    if (long_9 != null)
      paramzzflk.zzf(4, long_9.longValue()); 
    long_9 = this.zzdd;
    if (long_9 != null)
      paramzzflk.zzf(5, long_9.longValue()); 
    long_9 = this.zzde;
    if (long_9 != null)
      paramzzflk.zzf(6, long_9.longValue()); 
    long_9 = this.zzdf;
    if (long_9 != null)
      paramzzflk.zzf(7, long_9.longValue()); 
    long_9 = this.zzdg;
    if (long_9 != null)
      paramzzflk.zzf(8, long_9.longValue()); 
    long_9 = this.zzdh;
    if (long_9 != null)
      paramzzflk.zzf(9, long_9.longValue()); 
    long_9 = this.zzdi;
    if (long_9 != null)
      paramzzflk.zzf(10, long_9.longValue()); 
    long_9 = this.zzdj;
    if (long_9 != null)
      paramzzflk.zzf(11, long_9.longValue()); 
    long_9 = this.zzdk;
    if (long_9 != null)
      paramzzflk.zzf(12, long_9.longValue()); 
    String str6 = this.zzdl;
    if (str6 != null)
      paramzzflk.zzp(13, str6); 
    Long long_8 = this.zzdm;
    if (long_8 != null)
      paramzzflk.zzf(14, long_8.longValue()); 
    long_8 = this.zzdn;
    if (long_8 != null)
      paramzzflk.zzf(15, long_8.longValue()); 
    long_8 = this.zzdo;
    if (long_8 != null)
      paramzzflk.zzf(16, long_8.longValue()); 
    long_8 = this.zzdp;
    if (long_8 != null)
      paramzzflk.zzf(17, long_8.longValue()); 
    long_8 = this.zzdq;
    if (long_8 != null)
      paramzzflk.zzf(18, long_8.longValue()); 
    long_8 = this.zzdr;
    if (long_8 != null)
      paramzzflk.zzf(19, long_8.longValue()); 
    long_8 = this.zzds;
    if (long_8 != null)
      paramzzflk.zzf(20, long_8.longValue()); 
    long_8 = this.zzfb;
    if (long_8 != null)
      paramzzflk.zzf(21, long_8.longValue()); 
    long_8 = this.zzdt;
    if (long_8 != null)
      paramzzflk.zzf(22, long_8.longValue()); 
    long_8 = this.zzdu;
    if (long_8 != null)
      paramzzflk.zzf(23, long_8.longValue()); 
    String str5 = this.zzfc;
    if (str5 != null)
      paramzzflk.zzp(24, str5); 
    Long long_7 = this.zzfg;
    if (long_7 != null)
      paramzzflk.zzf(25, long_7.longValue()); 
    Integer integer3 = this.zzfd;
    if (integer3 != null)
      paramzzflk.zzad(26, integer3.intValue()); 
    String str4 = this.zzcv;
    if (str4 != null)
      paramzzflk.zzp(27, str4); 
    Boolean bool = this.zzfe;
    if (bool != null)
      paramzzflk.zzl(28, bool.booleanValue()); 
    String str3 = this.zzdv;
    if (str3 != null)
      paramzzflk.zzp(29, str3); 
    str3 = this.zzff;
    if (str3 != null)
      paramzzflk.zzp(30, str3); 
    Long long_6 = this.zzdw;
    if (long_6 != null)
      paramzzflk.zzf(31, long_6.longValue()); 
    long_6 = this.zzdx;
    if (long_6 != null)
      paramzzflk.zzf(32, long_6.longValue()); 
    long_6 = this.zzdy;
    if (long_6 != null)
      paramzzflk.zzf(33, long_6.longValue()); 
    String str2 = this.zzcx;
    if (str2 != null)
      paramzzflk.zzp(34, str2); 
    Long long_5 = this.zzdz;
    if (long_5 != null)
      paramzzflk.zzf(35, long_5.longValue()); 
    long_5 = this.zzea;
    if (long_5 != null)
      paramzzflk.zzf(36, long_5.longValue()); 
    long_5 = this.zzeb;
    if (long_5 != null)
      paramzzflk.zzf(37, long_5.longValue()); 
    zzbd zzbd1 = this.zzec;
    if (zzbd1 != null)
      paramzzflk.zza(38, zzbd1); 
    Long long_4 = this.zzed;
    if (long_4 != null)
      paramzzflk.zzf(39, long_4.longValue()); 
    long_4 = this.zzee;
    if (long_4 != null)
      paramzzflk.zzf(40, long_4.longValue()); 
    long_4 = this.zzef;
    if (long_4 != null)
      paramzzflk.zzf(41, long_4.longValue()); 
    long_4 = this.zzeg;
    if (long_4 != null)
      paramzzflk.zzf(42, long_4.longValue()); 
    zzbb[] arrayOfZzbb = this.zzes;
    if (arrayOfZzbb != null && arrayOfZzbb.length > 0) {
      int i = 0;
      while (true) {
        arrayOfZzbb = this.zzes;
        if (i < arrayOfZzbb.length) {
          zzbb zzbb2 = arrayOfZzbb[i];
          if (zzbb2 != null)
            paramzzflk.zza(43, zzbb2); 
          i++;
          continue;
        } 
        break;
      } 
    } 
    Long long_3 = this.zzeh;
    if (long_3 != null)
      paramzzflk.zzf(44, long_3.longValue()); 
    long_3 = this.zzei;
    if (long_3 != null)
      paramzzflk.zzf(45, long_3.longValue()); 
    String str1 = this.zzcy;
    if (str1 != null)
      paramzzflk.zzp(46, str1); 
    str1 = this.zzcz;
    if (str1 != null)
      paramzzflk.zzp(47, str1); 
    Integer integer2 = this.zzej;
    if (integer2 != null)
      paramzzflk.zzad(48, integer2.intValue()); 
    integer2 = this.zzek;
    if (integer2 != null)
      paramzzflk.zzad(49, integer2.intValue()); 
    zzbb zzbb1 = this.zzer;
    if (zzbb1 != null)
      paramzzflk.zza(50, zzbb1); 
    Long long_2 = this.zzel;
    if (long_2 != null)
      paramzzflk.zzf(51, long_2.longValue()); 
    long_2 = this.zzem;
    if (long_2 != null)
      paramzzflk.zzf(52, long_2.longValue()); 
    long_2 = this.zzen;
    if (long_2 != null)
      paramzzflk.zzf(53, long_2.longValue()); 
    long_2 = this.zzeo;
    if (long_2 != null)
      paramzzflk.zzf(54, long_2.longValue()); 
    long_2 = this.zzep;
    if (long_2 != null)
      paramzzflk.zzf(55, long_2.longValue()); 
    Integer integer1 = this.zzeq;
    if (integer1 != null)
      paramzzflk.zzad(56, integer1.intValue()); 
    zzbc zzbc1 = this.zzet;
    if (zzbc1 != null)
      paramzzflk.zza(57, zzbc1); 
    Long long_1 = this.zzeu;
    if (long_1 != null)
      paramzzflk.zzf(58, long_1.longValue()); 
    long_1 = this.zzev;
    if (long_1 != null)
      paramzzflk.zzf(59, long_1.longValue()); 
    long_1 = this.zzew;
    if (long_1 != null)
      paramzzflk.zzf(60, long_1.longValue()); 
    long_1 = this.zzex;
    if (long_1 != null)
      paramzzflk.zzf(61, long_1.longValue()); 
    long_1 = this.zzey;
    if (long_1 != null)
      paramzzflk.zzf(62, long_1.longValue()); 
    long_1 = this.zzez;
    if (long_1 != null)
      paramzzflk.zzf(63, long_1.longValue()); 
    long_1 = this.zzfa;
    if (long_1 != null)
      paramzzflk.zzf(64, long_1.longValue()); 
    zzbf zzbf1 = this.zzfh;
    if (zzbf1 != null)
      paramzzflk.zza(201, zzbf1); 
    super.zza(paramzzflk);
  }
  
  protected final int zzq() {
    int j = super.zzq();
    String str7 = this.zzda;
    int i = j;
    if (str7 != null)
      i = j + zzflk.zzq(1, str7); 
    str7 = this.zzcu;
    j = i;
    if (str7 != null)
      j = i + zzflk.zzq(2, str7); 
    Long long_9 = this.zzdb;
    i = j;
    if (long_9 != null)
      i = j + zzflk.zzc(3, long_9.longValue()); 
    long_9 = this.zzdc;
    j = i;
    if (long_9 != null)
      j = i + zzflk.zzc(4, long_9.longValue()); 
    long_9 = this.zzdd;
    i = j;
    if (long_9 != null)
      i = j + zzflk.zzc(5, long_9.longValue()); 
    long_9 = this.zzde;
    j = i;
    if (long_9 != null)
      j = i + zzflk.zzc(6, long_9.longValue()); 
    long_9 = this.zzdf;
    i = j;
    if (long_9 != null)
      i = j + zzflk.zzc(7, long_9.longValue()); 
    long_9 = this.zzdg;
    j = i;
    if (long_9 != null)
      j = i + zzflk.zzc(8, long_9.longValue()); 
    long_9 = this.zzdh;
    i = j;
    if (long_9 != null)
      i = j + zzflk.zzc(9, long_9.longValue()); 
    long_9 = this.zzdi;
    j = i;
    if (long_9 != null)
      j = i + zzflk.zzc(10, long_9.longValue()); 
    long_9 = this.zzdj;
    i = j;
    if (long_9 != null)
      i = j + zzflk.zzc(11, long_9.longValue()); 
    long_9 = this.zzdk;
    j = i;
    if (long_9 != null)
      j = i + zzflk.zzc(12, long_9.longValue()); 
    String str6 = this.zzdl;
    i = j;
    if (str6 != null)
      i = j + zzflk.zzq(13, str6); 
    Long long_8 = this.zzdm;
    j = i;
    if (long_8 != null)
      j = i + zzflk.zzc(14, long_8.longValue()); 
    long_8 = this.zzdn;
    i = j;
    if (long_8 != null)
      i = j + zzflk.zzc(15, long_8.longValue()); 
    long_8 = this.zzdo;
    j = i;
    if (long_8 != null)
      j = i + zzflk.zzc(16, long_8.longValue()); 
    long_8 = this.zzdp;
    i = j;
    if (long_8 != null)
      i = j + zzflk.zzc(17, long_8.longValue()); 
    long_8 = this.zzdq;
    j = i;
    if (long_8 != null)
      j = i + zzflk.zzc(18, long_8.longValue()); 
    long_8 = this.zzdr;
    i = j;
    if (long_8 != null)
      i = j + zzflk.zzc(19, long_8.longValue()); 
    long_8 = this.zzds;
    j = i;
    if (long_8 != null)
      j = i + zzflk.zzc(20, long_8.longValue()); 
    long_8 = this.zzfb;
    i = j;
    if (long_8 != null)
      i = j + zzflk.zzc(21, long_8.longValue()); 
    long_8 = this.zzdt;
    j = i;
    if (long_8 != null)
      j = i + zzflk.zzc(22, long_8.longValue()); 
    long_8 = this.zzdu;
    i = j;
    if (long_8 != null)
      i = j + zzflk.zzc(23, long_8.longValue()); 
    String str5 = this.zzfc;
    j = i;
    if (str5 != null)
      j = i + zzflk.zzq(24, str5); 
    Long long_7 = this.zzfg;
    i = j;
    if (long_7 != null)
      i = j + zzflk.zzc(25, long_7.longValue()); 
    Integer integer3 = this.zzfd;
    j = i;
    if (integer3 != null)
      j = i + zzflk.zzag(26, integer3.intValue()); 
    String str4 = this.zzcv;
    i = j;
    if (str4 != null)
      i = j + zzflk.zzq(27, str4); 
    Boolean bool = this.zzfe;
    j = i;
    if (bool != null) {
      bool.booleanValue();
      j = i + zzflk.zzlw(28) + 1;
    } 
    String str3 = this.zzdv;
    i = j;
    if (str3 != null)
      i = j + zzflk.zzq(29, str3); 
    str3 = this.zzff;
    j = i;
    if (str3 != null)
      j = i + zzflk.zzq(30, str3); 
    Long long_6 = this.zzdw;
    i = j;
    if (long_6 != null)
      i = j + zzflk.zzc(31, long_6.longValue()); 
    long_6 = this.zzdx;
    j = i;
    if (long_6 != null)
      j = i + zzflk.zzc(32, long_6.longValue()); 
    long_6 = this.zzdy;
    i = j;
    if (long_6 != null)
      i = j + zzflk.zzc(33, long_6.longValue()); 
    String str2 = this.zzcx;
    j = i;
    if (str2 != null)
      j = i + zzflk.zzq(34, str2); 
    Long long_5 = this.zzdz;
    i = j;
    if (long_5 != null)
      i = j + zzflk.zzc(35, long_5.longValue()); 
    long_5 = this.zzea;
    j = i;
    if (long_5 != null)
      j = i + zzflk.zzc(36, long_5.longValue()); 
    long_5 = this.zzeb;
    i = j;
    if (long_5 != null)
      i = j + zzflk.zzc(37, long_5.longValue()); 
    zzbd zzbd1 = this.zzec;
    j = i;
    if (zzbd1 != null)
      j = i + zzflk.zzb(38, zzbd1); 
    Long long_4 = this.zzed;
    i = j;
    if (long_4 != null)
      i = j + zzflk.zzc(39, long_4.longValue()); 
    long_4 = this.zzee;
    j = i;
    if (long_4 != null)
      j = i + zzflk.zzc(40, long_4.longValue()); 
    long_4 = this.zzef;
    int k = j;
    if (long_4 != null)
      k = j + zzflk.zzc(41, long_4.longValue()); 
    long_4 = this.zzeg;
    i = k;
    if (long_4 != null)
      i = k + zzflk.zzc(42, long_4.longValue()); 
    zzbb[] arrayOfZzbb = this.zzes;
    j = i;
    if (arrayOfZzbb != null) {
      j = i;
      if (arrayOfZzbb.length > 0) {
        k = 0;
        while (true) {
          arrayOfZzbb = this.zzes;
          j = i;
          if (k < arrayOfZzbb.length) {
            zzbb zzbb2 = arrayOfZzbb[k];
            j = i;
            if (zzbb2 != null)
              j = i + zzflk.zzb(43, zzbb2); 
            k++;
            i = j;
            continue;
          } 
          break;
        } 
      } 
    } 
    Long long_3 = this.zzeh;
    i = j;
    if (long_3 != null)
      i = j + zzflk.zzc(44, long_3.longValue()); 
    long_3 = this.zzei;
    j = i;
    if (long_3 != null)
      j = i + zzflk.zzc(45, long_3.longValue()); 
    String str1 = this.zzcy;
    i = j;
    if (str1 != null)
      i = j + zzflk.zzq(46, str1); 
    str1 = this.zzcz;
    j = i;
    if (str1 != null)
      j = i + zzflk.zzq(47, str1); 
    Integer integer2 = this.zzej;
    i = j;
    if (integer2 != null)
      i = j + zzflk.zzag(48, integer2.intValue()); 
    integer2 = this.zzek;
    j = i;
    if (integer2 != null)
      j = i + zzflk.zzag(49, integer2.intValue()); 
    zzbb zzbb1 = this.zzer;
    i = j;
    if (zzbb1 != null)
      i = j + zzflk.zzb(50, zzbb1); 
    Long long_2 = this.zzel;
    j = i;
    if (long_2 != null)
      j = i + zzflk.zzc(51, long_2.longValue()); 
    long_2 = this.zzem;
    i = j;
    if (long_2 != null)
      i = j + zzflk.zzc(52, long_2.longValue()); 
    long_2 = this.zzen;
    j = i;
    if (long_2 != null)
      j = i + zzflk.zzc(53, long_2.longValue()); 
    long_2 = this.zzeo;
    i = j;
    if (long_2 != null)
      i = j + zzflk.zzc(54, long_2.longValue()); 
    long_2 = this.zzep;
    j = i;
    if (long_2 != null)
      j = i + zzflk.zzc(55, long_2.longValue()); 
    Integer integer1 = this.zzeq;
    i = j;
    if (integer1 != null)
      i = j + zzflk.zzag(56, integer1.intValue()); 
    zzbc zzbc1 = this.zzet;
    j = i;
    if (zzbc1 != null)
      j = i + zzflk.zzb(57, zzbc1); 
    Long long_1 = this.zzeu;
    i = j;
    if (long_1 != null)
      i = j + zzflk.zzc(58, long_1.longValue()); 
    long_1 = this.zzev;
    j = i;
    if (long_1 != null)
      j = i + zzflk.zzc(59, long_1.longValue()); 
    long_1 = this.zzew;
    i = j;
    if (long_1 != null)
      i = j + zzflk.zzc(60, long_1.longValue()); 
    long_1 = this.zzex;
    j = i;
    if (long_1 != null)
      j = i + zzflk.zzc(61, long_1.longValue()); 
    long_1 = this.zzey;
    i = j;
    if (long_1 != null)
      i = j + zzflk.zzc(62, long_1.longValue()); 
    long_1 = this.zzez;
    j = i;
    if (long_1 != null)
      j = i + zzflk.zzc(63, long_1.longValue()); 
    long_1 = this.zzfa;
    i = j;
    if (long_1 != null)
      i = j + zzflk.zzc(64, long_1.longValue()); 
    zzbf zzbf1 = this.zzfh;
    j = i;
    if (zzbf1 != null)
      j = i + zzflk.zzb(201, zzbf1); 
    return j;
  }
}


/* Location:              /home/egaebel/Programs/sony-headphones-hack/base-dex2jar.jar!/com/google/android/gms/internal/zzba.class
 * Java compiler version: 6 (50.0)
 * JD-Core Version:       1.1.3
 */