package com.google.android.gms.internal;

import com.google.android.gms.common.internal.Hide;

@Hide
public final class zzbhg {
  private static zzbhi zzgih;
  
  @Hide
  public static zzbhi zzanc() {
    // Byte code:
    //   0: ldc com/google/android/gms/internal/zzbhg
    //   2: monitorenter
    //   3: getstatic com/google/android/gms/internal/zzbhg.zzgih : Lcom/google/android/gms/internal/zzbhi;
    //   6: ifnonnull -> 19
    //   9: new com/google/android/gms/internal/zzbhh
    //   12: dup
    //   13: invokespecial <init> : ()V
    //   16: putstatic com/google/android/gms/internal/zzbhg.zzgih : Lcom/google/android/gms/internal/zzbhi;
    //   19: getstatic com/google/android/gms/internal/zzbhg.zzgih : Lcom/google/android/gms/internal/zzbhi;
    //   22: astore_0
    //   23: ldc com/google/android/gms/internal/zzbhg
    //   25: monitorexit
    //   26: aload_0
    //   27: areturn
    //   28: astore_0
    //   29: ldc com/google/android/gms/internal/zzbhg
    //   31: monitorexit
    //   32: aload_0
    //   33: athrow
    // Exception table:
    //   from	to	target	type
    //   3	19	28	finally
    //   19	23	28	finally
  }
}


/* Location:              /home/egaebel/Programs/sony-headphones-hack/base-dex2jar.jar!/com/google/android/gms/internal/zzbhg.class
 * Java compiler version: 6 (50.0)
 * JD-Core Version:       1.1.3
 */