package com.google.android.gms.internal;

import android.text.TextUtils;
import androidx.b.a;
import com.google.android.gms.common.internal.zzbq;
import java.math.BigDecimal;
import java.util.ArrayList;
import java.util.Arrays;
import java.util.HashSet;
import java.util.List;
import java.util.Locale;
import java.util.regex.Pattern;
import java.util.regex.PatternSyntaxException;

final class zzcih extends zzcli {
  zzcih(zzckj paramzzckj) {
    super(paramzzckj);
  }
  
  private final Boolean zza(double paramDouble, zzcnu paramzzcnu) {
    try {
      return zza(new BigDecimal(paramDouble), paramzzcnu, Math.ulp(paramDouble));
    } catch (NumberFormatException numberFormatException) {
      return null;
    } 
  }
  
  private final Boolean zza(long paramLong, zzcnu paramzzcnu) {
    try {
      return zza(new BigDecimal(paramLong), paramzzcnu, 0.0D);
    } catch (NumberFormatException numberFormatException) {
      return null;
    } 
  }
  
  private final Boolean zza(zzcns paramzzcns, String paramString, zzcoc[] paramArrayOfzzcoc, long paramLong) {
    if (paramzzcns.zzjtb != null) {
      Boolean bool = zza(paramLong, paramzzcns.zzjtb);
      if (bool == null)
        return null; 
      if (!bool.booleanValue())
        return Boolean.valueOf(false); 
    } 
    HashSet<String> hashSet = new HashSet();
    for (zzcnt zzcnt : paramzzcns.zzjsz) {
      if (TextUtils.isEmpty(zzcnt.zzjtg)) {
        zzayp().zzbaw().zzj("null or empty param name in filter. event", zzayk().zzjp(paramString));
        return null;
      } 
      hashSet.add(zzcnt.zzjtg);
    } 
    a<String, String> a = new a();
    null = paramArrayOfzzcoc.length;
    for (null = 0; null < null; null++) {
      zzcoc zzcoc1 = paramArrayOfzzcoc[null];
      if (hashSet.contains(zzcoc1.name)) {
        Long long_;
        String str1;
        String str2;
        if (zzcoc1.zzjum != null) {
          str2 = zzcoc1.name;
          long_ = zzcoc1.zzjum;
        } else {
          Double double_;
          if (((zzcoc)long_).zzjsl != null) {
            str2 = ((zzcoc)long_).name;
            double_ = ((zzcoc)long_).zzjsl;
          } else if (((zzcoc)double_).zzgim != null) {
            str2 = ((zzcoc)double_).name;
            str1 = ((zzcoc)double_).zzgim;
          } else {
            zzayp().zzbaw().zze("Unknown value for param. event, param", zzayk().zzjp(paramString), zzayk().zzjq(((zzcoc)str1).name));
            return null;
          } 
        } 
        a.put(str2, str1);
      } 
    } 
    for (zzcnt zzcnt : paramzzcns.zzjsz) {
      Boolean bool;
      boolean bool1 = Boolean.TRUE.equals(zzcnt.zzjtf);
      String str = zzcnt.zzjtg;
      if (TextUtils.isEmpty(str)) {
        zzayp().zzbaw().zzj("Event has empty param name. event", zzayk().zzjp(paramString));
        return null;
      } 
      Long long_ = (Long)a.get(str);
      if (long_ instanceof Long) {
        if (zzcnt.zzjte == null) {
          zzayp().zzbaw().zze("No number filter for long param. event, param", zzayk().zzjp(paramString), zzayk().zzjq(str));
          return null;
        } 
        bool = zza(((Long)long_).longValue(), zzcnt.zzjte);
        if (bool == null)
          return null; 
        if ((true ^ bool.booleanValue() ^ bool1) != 0)
          return Boolean.valueOf(false); 
      } else if (long_ instanceof Double) {
        if (((zzcnt)bool).zzjte == null) {
          zzayp().zzbaw().zze("No number filter for double param. event, param", zzayk().zzjp(paramString), zzayk().zzjq(str));
          return null;
        } 
        bool = zza(((Double)long_).doubleValue(), ((zzcnt)bool).zzjte);
        if (bool == null)
          return null; 
        if ((true ^ bool.booleanValue() ^ bool1) != 0)
          return Boolean.valueOf(false); 
      } else {
        String str1;
        if (long_ instanceof String) {
          if (((zzcnt)bool).zzjtd != null) {
            bool = zza((String)long_, ((zzcnt)bool).zzjtd);
          } else if (((zzcnt)bool).zzjte != null) {
            str1 = (String)long_;
            if (zzcno.zzkr(str1)) {
              bool = zza(str1, ((zzcnt)bool).zzjte);
            } else {
              zzayp().zzbaw().zze("Invalid param value for number filter. event, param", zzayk().zzjp(paramString), zzayk().zzjq(str));
              return null;
            } 
          } else {
            zzayp().zzbaw().zze("No filter for String param. event, param", zzayk().zzjp(paramString), zzayk().zzjq(str));
            return null;
          } 
          if (bool == null)
            return null; 
          if ((true ^ bool.booleanValue() ^ bool1) != 0)
            return Boolean.valueOf(false); 
        } else {
          if (str1 == null) {
            zzayp().zzbba().zze("Missing param for filter. event, param", zzayk().zzjp(paramString), zzayk().zzjq(str));
            return Boolean.valueOf(false);
          } 
          zzayp().zzbaw().zze("Unknown param type. event, param", zzayk().zzjp(paramString), zzayk().zzjq(str));
          return null;
        } 
      } 
    } 
    return Boolean.valueOf(true);
  }
  
  private static Boolean zza(Boolean paramBoolean, boolean paramBoolean1) {
    return (paramBoolean == null) ? null : Boolean.valueOf(paramBoolean.booleanValue() ^ paramBoolean1);
  }
  
  private final Boolean zza(String paramString1, int paramInt, boolean paramBoolean, String paramString2, List<String> paramList, String paramString3) {
    if (paramString1 == null)
      return null; 
    if (paramInt == 6) {
      if (paramList == null || paramList.size() == 0)
        return null; 
    } else if (paramString2 == null) {
      return null;
    } 
    String str = paramString1;
    if (!paramBoolean)
      if (paramInt == 1) {
        str = paramString1;
      } else {
        str = paramString1.toUpperCase(Locale.ENGLISH);
      }  
    switch (paramInt) {
      default:
        return null;
      case 6:
        paramBoolean = paramList.contains(str);
        return Boolean.valueOf(paramBoolean);
      case 5:
        paramBoolean = str.equals(paramString2);
        return Boolean.valueOf(paramBoolean);
      case 4:
        paramBoolean = str.contains(paramString2);
        return Boolean.valueOf(paramBoolean);
      case 3:
        paramBoolean = str.endsWith(paramString2);
        return Boolean.valueOf(paramBoolean);
      case 2:
        paramBoolean = str.startsWith(paramString2);
        return Boolean.valueOf(paramBoolean);
      case 1:
        break;
    } 
    if (paramBoolean) {
      paramInt = 0;
    } else {
      paramInt = 66;
    } 
    try {
      paramBoolean = Pattern.compile(paramString3, paramInt).matcher(str).matches();
      return Boolean.valueOf(paramBoolean);
    } catch (PatternSyntaxException patternSyntaxException) {
      zzayp().zzbaw().zzj("Invalid regular expression in REGEXP audience filter. expression", paramString3);
      return null;
    } 
  }
  
  private final Boolean zza(String paramString, zzcnu paramzzcnu) {
    if (!zzcno.zzkr(paramString))
      return null; 
    try {
      return zza(new BigDecimal(paramString), paramzzcnu, 0.0D);
    } catch (NumberFormatException numberFormatException) {
      return null;
    } 
  }
  
  private final Boolean zza(String paramString, zzcnw paramzzcnw) {
    zzbq.checkNotNull(paramzzcnw);
    if (paramString == null)
      return null; 
    if (paramzzcnw.zzjtp != null) {
      List<String> list;
      boolean bool;
      String str1;
      String str2;
      if (paramzzcnw.zzjtp.intValue() == 0)
        return null; 
      if (paramzzcnw.zzjtp.intValue() == 6) {
        if (paramzzcnw.zzjts == null || paramzzcnw.zzjts.length == 0)
          return null; 
      } else if (paramzzcnw.zzjtq == null) {
        return null;
      } 
      int j = paramzzcnw.zzjtp.intValue();
      Boolean bool1 = paramzzcnw.zzjtr;
      int i = 0;
      if (bool1 != null && paramzzcnw.zzjtr.booleanValue()) {
        bool = true;
      } else {
        bool = false;
      } 
      if (bool || j == 1 || j == 6) {
        str1 = paramzzcnw.zzjtq;
      } else {
        str1 = paramzzcnw.zzjtq.toUpperCase(Locale.ENGLISH);
      } 
      if (paramzzcnw.zzjts == null) {
        paramzzcnw = null;
      } else {
        str2 = (String)paramzzcnw.zzjts;
        if (bool) {
          list = Arrays.asList((String[])str2);
        } else {
          list = new ArrayList();
          int k = str2.length;
          while (i < k) {
            list.add(str2[i].toUpperCase(Locale.ENGLISH));
            i++;
          } 
        } 
      } 
      if (j == 1) {
        str2 = str1;
      } else {
        str2 = null;
      } 
      return zza(paramString, j, bool, str1, list, str2);
    } 
    return null;
  }
  
  private static Boolean zza(BigDecimal paramBigDecimal, zzcnu paramzzcnu, double paramDouble) {
    // Byte code:
    //   0: aload_1
    //   1: invokestatic checkNotNull : (Ljava/lang/Object;)Ljava/lang/Object;
    //   4: pop
    //   5: aload_1
    //   6: getfield zzjth : Ljava/lang/Integer;
    //   9: ifnull -> 421
    //   12: aload_1
    //   13: getfield zzjth : Ljava/lang/Integer;
    //   16: invokevirtual intValue : ()I
    //   19: ifne -> 24
    //   22: aconst_null
    //   23: areturn
    //   24: aload_1
    //   25: getfield zzjth : Ljava/lang/Integer;
    //   28: invokevirtual intValue : ()I
    //   31: iconst_4
    //   32: if_icmpne -> 51
    //   35: aload_1
    //   36: getfield zzjtk : Ljava/lang/String;
    //   39: ifnull -> 49
    //   42: aload_1
    //   43: getfield zzjtl : Ljava/lang/String;
    //   46: ifnonnull -> 60
    //   49: aconst_null
    //   50: areturn
    //   51: aload_1
    //   52: getfield zzjtj : Ljava/lang/String;
    //   55: ifnonnull -> 60
    //   58: aconst_null
    //   59: areturn
    //   60: aload_1
    //   61: getfield zzjth : Ljava/lang/Integer;
    //   64: invokevirtual intValue : ()I
    //   67: istore #4
    //   69: aload_1
    //   70: getfield zzjth : Ljava/lang/Integer;
    //   73: invokevirtual intValue : ()I
    //   76: iconst_4
    //   77: if_icmpne -> 139
    //   80: aload_1
    //   81: getfield zzjtk : Ljava/lang/String;
    //   84: invokestatic zzkr : (Ljava/lang/String;)Z
    //   87: ifeq -> 137
    //   90: aload_1
    //   91: getfield zzjtl : Ljava/lang/String;
    //   94: invokestatic zzkr : (Ljava/lang/String;)Z
    //   97: ifne -> 102
    //   100: aconst_null
    //   101: areturn
    //   102: new java/math/BigDecimal
    //   105: dup
    //   106: aload_1
    //   107: getfield zzjtk : Ljava/lang/String;
    //   110: invokespecial <init> : (Ljava/lang/String;)V
    //   113: astore #10
    //   115: new java/math/BigDecimal
    //   118: dup
    //   119: aload_1
    //   120: getfield zzjtl : Ljava/lang/String;
    //   123: invokespecial <init> : (Ljava/lang/String;)V
    //   126: astore #11
    //   128: aload #10
    //   130: astore_1
    //   131: aconst_null
    //   132: astore #10
    //   134: goto -> 169
    //   137: aconst_null
    //   138: areturn
    //   139: aload_1
    //   140: getfield zzjtj : Ljava/lang/String;
    //   143: invokestatic zzkr : (Ljava/lang/String;)Z
    //   146: ifne -> 151
    //   149: aconst_null
    //   150: areturn
    //   151: new java/math/BigDecimal
    //   154: dup
    //   155: aload_1
    //   156: getfield zzjtj : Ljava/lang/String;
    //   159: invokespecial <init> : (Ljava/lang/String;)V
    //   162: astore #10
    //   164: aconst_null
    //   165: astore_1
    //   166: aload_1
    //   167: astore #11
    //   169: iload #4
    //   171: iconst_4
    //   172: if_icmpne -> 181
    //   175: aload_1
    //   176: ifnonnull -> 186
    //   179: aconst_null
    //   180: areturn
    //   181: aload #10
    //   183: ifnull -> 421
    //   186: iconst_0
    //   187: istore #7
    //   189: iconst_0
    //   190: istore #5
    //   192: iconst_0
    //   193: istore #8
    //   195: iconst_0
    //   196: istore #9
    //   198: iconst_0
    //   199: istore #6
    //   201: iload #4
    //   203: tableswitch default -> 232, 1 -> 398, 2 -> 375, 3 -> 270, 4 -> 234
    //   232: aconst_null
    //   233: areturn
    //   234: iload #6
    //   236: istore #5
    //   238: aload_0
    //   239: aload_1
    //   240: invokevirtual compareTo : (Ljava/math/BigDecimal;)I
    //   243: iconst_m1
    //   244: if_icmpeq -> 264
    //   247: iload #6
    //   249: istore #5
    //   251: aload_0
    //   252: aload #11
    //   254: invokevirtual compareTo : (Ljava/math/BigDecimal;)I
    //   257: iconst_1
    //   258: if_icmpeq -> 264
    //   261: iconst_1
    //   262: istore #5
    //   264: iload #5
    //   266: invokestatic valueOf : (Z)Ljava/lang/Boolean;
    //   269: areturn
    //   270: dload_2
    //   271: dconst_0
    //   272: dcmpl
    //   273: ifeq -> 357
    //   276: iload #7
    //   278: istore #5
    //   280: aload_0
    //   281: aload #10
    //   283: new java/math/BigDecimal
    //   286: dup
    //   287: dload_2
    //   288: invokespecial <init> : (D)V
    //   291: new java/math/BigDecimal
    //   294: dup
    //   295: iconst_2
    //   296: invokespecial <init> : (I)V
    //   299: invokevirtual multiply : (Ljava/math/BigDecimal;)Ljava/math/BigDecimal;
    //   302: invokevirtual subtract : (Ljava/math/BigDecimal;)Ljava/math/BigDecimal;
    //   305: invokevirtual compareTo : (Ljava/math/BigDecimal;)I
    //   308: iconst_1
    //   309: if_icmpne -> 351
    //   312: iload #7
    //   314: istore #5
    //   316: aload_0
    //   317: aload #10
    //   319: new java/math/BigDecimal
    //   322: dup
    //   323: dload_2
    //   324: invokespecial <init> : (D)V
    //   327: new java/math/BigDecimal
    //   330: dup
    //   331: iconst_2
    //   332: invokespecial <init> : (I)V
    //   335: invokevirtual multiply : (Ljava/math/BigDecimal;)Ljava/math/BigDecimal;
    //   338: invokevirtual add : (Ljava/math/BigDecimal;)Ljava/math/BigDecimal;
    //   341: invokevirtual compareTo : (Ljava/math/BigDecimal;)I
    //   344: iconst_m1
    //   345: if_icmpne -> 351
    //   348: iconst_1
    //   349: istore #5
    //   351: iload #5
    //   353: invokestatic valueOf : (Z)Ljava/lang/Boolean;
    //   356: areturn
    //   357: aload_0
    //   358: aload #10
    //   360: invokevirtual compareTo : (Ljava/math/BigDecimal;)I
    //   363: ifne -> 369
    //   366: iconst_1
    //   367: istore #5
    //   369: iload #5
    //   371: invokestatic valueOf : (Z)Ljava/lang/Boolean;
    //   374: areturn
    //   375: iload #8
    //   377: istore #5
    //   379: aload_0
    //   380: aload #10
    //   382: invokevirtual compareTo : (Ljava/math/BigDecimal;)I
    //   385: iconst_1
    //   386: if_icmpne -> 392
    //   389: iconst_1
    //   390: istore #5
    //   392: iload #5
    //   394: invokestatic valueOf : (Z)Ljava/lang/Boolean;
    //   397: areturn
    //   398: iload #9
    //   400: istore #5
    //   402: aload_0
    //   403: aload #10
    //   405: invokevirtual compareTo : (Ljava/math/BigDecimal;)I
    //   408: iconst_m1
    //   409: if_icmpne -> 415
    //   412: iconst_1
    //   413: istore #5
    //   415: iload #5
    //   417: invokestatic valueOf : (Z)Ljava/lang/Boolean;
    //   420: areturn
    //   421: aconst_null
    //   422: areturn
    //   423: astore_0
    //   424: aconst_null
    //   425: areturn
    //   426: astore_0
    //   427: aconst_null
    //   428: areturn
    // Exception table:
    //   from	to	target	type
    //   102	128	423	java/lang/NumberFormatException
    //   151	164	426	java/lang/NumberFormatException
  }
  
  final zzcoa[] zza(String paramString, zzcob[] paramArrayOfzzcob, zzcog[] paramArrayOfzzcog) {
    // Byte code:
    //   0: aload_1
    //   1: astore #18
    //   3: aload_2
    //   4: astore #30
    //   6: aload_3
    //   7: astore #17
    //   9: aload_1
    //   10: invokestatic zzgv : (Ljava/lang/String;)Ljava/lang/String;
    //   13: pop
    //   14: new java/util/HashSet
    //   17: dup
    //   18: invokespecial <init> : ()V
    //   21: astore #22
    //   23: new androidx/b/a
    //   26: dup
    //   27: invokespecial <init> : ()V
    //   30: astore #23
    //   32: new androidx/b/a
    //   35: dup
    //   36: invokespecial <init> : ()V
    //   39: astore #21
    //   41: new androidx/b/a
    //   44: dup
    //   45: invokespecial <init> : ()V
    //   48: astore #19
    //   50: aload_0
    //   51: invokevirtual zzayj : ()Lcom/google/android/gms/internal/zzcil;
    //   54: aload #18
    //   56: invokevirtual zzjm : (Ljava/lang/String;)Ljava/util/Map;
    //   59: astore #15
    //   61: aload #19
    //   63: astore #20
    //   65: aload #15
    //   67: ifnull -> 394
    //   70: aload #15
    //   72: invokeinterface keySet : ()Ljava/util/Set;
    //   77: invokeinterface iterator : ()Ljava/util/Iterator;
    //   82: astore #16
    //   84: aload #19
    //   86: astore #20
    //   88: aload #16
    //   90: invokeinterface hasNext : ()Z
    //   95: ifeq -> 394
    //   98: aload #16
    //   100: invokeinterface next : ()Ljava/lang/Object;
    //   105: checkcast java/lang/Integer
    //   108: invokevirtual intValue : ()I
    //   111: istore #5
    //   113: aload #15
    //   115: iload #5
    //   117: invokestatic valueOf : (I)Ljava/lang/Integer;
    //   120: invokeinterface get : (Ljava/lang/Object;)Ljava/lang/Object;
    //   125: checkcast com/google/android/gms/internal/zzcof
    //   128: astore #26
    //   130: aload #21
    //   132: iload #5
    //   134: invokestatic valueOf : (I)Ljava/lang/Integer;
    //   137: invokeinterface get : (Ljava/lang/Object;)Ljava/lang/Object;
    //   142: checkcast java/util/BitSet
    //   145: astore #25
    //   147: aload #19
    //   149: iload #5
    //   151: invokestatic valueOf : (I)Ljava/lang/Integer;
    //   154: invokeinterface get : (Ljava/lang/Object;)Ljava/lang/Object;
    //   159: checkcast java/util/BitSet
    //   162: astore #24
    //   164: aload #25
    //   166: astore #20
    //   168: aload #25
    //   170: ifnonnull -> 221
    //   173: new java/util/BitSet
    //   176: dup
    //   177: invokespecial <init> : ()V
    //   180: astore #20
    //   182: aload #21
    //   184: iload #5
    //   186: invokestatic valueOf : (I)Ljava/lang/Integer;
    //   189: aload #20
    //   191: invokeinterface put : (Ljava/lang/Object;Ljava/lang/Object;)Ljava/lang/Object;
    //   196: pop
    //   197: new java/util/BitSet
    //   200: dup
    //   201: invokespecial <init> : ()V
    //   204: astore #24
    //   206: aload #19
    //   208: iload #5
    //   210: invokestatic valueOf : (I)Ljava/lang/Integer;
    //   213: aload #24
    //   215: invokeinterface put : (Ljava/lang/Object;Ljava/lang/Object;)Ljava/lang/Object;
    //   220: pop
    //   221: iconst_0
    //   222: istore #4
    //   224: iload #4
    //   226: aload #26
    //   228: getfield zzjvo : [J
    //   231: arraylength
    //   232: bipush #6
    //   234: ishl
    //   235: if_icmpge -> 313
    //   238: aload #26
    //   240: getfield zzjvo : [J
    //   243: iload #4
    //   245: invokestatic zza : ([JI)Z
    //   248: ifeq -> 304
    //   251: aload_0
    //   252: invokevirtual zzayp : ()Lcom/google/android/gms/internal/zzcjj;
    //   255: invokevirtual zzbba : ()Lcom/google/android/gms/internal/zzcjl;
    //   258: ldc_w 'Filter already evaluated. audience ID, filter ID'
    //   261: iload #5
    //   263: invokestatic valueOf : (I)Ljava/lang/Integer;
    //   266: iload #4
    //   268: invokestatic valueOf : (I)Ljava/lang/Integer;
    //   271: invokevirtual zze : (Ljava/lang/String;Ljava/lang/Object;Ljava/lang/Object;)V
    //   274: aload #24
    //   276: iload #4
    //   278: invokevirtual set : (I)V
    //   281: aload #26
    //   283: getfield zzjvp : [J
    //   286: iload #4
    //   288: invokestatic zza : ([JI)Z
    //   291: ifeq -> 304
    //   294: aload #20
    //   296: iload #4
    //   298: invokevirtual set : (I)V
    //   301: goto -> 304
    //   304: iload #4
    //   306: iconst_1
    //   307: iadd
    //   308: istore #4
    //   310: goto -> 224
    //   313: new com/google/android/gms/internal/zzcoa
    //   316: dup
    //   317: invokespecial <init> : ()V
    //   320: astore #25
    //   322: aload #23
    //   324: iload #5
    //   326: invokestatic valueOf : (I)Ljava/lang/Integer;
    //   329: aload #25
    //   331: invokeinterface put : (Ljava/lang/Object;Ljava/lang/Object;)Ljava/lang/Object;
    //   336: pop
    //   337: aload #25
    //   339: iconst_0
    //   340: invokestatic valueOf : (Z)Ljava/lang/Boolean;
    //   343: putfield zzjug : Ljava/lang/Boolean;
    //   346: aload #25
    //   348: aload #26
    //   350: putfield zzjuf : Lcom/google/android/gms/internal/zzcof;
    //   353: aload #25
    //   355: new com/google/android/gms/internal/zzcof
    //   358: dup
    //   359: invokespecial <init> : ()V
    //   362: putfield zzjue : Lcom/google/android/gms/internal/zzcof;
    //   365: aload #25
    //   367: getfield zzjue : Lcom/google/android/gms/internal/zzcof;
    //   370: aload #20
    //   372: invokestatic zza : (Ljava/util/BitSet;)[J
    //   375: putfield zzjvp : [J
    //   378: aload #25
    //   380: getfield zzjue : Lcom/google/android/gms/internal/zzcof;
    //   383: aload #24
    //   385: invokestatic zza : (Ljava/util/BitSet;)[J
    //   388: putfield zzjvo : [J
    //   391: goto -> 84
    //   394: aload #20
    //   396: astore #19
    //   398: aload #21
    //   400: astore #27
    //   402: aload #22
    //   404: astore #28
    //   406: aload #23
    //   408: astore #29
    //   410: aload #17
    //   412: astore #26
    //   414: aload #18
    //   416: astore #25
    //   418: aload #19
    //   420: astore #24
    //   422: aload #30
    //   424: ifnull -> 2226
    //   427: new androidx/b/a
    //   430: dup
    //   431: invokespecial <init> : ()V
    //   434: astore #25
    //   436: aload #30
    //   438: arraylength
    //   439: istore #4
    //   441: lconst_0
    //   442: lstore #10
    //   444: aconst_null
    //   445: astore #24
    //   447: aconst_null
    //   448: astore #26
    //   450: iconst_0
    //   451: istore #6
    //   453: aload #23
    //   455: astore #16
    //   457: aload #22
    //   459: astore #15
    //   461: aload #21
    //   463: astore #20
    //   465: aload #25
    //   467: astore #21
    //   469: aload #26
    //   471: astore #22
    //   473: aload #24
    //   475: astore #23
    //   477: aload #20
    //   479: astore #27
    //   481: aload #15
    //   483: astore #28
    //   485: aload #16
    //   487: astore #29
    //   489: aload #17
    //   491: astore #26
    //   493: aload #18
    //   495: astore #25
    //   497: aload #19
    //   499: astore #24
    //   501: iload #6
    //   503: iload #4
    //   505: if_icmpge -> 2226
    //   508: aload_2
    //   509: iload #6
    //   511: aaload
    //   512: astore #28
    //   514: aload #28
    //   516: getfield name : Ljava/lang/String;
    //   519: astore #25
    //   521: aload #28
    //   523: getfield zzjui : [Lcom/google/android/gms/internal/zzcoc;
    //   526: astore #26
    //   528: aload_0
    //   529: invokevirtual zzayr : ()Lcom/google/android/gms/internal/zzcik;
    //   532: aload #18
    //   534: getstatic com/google/android/gms/internal/zzciz.zzjjv : Lcom/google/android/gms/internal/zzcja;
    //   537: invokevirtual zzc : (Ljava/lang/String;Lcom/google/android/gms/internal/zzcja;)Z
    //   540: ifeq -> 1264
    //   543: aload_0
    //   544: invokevirtual zzayl : ()Lcom/google/android/gms/internal/zzcno;
    //   547: pop
    //   548: aload #28
    //   550: ldc_w '_eid'
    //   553: invokestatic zzb : (Lcom/google/android/gms/internal/zzcob;Ljava/lang/String;)Ljava/lang/Object;
    //   556: checkcast java/lang/Long
    //   559: astore #29
    //   561: aload #29
    //   563: ifnull -> 572
    //   566: iconst_1
    //   567: istore #7
    //   569: goto -> 575
    //   572: iconst_0
    //   573: istore #7
    //   575: iload #7
    //   577: ifeq -> 597
    //   580: aload #25
    //   582: ldc_w '_ep'
    //   585: invokevirtual equals : (Ljava/lang/Object;)Z
    //   588: ifeq -> 597
    //   591: iconst_1
    //   592: istore #5
    //   594: goto -> 600
    //   597: iconst_0
    //   598: istore #5
    //   600: iload #5
    //   602: ifeq -> 1160
    //   605: aload_0
    //   606: invokevirtual zzayl : ()Lcom/google/android/gms/internal/zzcno;
    //   609: pop
    //   610: aload #28
    //   612: ldc_w '_en'
    //   615: invokestatic zzb : (Lcom/google/android/gms/internal/zzcob;Ljava/lang/String;)Ljava/lang/Object;
    //   618: checkcast java/lang/String
    //   621: astore #27
    //   623: aload #27
    //   625: invokestatic isEmpty : (Ljava/lang/CharSequence;)Z
    //   628: ifeq -> 649
    //   631: aload_0
    //   632: invokevirtual zzayp : ()Lcom/google/android/gms/internal/zzcjj;
    //   635: invokevirtual zzbau : ()Lcom/google/android/gms/internal/zzcjl;
    //   638: ldc_w 'Extra parameter without an event name. eventId'
    //   641: aload #29
    //   643: invokevirtual zzj : (Ljava/lang/String;Ljava/lang/Object;)V
    //   646: goto -> 1113
    //   649: aload #23
    //   651: ifnull -> 695
    //   654: aload #22
    //   656: ifnull -> 695
    //   659: aload #23
    //   661: astore #24
    //   663: aload #22
    //   665: astore #25
    //   667: lload #10
    //   669: lstore #12
    //   671: aload #29
    //   673: invokevirtual longValue : ()J
    //   676: aload #22
    //   678: invokevirtual longValue : ()J
    //   681: lcmp
    //   682: ifeq -> 688
    //   685: goto -> 695
    //   688: aload #25
    //   690: astore #23
    //   692: goto -> 768
    //   695: aload_0
    //   696: invokevirtual zzayj : ()Lcom/google/android/gms/internal/zzcil;
    //   699: aload #18
    //   701: aload #29
    //   703: invokevirtual zzb : (Ljava/lang/String;Ljava/lang/Long;)Landroid/util/Pair;
    //   706: astore #25
    //   708: aload #25
    //   710: ifnull -> 1096
    //   713: aload #25
    //   715: getfield first : Ljava/lang/Object;
    //   718: ifnonnull -> 724
    //   721: goto -> 1096
    //   724: aload #25
    //   726: getfield first : Ljava/lang/Object;
    //   729: checkcast com/google/android/gms/internal/zzcob
    //   732: astore #24
    //   734: aload #25
    //   736: getfield second : Ljava/lang/Object;
    //   739: checkcast java/lang/Long
    //   742: invokevirtual longValue : ()J
    //   745: lstore #12
    //   747: aload_0
    //   748: invokevirtual zzayl : ()Lcom/google/android/gms/internal/zzcno;
    //   751: pop
    //   752: aload #24
    //   754: ldc_w '_eid'
    //   757: invokestatic zzb : (Lcom/google/android/gms/internal/zzcob;Ljava/lang/String;)Ljava/lang/Object;
    //   760: checkcast java/lang/Long
    //   763: astore #25
    //   765: goto -> 688
    //   768: lload #12
    //   770: lconst_1
    //   771: lsub
    //   772: lstore #10
    //   774: lload #10
    //   776: lconst_0
    //   777: lcmp
    //   778: ifgt -> 869
    //   781: aload_0
    //   782: invokevirtual zzayj : ()Lcom/google/android/gms/internal/zzcil;
    //   785: astore #25
    //   787: aload #25
    //   789: invokevirtual zzwj : ()V
    //   792: aload #25
    //   794: invokevirtual zzayp : ()Lcom/google/android/gms/internal/zzcjj;
    //   797: invokevirtual zzbba : ()Lcom/google/android/gms/internal/zzcjl;
    //   800: ldc_w 'Clearing complex main event info. appId'
    //   803: aload #18
    //   805: invokevirtual zzj : (Ljava/lang/String;Ljava/lang/Object;)V
    //   808: aload #25
    //   810: invokevirtual getWritableDatabase : ()Landroid/database/sqlite/SQLiteDatabase;
    //   813: astore #22
    //   815: aload #22
    //   817: ldc_w 'delete from main_event_params where app_id=?'
    //   820: iconst_1
    //   821: anewarray java/lang/String
    //   824: dup
    //   825: iconst_0
    //   826: aload #18
    //   828: aastore
    //   829: invokevirtual execSQL : (Ljava/lang/String;[Ljava/lang/Object;)V
    //   832: goto -> 862
    //   835: astore #22
    //   837: goto -> 846
    //   840: astore_1
    //   841: goto -> 846
    //   844: astore #22
    //   846: aload #25
    //   848: invokevirtual zzayp : ()Lcom/google/android/gms/internal/zzcjj;
    //   851: invokevirtual zzbau : ()Lcom/google/android/gms/internal/zzcjl;
    //   854: ldc_w 'Error clearing complex main event'
    //   857: aload #22
    //   859: invokevirtual zzj : (Ljava/lang/String;Ljava/lang/Object;)V
    //   862: aload #24
    //   864: astore #22
    //   866: goto -> 888
    //   869: aload_0
    //   870: invokevirtual zzayj : ()Lcom/google/android/gms/internal/zzcil;
    //   873: aload_1
    //   874: aload #29
    //   876: lload #10
    //   878: aload #24
    //   880: invokevirtual zza : (Ljava/lang/String;Ljava/lang/Long;JLcom/google/android/gms/internal/zzcob;)Z
    //   883: pop
    //   884: aload #24
    //   886: astore #22
    //   888: aload #26
    //   890: astore #24
    //   892: aload #22
    //   894: getfield zzjui : [Lcom/google/android/gms/internal/zzcoc;
    //   897: arraylength
    //   898: aload #24
    //   900: arraylength
    //   901: iadd
    //   902: anewarray com/google/android/gms/internal/zzcoc
    //   905: astore #25
    //   907: aload #22
    //   909: getfield zzjui : [Lcom/google/android/gms/internal/zzcoc;
    //   912: astore #29
    //   914: aload #29
    //   916: arraylength
    //   917: istore #9
    //   919: iconst_0
    //   920: istore #7
    //   922: iconst_0
    //   923: istore #5
    //   925: iload #7
    //   927: iload #9
    //   929: if_icmpge -> 987
    //   932: aload #29
    //   934: iload #7
    //   936: aaload
    //   937: astore #30
    //   939: aload_0
    //   940: invokevirtual zzayl : ()Lcom/google/android/gms/internal/zzcno;
    //   943: pop
    //   944: iload #5
    //   946: istore #8
    //   948: aload #28
    //   950: aload #30
    //   952: getfield name : Ljava/lang/String;
    //   955: invokestatic zza : (Lcom/google/android/gms/internal/zzcob;Ljava/lang/String;)Lcom/google/android/gms/internal/zzcoc;
    //   958: ifnonnull -> 974
    //   961: aload #25
    //   963: iload #5
    //   965: aload #30
    //   967: aastore
    //   968: iload #5
    //   970: iconst_1
    //   971: iadd
    //   972: istore #8
    //   974: iload #7
    //   976: iconst_1
    //   977: iadd
    //   978: istore #7
    //   980: iload #8
    //   982: istore #5
    //   984: goto -> 925
    //   987: iload #5
    //   989: ifle -> 1074
    //   992: aload #24
    //   994: arraylength
    //   995: istore #8
    //   997: iconst_0
    //   998: istore #7
    //   1000: iload #7
    //   1002: iload #8
    //   1004: if_icmpge -> 1032
    //   1007: aload #25
    //   1009: iload #5
    //   1011: aload #24
    //   1013: iload #7
    //   1015: aaload
    //   1016: aastore
    //   1017: iload #7
    //   1019: iconst_1
    //   1020: iadd
    //   1021: istore #7
    //   1023: iload #5
    //   1025: iconst_1
    //   1026: iadd
    //   1027: istore #5
    //   1029: goto -> 1000
    //   1032: iload #5
    //   1034: aload #25
    //   1036: arraylength
    //   1037: if_icmpne -> 1047
    //   1040: aload #25
    //   1042: astore #24
    //   1044: goto -> 1059
    //   1047: aload #25
    //   1049: iload #5
    //   1051: invokestatic copyOf : ([Ljava/lang/Object;I)[Ljava/lang/Object;
    //   1054: checkcast [Lcom/google/android/gms/internal/zzcoc;
    //   1057: astore #24
    //   1059: aload #24
    //   1061: astore #25
    //   1063: aload #27
    //   1065: astore #24
    //   1067: aload #25
    //   1069: astore #27
    //   1071: goto -> 1292
    //   1074: aload_0
    //   1075: invokevirtual zzayp : ()Lcom/google/android/gms/internal/zzcjj;
    //   1078: invokevirtual zzbaw : ()Lcom/google/android/gms/internal/zzcjl;
    //   1081: ldc_w 'No unique parameters in main event. eventName'
    //   1084: aload #27
    //   1086: invokevirtual zzj : (Ljava/lang/String;Ljava/lang/Object;)V
    //   1089: aload #27
    //   1091: astore #24
    //   1093: goto -> 1288
    //   1096: aload_0
    //   1097: invokevirtual zzayp : ()Lcom/google/android/gms/internal/zzcjj;
    //   1100: invokevirtual zzbau : ()Lcom/google/android/gms/internal/zzcjl;
    //   1103: ldc_w 'Extra parameter without existing main event. eventName, eventId'
    //   1106: aload #27
    //   1108: aload #29
    //   1110: invokevirtual zze : (Ljava/lang/String;Ljava/lang/Object;Ljava/lang/Object;)V
    //   1113: aload #21
    //   1115: astore #24
    //   1117: aload #17
    //   1119: astore #21
    //   1121: aload #18
    //   1123: astore #17
    //   1125: aload #19
    //   1127: astore #18
    //   1129: aload #20
    //   1131: astore #25
    //   1133: aload #15
    //   1135: astore #19
    //   1137: aload #21
    //   1139: astore #15
    //   1141: aload #19
    //   1143: astore #21
    //   1145: aload #16
    //   1147: astore #20
    //   1149: aload #24
    //   1151: astore #19
    //   1153: aload #25
    //   1155: astore #16
    //   1157: goto -> 2181
    //   1160: iload #4
    //   1162: istore #5
    //   1164: iload #7
    //   1166: ifeq -> 1268
    //   1169: aload_0
    //   1170: invokevirtual zzayl : ()Lcom/google/android/gms/internal/zzcno;
    //   1173: pop
    //   1174: aload #28
    //   1176: ldc_w '_epc'
    //   1179: invokestatic zzb : (Lcom/google/android/gms/internal/zzcob;Ljava/lang/String;)Ljava/lang/Object;
    //   1182: astore #23
    //   1184: aload #23
    //   1186: astore #22
    //   1188: aload #23
    //   1190: ifnonnull -> 1199
    //   1193: lconst_0
    //   1194: invokestatic valueOf : (J)Ljava/lang/Long;
    //   1197: astore #22
    //   1199: aload #22
    //   1201: checkcast java/lang/Long
    //   1204: invokevirtual longValue : ()J
    //   1207: lstore #10
    //   1209: lload #10
    //   1211: lconst_0
    //   1212: lcmp
    //   1213: ifgt -> 1234
    //   1216: aload_0
    //   1217: invokevirtual zzayp : ()Lcom/google/android/gms/internal/zzcjj;
    //   1220: invokevirtual zzbaw : ()Lcom/google/android/gms/internal/zzcjl;
    //   1223: ldc_w 'Complex event with zero extra param count. eventName'
    //   1226: aload #25
    //   1228: invokevirtual zzj : (Ljava/lang/String;Ljava/lang/Object;)V
    //   1231: goto -> 1249
    //   1234: aload_0
    //   1235: invokevirtual zzayj : ()Lcom/google/android/gms/internal/zzcil;
    //   1238: aload_1
    //   1239: aload #29
    //   1241: lload #10
    //   1243: aload #28
    //   1245: invokevirtual zza : (Ljava/lang/String;Ljava/lang/Long;JLcom/google/android/gms/internal/zzcob;)Z
    //   1248: pop
    //   1249: aload #29
    //   1251: astore #23
    //   1253: aload #28
    //   1255: astore #22
    //   1257: aload #25
    //   1259: astore #24
    //   1261: goto -> 1288
    //   1264: iload #4
    //   1266: istore #5
    //   1268: aload #23
    //   1270: astore #24
    //   1272: aload #22
    //   1274: astore #23
    //   1276: aload #24
    //   1278: astore #22
    //   1280: iload #5
    //   1282: istore #4
    //   1284: aload #25
    //   1286: astore #24
    //   1288: aload #26
    //   1290: astore #27
    //   1292: aload_0
    //   1293: invokevirtual zzayj : ()Lcom/google/android/gms/internal/zzcil;
    //   1296: aload #18
    //   1298: aload #28
    //   1300: getfield name : Ljava/lang/String;
    //   1303: invokevirtual zzae : (Ljava/lang/String;Ljava/lang/String;)Lcom/google/android/gms/internal/zzcit;
    //   1306: astore #25
    //   1308: aload #25
    //   1310: ifnonnull -> 1371
    //   1313: aload_0
    //   1314: invokevirtual zzayp : ()Lcom/google/android/gms/internal/zzcjj;
    //   1317: invokevirtual zzbaw : ()Lcom/google/android/gms/internal/zzcjl;
    //   1320: ldc_w 'Event aggregate wasn't created during raw event logging. appId, event'
    //   1323: aload_1
    //   1324: invokestatic zzjs : (Ljava/lang/String;)Ljava/lang/Object;
    //   1327: aload_0
    //   1328: invokevirtual zzayk : ()Lcom/google/android/gms/internal/zzcjh;
    //   1331: aload #24
    //   1333: invokevirtual zzjp : (Ljava/lang/String;)Ljava/lang/String;
    //   1336: invokevirtual zze : (Ljava/lang/String;Ljava/lang/Object;Ljava/lang/Object;)V
    //   1339: new com/google/android/gms/internal/zzcit
    //   1342: dup
    //   1343: aload_1
    //   1344: aload #28
    //   1346: getfield name : Ljava/lang/String;
    //   1349: lconst_1
    //   1350: lconst_1
    //   1351: aload #28
    //   1353: getfield zzjuj : Ljava/lang/Long;
    //   1356: invokevirtual longValue : ()J
    //   1359: lconst_0
    //   1360: aconst_null
    //   1361: aconst_null
    //   1362: aconst_null
    //   1363: invokespecial <init> : (Ljava/lang/String;Ljava/lang/String;JJJJLjava/lang/Long;Ljava/lang/Long;Ljava/lang/Boolean;)V
    //   1366: astore #29
    //   1368: goto -> 1378
    //   1371: aload #25
    //   1373: invokevirtual zzban : ()Lcom/google/android/gms/internal/zzcit;
    //   1376: astore #29
    //   1378: aload #16
    //   1380: astore #28
    //   1382: aload #15
    //   1384: astore #16
    //   1386: aload #20
    //   1388: astore #26
    //   1390: aload #18
    //   1392: astore #25
    //   1394: aload #17
    //   1396: astore #20
    //   1398: aload_0
    //   1399: invokevirtual zzayj : ()Lcom/google/android/gms/internal/zzcil;
    //   1402: aload #29
    //   1404: invokevirtual zza : (Lcom/google/android/gms/internal/zzcit;)V
    //   1407: aload #29
    //   1409: getfield zzjhs : J
    //   1412: lstore #12
    //   1414: aload #21
    //   1416: astore #29
    //   1418: aload #29
    //   1420: aload #24
    //   1422: invokeinterface get : (Ljava/lang/Object;)Ljava/lang/Object;
    //   1427: checkcast java/util/Map
    //   1430: astore #17
    //   1432: aload #17
    //   1434: astore #15
    //   1436: aload #17
    //   1438: ifnonnull -> 1484
    //   1441: aload_0
    //   1442: invokevirtual zzayj : ()Lcom/google/android/gms/internal/zzcil;
    //   1445: aload #25
    //   1447: aload #24
    //   1449: invokevirtual zzaj : (Ljava/lang/String;Ljava/lang/String;)Ljava/util/Map;
    //   1452: astore #17
    //   1454: aload #17
    //   1456: astore #15
    //   1458: aload #17
    //   1460: ifnonnull -> 1472
    //   1463: new androidx/b/a
    //   1466: dup
    //   1467: invokespecial <init> : ()V
    //   1470: astore #15
    //   1472: aload #29
    //   1474: aload #24
    //   1476: aload #15
    //   1478: invokeinterface put : (Ljava/lang/Object;Ljava/lang/Object;)Ljava/lang/Object;
    //   1483: pop
    //   1484: aload #15
    //   1486: astore #21
    //   1488: aload #21
    //   1490: invokeinterface keySet : ()Ljava/util/Set;
    //   1495: invokeinterface iterator : ()Ljava/util/Iterator;
    //   1500: astore #30
    //   1502: aload #28
    //   1504: astore #18
    //   1506: aload #26
    //   1508: astore #17
    //   1510: aload #19
    //   1512: astore #15
    //   1514: aload #30
    //   1516: astore #26
    //   1518: aload #29
    //   1520: astore #19
    //   1522: aload #24
    //   1524: astore #28
    //   1526: aload #26
    //   1528: invokeinterface hasNext : ()Z
    //   1533: ifeq -> 2133
    //   1536: aload #26
    //   1538: invokeinterface next : ()Ljava/lang/Object;
    //   1543: checkcast java/lang/Integer
    //   1546: invokevirtual intValue : ()I
    //   1549: istore #5
    //   1551: aload #16
    //   1553: iload #5
    //   1555: invokestatic valueOf : (I)Ljava/lang/Integer;
    //   1558: invokeinterface contains : (Ljava/lang/Object;)Z
    //   1563: ifeq -> 1587
    //   1566: aload_0
    //   1567: invokevirtual zzayp : ()Lcom/google/android/gms/internal/zzcjj;
    //   1570: invokevirtual zzbba : ()Lcom/google/android/gms/internal/zzcjl;
    //   1573: ldc_w 'Skipping failed audience ID'
    //   1576: iload #5
    //   1578: invokestatic valueOf : (I)Ljava/lang/Integer;
    //   1581: invokevirtual zzj : (Ljava/lang/String;Ljava/lang/Object;)V
    //   1584: goto -> 1526
    //   1587: aload #18
    //   1589: iload #5
    //   1591: invokestatic valueOf : (I)Ljava/lang/Integer;
    //   1594: invokeinterface get : (Ljava/lang/Object;)Ljava/lang/Object;
    //   1599: checkcast com/google/android/gms/internal/zzcoa
    //   1602: astore #24
    //   1604: aload #17
    //   1606: astore #29
    //   1608: aload #29
    //   1610: iload #5
    //   1612: invokestatic valueOf : (I)Ljava/lang/Integer;
    //   1615: invokeinterface get : (Ljava/lang/Object;)Ljava/lang/Object;
    //   1620: checkcast java/util/BitSet
    //   1623: astore #17
    //   1625: aload #15
    //   1627: astore #30
    //   1629: aload #30
    //   1631: iload #5
    //   1633: invokestatic valueOf : (I)Ljava/lang/Integer;
    //   1636: invokeinterface get : (Ljava/lang/Object;)Ljava/lang/Object;
    //   1641: checkcast java/util/BitSet
    //   1644: astore #15
    //   1646: aload #24
    //   1648: ifnonnull -> 1732
    //   1651: new com/google/android/gms/internal/zzcoa
    //   1654: dup
    //   1655: invokespecial <init> : ()V
    //   1658: astore #15
    //   1660: aload #18
    //   1662: iload #5
    //   1664: invokestatic valueOf : (I)Ljava/lang/Integer;
    //   1667: aload #15
    //   1669: invokeinterface put : (Ljava/lang/Object;Ljava/lang/Object;)Ljava/lang/Object;
    //   1674: pop
    //   1675: aload #15
    //   1677: iconst_1
    //   1678: invokestatic valueOf : (Z)Ljava/lang/Boolean;
    //   1681: putfield zzjug : Ljava/lang/Boolean;
    //   1684: new java/util/BitSet
    //   1687: dup
    //   1688: invokespecial <init> : ()V
    //   1691: astore #17
    //   1693: aload #29
    //   1695: iload #5
    //   1697: invokestatic valueOf : (I)Ljava/lang/Integer;
    //   1700: aload #17
    //   1702: invokeinterface put : (Ljava/lang/Object;Ljava/lang/Object;)Ljava/lang/Object;
    //   1707: pop
    //   1708: new java/util/BitSet
    //   1711: dup
    //   1712: invokespecial <init> : ()V
    //   1715: astore #15
    //   1717: aload #30
    //   1719: iload #5
    //   1721: invokestatic valueOf : (I)Ljava/lang/Integer;
    //   1724: aload #15
    //   1726: invokeinterface put : (Ljava/lang/Object;Ljava/lang/Object;)Ljava/lang/Object;
    //   1731: pop
    //   1732: aload #17
    //   1734: astore #32
    //   1736: aload #15
    //   1738: astore #31
    //   1740: aload #21
    //   1742: iload #5
    //   1744: invokestatic valueOf : (I)Ljava/lang/Integer;
    //   1747: invokeinterface get : (Ljava/lang/Object;)Ljava/lang/Object;
    //   1752: checkcast java/util/List
    //   1755: invokeinterface iterator : ()Ljava/util/Iterator;
    //   1760: astore #33
    //   1762: aload #26
    //   1764: astore #17
    //   1766: aload #21
    //   1768: astore #24
    //   1770: aload #30
    //   1772: astore #21
    //   1774: aload #29
    //   1776: astore #15
    //   1778: aload #25
    //   1780: astore #26
    //   1782: aload #32
    //   1784: astore #29
    //   1786: aload #20
    //   1788: astore #25
    //   1790: aload #31
    //   1792: astore #20
    //   1794: aload #33
    //   1796: invokeinterface hasNext : ()Z
    //   1801: ifeq -> 2102
    //   1804: aload #33
    //   1806: invokeinterface next : ()Ljava/lang/Object;
    //   1811: checkcast com/google/android/gms/internal/zzcns
    //   1814: astore #30
    //   1816: aload_0
    //   1817: invokevirtual zzayp : ()Lcom/google/android/gms/internal/zzcjj;
    //   1820: iconst_2
    //   1821: invokevirtual zzae : (I)Z
    //   1824: ifeq -> 1887
    //   1827: aload_0
    //   1828: invokevirtual zzayp : ()Lcom/google/android/gms/internal/zzcjj;
    //   1831: invokevirtual zzbba : ()Lcom/google/android/gms/internal/zzcjl;
    //   1834: ldc_w 'Evaluating filter. audience, filter, event'
    //   1837: iload #5
    //   1839: invokestatic valueOf : (I)Ljava/lang/Integer;
    //   1842: aload #30
    //   1844: getfield zzjsx : Ljava/lang/Integer;
    //   1847: aload_0
    //   1848: invokevirtual zzayk : ()Lcom/google/android/gms/internal/zzcjh;
    //   1851: aload #30
    //   1853: getfield zzjsy : Ljava/lang/String;
    //   1856: invokevirtual zzjp : (Ljava/lang/String;)Ljava/lang/String;
    //   1859: invokevirtual zzd : (Ljava/lang/String;Ljava/lang/Object;Ljava/lang/Object;Ljava/lang/Object;)V
    //   1862: aload_0
    //   1863: invokevirtual zzayp : ()Lcom/google/android/gms/internal/zzcjj;
    //   1866: invokevirtual zzbba : ()Lcom/google/android/gms/internal/zzcjl;
    //   1869: ldc_w 'Filter definition'
    //   1872: aload_0
    //   1873: invokevirtual zzayk : ()Lcom/google/android/gms/internal/zzcjh;
    //   1876: aload #30
    //   1878: invokevirtual zza : (Lcom/google/android/gms/internal/zzcns;)Ljava/lang/String;
    //   1881: invokevirtual zzj : (Ljava/lang/String;Ljava/lang/Object;)V
    //   1884: goto -> 1887
    //   1887: aload #30
    //   1889: getfield zzjsx : Ljava/lang/Integer;
    //   1892: ifnull -> 2068
    //   1895: aload #30
    //   1897: getfield zzjsx : Ljava/lang/Integer;
    //   1900: invokevirtual intValue : ()I
    //   1903: sipush #256
    //   1906: if_icmple -> 1912
    //   1909: goto -> 2068
    //   1912: aload #29
    //   1914: aload #30
    //   1916: getfield zzjsx : Ljava/lang/Integer;
    //   1919: invokevirtual intValue : ()I
    //   1922: invokevirtual get : (I)Z
    //   1925: ifeq -> 1960
    //   1928: aload_0
    //   1929: invokevirtual zzayp : ()Lcom/google/android/gms/internal/zzcjj;
    //   1932: invokevirtual zzbba : ()Lcom/google/android/gms/internal/zzcjl;
    //   1935: ldc_w 'Event filter already evaluated true. audience ID, filter ID'
    //   1938: iload #5
    //   1940: invokestatic valueOf : (I)Ljava/lang/Integer;
    //   1943: aload #30
    //   1945: getfield zzjsx : Ljava/lang/Integer;
    //   1948: invokevirtual zze : (Ljava/lang/String;Ljava/lang/Object;Ljava/lang/Object;)V
    //   1951: aload_3
    //   1952: astore #25
    //   1954: aload_1
    //   1955: astore #26
    //   1957: goto -> 1794
    //   1960: aload_0
    //   1961: aload #30
    //   1963: aload #28
    //   1965: aload #27
    //   1967: lload #12
    //   1969: invokespecial zza : (Lcom/google/android/gms/internal/zzcns;Ljava/lang/String;[Lcom/google/android/gms/internal/zzcoc;J)Ljava/lang/Boolean;
    //   1972: astore #26
    //   1974: aload_0
    //   1975: invokevirtual zzayp : ()Lcom/google/android/gms/internal/zzcjj;
    //   1978: invokevirtual zzbba : ()Lcom/google/android/gms/internal/zzcjl;
    //   1981: astore #31
    //   1983: aload #26
    //   1985: ifnonnull -> 1996
    //   1988: ldc_w 'null'
    //   1991: astore #25
    //   1993: goto -> 2000
    //   1996: aload #26
    //   1998: astore #25
    //   2000: aload #31
    //   2002: ldc_w 'Event filter result'
    //   2005: aload #25
    //   2007: invokevirtual zzj : (Ljava/lang/String;Ljava/lang/Object;)V
    //   2010: aload #26
    //   2012: ifnonnull -> 2031
    //   2015: aload #16
    //   2017: iload #5
    //   2019: invokestatic valueOf : (I)Ljava/lang/Integer;
    //   2022: invokeinterface add : (Ljava/lang/Object;)Z
    //   2027: pop
    //   2028: goto -> 2093
    //   2031: aload #20
    //   2033: aload #30
    //   2035: getfield zzjsx : Ljava/lang/Integer;
    //   2038: invokevirtual intValue : ()I
    //   2041: invokevirtual set : (I)V
    //   2044: aload #26
    //   2046: invokevirtual booleanValue : ()Z
    //   2049: ifeq -> 2093
    //   2052: aload #29
    //   2054: aload #30
    //   2056: getfield zzjsx : Ljava/lang/Integer;
    //   2059: invokevirtual intValue : ()I
    //   2062: invokevirtual set : (I)V
    //   2065: goto -> 2093
    //   2068: aload_0
    //   2069: invokevirtual zzayp : ()Lcom/google/android/gms/internal/zzcjj;
    //   2072: invokevirtual zzbaw : ()Lcom/google/android/gms/internal/zzcjl;
    //   2075: ldc_w 'Invalid event filter ID. appId, id'
    //   2078: aload_1
    //   2079: invokestatic zzjs : (Ljava/lang/String;)Ljava/lang/Object;
    //   2082: aload #30
    //   2084: getfield zzjsx : Ljava/lang/Integer;
    //   2087: invokestatic valueOf : (Ljava/lang/Object;)Ljava/lang/String;
    //   2090: invokevirtual zze : (Ljava/lang/String;Ljava/lang/Object;Ljava/lang/Object;)V
    //   2093: aload_1
    //   2094: astore #26
    //   2096: aload_3
    //   2097: astore #25
    //   2099: goto -> 1794
    //   2102: aload #15
    //   2104: astore #29
    //   2106: aload #21
    //   2108: astore #15
    //   2110: aload #25
    //   2112: astore #20
    //   2114: aload #26
    //   2116: astore #25
    //   2118: aload #24
    //   2120: astore #21
    //   2122: aload #17
    //   2124: astore #26
    //   2126: aload #29
    //   2128: astore #17
    //   2130: goto -> 1526
    //   2133: aload #17
    //   2135: astore #27
    //   2137: aload #16
    //   2139: astore #21
    //   2141: aload #18
    //   2143: astore #26
    //   2145: aload #20
    //   2147: astore #17
    //   2149: aload #22
    //   2151: astore #24
    //   2153: aload #23
    //   2155: astore #22
    //   2157: aload #27
    //   2159: astore #16
    //   2161: aload #15
    //   2163: astore #18
    //   2165: aload #26
    //   2167: astore #20
    //   2169: aload #17
    //   2171: astore #15
    //   2173: aload #25
    //   2175: astore #17
    //   2177: aload #24
    //   2179: astore #23
    //   2181: iload #6
    //   2183: iconst_1
    //   2184: iadd
    //   2185: istore #6
    //   2187: aload #21
    //   2189: astore #24
    //   2191: aload #20
    //   2193: astore #25
    //   2195: aload #19
    //   2197: astore #21
    //   2199: aload #18
    //   2201: astore #19
    //   2203: aload #17
    //   2205: astore #18
    //   2207: aload #15
    //   2209: astore #17
    //   2211: aload #16
    //   2213: astore #20
    //   2215: aload #24
    //   2217: astore #15
    //   2219: aload #25
    //   2221: astore #16
    //   2223: goto -> 477
    //   2226: aload #27
    //   2228: astore #15
    //   2230: aload #25
    //   2232: astore #17
    //   2234: aload #24
    //   2236: astore_2
    //   2237: aload #17
    //   2239: astore #16
    //   2241: aload_2
    //   2242: astore #18
    //   2244: aload #15
    //   2246: astore #19
    //   2248: aload #26
    //   2250: ifnull -> 3317
    //   2253: new androidx/b/a
    //   2256: dup
    //   2257: invokespecial <init> : ()V
    //   2260: astore #21
    //   2262: aload #26
    //   2264: arraylength
    //   2265: istore #4
    //   2267: iconst_0
    //   2268: istore #5
    //   2270: aload #17
    //   2272: astore #16
    //   2274: aload_2
    //   2275: astore #18
    //   2277: aload #15
    //   2279: astore #19
    //   2281: iload #5
    //   2283: iload #4
    //   2285: if_icmpge -> 3317
    //   2288: aload #26
    //   2290: iload #5
    //   2292: aaload
    //   2293: astore #24
    //   2295: aload #21
    //   2297: aload #24
    //   2299: getfield name : Ljava/lang/String;
    //   2302: invokeinterface get : (Ljava/lang/Object;)Ljava/lang/Object;
    //   2307: checkcast java/util/Map
    //   2310: astore #16
    //   2312: aload #16
    //   2314: astore #18
    //   2316: aload #16
    //   2318: ifnonnull -> 2370
    //   2321: aload_0
    //   2322: invokevirtual zzayj : ()Lcom/google/android/gms/internal/zzcil;
    //   2325: aload #17
    //   2327: aload #24
    //   2329: getfield name : Ljava/lang/String;
    //   2332: invokevirtual zzak : (Ljava/lang/String;Ljava/lang/String;)Ljava/util/Map;
    //   2335: astore #16
    //   2337: aload #16
    //   2339: astore #18
    //   2341: aload #16
    //   2343: ifnonnull -> 2355
    //   2346: new androidx/b/a
    //   2349: dup
    //   2350: invokespecial <init> : ()V
    //   2353: astore #18
    //   2355: aload #21
    //   2357: aload #24
    //   2359: getfield name : Ljava/lang/String;
    //   2362: aload #18
    //   2364: invokeinterface put : (Ljava/lang/Object;Ljava/lang/Object;)Ljava/lang/Object;
    //   2369: pop
    //   2370: aload #18
    //   2372: invokeinterface keySet : ()Ljava/util/Set;
    //   2377: invokeinterface iterator : ()Ljava/util/Iterator;
    //   2382: astore #16
    //   2384: aload #15
    //   2386: astore #20
    //   2388: aload_2
    //   2389: astore #19
    //   2391: aload #18
    //   2393: astore_2
    //   2394: aload #21
    //   2396: astore #15
    //   2398: aload #16
    //   2400: invokeinterface hasNext : ()Z
    //   2405: ifeq -> 3294
    //   2408: aload #16
    //   2410: invokeinterface next : ()Ljava/lang/Object;
    //   2415: checkcast java/lang/Integer
    //   2418: invokevirtual intValue : ()I
    //   2421: istore #6
    //   2423: aload #28
    //   2425: iload #6
    //   2427: invokestatic valueOf : (I)Ljava/lang/Integer;
    //   2430: invokeinterface contains : (Ljava/lang/Object;)Z
    //   2435: ifeq -> 2459
    //   2438: aload_0
    //   2439: invokevirtual zzayp : ()Lcom/google/android/gms/internal/zzcjj;
    //   2442: invokevirtual zzbba : ()Lcom/google/android/gms/internal/zzcjl;
    //   2445: ldc_w 'Skipping failed audience ID'
    //   2448: iload #6
    //   2450: invokestatic valueOf : (I)Ljava/lang/Integer;
    //   2453: invokevirtual zzj : (Ljava/lang/String;Ljava/lang/Object;)V
    //   2456: goto -> 2398
    //   2459: aload #29
    //   2461: iload #6
    //   2463: invokestatic valueOf : (I)Ljava/lang/Integer;
    //   2466: invokeinterface get : (Ljava/lang/Object;)Ljava/lang/Object;
    //   2471: checkcast com/google/android/gms/internal/zzcoa
    //   2474: astore #18
    //   2476: aload #20
    //   2478: iload #6
    //   2480: invokestatic valueOf : (I)Ljava/lang/Integer;
    //   2483: invokeinterface get : (Ljava/lang/Object;)Ljava/lang/Object;
    //   2488: checkcast java/util/BitSet
    //   2491: astore #21
    //   2493: aload #19
    //   2495: iload #6
    //   2497: invokestatic valueOf : (I)Ljava/lang/Integer;
    //   2500: invokeinterface get : (Ljava/lang/Object;)Ljava/lang/Object;
    //   2505: checkcast java/util/BitSet
    //   2508: astore #22
    //   2510: aload #18
    //   2512: ifnonnull -> 2596
    //   2515: new com/google/android/gms/internal/zzcoa
    //   2518: dup
    //   2519: invokespecial <init> : ()V
    //   2522: astore #18
    //   2524: aload #29
    //   2526: iload #6
    //   2528: invokestatic valueOf : (I)Ljava/lang/Integer;
    //   2531: aload #18
    //   2533: invokeinterface put : (Ljava/lang/Object;Ljava/lang/Object;)Ljava/lang/Object;
    //   2538: pop
    //   2539: aload #18
    //   2541: iconst_1
    //   2542: invokestatic valueOf : (Z)Ljava/lang/Boolean;
    //   2545: putfield zzjug : Ljava/lang/Boolean;
    //   2548: new java/util/BitSet
    //   2551: dup
    //   2552: invokespecial <init> : ()V
    //   2555: astore #21
    //   2557: aload #20
    //   2559: iload #6
    //   2561: invokestatic valueOf : (I)Ljava/lang/Integer;
    //   2564: aload #21
    //   2566: invokeinterface put : (Ljava/lang/Object;Ljava/lang/Object;)Ljava/lang/Object;
    //   2571: pop
    //   2572: new java/util/BitSet
    //   2575: dup
    //   2576: invokespecial <init> : ()V
    //   2579: astore #22
    //   2581: aload #19
    //   2583: iload #6
    //   2585: invokestatic valueOf : (I)Ljava/lang/Integer;
    //   2588: aload #22
    //   2590: invokeinterface put : (Ljava/lang/Object;Ljava/lang/Object;)Ljava/lang/Object;
    //   2595: pop
    //   2596: aload_2
    //   2597: iload #6
    //   2599: invokestatic valueOf : (I)Ljava/lang/Integer;
    //   2602: invokeinterface get : (Ljava/lang/Object;)Ljava/lang/Object;
    //   2607: checkcast java/util/List
    //   2610: invokeinterface iterator : ()Ljava/util/Iterator;
    //   2615: astore #18
    //   2617: aload #18
    //   2619: invokeinterface hasNext : ()Z
    //   2624: ifeq -> 3291
    //   2627: aload #18
    //   2629: invokeinterface next : ()Ljava/lang/Object;
    //   2634: checkcast com/google/android/gms/internal/zzcnv
    //   2637: astore #25
    //   2639: aload_0
    //   2640: invokevirtual zzayp : ()Lcom/google/android/gms/internal/zzcjj;
    //   2643: iconst_2
    //   2644: invokevirtual zzae : (I)Z
    //   2647: ifeq -> 2710
    //   2650: aload_0
    //   2651: invokevirtual zzayp : ()Lcom/google/android/gms/internal/zzcjj;
    //   2654: invokevirtual zzbba : ()Lcom/google/android/gms/internal/zzcjl;
    //   2657: ldc_w 'Evaluating filter. audience, filter, property'
    //   2660: iload #6
    //   2662: invokestatic valueOf : (I)Ljava/lang/Integer;
    //   2665: aload #25
    //   2667: getfield zzjsx : Ljava/lang/Integer;
    //   2670: aload_0
    //   2671: invokevirtual zzayk : ()Lcom/google/android/gms/internal/zzcjh;
    //   2674: aload #25
    //   2676: getfield zzjtn : Ljava/lang/String;
    //   2679: invokevirtual zzjr : (Ljava/lang/String;)Ljava/lang/String;
    //   2682: invokevirtual zzd : (Ljava/lang/String;Ljava/lang/Object;Ljava/lang/Object;Ljava/lang/Object;)V
    //   2685: aload_0
    //   2686: invokevirtual zzayp : ()Lcom/google/android/gms/internal/zzcjj;
    //   2689: invokevirtual zzbba : ()Lcom/google/android/gms/internal/zzcjl;
    //   2692: ldc_w 'Filter definition'
    //   2695: aload_0
    //   2696: invokevirtual zzayk : ()Lcom/google/android/gms/internal/zzcjh;
    //   2699: aload #25
    //   2701: invokevirtual zza : (Lcom/google/android/gms/internal/zzcnv;)Ljava/lang/String;
    //   2704: invokevirtual zzj : (Ljava/lang/String;Ljava/lang/Object;)V
    //   2707: goto -> 2710
    //   2710: aload #18
    //   2712: astore #23
    //   2714: aload #16
    //   2716: astore #17
    //   2718: aload #25
    //   2720: getfield zzjsx : Ljava/lang/Integer;
    //   2723: ifnull -> 3239
    //   2726: aload #25
    //   2728: getfield zzjsx : Ljava/lang/Integer;
    //   2731: invokevirtual intValue : ()I
    //   2734: sipush #256
    //   2737: if_icmple -> 2743
    //   2740: goto -> 3239
    //   2743: aload #21
    //   2745: aload #25
    //   2747: getfield zzjsx : Ljava/lang/Integer;
    //   2750: invokevirtual intValue : ()I
    //   2753: invokevirtual get : (I)Z
    //   2756: ifeq -> 2800
    //   2759: aload_0
    //   2760: invokevirtual zzayp : ()Lcom/google/android/gms/internal/zzcjj;
    //   2763: invokevirtual zzbba : ()Lcom/google/android/gms/internal/zzcjl;
    //   2766: ldc_w 'Property filter already evaluated true. audience ID, filter ID'
    //   2769: iload #6
    //   2771: invokestatic valueOf : (I)Ljava/lang/Integer;
    //   2774: aload #25
    //   2776: getfield zzjsx : Ljava/lang/Integer;
    //   2779: invokevirtual zze : (Ljava/lang/String;Ljava/lang/Object;Ljava/lang/Object;)V
    //   2782: aload_1
    //   2783: astore #18
    //   2785: aload #17
    //   2787: astore #16
    //   2789: aload #18
    //   2791: astore #17
    //   2793: aload #23
    //   2795: astore #18
    //   2797: goto -> 2617
    //   2800: aload #25
    //   2802: getfield zzjto : Lcom/google/android/gms/internal/zzcnt;
    //   2805: astore #16
    //   2807: aload #16
    //   2809: ifnonnull -> 2851
    //   2812: aload_0
    //   2813: invokevirtual zzayp : ()Lcom/google/android/gms/internal/zzcjj;
    //   2816: invokevirtual zzbaw : ()Lcom/google/android/gms/internal/zzcjl;
    //   2819: astore #16
    //   2821: ldc_w 'Missing property filter. property'
    //   2824: astore #18
    //   2826: aload #16
    //   2828: aload #18
    //   2830: aload_0
    //   2831: invokevirtual zzayk : ()Lcom/google/android/gms/internal/zzcjh;
    //   2834: aload #24
    //   2836: getfield name : Ljava/lang/String;
    //   2839: invokevirtual zzjr : (Ljava/lang/String;)Ljava/lang/String;
    //   2842: invokevirtual zzj : (Ljava/lang/String;Ljava/lang/Object;)V
    //   2845: aconst_null
    //   2846: astore #16
    //   2848: goto -> 3142
    //   2851: getstatic java/lang/Boolean.TRUE : Ljava/lang/Boolean;
    //   2854: aload #16
    //   2856: getfield zzjtf : Ljava/lang/Boolean;
    //   2859: invokevirtual equals : (Ljava/lang/Object;)Z
    //   2862: istore #14
    //   2864: aload #24
    //   2866: getfield zzjum : Ljava/lang/Long;
    //   2869: ifnull -> 2928
    //   2872: aload #16
    //   2874: getfield zzjte : Lcom/google/android/gms/internal/zzcnu;
    //   2877: ifnonnull -> 2897
    //   2880: aload_0
    //   2881: invokevirtual zzayp : ()Lcom/google/android/gms/internal/zzcjj;
    //   2884: invokevirtual zzbaw : ()Lcom/google/android/gms/internal/zzcjl;
    //   2887: astore #16
    //   2889: ldc_w 'No number filter for long property. property'
    //   2892: astore #18
    //   2894: goto -> 2826
    //   2897: aload_0
    //   2898: aload #24
    //   2900: getfield zzjum : Ljava/lang/Long;
    //   2903: invokevirtual longValue : ()J
    //   2906: aload #16
    //   2908: getfield zzjte : Lcom/google/android/gms/internal/zzcnu;
    //   2911: invokespecial zza : (JLcom/google/android/gms/internal/zzcnu;)Ljava/lang/Boolean;
    //   2914: astore #16
    //   2916: aload #16
    //   2918: iload #14
    //   2920: invokestatic zza : (Ljava/lang/Boolean;Z)Ljava/lang/Boolean;
    //   2923: astore #16
    //   2925: goto -> 3142
    //   2928: aload #24
    //   2930: getfield zzjsl : Ljava/lang/Double;
    //   2933: ifnull -> 2983
    //   2936: aload #16
    //   2938: getfield zzjte : Lcom/google/android/gms/internal/zzcnu;
    //   2941: ifnonnull -> 2961
    //   2944: aload_0
    //   2945: invokevirtual zzayp : ()Lcom/google/android/gms/internal/zzcjj;
    //   2948: invokevirtual zzbaw : ()Lcom/google/android/gms/internal/zzcjl;
    //   2951: astore #16
    //   2953: ldc_w 'No number filter for double property. property'
    //   2956: astore #18
    //   2958: goto -> 3120
    //   2961: aload_0
    //   2962: aload #24
    //   2964: getfield zzjsl : Ljava/lang/Double;
    //   2967: invokevirtual doubleValue : ()D
    //   2970: aload #16
    //   2972: getfield zzjte : Lcom/google/android/gms/internal/zzcnu;
    //   2975: invokespecial zza : (DLcom/google/android/gms/internal/zzcnu;)Ljava/lang/Boolean;
    //   2978: astore #16
    //   2980: goto -> 2916
    //   2983: aload #24
    //   2985: getfield zzgim : Ljava/lang/String;
    //   2988: ifnull -> 3106
    //   2991: aload #16
    //   2993: getfield zzjtd : Lcom/google/android/gms/internal/zzcnw;
    //   2996: ifnonnull -> 3087
    //   2999: aload #16
    //   3001: getfield zzjte : Lcom/google/android/gms/internal/zzcnu;
    //   3004: ifnonnull -> 3024
    //   3007: aload_0
    //   3008: invokevirtual zzayp : ()Lcom/google/android/gms/internal/zzcjj;
    //   3011: invokevirtual zzbaw : ()Lcom/google/android/gms/internal/zzcjl;
    //   3014: astore #16
    //   3016: ldc_w 'No string or number filter defined. property'
    //   3019: astore #18
    //   3021: goto -> 3120
    //   3024: aload #24
    //   3026: getfield zzgim : Ljava/lang/String;
    //   3029: invokestatic zzkr : (Ljava/lang/String;)Z
    //   3032: ifeq -> 3054
    //   3035: aload_0
    //   3036: aload #24
    //   3038: getfield zzgim : Ljava/lang/String;
    //   3041: aload #16
    //   3043: getfield zzjte : Lcom/google/android/gms/internal/zzcnu;
    //   3046: invokespecial zza : (Ljava/lang/String;Lcom/google/android/gms/internal/zzcnu;)Ljava/lang/Boolean;
    //   3049: astore #16
    //   3051: goto -> 2916
    //   3054: aload_0
    //   3055: invokevirtual zzayp : ()Lcom/google/android/gms/internal/zzcjj;
    //   3058: invokevirtual zzbaw : ()Lcom/google/android/gms/internal/zzcjl;
    //   3061: ldc_w 'Invalid user property value for Numeric number filter. property, value'
    //   3064: aload_0
    //   3065: invokevirtual zzayk : ()Lcom/google/android/gms/internal/zzcjh;
    //   3068: aload #24
    //   3070: getfield name : Ljava/lang/String;
    //   3073: invokevirtual zzjr : (Ljava/lang/String;)Ljava/lang/String;
    //   3076: aload #24
    //   3078: getfield zzgim : Ljava/lang/String;
    //   3081: invokevirtual zze : (Ljava/lang/String;Ljava/lang/Object;Ljava/lang/Object;)V
    //   3084: goto -> 3139
    //   3087: aload_0
    //   3088: aload #24
    //   3090: getfield zzgim : Ljava/lang/String;
    //   3093: aload #16
    //   3095: getfield zzjtd : Lcom/google/android/gms/internal/zzcnw;
    //   3098: invokespecial zza : (Ljava/lang/String;Lcom/google/android/gms/internal/zzcnw;)Ljava/lang/Boolean;
    //   3101: astore #16
    //   3103: goto -> 2916
    //   3106: aload_0
    //   3107: invokevirtual zzayp : ()Lcom/google/android/gms/internal/zzcjj;
    //   3110: invokevirtual zzbaw : ()Lcom/google/android/gms/internal/zzcjl;
    //   3113: astore #16
    //   3115: ldc_w 'User property has no value, property'
    //   3118: astore #18
    //   3120: aload #16
    //   3122: aload #18
    //   3124: aload_0
    //   3125: invokevirtual zzayk : ()Lcom/google/android/gms/internal/zzcjh;
    //   3128: aload #24
    //   3130: getfield name : Ljava/lang/String;
    //   3133: invokevirtual zzjr : (Ljava/lang/String;)Ljava/lang/String;
    //   3136: invokevirtual zzj : (Ljava/lang/String;Ljava/lang/Object;)V
    //   3139: aconst_null
    //   3140: astore #16
    //   3142: aload_0
    //   3143: invokevirtual zzayp : ()Lcom/google/android/gms/internal/zzcjj;
    //   3146: invokevirtual zzbba : ()Lcom/google/android/gms/internal/zzcjl;
    //   3149: astore #26
    //   3151: aload #16
    //   3153: ifnonnull -> 3164
    //   3156: ldc_w 'null'
    //   3159: astore #18
    //   3161: goto -> 3168
    //   3164: aload #16
    //   3166: astore #18
    //   3168: aload #26
    //   3170: ldc_w 'Property filter result'
    //   3173: aload #18
    //   3175: invokevirtual zzj : (Ljava/lang/String;Ljava/lang/Object;)V
    //   3178: aload #16
    //   3180: ifnonnull -> 3202
    //   3183: aload #28
    //   3185: iload #6
    //   3187: invokestatic valueOf : (I)Ljava/lang/Integer;
    //   3190: invokeinterface add : (Ljava/lang/Object;)Z
    //   3195: pop
    //   3196: aload_1
    //   3197: astore #18
    //   3199: goto -> 2785
    //   3202: aload #22
    //   3204: aload #25
    //   3206: getfield zzjsx : Ljava/lang/Integer;
    //   3209: invokevirtual intValue : ()I
    //   3212: invokevirtual set : (I)V
    //   3215: aload #16
    //   3217: invokevirtual booleanValue : ()Z
    //   3220: ifeq -> 3196
    //   3223: aload #21
    //   3225: aload #25
    //   3227: getfield zzjsx : Ljava/lang/Integer;
    //   3230: invokevirtual intValue : ()I
    //   3233: invokevirtual set : (I)V
    //   3236: goto -> 3196
    //   3239: aload_0
    //   3240: invokevirtual zzayp : ()Lcom/google/android/gms/internal/zzcjj;
    //   3243: invokevirtual zzbaw : ()Lcom/google/android/gms/internal/zzcjl;
    //   3246: ldc_w 'Invalid property filter ID. appId, id'
    //   3249: aload_1
    //   3250: invokestatic zzjs : (Ljava/lang/String;)Ljava/lang/Object;
    //   3253: aload #25
    //   3255: getfield zzjsx : Ljava/lang/Integer;
    //   3258: invokestatic valueOf : (Ljava/lang/Object;)Ljava/lang/String;
    //   3261: invokevirtual zze : (Ljava/lang/String;Ljava/lang/Object;Ljava/lang/Object;)V
    //   3264: aload #28
    //   3266: iload #6
    //   3268: invokestatic valueOf : (I)Ljava/lang/Integer;
    //   3271: invokeinterface add : (Ljava/lang/Object;)Z
    //   3276: pop
    //   3277: aload_1
    //   3278: astore #18
    //   3280: aload #17
    //   3282: astore #16
    //   3284: aload #18
    //   3286: astore #17
    //   3288: goto -> 3291
    //   3291: goto -> 2398
    //   3294: iload #5
    //   3296: iconst_1
    //   3297: iadd
    //   3298: istore #5
    //   3300: aload_3
    //   3301: astore #26
    //   3303: aload #15
    //   3305: astore #21
    //   3307: aload #19
    //   3309: astore_2
    //   3310: aload #20
    //   3312: astore #15
    //   3314: goto -> 2270
    //   3317: aload #19
    //   3319: invokeinterface size : ()I
    //   3324: anewarray com/google/android/gms/internal/zzcoa
    //   3327: astore #17
    //   3329: aload #19
    //   3331: invokeinterface keySet : ()Ljava/util/Set;
    //   3336: invokeinterface iterator : ()Ljava/util/Iterator;
    //   3341: astore #20
    //   3343: iconst_0
    //   3344: istore #4
    //   3346: aload #20
    //   3348: invokeinterface hasNext : ()Z
    //   3353: ifeq -> 3698
    //   3356: aload #20
    //   3358: invokeinterface next : ()Ljava/lang/Object;
    //   3363: checkcast java/lang/Integer
    //   3366: invokevirtual intValue : ()I
    //   3369: istore #5
    //   3371: aload #28
    //   3373: iload #5
    //   3375: invokestatic valueOf : (I)Ljava/lang/Integer;
    //   3378: invokeinterface contains : (Ljava/lang/Object;)Z
    //   3383: ifne -> 3346
    //   3386: aload #29
    //   3388: iload #5
    //   3390: invokestatic valueOf : (I)Ljava/lang/Integer;
    //   3393: invokeinterface get : (Ljava/lang/Object;)Ljava/lang/Object;
    //   3398: checkcast com/google/android/gms/internal/zzcoa
    //   3401: astore_3
    //   3402: aload_3
    //   3403: astore_2
    //   3404: aload_3
    //   3405: ifnonnull -> 3416
    //   3408: new com/google/android/gms/internal/zzcoa
    //   3411: dup
    //   3412: invokespecial <init> : ()V
    //   3415: astore_2
    //   3416: aload #17
    //   3418: iload #4
    //   3420: aload_2
    //   3421: aastore
    //   3422: aload_2
    //   3423: iload #5
    //   3425: invokestatic valueOf : (I)Ljava/lang/Integer;
    //   3428: putfield zzjst : Ljava/lang/Integer;
    //   3431: aload_2
    //   3432: new com/google/android/gms/internal/zzcof
    //   3435: dup
    //   3436: invokespecial <init> : ()V
    //   3439: putfield zzjue : Lcom/google/android/gms/internal/zzcof;
    //   3442: aload_2
    //   3443: getfield zzjue : Lcom/google/android/gms/internal/zzcof;
    //   3446: aload #19
    //   3448: iload #5
    //   3450: invokestatic valueOf : (I)Ljava/lang/Integer;
    //   3453: invokeinterface get : (Ljava/lang/Object;)Ljava/lang/Object;
    //   3458: checkcast java/util/BitSet
    //   3461: invokestatic zza : (Ljava/util/BitSet;)[J
    //   3464: putfield zzjvp : [J
    //   3467: aload_2
    //   3468: getfield zzjue : Lcom/google/android/gms/internal/zzcof;
    //   3471: aload #18
    //   3473: iload #5
    //   3475: invokestatic valueOf : (I)Ljava/lang/Integer;
    //   3478: invokeinterface get : (Ljava/lang/Object;)Ljava/lang/Object;
    //   3483: checkcast java/util/BitSet
    //   3486: invokestatic zza : (Ljava/util/BitSet;)[J
    //   3489: putfield zzjvo : [J
    //   3492: aload_0
    //   3493: invokevirtual zzayj : ()Lcom/google/android/gms/internal/zzcil;
    //   3496: astore_3
    //   3497: aload_2
    //   3498: getfield zzjue : Lcom/google/android/gms/internal/zzcof;
    //   3501: astore #15
    //   3503: aload_3
    //   3504: invokevirtual zzyk : ()V
    //   3507: aload_3
    //   3508: invokevirtual zzwj : ()V
    //   3511: aload_1
    //   3512: invokestatic zzgv : (Ljava/lang/String;)Ljava/lang/String;
    //   3515: pop
    //   3516: aload #15
    //   3518: invokestatic checkNotNull : (Ljava/lang/Object;)Ljava/lang/Object;
    //   3521: pop
    //   3522: aload #15
    //   3524: invokevirtual zzhs : ()I
    //   3527: newarray byte
    //   3529: astore_2
    //   3530: aload_2
    //   3531: arraylength
    //   3532: istore #6
    //   3534: aload_2
    //   3535: iconst_0
    //   3536: iload #6
    //   3538: invokestatic zzp : ([BII)Lcom/google/android/gms/internal/zzflk;
    //   3541: astore #21
    //   3543: aload #15
    //   3545: aload #21
    //   3547: invokevirtual zza : (Lcom/google/android/gms/internal/zzflk;)V
    //   3550: aload #21
    //   3552: invokevirtual zzcyx : ()V
    //   3555: new android/content/ContentValues
    //   3558: dup
    //   3559: invokespecial <init> : ()V
    //   3562: astore #15
    //   3564: aload #15
    //   3566: ldc_w 'app_id'
    //   3569: aload #16
    //   3571: invokevirtual put : (Ljava/lang/String;Ljava/lang/String;)V
    //   3574: aload #15
    //   3576: ldc_w 'audience_id'
    //   3579: iload #5
    //   3581: invokestatic valueOf : (I)Ljava/lang/Integer;
    //   3584: invokevirtual put : (Ljava/lang/String;Ljava/lang/Integer;)V
    //   3587: aload #15
    //   3589: ldc_w 'current_results'
    //   3592: aload_2
    //   3593: invokevirtual put : (Ljava/lang/String;[B)V
    //   3596: aload_3
    //   3597: invokevirtual getWritableDatabase : ()Landroid/database/sqlite/SQLiteDatabase;
    //   3600: astore_2
    //   3601: aload_2
    //   3602: ldc_w 'audience_filter_values'
    //   3605: aconst_null
    //   3606: aload #15
    //   3608: iconst_5
    //   3609: invokevirtual insertWithOnConflict : (Ljava/lang/String;Ljava/lang/String;Landroid/content/ContentValues;I)J
    //   3612: ldc2_w -1
    //   3615: lcmp
    //   3616: ifne -> 3689
    //   3619: aload_3
    //   3620: invokevirtual zzayp : ()Lcom/google/android/gms/internal/zzcjj;
    //   3623: invokevirtual zzbau : ()Lcom/google/android/gms/internal/zzcjl;
    //   3626: ldc_w 'Failed to insert filter results (got -1). appId'
    //   3629: aload_1
    //   3630: invokestatic zzjs : (Ljava/lang/String;)Ljava/lang/Object;
    //   3633: invokevirtual zzj : (Ljava/lang/String;Ljava/lang/Object;)V
    //   3636: goto -> 3689
    //   3639: astore_2
    //   3640: goto -> 3644
    //   3643: astore_2
    //   3644: aload_3
    //   3645: invokevirtual zzayp : ()Lcom/google/android/gms/internal/zzcjj;
    //   3648: invokevirtual zzbau : ()Lcom/google/android/gms/internal/zzcjl;
    //   3651: astore_3
    //   3652: ldc_w 'Error storing filter results. appId'
    //   3655: astore #15
    //   3657: goto -> 3678
    //   3660: astore_2
    //   3661: goto -> 3665
    //   3664: astore_2
    //   3665: aload_3
    //   3666: invokevirtual zzayp : ()Lcom/google/android/gms/internal/zzcjj;
    //   3669: invokevirtual zzbau : ()Lcom/google/android/gms/internal/zzcjl;
    //   3672: astore_3
    //   3673: ldc_w 'Configuration loss. Failed to serialize filter results. appId'
    //   3676: astore #15
    //   3678: aload_3
    //   3679: aload #15
    //   3681: aload_1
    //   3682: invokestatic zzjs : (Ljava/lang/String;)Ljava/lang/Object;
    //   3685: aload_2
    //   3686: invokevirtual zze : (Ljava/lang/String;Ljava/lang/Object;Ljava/lang/Object;)V
    //   3689: iload #4
    //   3691: iconst_1
    //   3692: iadd
    //   3693: istore #4
    //   3695: goto -> 3346
    //   3698: aload #17
    //   3700: iload #4
    //   3702: invokestatic copyOf : ([Ljava/lang/Object;I)[Ljava/lang/Object;
    //   3705: checkcast [Lcom/google/android/gms/internal/zzcoa;
    //   3708: areturn
    // Exception table:
    //   from	to	target	type
    //   808	815	844	android/database/sqlite/SQLiteException
    //   815	832	835	android/database/sqlite/SQLiteException
    //   3522	3534	3664	java/io/IOException
    //   3534	3555	3660	java/io/IOException
    //   3596	3601	3643	android/database/sqlite/SQLiteException
    //   3601	3636	3639	android/database/sqlite/SQLiteException
  }
  
  protected final boolean zzazq() {
    return false;
  }
}


/* Location:              /home/egaebel/Programs/sony-headphones-hack/base-dex2jar.jar!/com/google/android/gms/internal/zzcih.class
 * Java compiler version: 6 (50.0)
 * JD-Core Version:       1.1.3
 */