package com.google.android.gms.internal;

import com.google.android.gms.common.internal.zzbq;
import java.net.URL;
import java.util.Map;

final class zzcjr implements Runnable {
  private final String packageName;
  
  private final URL url;
  
  private final byte[] zzjlc;
  
  private final zzcjp zzjld;
  
  private final Map<String, String> zzjle;
  
  public zzcjr(zzcjn paramzzcjn, String paramString, URL paramURL, byte[] paramArrayOfbyte, Map<String, String> paramMap, zzcjp paramzzcjp) {
    zzbq.zzgv(paramString);
    zzbq.checkNotNull(paramURL);
    zzbq.checkNotNull(paramzzcjp);
    this.url = paramURL;
    this.zzjlc = paramArrayOfbyte;
    this.zzjld = paramzzcjp;
    this.packageName = paramString;
    this.zzjle = paramMap;
  }
  
  public final void run() {
    // Byte code:
    //   0: aload_0
    //   1: getfield zzjlf : Lcom/google/android/gms/internal/zzcjn;
    //   4: invokevirtual zzaya : ()V
    //   7: aconst_null
    //   8: astore #4
    //   10: aconst_null
    //   11: astore #5
    //   13: aconst_null
    //   14: astore #6
    //   16: aconst_null
    //   17: astore #7
    //   19: aload_0
    //   20: getfield zzjlf : Lcom/google/android/gms/internal/zzcjn;
    //   23: aload_0
    //   24: getfield url : Ljava/net/URL;
    //   27: invokevirtual zzb : (Ljava/net/URL;)Ljava/net/HttpURLConnection;
    //   30: astore_2
    //   31: aload_0
    //   32: getfield zzjle : Ljava/util/Map;
    //   35: ifnull -> 100
    //   38: aload_0
    //   39: getfield zzjle : Ljava/util/Map;
    //   42: invokeinterface entrySet : ()Ljava/util/Set;
    //   47: invokeinterface iterator : ()Ljava/util/Iterator;
    //   52: astore_3
    //   53: aload_3
    //   54: invokeinterface hasNext : ()Z
    //   59: ifeq -> 100
    //   62: aload_3
    //   63: invokeinterface next : ()Ljava/lang/Object;
    //   68: checkcast java/util/Map$Entry
    //   71: astore #8
    //   73: aload_2
    //   74: aload #8
    //   76: invokeinterface getKey : ()Ljava/lang/Object;
    //   81: checkcast java/lang/String
    //   84: aload #8
    //   86: invokeinterface getValue : ()Ljava/lang/Object;
    //   91: checkcast java/lang/String
    //   94: invokevirtual addRequestProperty : (Ljava/lang/String;Ljava/lang/String;)V
    //   97: goto -> 53
    //   100: aload_0
    //   101: getfield zzjlc : [B
    //   104: ifnull -> 202
    //   107: aload_0
    //   108: getfield zzjlf : Lcom/google/android/gms/internal/zzcjn;
    //   111: invokevirtual zzayl : ()Lcom/google/android/gms/internal/zzcno;
    //   114: aload_0
    //   115: getfield zzjlc : [B
    //   118: invokevirtual zzr : ([B)[B
    //   121: astore #8
    //   123: aload_0
    //   124: getfield zzjlf : Lcom/google/android/gms/internal/zzcjn;
    //   127: invokevirtual zzayp : ()Lcom/google/android/gms/internal/zzcjj;
    //   130: invokevirtual zzbba : ()Lcom/google/android/gms/internal/zzcjl;
    //   133: ldc 'Uploading data. size'
    //   135: aload #8
    //   137: arraylength
    //   138: invokestatic valueOf : (I)Ljava/lang/Integer;
    //   141: invokevirtual zzj : (Ljava/lang/String;Ljava/lang/Object;)V
    //   144: aload_2
    //   145: iconst_1
    //   146: invokevirtual setDoOutput : (Z)V
    //   149: aload_2
    //   150: ldc 'Content-Encoding'
    //   152: ldc 'gzip'
    //   154: invokevirtual addRequestProperty : (Ljava/lang/String;Ljava/lang/String;)V
    //   157: aload_2
    //   158: aload #8
    //   160: arraylength
    //   161: invokevirtual setFixedLengthStreamingMode : (I)V
    //   164: aload_2
    //   165: invokevirtual connect : ()V
    //   168: aload_2
    //   169: invokevirtual getOutputStream : ()Ljava/io/OutputStream;
    //   172: astore_3
    //   173: aload_3
    //   174: aload #8
    //   176: invokevirtual write : ([B)V
    //   179: aload_3
    //   180: invokevirtual close : ()V
    //   183: goto -> 202
    //   186: astore #5
    //   188: aload_2
    //   189: astore #4
    //   191: aload #5
    //   193: astore_2
    //   194: goto -> 340
    //   197: astore #4
    //   199: goto -> 437
    //   202: aload_2
    //   203: invokevirtual getResponseCode : ()I
    //   206: istore_1
    //   207: aload_2
    //   208: invokevirtual getHeaderFields : ()Ljava/util/Map;
    //   211: astore_3
    //   212: aload_0
    //   213: getfield zzjlf : Lcom/google/android/gms/internal/zzcjn;
    //   216: aload_2
    //   217: invokestatic zza : (Lcom/google/android/gms/internal/zzcjn;Ljava/net/HttpURLConnection;)[B
    //   220: astore #5
    //   222: aload_2
    //   223: ifnull -> 230
    //   226: aload_2
    //   227: invokevirtual disconnect : ()V
    //   230: aload_0
    //   231: getfield zzjlf : Lcom/google/android/gms/internal/zzcjn;
    //   234: invokevirtual zzayo : ()Lcom/google/android/gms/internal/zzcke;
    //   237: astore_2
    //   238: new com/google/android/gms/internal/zzcjq
    //   241: dup
    //   242: aload_0
    //   243: getfield packageName : Ljava/lang/String;
    //   246: aload_0
    //   247: getfield zzjld : Lcom/google/android/gms/internal/zzcjp;
    //   250: iload_1
    //   251: aconst_null
    //   252: aload #5
    //   254: aload_3
    //   255: aconst_null
    //   256: invokespecial <init> : (Ljava/lang/String;Lcom/google/android/gms/internal/zzcjp;ILjava/lang/Throwable;[BLjava/util/Map;Lcom/google/android/gms/internal/zzcjo;)V
    //   259: astore_3
    //   260: aload_2
    //   261: aload_3
    //   262: invokevirtual zzh : (Ljava/lang/Runnable;)V
    //   265: return
    //   266: astore #5
    //   268: aload #4
    //   270: astore #6
    //   272: aload_2
    //   273: astore #4
    //   275: aload #5
    //   277: astore_2
    //   278: aload_3
    //   279: astore #5
    //   281: goto -> 348
    //   284: astore #4
    //   286: goto -> 309
    //   289: astore_3
    //   290: aconst_null
    //   291: astore #5
    //   293: aload #4
    //   295: astore #6
    //   297: aload_2
    //   298: astore #4
    //   300: aload_3
    //   301: astore_2
    //   302: goto -> 348
    //   305: astore #4
    //   307: aconst_null
    //   308: astore_3
    //   309: aload_3
    //   310: astore #5
    //   312: goto -> 445
    //   315: astore #5
    //   317: aload #7
    //   319: astore_3
    //   320: aload_2
    //   321: astore #4
    //   323: aload #5
    //   325: astore_2
    //   326: goto -> 340
    //   329: astore_3
    //   330: goto -> 431
    //   333: astore_2
    //   334: aconst_null
    //   335: astore #4
    //   337: aload #7
    //   339: astore_3
    //   340: aconst_null
    //   341: astore #5
    //   343: iconst_0
    //   344: istore_1
    //   345: aload_3
    //   346: astore #6
    //   348: aload #6
    //   350: ifnull -> 385
    //   353: aload #6
    //   355: invokevirtual close : ()V
    //   358: goto -> 385
    //   361: astore_3
    //   362: aload_0
    //   363: getfield zzjlf : Lcom/google/android/gms/internal/zzcjn;
    //   366: invokevirtual zzayp : ()Lcom/google/android/gms/internal/zzcjj;
    //   369: invokevirtual zzbau : ()Lcom/google/android/gms/internal/zzcjl;
    //   372: ldc 'Error closing HTTP compressed POST connection output stream. appId'
    //   374: aload_0
    //   375: getfield packageName : Ljava/lang/String;
    //   378: invokestatic zzjs : (Ljava/lang/String;)Ljava/lang/Object;
    //   381: aload_3
    //   382: invokevirtual zze : (Ljava/lang/String;Ljava/lang/Object;Ljava/lang/Object;)V
    //   385: aload #4
    //   387: ifnull -> 395
    //   390: aload #4
    //   392: invokevirtual disconnect : ()V
    //   395: aload_0
    //   396: getfield zzjlf : Lcom/google/android/gms/internal/zzcjn;
    //   399: invokevirtual zzayo : ()Lcom/google/android/gms/internal/zzcke;
    //   402: new com/google/android/gms/internal/zzcjq
    //   405: dup
    //   406: aload_0
    //   407: getfield packageName : Ljava/lang/String;
    //   410: aload_0
    //   411: getfield zzjld : Lcom/google/android/gms/internal/zzcjp;
    //   414: iload_1
    //   415: aconst_null
    //   416: aconst_null
    //   417: aload #5
    //   419: aconst_null
    //   420: invokespecial <init> : (Ljava/lang/String;Lcom/google/android/gms/internal/zzcjp;ILjava/lang/Throwable;[BLjava/util/Map;Lcom/google/android/gms/internal/zzcjo;)V
    //   423: invokevirtual zzh : (Ljava/lang/Runnable;)V
    //   426: aload_2
    //   427: athrow
    //   428: astore_3
    //   429: aconst_null
    //   430: astore_2
    //   431: aload_3
    //   432: astore #4
    //   434: aload #5
    //   436: astore_3
    //   437: aconst_null
    //   438: astore #5
    //   440: iconst_0
    //   441: istore_1
    //   442: aload_3
    //   443: astore #6
    //   445: aload #6
    //   447: ifnull -> 482
    //   450: aload #6
    //   452: invokevirtual close : ()V
    //   455: goto -> 482
    //   458: astore_3
    //   459: aload_0
    //   460: getfield zzjlf : Lcom/google/android/gms/internal/zzcjn;
    //   463: invokevirtual zzayp : ()Lcom/google/android/gms/internal/zzcjj;
    //   466: invokevirtual zzbau : ()Lcom/google/android/gms/internal/zzcjl;
    //   469: ldc 'Error closing HTTP compressed POST connection output stream. appId'
    //   471: aload_0
    //   472: getfield packageName : Ljava/lang/String;
    //   475: invokestatic zzjs : (Ljava/lang/String;)Ljava/lang/Object;
    //   478: aload_3
    //   479: invokevirtual zze : (Ljava/lang/String;Ljava/lang/Object;Ljava/lang/Object;)V
    //   482: aload_2
    //   483: ifnull -> 490
    //   486: aload_2
    //   487: invokevirtual disconnect : ()V
    //   490: aload_0
    //   491: getfield zzjlf : Lcom/google/android/gms/internal/zzcjn;
    //   494: invokevirtual zzayo : ()Lcom/google/android/gms/internal/zzcke;
    //   497: astore_2
    //   498: new com/google/android/gms/internal/zzcjq
    //   501: dup
    //   502: aload_0
    //   503: getfield packageName : Ljava/lang/String;
    //   506: aload_0
    //   507: getfield zzjld : Lcom/google/android/gms/internal/zzcjp;
    //   510: iload_1
    //   511: aload #4
    //   513: aconst_null
    //   514: aload #5
    //   516: aconst_null
    //   517: invokespecial <init> : (Ljava/lang/String;Lcom/google/android/gms/internal/zzcjp;ILjava/lang/Throwable;[BLjava/util/Map;Lcom/google/android/gms/internal/zzcjo;)V
    //   520: astore_3
    //   521: goto -> 260
    // Exception table:
    //   from	to	target	type
    //   19	31	428	java/io/IOException
    //   19	31	333	finally
    //   31	53	329	java/io/IOException
    //   31	53	315	finally
    //   53	97	329	java/io/IOException
    //   53	97	315	finally
    //   100	173	329	java/io/IOException
    //   100	173	315	finally
    //   173	183	197	java/io/IOException
    //   173	183	186	finally
    //   202	207	329	java/io/IOException
    //   202	207	315	finally
    //   207	212	305	java/io/IOException
    //   207	212	289	finally
    //   212	222	284	java/io/IOException
    //   212	222	266	finally
    //   353	358	361	java/io/IOException
    //   450	455	458	java/io/IOException
  }
}


/* Location:              /home/egaebel/Programs/sony-headphones-hack/base-dex2jar.jar!/com/google/android/gms/internal/zzcjr.class
 * Java compiler version: 6 (50.0)
 * JD-Core Version:       1.1.3
 */