package com.google.android.gms.internal;

import android.content.BroadcastReceiver;
import android.content.Context;
import android.os.Bundle;

final class zzckb implements Runnable {
  zzckb(zzcka paramzzcka, zzckj paramzzckj, long paramLong, Bundle paramBundle, Context paramContext, zzcjj paramzzcjj) {}
  
  public final void run() {
    // Byte code:
    //   0: aload_0
    //   1: getfield zzjhl : Lcom/google/android/gms/internal/zzckj;
    //   4: invokevirtual zzayq : ()Lcom/google/android/gms/internal/zzcju;
    //   7: getfield zzjls : Lcom/google/android/gms/internal/zzcjx;
    //   10: invokevirtual get : ()J
    //   13: lstore #5
    //   15: aload_0
    //   16: getfield zzjmq : J
    //   19: lstore_3
    //   20: lload_3
    //   21: lstore_1
    //   22: lload #5
    //   24: lconst_0
    //   25: lcmp
    //   26: ifle -> 49
    //   29: lload_3
    //   30: lload #5
    //   32: lcmp
    //   33: ifge -> 44
    //   36: lload_3
    //   37: lstore_1
    //   38: lload_3
    //   39: lconst_0
    //   40: lcmp
    //   41: ifgt -> 49
    //   44: lload #5
    //   46: lconst_1
    //   47: lsub
    //   48: lstore_1
    //   49: lload_1
    //   50: lconst_0
    //   51: lcmp
    //   52: ifle -> 65
    //   55: aload_0
    //   56: getfield zzjmr : Landroid/os/Bundle;
    //   59: ldc 'click_timestamp'
    //   61: lload_1
    //   62: invokevirtual putLong : (Ljava/lang/String;J)V
    //   65: aload_0
    //   66: getfield val$context : Landroid/content/Context;
    //   69: invokestatic getInstance : (Landroid/content/Context;)Lcom/google/android/gms/measurement/AppMeasurement;
    //   72: ldc 'auto'
    //   74: ldc '_cmp'
    //   76: aload_0
    //   77: getfield zzjmr : Landroid/os/Bundle;
    //   80: invokevirtual logEventInternal : (Ljava/lang/String;Ljava/lang/String;Landroid/os/Bundle;)V
    //   83: aload_0
    //   84: getfield zzjms : Lcom/google/android/gms/internal/zzcjj;
    //   87: invokevirtual zzbba : ()Lcom/google/android/gms/internal/zzcjl;
    //   90: ldc 'Install campaign recorded'
    //   92: invokevirtual log : (Ljava/lang/String;)V
    //   95: aload_0
    //   96: getfield zzdue : Landroid/content/BroadcastReceiver$PendingResult;
    //   99: astore #7
    //   101: aload #7
    //   103: ifnull -> 111
    //   106: aload #7
    //   108: invokevirtual finish : ()V
    //   111: return
  }
}


/* Location:              /home/egaebel/Programs/sony-headphones-hack/base-dex2jar.jar!/com/google/android/gms/internal/zzckb.class
 * Java compiler version: 6 (50.0)
 * JD-Core Version:       1.1.3
 */