package com.google.android.gms.internal;

import android.content.Context;
import android.content.pm.PackageInfo;
import android.content.pm.PackageManager;
import android.database.sqlite.SQLiteDatabase;
import android.database.sqlite.SQLiteException;
import android.net.Uri;
import android.os.Build;
import android.os.Bundle;
import android.text.TextUtils;
import androidx.b.a;
import com.google.android.gms.common.api.internal.zzbz;
import com.google.android.gms.common.internal.zzbq;
import com.google.android.gms.common.util.zze;
import com.google.android.gms.measurement.AppMeasurement;
import com.google.firebase.analytics.FirebaseAnalytics;
import java.io.File;
import java.io.FileNotFoundException;
import java.io.IOException;
import java.io.RandomAccessFile;
import java.net.MalformedURLException;
import java.net.URL;
import java.nio.ByteBuffer;
import java.nio.channels.FileChannel;
import java.nio.channels.FileLock;
import java.util.ArrayList;
import java.util.Collections;
import java.util.Iterator;
import java.util.List;
import java.util.Locale;
import java.util.Map;
import java.util.concurrent.ExecutionException;
import java.util.concurrent.Future;
import java.util.concurrent.TimeUnit;
import java.util.concurrent.TimeoutException;
import java.util.concurrent.atomic.AtomicReference;

public class zzckj {
  private static volatile zzckj zzjnr;
  
  private boolean initialized;
  
  private final Context zzaiq;
  
  private final zze zzdir;
  
  private final long zzjgk;
  
  private final zzcik zzjns;
  
  private final zzcju zzjnt;
  
  private final zzcjj zzjnu;
  
  private final zzcke zzjnv;
  
  private final zzcnd zzjnw;
  
  private final zzckd zzjnx;
  
  private final AppMeasurement zzjny;
  
  private final FirebaseAnalytics zzjnz;
  
  private final zzcno zzjoa;
  
  private final zzcjh zzjob;
  
  private final zzcjn zzjoc;
  
  private final zzcma zzjod;
  
  private final zzclk zzjoe;
  
  private final zzcia zzjof;
  
  private zzcil zzjog;
  
  private zzcjf zzjoh;
  
  private zzcme zzjoi;
  
  private zzcir zzjoj;
  
  private zzcje zzjok;
  
  private zzcjs zzjol;
  
  private zzcnj zzjom;
  
  private zzcih zzjon;
  
  private boolean zzjoo;
  
  private Boolean zzjop;
  
  private long zzjoq;
  
  private FileLock zzjor;
  
  private FileChannel zzjos;
  
  private List<Long> zzjot;
  
  private List<Runnable> zzjou;
  
  private int zzjov;
  
  private int zzjow;
  
  private long zzjox;
  
  private long zzjoy;
  
  private boolean zzjoz;
  
  private boolean zzjpa;
  
  private boolean zzjpb;
  
  private zzckj(zzclj paramzzclj) {
    // Byte code:
    //   0: aload_0
    //   1: invokespecial <init> : ()V
    //   4: aload_0
    //   5: iconst_0
    //   6: putfield initialized : Z
    //   9: aload_1
    //   10: invokestatic checkNotNull : (Ljava/lang/Object;)Ljava/lang/Object;
    //   13: pop
    //   14: aload_0
    //   15: aload_1
    //   16: getfield zzaiq : Landroid/content/Context;
    //   19: putfield zzaiq : Landroid/content/Context;
    //   22: aload_0
    //   23: ldc2_w -1
    //   26: putfield zzjox : J
    //   29: aload_0
    //   30: invokestatic zzanq : ()Lcom/google/android/gms/common/util/zze;
    //   33: putfield zzdir : Lcom/google/android/gms/common/util/zze;
    //   36: aload_0
    //   37: aload_0
    //   38: getfield zzdir : Lcom/google/android/gms/common/util/zze;
    //   41: invokeinterface currentTimeMillis : ()J
    //   46: putfield zzjgk : J
    //   49: aload_0
    //   50: new com/google/android/gms/internal/zzcik
    //   53: dup
    //   54: aload_0
    //   55: invokespecial <init> : (Lcom/google/android/gms/internal/zzckj;)V
    //   58: putfield zzjns : Lcom/google/android/gms/internal/zzcik;
    //   61: new com/google/android/gms/internal/zzcju
    //   64: dup
    //   65: aload_0
    //   66: invokespecial <init> : (Lcom/google/android/gms/internal/zzckj;)V
    //   69: astore_2
    //   70: aload_2
    //   71: invokevirtual initialize : ()V
    //   74: aload_0
    //   75: aload_2
    //   76: putfield zzjnt : Lcom/google/android/gms/internal/zzcju;
    //   79: new com/google/android/gms/internal/zzcjj
    //   82: dup
    //   83: aload_0
    //   84: invokespecial <init> : (Lcom/google/android/gms/internal/zzckj;)V
    //   87: astore_2
    //   88: aload_2
    //   89: invokevirtual initialize : ()V
    //   92: aload_0
    //   93: aload_2
    //   94: putfield zzjnu : Lcom/google/android/gms/internal/zzcjj;
    //   97: new com/google/android/gms/internal/zzcno
    //   100: dup
    //   101: aload_0
    //   102: invokespecial <init> : (Lcom/google/android/gms/internal/zzckj;)V
    //   105: astore_2
    //   106: aload_2
    //   107: invokevirtual initialize : ()V
    //   110: aload_0
    //   111: aload_2
    //   112: putfield zzjoa : Lcom/google/android/gms/internal/zzcno;
    //   115: new com/google/android/gms/internal/zzcjh
    //   118: dup
    //   119: aload_0
    //   120: invokespecial <init> : (Lcom/google/android/gms/internal/zzckj;)V
    //   123: astore_2
    //   124: aload_2
    //   125: invokevirtual initialize : ()V
    //   128: aload_0
    //   129: aload_2
    //   130: putfield zzjob : Lcom/google/android/gms/internal/zzcjh;
    //   133: aload_0
    //   134: new com/google/android/gms/internal/zzcia
    //   137: dup
    //   138: aload_0
    //   139: invokespecial <init> : (Lcom/google/android/gms/internal/zzckj;)V
    //   142: putfield zzjof : Lcom/google/android/gms/internal/zzcia;
    //   145: new com/google/android/gms/internal/zzcjn
    //   148: dup
    //   149: aload_0
    //   150: invokespecial <init> : (Lcom/google/android/gms/internal/zzckj;)V
    //   153: astore_2
    //   154: aload_2
    //   155: invokevirtual initialize : ()V
    //   158: aload_0
    //   159: aload_2
    //   160: putfield zzjoc : Lcom/google/android/gms/internal/zzcjn;
    //   163: new com/google/android/gms/internal/zzcma
    //   166: dup
    //   167: aload_0
    //   168: invokespecial <init> : (Lcom/google/android/gms/internal/zzckj;)V
    //   171: astore_2
    //   172: aload_2
    //   173: invokevirtual initialize : ()V
    //   176: aload_0
    //   177: aload_2
    //   178: putfield zzjod : Lcom/google/android/gms/internal/zzcma;
    //   181: new com/google/android/gms/internal/zzclk
    //   184: dup
    //   185: aload_0
    //   186: invokespecial <init> : (Lcom/google/android/gms/internal/zzckj;)V
    //   189: astore_2
    //   190: aload_2
    //   191: invokevirtual initialize : ()V
    //   194: aload_0
    //   195: aload_2
    //   196: putfield zzjoe : Lcom/google/android/gms/internal/zzclk;
    //   199: aload_0
    //   200: new com/google/android/gms/measurement/AppMeasurement
    //   203: dup
    //   204: aload_0
    //   205: invokespecial <init> : (Lcom/google/android/gms/internal/zzckj;)V
    //   208: putfield zzjny : Lcom/google/android/gms/measurement/AppMeasurement;
    //   211: aload_0
    //   212: new com/google/firebase/analytics/FirebaseAnalytics
    //   215: dup
    //   216: aload_0
    //   217: invokespecial <init> : (Lcom/google/android/gms/internal/zzckj;)V
    //   220: putfield zzjnz : Lcom/google/firebase/analytics/FirebaseAnalytics;
    //   223: new com/google/android/gms/internal/zzcnd
    //   226: dup
    //   227: aload_0
    //   228: invokespecial <init> : (Lcom/google/android/gms/internal/zzckj;)V
    //   231: astore_2
    //   232: aload_2
    //   233: invokevirtual initialize : ()V
    //   236: aload_0
    //   237: aload_2
    //   238: putfield zzjnw : Lcom/google/android/gms/internal/zzcnd;
    //   241: new com/google/android/gms/internal/zzckd
    //   244: dup
    //   245: aload_0
    //   246: invokespecial <init> : (Lcom/google/android/gms/internal/zzckj;)V
    //   249: astore_2
    //   250: aload_2
    //   251: invokevirtual initialize : ()V
    //   254: aload_0
    //   255: aload_2
    //   256: putfield zzjnx : Lcom/google/android/gms/internal/zzckd;
    //   259: new com/google/android/gms/internal/zzcke
    //   262: dup
    //   263: aload_0
    //   264: invokespecial <init> : (Lcom/google/android/gms/internal/zzckj;)V
    //   267: astore_2
    //   268: aload_2
    //   269: invokevirtual initialize : ()V
    //   272: aload_0
    //   273: aload_2
    //   274: putfield zzjnv : Lcom/google/android/gms/internal/zzcke;
    //   277: aload_0
    //   278: getfield zzaiq : Landroid/content/Context;
    //   281: invokevirtual getApplicationContext : ()Landroid/content/Context;
    //   284: instanceof android/app/Application
    //   287: ifeq -> 369
    //   290: aload_0
    //   291: invokevirtual zzayd : ()Lcom/google/android/gms/internal/zzclk;
    //   294: astore_2
    //   295: aload_2
    //   296: invokevirtual getContext : ()Landroid/content/Context;
    //   299: invokevirtual getApplicationContext : ()Landroid/content/Context;
    //   302: instanceof android/app/Application
    //   305: ifeq -> 385
    //   308: aload_2
    //   309: invokevirtual getContext : ()Landroid/content/Context;
    //   312: invokevirtual getApplicationContext : ()Landroid/content/Context;
    //   315: checkcast android/app/Application
    //   318: astore_3
    //   319: aload_2
    //   320: getfield zzjpt : Lcom/google/android/gms/internal/zzcly;
    //   323: ifnonnull -> 339
    //   326: aload_2
    //   327: new com/google/android/gms/internal/zzcly
    //   330: dup
    //   331: aload_2
    //   332: aconst_null
    //   333: invokespecial <init> : (Lcom/google/android/gms/internal/zzclk;Lcom/google/android/gms/internal/zzcll;)V
    //   336: putfield zzjpt : Lcom/google/android/gms/internal/zzcly;
    //   339: aload_3
    //   340: aload_2
    //   341: getfield zzjpt : Lcom/google/android/gms/internal/zzcly;
    //   344: invokevirtual unregisterActivityLifecycleCallbacks : (Landroid/app/Application$ActivityLifecycleCallbacks;)V
    //   347: aload_3
    //   348: aload_2
    //   349: getfield zzjpt : Lcom/google/android/gms/internal/zzcly;
    //   352: invokevirtual registerActivityLifecycleCallbacks : (Landroid/app/Application$ActivityLifecycleCallbacks;)V
    //   355: aload_2
    //   356: invokevirtual zzayp : ()Lcom/google/android/gms/internal/zzcjj;
    //   359: invokevirtual zzbba : ()Lcom/google/android/gms/internal/zzcjl;
    //   362: astore_2
    //   363: ldc 'Registered activity lifecycle callback'
    //   365: astore_3
    //   366: goto -> 380
    //   369: aload_0
    //   370: invokevirtual zzayp : ()Lcom/google/android/gms/internal/zzcjj;
    //   373: invokevirtual zzbaw : ()Lcom/google/android/gms/internal/zzcjl;
    //   376: astore_2
    //   377: ldc 'Application context is not an Application'
    //   379: astore_3
    //   380: aload_2
    //   381: aload_3
    //   382: invokevirtual log : (Ljava/lang/String;)V
    //   385: aload_0
    //   386: getfield zzjnv : Lcom/google/android/gms/internal/zzcke;
    //   389: new com/google/android/gms/internal/zzckk
    //   392: dup
    //   393: aload_0
    //   394: aload_1
    //   395: invokespecial <init> : (Lcom/google/android/gms/internal/zzckj;Lcom/google/android/gms/internal/zzclj;)V
    //   398: invokevirtual zzh : (Ljava/lang/Runnable;)V
    //   401: return
  }
  
  private final int zza(FileChannel paramFileChannel) {
    zzayo().zzwj();
    if (paramFileChannel == null || !paramFileChannel.isOpen()) {
      zzayp().zzbau().log("Bad channel to read from");
      return 0;
    } 
    ByteBuffer byteBuffer = ByteBuffer.allocate(4);
    try {
      paramFileChannel.position(0L);
      int i = paramFileChannel.read(byteBuffer);
      if (i != 4) {
        if (i != -1) {
          zzayp().zzbaw().zzj("Unexpected data length. Bytes read", Integer.valueOf(i));
          return 0;
        } 
      } else {
        byteBuffer.flip();
        return byteBuffer.getInt();
      } 
    } catch (IOException iOException) {
      zzayp().zzbau().zzj("Failed to read from channel", iOException);
      return 0;
    } 
    return 0;
  }
  
  private final zzcif zza(Context paramContext, String paramString1, String paramString2, boolean paramBoolean1, boolean paramBoolean2) {
    String str1;
    String str2 = "Unknown";
    String str3 = "Unknown";
    PackageManager packageManager = paramContext.getPackageManager();
    if (packageManager == null) {
      zzayp().zzbau().log("PackageManager is null, can not log app install information");
      return null;
    } 
    try {
      str1 = packageManager.getInstallerPackageName(paramString1);
      str2 = str1;
    } catch (IllegalArgumentException illegalArgumentException) {
      zzayp().zzbau().zzj("Error retrieving installer package name. appId", zzcjj.zzjs(paramString1));
    } 
    if (str2 == null) {
      str1 = "manual_install";
    } else {
      str1 = str2;
      if ("com.android.vending".equals(str2))
        str1 = ""; 
    } 
    String str4 = str3;
    try {
      int i;
      PackageInfo packageInfo = zzbih.zzdd(paramContext).getPackageInfo(paramString1, 0);
      if (packageInfo != null) {
        str4 = str3;
        CharSequence charSequence = zzbih.zzdd(paramContext).zzhc(paramString1);
        str2 = str3;
        str4 = str3;
        if (!TextUtils.isEmpty(charSequence)) {
          str4 = str3;
          str2 = charSequence.toString();
        } 
        str4 = str2;
        str3 = packageInfo.versionName;
        str4 = str2;
        i = packageInfo.versionCode;
        str2 = str3;
      } else {
        str2 = "Unknown";
        i = Integer.MIN_VALUE;
      } 
      return new zzcif(paramString1, paramString2, str2, i, str1, 12211L, zzayl().zzab(paramContext, paramString1), null, paramBoolean1, false, "", 0L, 0L, 0, paramBoolean2);
    } catch (android.content.pm.PackageManager.NameNotFoundException nameNotFoundException) {}
    zzayp().zzbau().zze("Error retrieving newly installed package info. appId, appName", zzcjj.zzjs(paramString1), str4);
    return null;
  }
  
  private static void zza(zzclh paramzzclh) {
    if (paramzzclh != null)
      return; 
    throw new IllegalStateException("Component not created");
  }
  
  private static void zza(zzcli paramzzcli) {
    if (paramzzcli != null) {
      if (paramzzcli.isInitialized())
        return; 
      String str = String.valueOf(paramzzcli.getClass());
      StringBuilder stringBuilder = new StringBuilder(String.valueOf(str).length() + 27);
      stringBuilder.append("Component not initialized: ");
      stringBuilder.append(str);
      throw new IllegalStateException(stringBuilder.toString());
    } 
    throw new IllegalStateException("Component not created");
  }
  
  private final void zza(zzclj paramzzclj) {
    zzcjl zzcjl;
    zzayo().zzwj();
    zzcir zzcir1 = new zzcir(this);
    zzcir1.initialize();
    this.zzjoj = zzcir1;
    zzcje zzcje1 = new zzcje(this);
    zzcje1.initialize();
    this.zzjok = zzcje1;
    zzcil zzcil1 = new zzcil(this);
    zzcil1.initialize();
    this.zzjog = zzcil1;
    zzcjf zzcjf1 = new zzcjf(this);
    zzcjf1.initialize();
    this.zzjoh = zzcjf1;
    zzcih zzcih1 = new zzcih(this);
    zzcih1.initialize();
    this.zzjon = zzcih1;
    zzcme zzcme1 = new zzcme(this);
    zzcme1.initialize();
    this.zzjoi = zzcme1;
    zzcnj zzcnj1 = new zzcnj(this);
    zzcnj1.initialize();
    this.zzjom = zzcnj1;
    this.zzjol = new zzcjs(this);
    this.zzjoa.zzbcf();
    this.zzjnt.zzbcf();
    this.zzjok.zzbcf();
    zzayp().zzbay().zzj("App measurement is starting up, version", Long.valueOf(12211L));
    zzayp().zzbay().log("To enable debug logging run: adb shell setprop log.tag.FA VERBOSE");
    String str = zzcje1.getAppId();
    if (zzayl().zzkq(str)) {
      zzcjl = zzayp().zzbay();
      str = "Faster debug mode event logging enabled. To disable, run:\n  adb shell setprop debug.firebase.analytics.app .none.";
    } else {
      zzcjl = zzayp().zzbay();
      str = String.valueOf(str);
      if (str.length() != 0) {
        str = "To enable faster debug mode event logging run:\n  adb shell setprop debug.firebase.analytics.app ".concat(str);
      } else {
        str = new String("To enable faster debug mode event logging run:\n  adb shell setprop debug.firebase.analytics.app ");
      } 
    } 
    zzcjl.log(str);
    zzayp().zzbaz().log("Debug-level message logging enabled");
    if (this.zzjov != this.zzjow)
      zzayp().zzbau().zze("Not all components initialized", Integer.valueOf(this.zzjov), Integer.valueOf(this.zzjow)); 
    this.initialized = true;
  }
  
  private final boolean zza(int paramInt, FileChannel paramFileChannel) {
    zzayo().zzwj();
    if (paramFileChannel == null || !paramFileChannel.isOpen()) {
      zzayp().zzbau().log("Bad channel to read from");
      return false;
    } 
    ByteBuffer byteBuffer = ByteBuffer.allocate(4);
    byteBuffer.putInt(paramInt);
    byteBuffer.flip();
    try {
      paramFileChannel.truncate(0L);
      paramFileChannel.write(byteBuffer);
      paramFileChannel.force(true);
      if (paramFileChannel.size() != 4L)
        zzayp().zzbau().zzj("Error writing to channel. Bytes written", Long.valueOf(paramFileChannel.size())); 
      return true;
    } catch (IOException iOException) {
      zzayp().zzbau().zzj("Failed to write to channel", iOException);
      return false;
    } 
  }
  
  private static boolean zza(zzcob paramzzcob, String paramString, Object paramObject) {
    if (!TextUtils.isEmpty(paramString)) {
      if (paramObject == null)
        return false; 
      for (zzcoc zzcoc : paramzzcob.zzjui) {
        if (paramString.equals(zzcoc.name))
          return ((paramObject instanceof Long && paramObject.equals(zzcoc.zzjum)) || (paramObject instanceof String && paramObject.equals(zzcoc.zzgim)) || (paramObject instanceof Double && paramObject.equals(zzcoc.zzjsl))); 
      } 
    } 
    return false;
  }
  
  private final boolean zza(String paramString, zzcix paramzzcix) {
    long l;
    String str = paramzzcix.zzjhr.getString("currency");
    if ("ecommerce_purchase".equals(paramzzcix.name)) {
      double d2 = paramzzcix.zzjhr.getDouble("value").doubleValue() * 1000000.0D;
      double d1 = d2;
      if (d2 == 0.0D)
        d1 = paramzzcix.zzjhr.getLong("value").longValue() * 1000000.0D; 
      if (d1 <= 9.223372036854776E18D && d1 >= -9.223372036854776E18D) {
        l = Math.round(d1);
      } else {
        zzayp().zzbaw().zze("Data lost. Currency value is too big. appId", zzcjj.zzjs(paramString), Double.valueOf(d1));
        return false;
      } 
    } else {
      l = paramzzcix.zzjhr.getLong("value").longValue();
    } 
    if (!TextUtils.isEmpty(str)) {
      String str1 = str.toUpperCase(Locale.US);
      if (str1.matches("[A-Z]{3}")) {
        zzcnn zzcnn1;
        zzcil zzcil1;
        str = String.valueOf("_ltv_");
        str1 = String.valueOf(str1);
        if (str1.length() != 0) {
          str = str.concat(str1);
        } else {
          str = new String(str);
        } 
        zzcnn zzcnn2 = zzayj().zzag(paramString, str);
        if (zzcnn2 == null || !(zzcnn2.value instanceof Long)) {
          zzcil1 = zzayj();
          int i = this.zzjns.zzb(paramString, zzciz.zzjjr);
          zzbq.zzgv(paramString);
          zzcil1.zzwj();
          zzcil1.zzyk();
          try {
            zzcil1.getWritableDatabase().execSQL("delete from user_attributes where app_id=? and name in (select name from user_attributes where app_id=? and name like '_ltv_%' order by set_timestamp desc limit ?,10);", (Object[])new String[] { paramString, paramString, String.valueOf(i - 1) });
          } catch (SQLiteException sQLiteException) {
            zzcil1.zzayp().zzbau().zze("Error pruning currencies. appId", zzcjj.zzjs(paramString), sQLiteException);
          } 
          zzcnn1 = new zzcnn(paramString, paramzzcix.zzjgm, str, this.zzdir.currentTimeMillis(), Long.valueOf(l));
        } else {
          long l1 = ((Long)((zzcnn)zzcil1).value).longValue();
          zzcnn1 = new zzcnn(paramString, ((zzcix)zzcnn1).zzjgm, str, this.zzdir.currentTimeMillis(), Long.valueOf(l1 + l));
        } 
        if (!zzayj().zza(zzcnn1)) {
          zzayp().zzbau().zzd("Too many unique user properties are set. Ignoring user property. appId", zzcjj.zzjs(paramString), zzayk().zzjr(zzcnn1.name), zzcnn1.value);
          zzayl().zza(paramString, 9, (String)null, (String)null, 0);
        } 
      } 
    } 
    return true;
  }
  
  private final zzcoa[] zza(String paramString, zzcog[] paramArrayOfzzcog, zzcob[] paramArrayOfzzcob) {
    zzbq.zzgv(paramString);
    return zzayc().zza(paramString, paramArrayOfzzcob, paramArrayOfzzcog);
  }
  
  static void zzaxz() {
    throw new IllegalStateException("Unexpected call on client side");
  }
  
  private final void zzb(zzcie paramzzcie) {
    zzayo().zzwj();
    if (TextUtils.isEmpty(paramzzcie.getGmpAppId())) {
      zzb(paramzzcie.getAppId(), 204, null, null, null);
      return;
    } 
    String str1 = paramzzcie.getGmpAppId();
    String str2 = paramzzcie.getAppInstanceId();
    Uri.Builder builder1 = new Uri.Builder();
    Uri.Builder builder2 = builder1.scheme(zzciz.zzjir.get()).encodedAuthority(zzciz.zzjis.get());
    str1 = String.valueOf(str1);
    if (str1.length() != 0) {
      str1 = "config/app/".concat(str1);
    } else {
      str1 = new String("config/app/");
    } 
    builder2.path(str1).appendQueryParameter("app_instance_id", str2).appendQueryParameter("platform", "android").appendQueryParameter("gmp_version", "12211");
    str2 = builder1.build().toString();
    try {
      URL uRL = new URL(str2);
      zzayp().zzbba().zzj("Fetching remote configuration", paramzzcie.getAppId());
      zzcny zzcny = zzaym().zzka(paramzzcie.getAppId());
      String str3 = zzaym().zzkb(paramzzcie.getAppId());
      if (zzcny != null && !TextUtils.isEmpty(str3)) {
        a<String, String> a = new a();
        a.put("If-Modified-Since", str3);
      } else {
        zzcny = null;
      } 
      this.zzjoz = true;
      zzcjn zzcjn1 = zzbbs();
      String str4 = paramzzcie.getAppId();
      zzckn zzckn = new zzckn(this);
      zzcjn1.zzwj();
      zzcjn1.zzyk();
      zzbq.checkNotNull(uRL);
      zzbq.checkNotNull(zzckn);
      zzcjn1.zzayo().zzi(new zzcjr(zzcjn1, str4, uRL, null, (Map<String, String>)zzcny, zzckn));
      return;
    } catch (MalformedURLException malformedURLException) {
      zzayp().zzbau().zze("Failed to parse config URL. Not fetching. appId", zzcjj.zzjs(paramzzcie.getAppId()), str2);
      return;
    } 
  }
  
  private final zzcjs zzbbt() {
    zzcjs zzcjs1 = this.zzjol;
    if (zzcjs1 != null)
      return zzcjs1; 
    throw new IllegalStateException("Network broadcast receiver not created");
  }
  
  private final zzcnj zzbbu() {
    zza(this.zzjom);
    return this.zzjom;
  }
  
  private final boolean zzbbv() {
    zzayo().zzwj();
    File file = new File(this.zzaiq.getFilesDir(), "google_app_measurement.db");
    try {
      this.zzjos = (new RandomAccessFile(file, "rw")).getChannel();
      this.zzjor = this.zzjos.tryLock();
      if (this.zzjor != null) {
        zzayp().zzbba().log("Storage concurrent access okay");
        return true;
      } 
      zzayp().zzbau().log("Storage concurrent data access panic");
    } catch (FileNotFoundException fileNotFoundException) {
      zzcjl zzcjl = zzayp().zzbau();
      String str = "Failed to acquire storage lock";
      zzcjl.zzj(str, fileNotFoundException);
    } catch (IOException iOException) {
      zzcjl zzcjl = zzayp().zzbau();
      String str = "Failed to access storage lock file";
    } 
    return false;
  }
  
  private final long zzbbx() {
    long l3 = this.zzdir.currentTimeMillis();
    zzcju zzcju1 = zzayq();
    zzcju1.zzyk();
    zzcju1.zzwj();
    long l2 = zzcju1.zzjlr.get();
    long l1 = l2;
    if (l2 == 0L) {
      l1 = (zzcju1.zzayl().zzbcr().nextInt(86400000) + 1);
      zzcju1.zzjlr.set(l1);
    } 
    return (l3 + l1) / 1000L / 60L / 60L / 24L;
  }
  
  private final boolean zzbbz() {
    zzayo().zzwj();
    zzyk();
    return (zzayj().zzbab() || !TextUtils.isEmpty(zzayj().zzazw()));
  }
  
  private final void zzbca() {
    int i;
    zzcja<Long> zzcja;
    zzayo().zzwj();
    zzyk();
    if (!zzbcd())
      return; 
    if (this.zzjoy > 0L) {
      long l = 3600000L - Math.abs(this.zzdir.elapsedRealtime() - this.zzjoy);
      if (l > 0L) {
        zzayp().zzbba().zzj("Upload has been suspended. Will update scheduling later in approximately ms", Long.valueOf(l));
        zzbbt().unregister();
        zzbbu().cancel();
        return;
      } 
      this.zzjoy = 0L;
    } 
    if (!zzbbn() || !zzbbz()) {
      zzayp().zzbba().log("Nothing to upload or uploading impossible");
      zzbbt().unregister();
      zzbbu().cancel();
      return;
    } 
    long l2 = this.zzdir.currentTimeMillis();
    long l1 = Math.max(0L, ((Long)zzciz.zzjjn.get()).longValue());
    if (zzayj().zzbac() || zzayj().zzazx()) {
      i = 1;
    } else {
      i = 0;
    } 
    if (i) {
      String str = this.zzjns.zzazu();
      if (!TextUtils.isEmpty(str) && !".none.".equals(str)) {
        zzcja = zzciz.zzjji;
      } else {
        zzcja = zzciz.zzjjh;
      } 
    } else {
      zzcja = zzciz.zzjjg;
    } 
    long l5 = Math.max(0L, ((Long)zzcja.get()).longValue());
    long l6 = (zzayq()).zzjln.get();
    long l3 = (zzayq()).zzjlo.get();
    long l4 = Math.max(zzayj().zzazz(), zzayj().zzbaa());
    if (l4 != 0L) {
      l4 = l2 - Math.abs(l4 - l2);
      l6 = Math.abs(l6 - l2);
      l3 = l2 - Math.abs(l3 - l2);
      l6 = Math.max(l2 - l6, l3);
      l1 += l4;
      l2 = l1;
      if (i) {
        l2 = l1;
        if (l6 > 0L)
          l2 = Math.min(l4, l6) + l5; 
      } 
      if (!zzayl().zzf(l6, l5))
        l2 = l6 + l5; 
      l1 = l2;
      if (l3 != 0L) {
        l1 = l2;
        if (l3 >= l4) {
          l1 = l2;
          i = 0;
          while (true) {
            if (i < Math.min(20, Math.max(0, ((Integer)zzciz.zzjjp.get()).intValue()))) {
              l2 = (1 << i);
              l1 += Math.max(0L, ((Long)zzciz.zzjjo.get()).longValue()) * l2;
              if (l1 > l3)
                break; 
              i++;
              continue;
            } 
            l1 = 0L;
            break;
          } 
        } 
      } 
      if (l1 == 0L) {
        zzayp().zzbba().log("Next upload time is 0");
        zzbbt().unregister();
        zzbbu().cancel();
        return;
      } 
      if (!zzbbs().zzaax()) {
        zzayp().zzbba().log("No network");
        zzbbt().zzaau();
        zzbbu().cancel();
        return;
      } 
      l3 = (zzayq()).zzjlp.get();
      l4 = Math.max(0L, ((Long)zzciz.zzjje.get()).longValue());
      l2 = l1;
      if (!zzayl().zzf(l3, l4))
        l2 = Math.max(l1, l3 + l4); 
      zzbbt().unregister();
      l2 -= this.zzdir.currentTimeMillis();
      l1 = l2;
      if (l2 <= 0L) {
        l1 = Math.max(0L, ((Long)zzciz.zzjjj.get()).longValue());
        (zzayq()).zzjln.set(this.zzdir.currentTimeMillis());
      } 
      zzayp().zzbba().zzj("Upload scheduled in approximately ms", Long.valueOf(l1));
      zzbbu().zzs(l1);
      return;
    } 
    l1 = 0L;
    break;
  }
  
  private final boolean zzbcd() {
    zzayo().zzwj();
    zzyk();
    return this.zzjoo;
  }
  
  private final void zzbce() {
    zzayo().zzwj();
    if (this.zzjoz || this.zzjpa || this.zzjpb) {
      zzayp().zzbba().zzd("Not stopping services. fetch, network, upload", Boolean.valueOf(this.zzjoz), Boolean.valueOf(this.zzjpa), Boolean.valueOf(this.zzjpb));
      return;
    } 
    zzayp().zzbba().log("Stopping uploading service(s)");
    List<Runnable> list = this.zzjou;
    if (list == null)
      return; 
    Iterator<Runnable> iterator = list.iterator();
    while (iterator.hasNext())
      ((Runnable)iterator.next()).run(); 
    this.zzjou.clear();
  }
  
  private final Boolean zzc(zzcie paramzzcie) {
    try {
      if (paramzzcie.zzayx() != -2147483648L) {
        int i = (zzbih.zzdd(this.zzaiq).getPackageInfo(paramzzcie.getAppId(), 0)).versionCode;
        if (paramzzcie.zzayx() == i)
          return Boolean.valueOf(true); 
      } else {
        String str = (zzbih.zzdd(this.zzaiq).getPackageInfo(paramzzcie.getAppId(), 0)).versionName;
        if (paramzzcie.zzwo() != null && paramzzcie.zzwo().equals(str))
          return Boolean.valueOf(true); 
      } 
      return Boolean.valueOf(false);
    } catch (android.content.pm.PackageManager.NameNotFoundException nameNotFoundException) {
      return null;
    } 
  }
  
  private final void zzc(zzcix paramzzcix, zzcif paramzzcif) {
    // Byte code:
    //   0: aload_2
    //   1: invokestatic checkNotNull : (Ljava/lang/Object;)Ljava/lang/Object;
    //   4: pop
    //   5: aload_2
    //   6: getfield packageName : Ljava/lang/String;
    //   9: invokestatic zzgv : (Ljava/lang/String;)Ljava/lang/String;
    //   12: pop
    //   13: invokestatic nanoTime : ()J
    //   16: lstore #5
    //   18: aload_0
    //   19: invokevirtual zzayo : ()Lcom/google/android/gms/internal/zzcke;
    //   22: invokevirtual zzwj : ()V
    //   25: aload_0
    //   26: invokevirtual zzyk : ()V
    //   29: aload_2
    //   30: getfield packageName : Ljava/lang/String;
    //   33: astore #12
    //   35: aload_0
    //   36: invokevirtual zzayl : ()Lcom/google/android/gms/internal/zzcno;
    //   39: pop
    //   40: aload_1
    //   41: aload_2
    //   42: invokestatic zzd : (Lcom/google/android/gms/internal/zzcix;Lcom/google/android/gms/internal/zzcif;)Z
    //   45: ifne -> 49
    //   48: return
    //   49: aload_2
    //   50: getfield zzjfv : Z
    //   53: ifne -> 62
    //   56: aload_0
    //   57: aload_2
    //   58: invokespecial zzg : (Lcom/google/android/gms/internal/zzcif;)V
    //   61: return
    //   62: aload_0
    //   63: invokevirtual zzaym : ()Lcom/google/android/gms/internal/zzckd;
    //   66: aload #12
    //   68: aload_1
    //   69: getfield name : Ljava/lang/String;
    //   72: invokevirtual zzan : (Ljava/lang/String;Ljava/lang/String;)Z
    //   75: istore #9
    //   77: iconst_1
    //   78: istore #4
    //   80: iload #9
    //   82: ifeq -> 266
    //   85: aload_0
    //   86: invokevirtual zzayp : ()Lcom/google/android/gms/internal/zzcjj;
    //   89: invokevirtual zzbaw : ()Lcom/google/android/gms/internal/zzcjl;
    //   92: ldc_w 'Dropping blacklisted event. appId'
    //   95: aload #12
    //   97: invokestatic zzjs : (Ljava/lang/String;)Ljava/lang/Object;
    //   100: aload_0
    //   101: invokevirtual zzayk : ()Lcom/google/android/gms/internal/zzcjh;
    //   104: aload_1
    //   105: getfield name : Ljava/lang/String;
    //   108: invokevirtual zzjp : (Ljava/lang/String;)Ljava/lang/String;
    //   111: invokevirtual zze : (Ljava/lang/String;Ljava/lang/Object;Ljava/lang/Object;)V
    //   114: iload #4
    //   116: istore_3
    //   117: aload_0
    //   118: invokevirtual zzayl : ()Lcom/google/android/gms/internal/zzcno;
    //   121: aload #12
    //   123: invokevirtual zzks : (Ljava/lang/String;)Z
    //   126: ifne -> 149
    //   129: aload_0
    //   130: invokevirtual zzayl : ()Lcom/google/android/gms/internal/zzcno;
    //   133: aload #12
    //   135: invokevirtual zzkt : (Ljava/lang/String;)Z
    //   138: ifeq -> 147
    //   141: iload #4
    //   143: istore_3
    //   144: goto -> 149
    //   147: iconst_0
    //   148: istore_3
    //   149: iload_3
    //   150: ifne -> 185
    //   153: ldc_w '_err'
    //   156: aload_1
    //   157: getfield name : Ljava/lang/String;
    //   160: invokevirtual equals : (Ljava/lang/Object;)Z
    //   163: ifne -> 185
    //   166: aload_0
    //   167: invokevirtual zzayl : ()Lcom/google/android/gms/internal/zzcno;
    //   170: aload #12
    //   172: bipush #11
    //   174: ldc_w '_ev'
    //   177: aload_1
    //   178: getfield name : Ljava/lang/String;
    //   181: iconst_0
    //   182: invokevirtual zza : (Ljava/lang/String;ILjava/lang/String;Ljava/lang/String;I)V
    //   185: iload_3
    //   186: ifeq -> 265
    //   189: aload_0
    //   190: invokevirtual zzayj : ()Lcom/google/android/gms/internal/zzcil;
    //   193: aload #12
    //   195: invokevirtual zzjj : (Ljava/lang/String;)Lcom/google/android/gms/internal/zzcie;
    //   198: astore_1
    //   199: aload_1
    //   200: ifnull -> 265
    //   203: aload_1
    //   204: invokevirtual zzaze : ()J
    //   207: aload_1
    //   208: invokevirtual zzazd : ()J
    //   211: invokestatic max : (JJ)J
    //   214: lstore #5
    //   216: aload_0
    //   217: getfield zzdir : Lcom/google/android/gms/common/util/zze;
    //   220: invokeinterface currentTimeMillis : ()J
    //   225: lload #5
    //   227: lsub
    //   228: invokestatic abs : (J)J
    //   231: getstatic com/google/android/gms/internal/zzciz.zzjjm : Lcom/google/android/gms/internal/zzcja;
    //   234: invokevirtual get : ()Ljava/lang/Object;
    //   237: checkcast java/lang/Long
    //   240: invokevirtual longValue : ()J
    //   243: lcmp
    //   244: ifle -> 265
    //   247: aload_0
    //   248: invokevirtual zzayp : ()Lcom/google/android/gms/internal/zzcjj;
    //   251: invokevirtual zzbaz : ()Lcom/google/android/gms/internal/zzcjl;
    //   254: ldc_w 'Fetching config for blacklisted app'
    //   257: invokevirtual log : (Ljava/lang/String;)V
    //   260: aload_0
    //   261: aload_1
    //   262: invokespecial zzb : (Lcom/google/android/gms/internal/zzcie;)V
    //   265: return
    //   266: aload_0
    //   267: invokevirtual zzayp : ()Lcom/google/android/gms/internal/zzcjj;
    //   270: iconst_2
    //   271: invokevirtual zzae : (I)Z
    //   274: ifeq -> 298
    //   277: aload_0
    //   278: invokevirtual zzayp : ()Lcom/google/android/gms/internal/zzcjj;
    //   281: invokevirtual zzbba : ()Lcom/google/android/gms/internal/zzcjl;
    //   284: ldc_w 'Logging event'
    //   287: aload_0
    //   288: invokevirtual zzayk : ()Lcom/google/android/gms/internal/zzcjh;
    //   291: aload_1
    //   292: invokevirtual zzb : (Lcom/google/android/gms/internal/zzcix;)Ljava/lang/String;
    //   295: invokevirtual zzj : (Ljava/lang/String;Ljava/lang/Object;)V
    //   298: aload_0
    //   299: invokevirtual zzayj : ()Lcom/google/android/gms/internal/zzcil;
    //   302: invokevirtual beginTransaction : ()V
    //   305: aload_0
    //   306: aload_2
    //   307: invokespecial zzg : (Lcom/google/android/gms/internal/zzcif;)V
    //   310: ldc_w '_iap'
    //   313: aload_1
    //   314: getfield name : Ljava/lang/String;
    //   317: invokevirtual equals : (Ljava/lang/Object;)Z
    //   320: ifne -> 336
    //   323: ldc_w 'ecommerce_purchase'
    //   326: aload_1
    //   327: getfield name : Ljava/lang/String;
    //   330: invokevirtual equals : (Ljava/lang/Object;)Z
    //   333: ifeq -> 361
    //   336: aload_0
    //   337: aload #12
    //   339: aload_1
    //   340: invokespecial zza : (Ljava/lang/String;Lcom/google/android/gms/internal/zzcix;)Z
    //   343: ifne -> 361
    //   346: aload_0
    //   347: invokevirtual zzayj : ()Lcom/google/android/gms/internal/zzcil;
    //   350: invokevirtual setTransactionSuccessful : ()V
    //   353: aload_0
    //   354: invokevirtual zzayj : ()Lcom/google/android/gms/internal/zzcil;
    //   357: invokevirtual endTransaction : ()V
    //   360: return
    //   361: aload_1
    //   362: getfield name : Ljava/lang/String;
    //   365: invokestatic zzkh : (Ljava/lang/String;)Z
    //   368: istore #9
    //   370: ldc_w '_err'
    //   373: aload_1
    //   374: getfield name : Ljava/lang/String;
    //   377: invokevirtual equals : (Ljava/lang/Object;)Z
    //   380: istore #10
    //   382: aload_0
    //   383: invokevirtual zzayj : ()Lcom/google/android/gms/internal/zzcil;
    //   386: aload_0
    //   387: invokespecial zzbbx : ()J
    //   390: aload #12
    //   392: iconst_1
    //   393: iload #9
    //   395: iconst_0
    //   396: iload #10
    //   398: iconst_0
    //   399: invokevirtual zza : (JLjava/lang/String;ZZZZZ)Lcom/google/android/gms/internal/zzcim;
    //   402: astore #13
    //   404: aload #13
    //   406: getfield zzjhf : J
    //   409: getstatic com/google/android/gms/internal/zzciz.zzjix : Lcom/google/android/gms/internal/zzcja;
    //   412: invokevirtual get : ()Ljava/lang/Object;
    //   415: checkcast java/lang/Integer
    //   418: invokevirtual intValue : ()I
    //   421: i2l
    //   422: lsub
    //   423: lstore #7
    //   425: lload #7
    //   427: lconst_0
    //   428: lcmp
    //   429: ifle -> 484
    //   432: lload #7
    //   434: ldc2_w 1000
    //   437: lrem
    //   438: lconst_1
    //   439: lcmp
    //   440: ifne -> 469
    //   443: aload_0
    //   444: invokevirtual zzayp : ()Lcom/google/android/gms/internal/zzcjj;
    //   447: invokevirtual zzbau : ()Lcom/google/android/gms/internal/zzcjl;
    //   450: ldc_w 'Data loss. Too many events logged. appId, count'
    //   453: aload #12
    //   455: invokestatic zzjs : (Ljava/lang/String;)Ljava/lang/Object;
    //   458: aload #13
    //   460: getfield zzjhf : J
    //   463: invokestatic valueOf : (J)Ljava/lang/Long;
    //   466: invokevirtual zze : (Ljava/lang/String;Ljava/lang/Object;Ljava/lang/Object;)V
    //   469: aload_0
    //   470: invokevirtual zzayj : ()Lcom/google/android/gms/internal/zzcil;
    //   473: invokevirtual setTransactionSuccessful : ()V
    //   476: aload_0
    //   477: invokevirtual zzayj : ()Lcom/google/android/gms/internal/zzcil;
    //   480: invokevirtual endTransaction : ()V
    //   483: return
    //   484: iload #9
    //   486: ifeq -> 588
    //   489: aload #13
    //   491: getfield zzjhe : J
    //   494: getstatic com/google/android/gms/internal/zzciz.zzjiz : Lcom/google/android/gms/internal/zzcja;
    //   497: invokevirtual get : ()Ljava/lang/Object;
    //   500: checkcast java/lang/Integer
    //   503: invokevirtual intValue : ()I
    //   506: i2l
    //   507: lsub
    //   508: lstore #7
    //   510: lload #7
    //   512: lconst_0
    //   513: lcmp
    //   514: ifle -> 588
    //   517: lload #7
    //   519: ldc2_w 1000
    //   522: lrem
    //   523: lconst_1
    //   524: lcmp
    //   525: ifne -> 554
    //   528: aload_0
    //   529: invokevirtual zzayp : ()Lcom/google/android/gms/internal/zzcjj;
    //   532: invokevirtual zzbau : ()Lcom/google/android/gms/internal/zzcjl;
    //   535: ldc_w 'Data loss. Too many public events logged. appId, count'
    //   538: aload #12
    //   540: invokestatic zzjs : (Ljava/lang/String;)Ljava/lang/Object;
    //   543: aload #13
    //   545: getfield zzjhe : J
    //   548: invokestatic valueOf : (J)Ljava/lang/Long;
    //   551: invokevirtual zze : (Ljava/lang/String;Ljava/lang/Object;Ljava/lang/Object;)V
    //   554: aload_0
    //   555: invokevirtual zzayl : ()Lcom/google/android/gms/internal/zzcno;
    //   558: aload #12
    //   560: bipush #16
    //   562: ldc_w '_ev'
    //   565: aload_1
    //   566: getfield name : Ljava/lang/String;
    //   569: iconst_0
    //   570: invokevirtual zza : (Ljava/lang/String;ILjava/lang/String;Ljava/lang/String;I)V
    //   573: aload_0
    //   574: invokevirtual zzayj : ()Lcom/google/android/gms/internal/zzcil;
    //   577: invokevirtual setTransactionSuccessful : ()V
    //   580: aload_0
    //   581: invokevirtual zzayj : ()Lcom/google/android/gms/internal/zzcil;
    //   584: invokevirtual endTransaction : ()V
    //   587: return
    //   588: iload #10
    //   590: ifeq -> 681
    //   593: aload #13
    //   595: getfield zzjhh : J
    //   598: iconst_0
    //   599: ldc_w 1000000
    //   602: aload_0
    //   603: getfield zzjns : Lcom/google/android/gms/internal/zzcik;
    //   606: aload_2
    //   607: getfield packageName : Ljava/lang/String;
    //   610: getstatic com/google/android/gms/internal/zzciz.zzjiy : Lcom/google/android/gms/internal/zzcja;
    //   613: invokevirtual zzb : (Ljava/lang/String;Lcom/google/android/gms/internal/zzcja;)I
    //   616: invokestatic min : (II)I
    //   619: invokestatic max : (II)I
    //   622: i2l
    //   623: lsub
    //   624: lstore #7
    //   626: lload #7
    //   628: lconst_0
    //   629: lcmp
    //   630: ifle -> 681
    //   633: lload #7
    //   635: lconst_1
    //   636: lcmp
    //   637: ifne -> 666
    //   640: aload_0
    //   641: invokevirtual zzayp : ()Lcom/google/android/gms/internal/zzcjj;
    //   644: invokevirtual zzbau : ()Lcom/google/android/gms/internal/zzcjl;
    //   647: ldc_w 'Too many error events logged. appId, count'
    //   650: aload #12
    //   652: invokestatic zzjs : (Ljava/lang/String;)Ljava/lang/Object;
    //   655: aload #13
    //   657: getfield zzjhh : J
    //   660: invokestatic valueOf : (J)Ljava/lang/Long;
    //   663: invokevirtual zze : (Ljava/lang/String;Ljava/lang/Object;Ljava/lang/Object;)V
    //   666: aload_0
    //   667: invokevirtual zzayj : ()Lcom/google/android/gms/internal/zzcil;
    //   670: invokevirtual setTransactionSuccessful : ()V
    //   673: aload_0
    //   674: invokevirtual zzayj : ()Lcom/google/android/gms/internal/zzcil;
    //   677: invokevirtual endTransaction : ()V
    //   680: return
    //   681: iconst_0
    //   682: istore #10
    //   684: aload_1
    //   685: getfield zzjhr : Lcom/google/android/gms/internal/zzciu;
    //   688: invokevirtual zzbao : ()Landroid/os/Bundle;
    //   691: astore #13
    //   693: aload_0
    //   694: invokevirtual zzayl : ()Lcom/google/android/gms/internal/zzcno;
    //   697: aload #13
    //   699: ldc_w '_o'
    //   702: aload_1
    //   703: getfield zzjgm : Ljava/lang/String;
    //   706: invokevirtual zza : (Landroid/os/Bundle;Ljava/lang/String;Ljava/lang/Object;)V
    //   709: aload_0
    //   710: invokevirtual zzayl : ()Lcom/google/android/gms/internal/zzcno;
    //   713: aload #12
    //   715: invokevirtual zzkq : (Ljava/lang/String;)Z
    //   718: ifeq -> 753
    //   721: aload_0
    //   722: invokevirtual zzayl : ()Lcom/google/android/gms/internal/zzcno;
    //   725: aload #13
    //   727: ldc_w '_dbg'
    //   730: lconst_1
    //   731: invokestatic valueOf : (J)Ljava/lang/Long;
    //   734: invokevirtual zza : (Landroid/os/Bundle;Ljava/lang/String;Ljava/lang/Object;)V
    //   737: aload_0
    //   738: invokevirtual zzayl : ()Lcom/google/android/gms/internal/zzcno;
    //   741: aload #13
    //   743: ldc_w '_r'
    //   746: lconst_1
    //   747: invokestatic valueOf : (J)Ljava/lang/Long;
    //   750: invokevirtual zza : (Landroid/os/Bundle;Ljava/lang/String;Ljava/lang/Object;)V
    //   753: aload_0
    //   754: invokevirtual zzayj : ()Lcom/google/android/gms/internal/zzcil;
    //   757: aload #12
    //   759: invokevirtual zzjk : (Ljava/lang/String;)J
    //   762: lstore #7
    //   764: lload #7
    //   766: lconst_0
    //   767: lcmp
    //   768: ifle -> 794
    //   771: aload_0
    //   772: invokevirtual zzayp : ()Lcom/google/android/gms/internal/zzcjj;
    //   775: invokevirtual zzbaw : ()Lcom/google/android/gms/internal/zzcjl;
    //   778: ldc_w 'Data lost. Too many events stored on disk, deleted. appId'
    //   781: aload #12
    //   783: invokestatic zzjs : (Ljava/lang/String;)Ljava/lang/Object;
    //   786: lload #7
    //   788: invokestatic valueOf : (J)Ljava/lang/Long;
    //   791: invokevirtual zze : (Ljava/lang/String;Ljava/lang/Object;Ljava/lang/Object;)V
    //   794: new com/google/android/gms/internal/zzcis
    //   797: dup
    //   798: aload_0
    //   799: aload_1
    //   800: getfield zzjgm : Ljava/lang/String;
    //   803: aload #12
    //   805: aload_1
    //   806: getfield name : Ljava/lang/String;
    //   809: aload_1
    //   810: getfield zzjib : J
    //   813: lconst_0
    //   814: aload #13
    //   816: invokespecial <init> : (Lcom/google/android/gms/internal/zzckj;Ljava/lang/String;Ljava/lang/String;Ljava/lang/String;JJLandroid/os/Bundle;)V
    //   819: astore_1
    //   820: aload_0
    //   821: invokevirtual zzayj : ()Lcom/google/android/gms/internal/zzcil;
    //   824: aload #12
    //   826: aload_1
    //   827: getfield name : Ljava/lang/String;
    //   830: invokevirtual zzae : (Ljava/lang/String;Ljava/lang/String;)Lcom/google/android/gms/internal/zzcit;
    //   833: astore #13
    //   835: aload #13
    //   837: ifnonnull -> 946
    //   840: aload_0
    //   841: invokevirtual zzayj : ()Lcom/google/android/gms/internal/zzcil;
    //   844: aload #12
    //   846: invokevirtual zzjn : (Ljava/lang/String;)J
    //   849: ldc2_w 500
    //   852: lcmp
    //   853: iflt -> 918
    //   856: iload #9
    //   858: ifeq -> 918
    //   861: aload_0
    //   862: invokevirtual zzayp : ()Lcom/google/android/gms/internal/zzcjj;
    //   865: invokevirtual zzbau : ()Lcom/google/android/gms/internal/zzcjl;
    //   868: ldc_w 'Too many event names used, ignoring event. appId, name, supported count'
    //   871: aload #12
    //   873: invokestatic zzjs : (Ljava/lang/String;)Ljava/lang/Object;
    //   876: aload_0
    //   877: invokevirtual zzayk : ()Lcom/google/android/gms/internal/zzcjh;
    //   880: aload_1
    //   881: getfield name : Ljava/lang/String;
    //   884: invokevirtual zzjp : (Ljava/lang/String;)Ljava/lang/String;
    //   887: sipush #500
    //   890: invokestatic valueOf : (I)Ljava/lang/Integer;
    //   893: invokevirtual zzd : (Ljava/lang/String;Ljava/lang/Object;Ljava/lang/Object;Ljava/lang/Object;)V
    //   896: aload_0
    //   897: invokevirtual zzayl : ()Lcom/google/android/gms/internal/zzcno;
    //   900: aload #12
    //   902: bipush #8
    //   904: aconst_null
    //   905: aconst_null
    //   906: iconst_0
    //   907: invokevirtual zza : (Ljava/lang/String;ILjava/lang/String;Ljava/lang/String;I)V
    //   910: aload_0
    //   911: invokevirtual zzayj : ()Lcom/google/android/gms/internal/zzcil;
    //   914: invokevirtual endTransaction : ()V
    //   917: return
    //   918: new com/google/android/gms/internal/zzcit
    //   921: dup
    //   922: aload #12
    //   924: aload_1
    //   925: getfield name : Ljava/lang/String;
    //   928: lconst_0
    //   929: lconst_0
    //   930: aload_1
    //   931: getfield timestamp : J
    //   934: lconst_0
    //   935: aconst_null
    //   936: aconst_null
    //   937: aconst_null
    //   938: invokespecial <init> : (Ljava/lang/String;Ljava/lang/String;JJJJLjava/lang/Long;Ljava/lang/Long;Ljava/lang/Boolean;)V
    //   941: astore #12
    //   943: goto -> 968
    //   946: aload_1
    //   947: aload_0
    //   948: aload #13
    //   950: getfield zzjhu : J
    //   953: invokevirtual zza : (Lcom/google/android/gms/internal/zzckj;J)Lcom/google/android/gms/internal/zzcis;
    //   956: astore_1
    //   957: aload #13
    //   959: aload_1
    //   960: getfield timestamp : J
    //   963: invokevirtual zzbb : (J)Lcom/google/android/gms/internal/zzcit;
    //   966: astore #12
    //   968: aload_0
    //   969: invokevirtual zzayj : ()Lcom/google/android/gms/internal/zzcil;
    //   972: aload #12
    //   974: invokevirtual zza : (Lcom/google/android/gms/internal/zzcit;)V
    //   977: aload_0
    //   978: invokevirtual zzayo : ()Lcom/google/android/gms/internal/zzcke;
    //   981: invokevirtual zzwj : ()V
    //   984: aload_0
    //   985: invokevirtual zzyk : ()V
    //   988: aload_1
    //   989: invokestatic checkNotNull : (Ljava/lang/Object;)Ljava/lang/Object;
    //   992: pop
    //   993: aload_2
    //   994: invokestatic checkNotNull : (Ljava/lang/Object;)Ljava/lang/Object;
    //   997: pop
    //   998: aload_1
    //   999: getfield zzcm : Ljava/lang/String;
    //   1002: invokestatic zzgv : (Ljava/lang/String;)Ljava/lang/String;
    //   1005: pop
    //   1006: aload_1
    //   1007: getfield zzcm : Ljava/lang/String;
    //   1010: aload_2
    //   1011: getfield packageName : Ljava/lang/String;
    //   1014: invokevirtual equals : (Ljava/lang/Object;)Z
    //   1017: invokestatic checkArgument : (Z)V
    //   1020: new com/google/android/gms/internal/zzcoe
    //   1023: dup
    //   1024: invokespecial <init> : ()V
    //   1027: astore #14
    //   1029: aload #14
    //   1031: iconst_1
    //   1032: invokestatic valueOf : (I)Ljava/lang/Integer;
    //   1035: putfield zzjup : Ljava/lang/Integer;
    //   1038: aload #14
    //   1040: ldc_w 'android'
    //   1043: putfield zzjux : Ljava/lang/String;
    //   1046: aload #14
    //   1048: aload_2
    //   1049: getfield packageName : Ljava/lang/String;
    //   1052: putfield zzcm : Ljava/lang/String;
    //   1055: aload #14
    //   1057: aload_2
    //   1058: getfield zzjfs : Ljava/lang/String;
    //   1061: putfield zzjfs : Ljava/lang/String;
    //   1064: aload #14
    //   1066: aload_2
    //   1067: getfield zzina : Ljava/lang/String;
    //   1070: putfield zzina : Ljava/lang/String;
    //   1073: aload_2
    //   1074: getfield zzjfr : J
    //   1077: ldc2_w -2147483648
    //   1080: lcmp
    //   1081: ifne -> 1090
    //   1084: aconst_null
    //   1085: astore #12
    //   1087: goto -> 1100
    //   1090: aload_2
    //   1091: getfield zzjfr : J
    //   1094: l2i
    //   1095: invokestatic valueOf : (I)Ljava/lang/Integer;
    //   1098: astore #12
    //   1100: aload #14
    //   1102: aload #12
    //   1104: putfield zzjvi : Ljava/lang/Integer;
    //   1107: aload #14
    //   1109: aload_2
    //   1110: getfield zzjft : J
    //   1113: invokestatic valueOf : (J)Ljava/lang/Long;
    //   1116: putfield zzjva : Ljava/lang/Long;
    //   1119: aload #14
    //   1121: aload_2
    //   1122: getfield zzjfl : Ljava/lang/String;
    //   1125: putfield zzjfl : Ljava/lang/String;
    //   1128: aload_2
    //   1129: getfield zzjfu : J
    //   1132: lconst_0
    //   1133: lcmp
    //   1134: ifne -> 1143
    //   1137: aconst_null
    //   1138: astore #12
    //   1140: goto -> 1152
    //   1143: aload_2
    //   1144: getfield zzjfu : J
    //   1147: invokestatic valueOf : (J)Ljava/lang/Long;
    //   1150: astore #12
    //   1152: aload #14
    //   1154: aload #12
    //   1156: putfield zzjve : Ljava/lang/Long;
    //   1159: aload_0
    //   1160: invokevirtual zzayq : ()Lcom/google/android/gms/internal/zzcju;
    //   1163: aload_2
    //   1164: getfield packageName : Ljava/lang/String;
    //   1167: invokevirtual zzju : (Ljava/lang/String;)Landroid/util/Pair;
    //   1170: astore #12
    //   1172: aload #12
    //   1174: ifnull -> 1227
    //   1177: aload #12
    //   1179: getfield first : Ljava/lang/Object;
    //   1182: checkcast java/lang/CharSequence
    //   1185: invokestatic isEmpty : (Ljava/lang/CharSequence;)Z
    //   1188: ifne -> 1227
    //   1191: aload_2
    //   1192: getfield zzjfx : Z
    //   1195: ifeq -> 1334
    //   1198: aload #14
    //   1200: aload #12
    //   1202: getfield first : Ljava/lang/Object;
    //   1205: checkcast java/lang/String
    //   1208: putfield zzjvc : Ljava/lang/String;
    //   1211: aload #14
    //   1213: aload #12
    //   1215: getfield second : Ljava/lang/Object;
    //   1218: checkcast java/lang/Boolean
    //   1221: putfield zzjvd : Ljava/lang/Boolean;
    //   1224: goto -> 1334
    //   1227: aload_0
    //   1228: invokevirtual zzayf : ()Lcom/google/android/gms/internal/zzcir;
    //   1231: aload_0
    //   1232: getfield zzaiq : Landroid/content/Context;
    //   1235: invokevirtual zzec : (Landroid/content/Context;)Z
    //   1238: ifne -> 1334
    //   1241: aload_0
    //   1242: getfield zzaiq : Landroid/content/Context;
    //   1245: invokevirtual getContentResolver : ()Landroid/content/ContentResolver;
    //   1248: ldc_w 'android_id'
    //   1251: invokestatic getString : (Landroid/content/ContentResolver;Ljava/lang/String;)Ljava/lang/String;
    //   1254: astore #13
    //   1256: aload #13
    //   1258: ifnonnull -> 1290
    //   1261: aload_0
    //   1262: invokevirtual zzayp : ()Lcom/google/android/gms/internal/zzcjj;
    //   1265: invokevirtual zzbaw : ()Lcom/google/android/gms/internal/zzcjl;
    //   1268: ldc_w 'null secure ID. appId'
    //   1271: aload #14
    //   1273: getfield zzcm : Ljava/lang/String;
    //   1276: invokestatic zzjs : (Ljava/lang/String;)Ljava/lang/Object;
    //   1279: invokevirtual zzj : (Ljava/lang/String;Ljava/lang/Object;)V
    //   1282: ldc_w 'null'
    //   1285: astore #12
    //   1287: goto -> 1327
    //   1290: aload #13
    //   1292: astore #12
    //   1294: aload #13
    //   1296: invokevirtual isEmpty : ()Z
    //   1299: ifeq -> 1327
    //   1302: aload_0
    //   1303: invokevirtual zzayp : ()Lcom/google/android/gms/internal/zzcjj;
    //   1306: invokevirtual zzbaw : ()Lcom/google/android/gms/internal/zzcjl;
    //   1309: ldc_w 'empty secure ID. appId'
    //   1312: aload #14
    //   1314: getfield zzcm : Ljava/lang/String;
    //   1317: invokestatic zzjs : (Ljava/lang/String;)Ljava/lang/Object;
    //   1320: invokevirtual zzj : (Ljava/lang/String;Ljava/lang/Object;)V
    //   1323: aload #13
    //   1325: astore #12
    //   1327: aload #14
    //   1329: aload #12
    //   1331: putfield zzjvl : Ljava/lang/String;
    //   1334: aload_0
    //   1335: invokevirtual zzayf : ()Lcom/google/android/gms/internal/zzcir;
    //   1338: invokevirtual zzyk : ()V
    //   1341: aload #14
    //   1343: getstatic android/os/Build.MODEL : Ljava/lang/String;
    //   1346: putfield zzjuy : Ljava/lang/String;
    //   1349: aload_0
    //   1350: invokevirtual zzayf : ()Lcom/google/android/gms/internal/zzcir;
    //   1353: invokevirtual zzyk : ()V
    //   1356: aload #14
    //   1358: getstatic android/os/Build$VERSION.RELEASE : Ljava/lang/String;
    //   1361: putfield zzda : Ljava/lang/String;
    //   1364: aload #14
    //   1366: aload_0
    //   1367: invokevirtual zzayf : ()Lcom/google/android/gms/internal/zzcir;
    //   1370: invokevirtual zzbal : ()J
    //   1373: l2i
    //   1374: invokestatic valueOf : (I)Ljava/lang/Integer;
    //   1377: putfield zzjuz : Ljava/lang/Integer;
    //   1380: aload #14
    //   1382: aload_0
    //   1383: invokevirtual zzayf : ()Lcom/google/android/gms/internal/zzcir;
    //   1386: invokevirtual zzbam : ()Ljava/lang/String;
    //   1389: putfield zzjho : Ljava/lang/String;
    //   1392: aload #14
    //   1394: aconst_null
    //   1395: putfield zzjvb : Ljava/lang/Long;
    //   1398: aload #14
    //   1400: aconst_null
    //   1401: putfield zzjus : Ljava/lang/Long;
    //   1404: aload #14
    //   1406: aconst_null
    //   1407: putfield zzjut : Ljava/lang/Long;
    //   1410: aload #14
    //   1412: aconst_null
    //   1413: putfield zzjuu : Ljava/lang/Long;
    //   1416: aload #14
    //   1418: aload_2
    //   1419: getfield zzjfw : J
    //   1422: invokestatic valueOf : (J)Ljava/lang/Long;
    //   1425: putfield zzfqm : Ljava/lang/Long;
    //   1428: aload_0
    //   1429: invokevirtual isEnabled : ()Z
    //   1432: ifeq -> 1447
    //   1435: invokestatic zzazv : ()Z
    //   1438: ifeq -> 1447
    //   1441: aload #14
    //   1443: aconst_null
    //   1444: putfield zzjvn : Ljava/lang/String;
    //   1447: aload_0
    //   1448: invokevirtual zzayj : ()Lcom/google/android/gms/internal/zzcil;
    //   1451: aload_2
    //   1452: getfield packageName : Ljava/lang/String;
    //   1455: invokevirtual zzjj : (Ljava/lang/String;)Lcom/google/android/gms/internal/zzcie;
    //   1458: astore #13
    //   1460: aload #13
    //   1462: astore #12
    //   1464: aload #13
    //   1466: ifnonnull -> 1619
    //   1469: new com/google/android/gms/internal/zzcie
    //   1472: dup
    //   1473: aload_0
    //   1474: aload_2
    //   1475: getfield packageName : Ljava/lang/String;
    //   1478: invokespecial <init> : (Lcom/google/android/gms/internal/zzckj;Ljava/lang/String;)V
    //   1481: astore #12
    //   1483: aload #12
    //   1485: aload_0
    //   1486: invokevirtual zzaye : ()Lcom/google/android/gms/internal/zzcje;
    //   1489: invokevirtual zzbaq : ()Ljava/lang/String;
    //   1492: invokevirtual zziy : (Ljava/lang/String;)V
    //   1495: aload #12
    //   1497: aload_2
    //   1498: getfield zzjfn : Ljava/lang/String;
    //   1501: invokevirtual zzjb : (Ljava/lang/String;)V
    //   1504: aload #12
    //   1506: aload_2
    //   1507: getfield zzjfl : Ljava/lang/String;
    //   1510: invokevirtual zziz : (Ljava/lang/String;)V
    //   1513: aload #12
    //   1515: aload_0
    //   1516: invokevirtual zzayq : ()Lcom/google/android/gms/internal/zzcju;
    //   1519: aload_2
    //   1520: getfield packageName : Ljava/lang/String;
    //   1523: invokevirtual zzjv : (Ljava/lang/String;)Ljava/lang/String;
    //   1526: invokevirtual zzja : (Ljava/lang/String;)V
    //   1529: aload #12
    //   1531: lconst_0
    //   1532: invokevirtual zzaq : (J)V
    //   1535: aload #12
    //   1537: lconst_0
    //   1538: invokevirtual zzal : (J)V
    //   1541: aload #12
    //   1543: lconst_0
    //   1544: invokevirtual zzam : (J)V
    //   1547: aload #12
    //   1549: aload_2
    //   1550: getfield zzina : Ljava/lang/String;
    //   1553: invokevirtual setAppVersion : (Ljava/lang/String;)V
    //   1556: aload #12
    //   1558: aload_2
    //   1559: getfield zzjfr : J
    //   1562: invokevirtual zzan : (J)V
    //   1565: aload #12
    //   1567: aload_2
    //   1568: getfield zzjfs : Ljava/lang/String;
    //   1571: invokevirtual zzjc : (Ljava/lang/String;)V
    //   1574: aload #12
    //   1576: aload_2
    //   1577: getfield zzjft : J
    //   1580: invokevirtual zzao : (J)V
    //   1583: aload #12
    //   1585: aload_2
    //   1586: getfield zzjfu : J
    //   1589: invokevirtual zzap : (J)V
    //   1592: aload #12
    //   1594: aload_2
    //   1595: getfield zzjfv : Z
    //   1598: invokevirtual setMeasurementEnabled : (Z)V
    //   1601: aload #12
    //   1603: aload_2
    //   1604: getfield zzjfw : J
    //   1607: invokevirtual zzaz : (J)V
    //   1610: aload_0
    //   1611: invokevirtual zzayj : ()Lcom/google/android/gms/internal/zzcil;
    //   1614: aload #12
    //   1616: invokevirtual zza : (Lcom/google/android/gms/internal/zzcie;)V
    //   1619: aload #14
    //   1621: aload #12
    //   1623: invokevirtual getAppInstanceId : ()Ljava/lang/String;
    //   1626: putfield zzjfk : Ljava/lang/String;
    //   1629: aload #14
    //   1631: aload #12
    //   1633: invokevirtual zzayu : ()Ljava/lang/String;
    //   1636: putfield zzjfn : Ljava/lang/String;
    //   1639: aload_0
    //   1640: invokevirtual zzayj : ()Lcom/google/android/gms/internal/zzcil;
    //   1643: aload_2
    //   1644: getfield packageName : Ljava/lang/String;
    //   1647: invokevirtual zzji : (Ljava/lang/String;)Ljava/util/List;
    //   1650: astore_2
    //   1651: aload #14
    //   1653: aload_2
    //   1654: invokeinterface size : ()I
    //   1659: anewarray com/google/android/gms/internal/zzcog
    //   1662: putfield zzjur : [Lcom/google/android/gms/internal/zzcog;
    //   1665: iconst_0
    //   1666: istore_3
    //   1667: iload_3
    //   1668: aload_2
    //   1669: invokeinterface size : ()I
    //   1674: if_icmpge -> 1763
    //   1677: new com/google/android/gms/internal/zzcog
    //   1680: dup
    //   1681: invokespecial <init> : ()V
    //   1684: astore #12
    //   1686: aload #14
    //   1688: getfield zzjur : [Lcom/google/android/gms/internal/zzcog;
    //   1691: iload_3
    //   1692: aload #12
    //   1694: aastore
    //   1695: aload #12
    //   1697: aload_2
    //   1698: iload_3
    //   1699: invokeinterface get : (I)Ljava/lang/Object;
    //   1704: checkcast com/google/android/gms/internal/zzcnn
    //   1707: getfield name : Ljava/lang/String;
    //   1710: putfield name : Ljava/lang/String;
    //   1713: aload #12
    //   1715: aload_2
    //   1716: iload_3
    //   1717: invokeinterface get : (I)Ljava/lang/Object;
    //   1722: checkcast com/google/android/gms/internal/zzcnn
    //   1725: getfield zzjsi : J
    //   1728: invokestatic valueOf : (J)Ljava/lang/Long;
    //   1731: putfield zzjvr : Ljava/lang/Long;
    //   1734: aload_0
    //   1735: invokevirtual zzayl : ()Lcom/google/android/gms/internal/zzcno;
    //   1738: aload #12
    //   1740: aload_2
    //   1741: iload_3
    //   1742: invokeinterface get : (I)Ljava/lang/Object;
    //   1747: checkcast com/google/android/gms/internal/zzcnn
    //   1750: getfield value : Ljava/lang/Object;
    //   1753: invokevirtual zza : (Lcom/google/android/gms/internal/zzcog;Ljava/lang/Object;)V
    //   1756: iload_3
    //   1757: iconst_1
    //   1758: iadd
    //   1759: istore_3
    //   1760: goto -> 1667
    //   1763: aload_0
    //   1764: invokevirtual zzayj : ()Lcom/google/android/gms/internal/zzcil;
    //   1767: aload #14
    //   1769: invokevirtual zza : (Lcom/google/android/gms/internal/zzcoe;)J
    //   1772: lstore #7
    //   1774: aload_0
    //   1775: invokevirtual zzayj : ()Lcom/google/android/gms/internal/zzcil;
    //   1778: astore_2
    //   1779: iload #10
    //   1781: istore #9
    //   1783: aload_1
    //   1784: getfield zzjhr : Lcom/google/android/gms/internal/zzciu;
    //   1787: ifnull -> 1907
    //   1790: aload_1
    //   1791: getfield zzjhr : Lcom/google/android/gms/internal/zzciu;
    //   1794: invokevirtual iterator : ()Ljava/util/Iterator;
    //   1797: astore #12
    //   1799: aload #12
    //   1801: invokeinterface hasNext : ()Z
    //   1806: ifeq -> 1831
    //   1809: ldc_w '_r'
    //   1812: aload #12
    //   1814: invokeinterface next : ()Ljava/lang/Object;
    //   1819: checkcast java/lang/String
    //   1822: invokevirtual equals : (Ljava/lang/Object;)Z
    //   1825: ifeq -> 1799
    //   1828: goto -> 2041
    //   1831: aload_0
    //   1832: invokevirtual zzaym : ()Lcom/google/android/gms/internal/zzckd;
    //   1835: aload_1
    //   1836: getfield zzcm : Ljava/lang/String;
    //   1839: aload_1
    //   1840: getfield name : Ljava/lang/String;
    //   1843: invokevirtual zzao : (Ljava/lang/String;Ljava/lang/String;)Z
    //   1846: istore #11
    //   1848: aload_0
    //   1849: invokevirtual zzayj : ()Lcom/google/android/gms/internal/zzcil;
    //   1852: aload_0
    //   1853: invokespecial zzbbx : ()J
    //   1856: aload_1
    //   1857: getfield zzcm : Ljava/lang/String;
    //   1860: iconst_0
    //   1861: iconst_0
    //   1862: iconst_0
    //   1863: iconst_0
    //   1864: iconst_0
    //   1865: invokevirtual zza : (JLjava/lang/String;ZZZZZ)Lcom/google/android/gms/internal/zzcim;
    //   1868: astore #12
    //   1870: iload #10
    //   1872: istore #9
    //   1874: iload #11
    //   1876: ifeq -> 1907
    //   1879: iload #10
    //   1881: istore #9
    //   1883: aload #12
    //   1885: getfield zzjhi : J
    //   1888: aload_0
    //   1889: getfield zzjns : Lcom/google/android/gms/internal/zzcik;
    //   1892: aload_1
    //   1893: getfield zzcm : Ljava/lang/String;
    //   1896: invokevirtual zzje : (Ljava/lang/String;)I
    //   1899: i2l
    //   1900: lcmp
    //   1901: ifge -> 1907
    //   1904: goto -> 2041
    //   1907: aload_2
    //   1908: aload_1
    //   1909: lload #7
    //   1911: iload #9
    //   1913: invokevirtual zza : (Lcom/google/android/gms/internal/zzcis;JZ)Z
    //   1916: ifeq -> 1950
    //   1919: aload_0
    //   1920: lconst_0
    //   1921: putfield zzjoy : J
    //   1924: goto -> 1950
    //   1927: astore_2
    //   1928: aload_0
    //   1929: invokevirtual zzayp : ()Lcom/google/android/gms/internal/zzcjj;
    //   1932: invokevirtual zzbau : ()Lcom/google/android/gms/internal/zzcjl;
    //   1935: ldc_w 'Data loss. Failed to insert raw event metadata. appId'
    //   1938: aload #14
    //   1940: getfield zzcm : Ljava/lang/String;
    //   1943: invokestatic zzjs : (Ljava/lang/String;)Ljava/lang/Object;
    //   1946: aload_2
    //   1947: invokevirtual zze : (Ljava/lang/String;Ljava/lang/Object;Ljava/lang/Object;)V
    //   1950: aload_0
    //   1951: invokevirtual zzayj : ()Lcom/google/android/gms/internal/zzcil;
    //   1954: invokevirtual setTransactionSuccessful : ()V
    //   1957: aload_0
    //   1958: invokevirtual zzayp : ()Lcom/google/android/gms/internal/zzcjj;
    //   1961: iconst_2
    //   1962: invokevirtual zzae : (I)Z
    //   1965: ifeq -> 1989
    //   1968: aload_0
    //   1969: invokevirtual zzayp : ()Lcom/google/android/gms/internal/zzcjj;
    //   1972: invokevirtual zzbba : ()Lcom/google/android/gms/internal/zzcjl;
    //   1975: ldc_w 'Event recorded'
    //   1978: aload_0
    //   1979: invokevirtual zzayk : ()Lcom/google/android/gms/internal/zzcjh;
    //   1982: aload_1
    //   1983: invokevirtual zza : (Lcom/google/android/gms/internal/zzcis;)Ljava/lang/String;
    //   1986: invokevirtual zzj : (Ljava/lang/String;Ljava/lang/Object;)V
    //   1989: aload_0
    //   1990: invokevirtual zzayj : ()Lcom/google/android/gms/internal/zzcil;
    //   1993: invokevirtual endTransaction : ()V
    //   1996: aload_0
    //   1997: invokespecial zzbca : ()V
    //   2000: aload_0
    //   2001: invokevirtual zzayp : ()Lcom/google/android/gms/internal/zzcjj;
    //   2004: invokevirtual zzbba : ()Lcom/google/android/gms/internal/zzcjl;
    //   2007: ldc_w 'Background event processing time, ms'
    //   2010: invokestatic nanoTime : ()J
    //   2013: lload #5
    //   2015: lsub
    //   2016: ldc2_w 500000
    //   2019: ladd
    //   2020: ldc2_w 1000000
    //   2023: ldiv
    //   2024: invokestatic valueOf : (J)Ljava/lang/Long;
    //   2027: invokevirtual zzj : (Ljava/lang/String;Ljava/lang/Object;)V
    //   2030: return
    //   2031: astore_1
    //   2032: aload_0
    //   2033: invokevirtual zzayj : ()Lcom/google/android/gms/internal/zzcil;
    //   2036: invokevirtual endTransaction : ()V
    //   2039: aload_1
    //   2040: athrow
    //   2041: iconst_1
    //   2042: istore #9
    //   2044: goto -> 1907
    // Exception table:
    //   from	to	target	type
    //   305	336	2031	finally
    //   336	353	2031	finally
    //   361	425	2031	finally
    //   443	469	2031	finally
    //   469	476	2031	finally
    //   489	510	2031	finally
    //   528	554	2031	finally
    //   554	580	2031	finally
    //   593	626	2031	finally
    //   640	666	2031	finally
    //   666	673	2031	finally
    //   684	753	2031	finally
    //   753	764	2031	finally
    //   771	794	2031	finally
    //   794	835	2031	finally
    //   840	856	2031	finally
    //   861	910	2031	finally
    //   918	943	2031	finally
    //   946	968	2031	finally
    //   968	1084	2031	finally
    //   1090	1100	2031	finally
    //   1100	1137	2031	finally
    //   1143	1152	2031	finally
    //   1152	1172	2031	finally
    //   1177	1224	2031	finally
    //   1227	1256	2031	finally
    //   1261	1282	2031	finally
    //   1294	1323	2031	finally
    //   1327	1334	2031	finally
    //   1334	1447	2031	finally
    //   1447	1460	2031	finally
    //   1469	1619	2031	finally
    //   1619	1665	2031	finally
    //   1667	1756	2031	finally
    //   1763	1774	1927	java/io/IOException
    //   1763	1774	2031	finally
    //   1774	1779	2031	finally
    //   1783	1799	2031	finally
    //   1799	1828	2031	finally
    //   1831	1870	2031	finally
    //   1883	1904	2031	finally
    //   1907	1924	2031	finally
    //   1928	1950	2031	finally
    //   1950	1989	2031	finally
  }
  
  public static zzckj zzed(Context paramContext) {
    // Byte code:
    //   0: aload_0
    //   1: invokestatic checkNotNull : (Ljava/lang/Object;)Ljava/lang/Object;
    //   4: pop
    //   5: aload_0
    //   6: invokevirtual getApplicationContext : ()Landroid/content/Context;
    //   9: invokestatic checkNotNull : (Ljava/lang/Object;)Ljava/lang/Object;
    //   12: pop
    //   13: getstatic com/google/android/gms/internal/zzckj.zzjnr : Lcom/google/android/gms/internal/zzckj;
    //   16: ifnonnull -> 58
    //   19: ldc com/google/android/gms/internal/zzckj
    //   21: monitorenter
    //   22: getstatic com/google/android/gms/internal/zzckj.zzjnr : Lcom/google/android/gms/internal/zzckj;
    //   25: ifnonnull -> 46
    //   28: new com/google/android/gms/internal/zzckj
    //   31: dup
    //   32: new com/google/android/gms/internal/zzclj
    //   35: dup
    //   36: aload_0
    //   37: invokespecial <init> : (Landroid/content/Context;)V
    //   40: invokespecial <init> : (Lcom/google/android/gms/internal/zzclj;)V
    //   43: putstatic com/google/android/gms/internal/zzckj.zzjnr : Lcom/google/android/gms/internal/zzckj;
    //   46: ldc com/google/android/gms/internal/zzckj
    //   48: monitorexit
    //   49: goto -> 58
    //   52: astore_0
    //   53: ldc com/google/android/gms/internal/zzckj
    //   55: monitorexit
    //   56: aload_0
    //   57: athrow
    //   58: getstatic com/google/android/gms/internal/zzckj.zzjnr : Lcom/google/android/gms/internal/zzckj;
    //   61: areturn
    // Exception table:
    //   from	to	target	type
    //   22	46	52	finally
    //   46	49	52	finally
    //   53	56	52	finally
  }
  
  private final void zzg(zzcif paramzzcif) {
    zzayo().zzwj();
    zzyk();
    zzbq.checkNotNull(paramzzcif);
    zzbq.zzgv(paramzzcif.packageName);
    zzcie zzcie = zzayj().zzjj(paramzzcif.packageName);
    String str = zzayq().zzjv(paramzzcif.packageName);
    if (zzcie == null) {
      zzcie = new zzcie(this, paramzzcif.packageName);
      zzcie.zziy(zzaye().zzbaq());
      zzcie.zzja(str);
    } else if (!str.equals(zzcie.zzayt())) {
      zzcie.zzja(str);
      zzcie.zziy(zzaye().zzbaq());
    } else {
      boolean bool4 = false;
      boolean bool3 = bool4;
    } 
    boolean bool2 = true;
    boolean bool1 = bool2;
  }
  
  private final boolean zzg(String paramString, long paramLong) {
    // Byte code:
    //   0: aload_0
    //   1: invokevirtual zzayj : ()Lcom/google/android/gms/internal/zzcil;
    //   4: invokevirtual beginTransaction : ()V
    //   7: aconst_null
    //   8: astore_1
    //   9: new com/google/android/gms/internal/zzckj$zza
    //   12: dup
    //   13: aload_0
    //   14: aconst_null
    //   15: invokespecial <init> : (Lcom/google/android/gms/internal/zzckj;Lcom/google/android/gms/internal/zzckk;)V
    //   18: astore #20
    //   20: aload_0
    //   21: invokevirtual zzayj : ()Lcom/google/android/gms/internal/zzcil;
    //   24: astore #22
    //   26: aload_0
    //   27: getfield zzjox : J
    //   30: lstore #11
    //   32: aload #20
    //   34: invokestatic checkNotNull : (Ljava/lang/Object;)Ljava/lang/Object;
    //   37: pop
    //   38: aload #22
    //   40: invokevirtual zzwj : ()V
    //   43: aload #22
    //   45: invokevirtual zzyk : ()V
    //   48: aload #22
    //   50: invokevirtual getWritableDatabase : ()Landroid/database/sqlite/SQLiteDatabase;
    //   53: astore #23
    //   55: aconst_null
    //   56: invokestatic isEmpty : (Ljava/lang/CharSequence;)Z
    //   59: istore #13
    //   61: iload #13
    //   63: ifeq -> 321
    //   66: lload #11
    //   68: ldc2_w -1
    //   71: lcmp
    //   72: istore #4
    //   74: iload #4
    //   76: ifeq -> 136
    //   79: aload_1
    //   80: astore #17
    //   82: iconst_2
    //   83: anewarray java/lang/String
    //   86: astore #18
    //   88: aload_1
    //   89: astore #17
    //   91: aload #18
    //   93: iconst_0
    //   94: lload #11
    //   96: invokestatic valueOf : (J)Ljava/lang/String;
    //   99: aastore
    //   100: aload_1
    //   101: astore #17
    //   103: aload #18
    //   105: iconst_1
    //   106: lload_2
    //   107: invokestatic valueOf : (J)Ljava/lang/String;
    //   110: aastore
    //   111: aload #18
    //   113: astore_1
    //   114: goto -> 148
    //   117: astore_1
    //   118: goto -> 4219
    //   121: astore_1
    //   122: aconst_null
    //   123: astore #17
    //   125: aload #17
    //   127: astore #18
    //   129: aload #18
    //   131: astore #19
    //   133: goto -> 1126
    //   136: iconst_1
    //   137: anewarray java/lang/String
    //   140: astore_1
    //   141: aload_1
    //   142: iconst_0
    //   143: lload_2
    //   144: invokestatic valueOf : (J)Ljava/lang/String;
    //   147: aastore
    //   148: iload #4
    //   150: ifeq -> 161
    //   153: ldc_w 'rowid <= ? and '
    //   156: astore #17
    //   158: goto -> 166
    //   161: ldc_w ''
    //   164: astore #17
    //   166: new java/lang/StringBuilder
    //   169: dup
    //   170: aload #17
    //   172: invokestatic valueOf : (Ljava/lang/Object;)Ljava/lang/String;
    //   175: invokevirtual length : ()I
    //   178: sipush #148
    //   181: iadd
    //   182: invokespecial <init> : (I)V
    //   185: astore #18
    //   187: aload #18
    //   189: ldc_w 'select app_id, metadata_fingerprint from raw_events where '
    //   192: invokevirtual append : (Ljava/lang/String;)Ljava/lang/StringBuilder;
    //   195: pop
    //   196: aload #18
    //   198: aload #17
    //   200: invokevirtual append : (Ljava/lang/String;)Ljava/lang/StringBuilder;
    //   203: pop
    //   204: aload #18
    //   206: ldc_w 'app_id in (select app_id from apps where config_fetched_time >= ?) order by rowid limit 1;'
    //   209: invokevirtual append : (Ljava/lang/String;)Ljava/lang/StringBuilder;
    //   212: pop
    //   213: aload #23
    //   215: aload #18
    //   217: invokevirtual toString : ()Ljava/lang/String;
    //   220: aload_1
    //   221: invokevirtual rawQuery : (Ljava/lang/String;[Ljava/lang/String;)Landroid/database/Cursor;
    //   224: astore_1
    //   225: aload_1
    //   226: astore #17
    //   228: aload_1
    //   229: astore #18
    //   231: aload_1
    //   232: invokeinterface moveToFirst : ()Z
    //   237: istore #13
    //   239: iload #13
    //   241: ifne -> 257
    //   244: aload_1
    //   245: ifnull -> 1158
    //   248: aload_1
    //   249: invokeinterface close : ()V
    //   254: goto -> 1158
    //   257: aload_1
    //   258: astore #17
    //   260: aload_1
    //   261: astore #18
    //   263: aload_1
    //   264: iconst_0
    //   265: invokeinterface getString : (I)Ljava/lang/String;
    //   270: astore #19
    //   272: aload_1
    //   273: astore #17
    //   275: aload_1
    //   276: iconst_1
    //   277: invokeinterface getString : (I)Ljava/lang/String;
    //   282: astore #21
    //   284: aload_1
    //   285: astore #17
    //   287: aload_1
    //   288: invokeinterface close : ()V
    //   293: aload_1
    //   294: astore #18
    //   296: aload #19
    //   298: astore_1
    //   299: aload #21
    //   301: astore #19
    //   303: goto -> 482
    //   306: astore #18
    //   308: aload_1
    //   309: astore #17
    //   311: aload #18
    //   313: astore_1
    //   314: aload #19
    //   316: astore #18
    //   318: goto -> 129
    //   321: lload #11
    //   323: ldc2_w -1
    //   326: lcmp
    //   327: istore #4
    //   329: iload #4
    //   331: ifeq -> 354
    //   334: iconst_2
    //   335: anewarray java/lang/String
    //   338: astore_1
    //   339: aload_1
    //   340: iconst_0
    //   341: aconst_null
    //   342: aastore
    //   343: aload_1
    //   344: iconst_1
    //   345: lload #11
    //   347: invokestatic valueOf : (J)Ljava/lang/String;
    //   350: aastore
    //   351: goto -> 4243
    //   354: iconst_1
    //   355: anewarray java/lang/String
    //   358: dup
    //   359: iconst_0
    //   360: aconst_null
    //   361: aastore
    //   362: astore_1
    //   363: goto -> 4243
    //   366: new java/lang/StringBuilder
    //   369: dup
    //   370: aload #17
    //   372: invokestatic valueOf : (Ljava/lang/Object;)Ljava/lang/String;
    //   375: invokevirtual length : ()I
    //   378: bipush #84
    //   380: iadd
    //   381: invokespecial <init> : (I)V
    //   384: astore #18
    //   386: aload #18
    //   388: ldc_w 'select metadata_fingerprint from raw_events where app_id = ?'
    //   391: invokevirtual append : (Ljava/lang/String;)Ljava/lang/StringBuilder;
    //   394: pop
    //   395: aload #18
    //   397: aload #17
    //   399: invokevirtual append : (Ljava/lang/String;)Ljava/lang/StringBuilder;
    //   402: pop
    //   403: aload #18
    //   405: ldc_w ' order by rowid limit 1;'
    //   408: invokevirtual append : (Ljava/lang/String;)Ljava/lang/StringBuilder;
    //   411: pop
    //   412: aload #23
    //   414: aload #18
    //   416: invokevirtual toString : ()Ljava/lang/String;
    //   419: aload_1
    //   420: invokevirtual rawQuery : (Ljava/lang/String;[Ljava/lang/String;)Landroid/database/Cursor;
    //   423: astore_1
    //   424: aload_1
    //   425: astore #17
    //   427: aload_1
    //   428: astore #18
    //   430: aload_1
    //   431: invokeinterface moveToFirst : ()Z
    //   436: ifne -> 446
    //   439: aload_1
    //   440: ifnull -> 1158
    //   443: goto -> 248
    //   446: aload_1
    //   447: astore #17
    //   449: aload_1
    //   450: astore #18
    //   452: aload_1
    //   453: iconst_0
    //   454: invokeinterface getString : (I)Ljava/lang/String;
    //   459: astore #19
    //   461: aload_1
    //   462: astore #17
    //   464: aload_1
    //   465: astore #18
    //   467: aload_1
    //   468: invokeinterface close : ()V
    //   473: aconst_null
    //   474: astore #17
    //   476: aload_1
    //   477: astore #18
    //   479: aload #17
    //   481: astore_1
    //   482: aload #23
    //   484: ldc_w 'raw_events_metadata'
    //   487: iconst_1
    //   488: anewarray java/lang/String
    //   491: dup
    //   492: iconst_0
    //   493: ldc_w 'metadata'
    //   496: aastore
    //   497: ldc_w 'app_id = ? and metadata_fingerprint = ?'
    //   500: iconst_2
    //   501: anewarray java/lang/String
    //   504: dup
    //   505: iconst_0
    //   506: aload_1
    //   507: aastore
    //   508: dup
    //   509: iconst_1
    //   510: aload #19
    //   512: aastore
    //   513: aconst_null
    //   514: aconst_null
    //   515: ldc_w 'rowid'
    //   518: ldc_w '2'
    //   521: invokevirtual query : (Ljava/lang/String;[Ljava/lang/String;Ljava/lang/String;[Ljava/lang/String;Ljava/lang/String;Ljava/lang/String;Ljava/lang/String;Ljava/lang/String;)Landroid/database/Cursor;
    //   524: astore #17
    //   526: aload #17
    //   528: invokeinterface moveToFirst : ()Z
    //   533: istore #13
    //   535: iload #13
    //   537: ifne -> 588
    //   540: aload #22
    //   542: invokevirtual zzayp : ()Lcom/google/android/gms/internal/zzcjj;
    //   545: invokevirtual zzbau : ()Lcom/google/android/gms/internal/zzcjl;
    //   548: ldc_w 'Raw event metadata record is missing. appId'
    //   551: aload_1
    //   552: invokestatic zzjs : (Ljava/lang/String;)Ljava/lang/Object;
    //   555: invokevirtual zzj : (Ljava/lang/String;Ljava/lang/Object;)V
    //   558: aload #17
    //   560: ifnull -> 1158
    //   563: aload #17
    //   565: invokeinterface close : ()V
    //   570: goto -> 1158
    //   573: astore_1
    //   574: goto -> 4219
    //   577: astore #19
    //   579: aload_1
    //   580: astore #18
    //   582: aload #19
    //   584: astore_1
    //   585: goto -> 129
    //   588: aload #17
    //   590: iconst_0
    //   591: invokeinterface getBlob : (I)[B
    //   596: astore #18
    //   598: aload #18
    //   600: iconst_0
    //   601: aload #18
    //   603: arraylength
    //   604: invokestatic zzo : ([BII)Lcom/google/android/gms/internal/zzflj;
    //   607: astore #18
    //   609: new com/google/android/gms/internal/zzcoe
    //   612: dup
    //   613: invokespecial <init> : ()V
    //   616: astore #21
    //   618: aload #21
    //   620: aload #18
    //   622: invokevirtual zza : (Lcom/google/android/gms/internal/zzflj;)Lcom/google/android/gms/internal/zzfls;
    //   625: pop
    //   626: aload #17
    //   628: invokeinterface moveToNext : ()Z
    //   633: istore #13
    //   635: iload #13
    //   637: ifeq -> 658
    //   640: aload #22
    //   642: invokevirtual zzayp : ()Lcom/google/android/gms/internal/zzcjj;
    //   645: invokevirtual zzbaw : ()Lcom/google/android/gms/internal/zzcjl;
    //   648: ldc_w 'Get multiple raw event metadata records, expected one. appId'
    //   651: aload_1
    //   652: invokestatic zzjs : (Ljava/lang/String;)Ljava/lang/Object;
    //   655: invokevirtual zzj : (Ljava/lang/String;Ljava/lang/Object;)V
    //   658: aload #17
    //   660: invokeinterface close : ()V
    //   665: aload #20
    //   667: aload #21
    //   669: invokeinterface zzb : (Lcom/google/android/gms/internal/zzcoe;)V
    //   674: lload #11
    //   676: ldc2_w -1
    //   679: lcmp
    //   680: ifeq -> 718
    //   683: ldc_w 'app_id = ? and metadata_fingerprint = ? and rowid <= ?'
    //   686: astore #18
    //   688: iconst_3
    //   689: anewarray java/lang/String
    //   692: dup
    //   693: iconst_0
    //   694: aload_1
    //   695: aastore
    //   696: dup
    //   697: iconst_1
    //   698: aload #19
    //   700: aastore
    //   701: dup
    //   702: iconst_2
    //   703: lload #11
    //   705: invokestatic valueOf : (J)Ljava/lang/String;
    //   708: aastore
    //   709: astore #21
    //   711: aload #18
    //   713: astore #19
    //   715: goto -> 742
    //   718: ldc_w 'app_id = ? and metadata_fingerprint = ?'
    //   721: astore #18
    //   723: iconst_2
    //   724: anewarray java/lang/String
    //   727: dup
    //   728: iconst_0
    //   729: aload_1
    //   730: aastore
    //   731: dup
    //   732: iconst_1
    //   733: aload #19
    //   735: aastore
    //   736: astore #21
    //   738: aload #18
    //   740: astore #19
    //   742: aload #17
    //   744: astore #18
    //   746: aload #23
    //   748: ldc_w 'raw_events'
    //   751: iconst_4
    //   752: anewarray java/lang/String
    //   755: dup
    //   756: iconst_0
    //   757: ldc_w 'rowid'
    //   760: aastore
    //   761: dup
    //   762: iconst_1
    //   763: ldc_w 'name'
    //   766: aastore
    //   767: dup
    //   768: iconst_2
    //   769: ldc_w 'timestamp'
    //   772: aastore
    //   773: dup
    //   774: iconst_3
    //   775: ldc_w 'data'
    //   778: aastore
    //   779: aload #19
    //   781: aload #21
    //   783: aconst_null
    //   784: aconst_null
    //   785: ldc_w 'rowid'
    //   788: aconst_null
    //   789: invokevirtual query : (Ljava/lang/String;[Ljava/lang/String;Ljava/lang/String;[Ljava/lang/String;Ljava/lang/String;Ljava/lang/String;Ljava/lang/String;Ljava/lang/String;)Landroid/database/Cursor;
    //   792: astore #19
    //   794: aload #19
    //   796: invokeinterface moveToFirst : ()Z
    //   801: ifne -> 837
    //   804: aload #22
    //   806: invokevirtual zzayp : ()Lcom/google/android/gms/internal/zzcjj;
    //   809: invokevirtual zzbaw : ()Lcom/google/android/gms/internal/zzcjl;
    //   812: ldc_w 'Raw event data disappeared while in transaction. appId'
    //   815: aload_1
    //   816: invokestatic zzjs : (Ljava/lang/String;)Ljava/lang/Object;
    //   819: invokevirtual zzj : (Ljava/lang/String;Ljava/lang/Object;)V
    //   822: aload #19
    //   824: ifnull -> 1158
    //   827: aload #19
    //   829: invokeinterface close : ()V
    //   834: goto -> 1158
    //   837: aload #19
    //   839: iconst_0
    //   840: invokeinterface getLong : (I)J
    //   845: lstore_2
    //   846: aload #19
    //   848: iconst_3
    //   849: invokeinterface getBlob : (I)[B
    //   854: astore #17
    //   856: aload #17
    //   858: iconst_0
    //   859: aload #17
    //   861: arraylength
    //   862: invokestatic zzo : ([BII)Lcom/google/android/gms/internal/zzflj;
    //   865: astore #17
    //   867: new com/google/android/gms/internal/zzcob
    //   870: dup
    //   871: invokespecial <init> : ()V
    //   874: astore #18
    //   876: aload #18
    //   878: aload #17
    //   880: invokevirtual zza : (Lcom/google/android/gms/internal/zzflj;)Lcom/google/android/gms/internal/zzfls;
    //   883: pop
    //   884: aload #18
    //   886: aload #19
    //   888: iconst_1
    //   889: invokeinterface getString : (I)Ljava/lang/String;
    //   894: putfield name : Ljava/lang/String;
    //   897: aload #18
    //   899: aload #19
    //   901: iconst_2
    //   902: invokeinterface getLong : (I)J
    //   907: invokestatic valueOf : (J)Ljava/lang/Long;
    //   910: putfield zzjuj : Ljava/lang/Long;
    //   913: aload #20
    //   915: lload_2
    //   916: aload #18
    //   918: invokeinterface zza : (JLcom/google/android/gms/internal/zzcob;)Z
    //   923: ifne -> 956
    //   926: aload #19
    //   928: ifnull -> 1158
    //   931: goto -> 827
    //   934: astore #17
    //   936: aload #22
    //   938: invokevirtual zzayp : ()Lcom/google/android/gms/internal/zzcjj;
    //   941: invokevirtual zzbau : ()Lcom/google/android/gms/internal/zzcjl;
    //   944: ldc_w 'Data loss. Failed to merge raw event. appId'
    //   947: aload_1
    //   948: invokestatic zzjs : (Ljava/lang/String;)Ljava/lang/Object;
    //   951: aload #17
    //   953: invokevirtual zze : (Ljava/lang/String;Ljava/lang/Object;Ljava/lang/Object;)V
    //   956: aload #19
    //   958: invokeinterface moveToNext : ()Z
    //   963: istore #13
    //   965: iload #13
    //   967: ifne -> 837
    //   970: aload #19
    //   972: ifnull -> 1158
    //   975: goto -> 827
    //   978: astore_1
    //   979: aload #19
    //   981: astore #17
    //   983: goto -> 4219
    //   986: astore #21
    //   988: aload_1
    //   989: astore #18
    //   991: aload #19
    //   993: astore #17
    //   995: aload #21
    //   997: astore_1
    //   998: goto -> 129
    //   1001: astore #21
    //   1003: aload #17
    //   1005: astore #19
    //   1007: aload #19
    //   1009: astore #18
    //   1011: aload #22
    //   1013: invokevirtual zzayp : ()Lcom/google/android/gms/internal/zzcjj;
    //   1016: invokevirtual zzbau : ()Lcom/google/android/gms/internal/zzcjl;
    //   1019: ldc_w 'Data loss. Failed to merge raw event metadata. appId'
    //   1022: aload_1
    //   1023: invokestatic zzjs : (Ljava/lang/String;)Ljava/lang/Object;
    //   1026: aload #21
    //   1028: invokevirtual zze : (Ljava/lang/String;Ljava/lang/Object;Ljava/lang/Object;)V
    //   1031: aload #19
    //   1033: ifnull -> 1158
    //   1036: aload #19
    //   1038: astore #17
    //   1040: aload #17
    //   1042: invokeinterface close : ()V
    //   1047: goto -> 1158
    //   1050: astore #18
    //   1052: goto -> 1061
    //   1055: astore_1
    //   1056: goto -> 4219
    //   1059: astore #18
    //   1061: aload_1
    //   1062: astore #19
    //   1064: aload #18
    //   1066: astore_1
    //   1067: aload #19
    //   1069: astore #18
    //   1071: goto -> 129
    //   1074: astore_1
    //   1075: aload #18
    //   1077: astore #17
    //   1079: goto -> 4219
    //   1082: astore #21
    //   1084: aload_1
    //   1085: astore #19
    //   1087: aload #18
    //   1089: astore #17
    //   1091: aload #21
    //   1093: astore_1
    //   1094: aload #19
    //   1096: astore #18
    //   1098: goto -> 129
    //   1101: astore_1
    //   1102: aload #18
    //   1104: astore #17
    //   1106: aconst_null
    //   1107: astore #18
    //   1109: goto -> 129
    //   1112: astore_1
    //   1113: aconst_null
    //   1114: astore #17
    //   1116: goto -> 4219
    //   1119: astore_1
    //   1120: aconst_null
    //   1121: astore #17
    //   1123: aconst_null
    //   1124: astore #19
    //   1126: aload #17
    //   1128: astore #18
    //   1130: aload #22
    //   1132: invokevirtual zzayp : ()Lcom/google/android/gms/internal/zzcjj;
    //   1135: invokevirtual zzbau : ()Lcom/google/android/gms/internal/zzcjl;
    //   1138: ldc_w 'Data loss. Error selecting raw event. appId'
    //   1141: aload #19
    //   1143: invokestatic zzjs : (Ljava/lang/String;)Ljava/lang/Object;
    //   1146: aload_1
    //   1147: invokevirtual zze : (Ljava/lang/String;Ljava/lang/Object;Ljava/lang/Object;)V
    //   1150: aload #17
    //   1152: ifnull -> 1158
    //   1155: goto -> 1040
    //   1158: aload #20
    //   1160: getfield zzaoz : Ljava/util/List;
    //   1163: ifnull -> 4270
    //   1166: aload #20
    //   1168: getfield zzaoz : Ljava/util/List;
    //   1171: invokeinterface isEmpty : ()Z
    //   1176: ifeq -> 4264
    //   1179: goto -> 4270
    //   1182: iload #4
    //   1184: ifne -> 4198
    //   1187: aload #20
    //   1189: getfield zzjpe : Lcom/google/android/gms/internal/zzcoe;
    //   1192: astore #21
    //   1194: aload #21
    //   1196: aload #20
    //   1198: getfield zzaoz : Ljava/util/List;
    //   1201: invokeinterface size : ()I
    //   1206: anewarray com/google/android/gms/internal/zzcob
    //   1209: putfield zzjuq : [Lcom/google/android/gms/internal/zzcob;
    //   1212: aload_0
    //   1213: getfield zzjns : Lcom/google/android/gms/internal/zzcik;
    //   1216: aload #21
    //   1218: getfield zzcm : Ljava/lang/String;
    //   1221: invokevirtual zzjh : (Ljava/lang/String;)Z
    //   1224: istore #15
    //   1226: iconst_0
    //   1227: istore #4
    //   1229: iconst_0
    //   1230: istore #5
    //   1232: iconst_0
    //   1233: istore #13
    //   1235: lconst_0
    //   1236: lstore_2
    //   1237: iload #4
    //   1239: aload #20
    //   1241: getfield zzaoz : Ljava/util/List;
    //   1244: invokeinterface size : ()I
    //   1249: if_icmpge -> 2351
    //   1252: aload #20
    //   1254: getfield zzaoz : Ljava/util/List;
    //   1257: iload #4
    //   1259: invokeinterface get : (I)Ljava/lang/Object;
    //   1264: checkcast com/google/android/gms/internal/zzcob
    //   1267: astore #22
    //   1269: aload_0
    //   1270: invokevirtual zzaym : ()Lcom/google/android/gms/internal/zzckd;
    //   1273: aload #20
    //   1275: getfield zzjpe : Lcom/google/android/gms/internal/zzcoe;
    //   1278: getfield zzcm : Ljava/lang/String;
    //   1281: aload #22
    //   1283: getfield name : Ljava/lang/String;
    //   1286: invokevirtual zzan : (Ljava/lang/String;Ljava/lang/String;)Z
    //   1289: ifeq -> 1415
    //   1292: aload_0
    //   1293: invokevirtual zzayp : ()Lcom/google/android/gms/internal/zzcjj;
    //   1296: invokevirtual zzbaw : ()Lcom/google/android/gms/internal/zzcjl;
    //   1299: ldc_w 'Dropping blacklisted raw event. appId'
    //   1302: aload #20
    //   1304: getfield zzjpe : Lcom/google/android/gms/internal/zzcoe;
    //   1307: getfield zzcm : Ljava/lang/String;
    //   1310: invokestatic zzjs : (Ljava/lang/String;)Ljava/lang/Object;
    //   1313: aload_0
    //   1314: invokevirtual zzayk : ()Lcom/google/android/gms/internal/zzcjh;
    //   1317: aload #22
    //   1319: getfield name : Ljava/lang/String;
    //   1322: invokevirtual zzjp : (Ljava/lang/String;)Ljava/lang/String;
    //   1325: invokevirtual zze : (Ljava/lang/String;Ljava/lang/Object;Ljava/lang/Object;)V
    //   1328: aload_0
    //   1329: invokevirtual zzayl : ()Lcom/google/android/gms/internal/zzcno;
    //   1332: aload #20
    //   1334: getfield zzjpe : Lcom/google/android/gms/internal/zzcoe;
    //   1337: getfield zzcm : Ljava/lang/String;
    //   1340: invokevirtual zzks : (Ljava/lang/String;)Z
    //   1343: ifne -> 4282
    //   1346: aload_0
    //   1347: invokevirtual zzayl : ()Lcom/google/android/gms/internal/zzcno;
    //   1350: aload #20
    //   1352: getfield zzjpe : Lcom/google/android/gms/internal/zzcoe;
    //   1355: getfield zzcm : Ljava/lang/String;
    //   1358: invokevirtual zzkt : (Ljava/lang/String;)Z
    //   1361: ifeq -> 4276
    //   1364: goto -> 4282
    //   1367: iload #6
    //   1369: ifne -> 4288
    //   1372: ldc_w '_err'
    //   1375: aload #22
    //   1377: getfield name : Ljava/lang/String;
    //   1380: invokevirtual equals : (Ljava/lang/Object;)Z
    //   1383: ifne -> 4288
    //   1386: aload_0
    //   1387: invokevirtual zzayl : ()Lcom/google/android/gms/internal/zzcno;
    //   1390: aload #20
    //   1392: getfield zzjpe : Lcom/google/android/gms/internal/zzcoe;
    //   1395: getfield zzcm : Ljava/lang/String;
    //   1398: bipush #11
    //   1400: ldc_w '_ev'
    //   1403: aload #22
    //   1405: getfield name : Ljava/lang/String;
    //   1408: iconst_0
    //   1409: invokevirtual zza : (Ljava/lang/String;ILjava/lang/String;Ljava/lang/String;I)V
    //   1412: goto -> 4288
    //   1415: aload_0
    //   1416: invokevirtual zzaym : ()Lcom/google/android/gms/internal/zzckd;
    //   1419: aload #20
    //   1421: getfield zzjpe : Lcom/google/android/gms/internal/zzcoe;
    //   1424: getfield zzcm : Ljava/lang/String;
    //   1427: aload #22
    //   1429: getfield name : Ljava/lang/String;
    //   1432: invokevirtual zzao : (Ljava/lang/String;Ljava/lang/String;)Z
    //   1435: istore #16
    //   1437: iload #16
    //   1439: ifne -> 1461
    //   1442: aload_0
    //   1443: invokevirtual zzayl : ()Lcom/google/android/gms/internal/zzcno;
    //   1446: pop
    //   1447: aload #22
    //   1449: getfield name : Ljava/lang/String;
    //   1452: invokestatic zzku : (Ljava/lang/String;)Z
    //   1455: ifeq -> 4291
    //   1458: goto -> 1461
    //   1461: aload #22
    //   1463: getfield zzjui : [Lcom/google/android/gms/internal/zzcoc;
    //   1466: ifnonnull -> 1478
    //   1469: aload #22
    //   1471: iconst_0
    //   1472: anewarray com/google/android/gms/internal/zzcoc
    //   1475: putfield zzjui : [Lcom/google/android/gms/internal/zzcoc;
    //   1478: aload #22
    //   1480: getfield zzjui : [Lcom/google/android/gms/internal/zzcoc;
    //   1483: astore_1
    //   1484: aload_1
    //   1485: arraylength
    //   1486: istore #6
    //   1488: iconst_0
    //   1489: istore #7
    //   1491: iconst_0
    //   1492: istore #8
    //   1494: iconst_0
    //   1495: istore #9
    //   1497: iload #7
    //   1499: iload #6
    //   1501: if_icmpge -> 1576
    //   1504: aload_1
    //   1505: iload #7
    //   1507: aaload
    //   1508: astore #17
    //   1510: ldc_w '_c'
    //   1513: aload #17
    //   1515: getfield name : Ljava/lang/String;
    //   1518: invokevirtual equals : (Ljava/lang/Object;)Z
    //   1521: ifeq -> 1539
    //   1524: aload #17
    //   1526: lconst_1
    //   1527: invokestatic valueOf : (J)Ljava/lang/Long;
    //   1530: putfield zzjum : Ljava/lang/Long;
    //   1533: iconst_1
    //   1534: istore #10
    //   1536: goto -> 4302
    //   1539: iload #8
    //   1541: istore #10
    //   1543: ldc_w '_r'
    //   1546: aload #17
    //   1548: getfield name : Ljava/lang/String;
    //   1551: invokevirtual equals : (Ljava/lang/Object;)Z
    //   1554: ifeq -> 4302
    //   1557: aload #17
    //   1559: lconst_1
    //   1560: invokestatic valueOf : (J)Ljava/lang/Long;
    //   1563: putfield zzjum : Ljava/lang/Long;
    //   1566: iconst_1
    //   1567: istore #9
    //   1569: iload #8
    //   1571: istore #10
    //   1573: goto -> 4302
    //   1576: iload #8
    //   1578: ifne -> 1671
    //   1581: iload #16
    //   1583: ifeq -> 1671
    //   1586: aload_0
    //   1587: invokevirtual zzayp : ()Lcom/google/android/gms/internal/zzcjj;
    //   1590: invokevirtual zzbba : ()Lcom/google/android/gms/internal/zzcjl;
    //   1593: ldc_w 'Marking event as conversion'
    //   1596: aload_0
    //   1597: invokevirtual zzayk : ()Lcom/google/android/gms/internal/zzcjh;
    //   1600: aload #22
    //   1602: getfield name : Ljava/lang/String;
    //   1605: invokevirtual zzjp : (Ljava/lang/String;)Ljava/lang/String;
    //   1608: invokevirtual zzj : (Ljava/lang/String;Ljava/lang/Object;)V
    //   1611: aload #22
    //   1613: getfield zzjui : [Lcom/google/android/gms/internal/zzcoc;
    //   1616: aload #22
    //   1618: getfield zzjui : [Lcom/google/android/gms/internal/zzcoc;
    //   1621: arraylength
    //   1622: iconst_1
    //   1623: iadd
    //   1624: invokestatic copyOf : ([Ljava/lang/Object;I)[Ljava/lang/Object;
    //   1627: checkcast [Lcom/google/android/gms/internal/zzcoc;
    //   1630: astore_1
    //   1631: new com/google/android/gms/internal/zzcoc
    //   1634: dup
    //   1635: invokespecial <init> : ()V
    //   1638: astore #17
    //   1640: aload #17
    //   1642: ldc_w '_c'
    //   1645: putfield name : Ljava/lang/String;
    //   1648: aload #17
    //   1650: lconst_1
    //   1651: invokestatic valueOf : (J)Ljava/lang/Long;
    //   1654: putfield zzjum : Ljava/lang/Long;
    //   1657: aload_1
    //   1658: aload_1
    //   1659: arraylength
    //   1660: iconst_1
    //   1661: isub
    //   1662: aload #17
    //   1664: aastore
    //   1665: aload #22
    //   1667: aload_1
    //   1668: putfield zzjui : [Lcom/google/android/gms/internal/zzcoc;
    //   1671: iload #9
    //   1673: ifne -> 1761
    //   1676: aload_0
    //   1677: invokevirtual zzayp : ()Lcom/google/android/gms/internal/zzcjj;
    //   1680: invokevirtual zzbba : ()Lcom/google/android/gms/internal/zzcjl;
    //   1683: ldc_w 'Marking event as real-time'
    //   1686: aload_0
    //   1687: invokevirtual zzayk : ()Lcom/google/android/gms/internal/zzcjh;
    //   1690: aload #22
    //   1692: getfield name : Ljava/lang/String;
    //   1695: invokevirtual zzjp : (Ljava/lang/String;)Ljava/lang/String;
    //   1698: invokevirtual zzj : (Ljava/lang/String;Ljava/lang/Object;)V
    //   1701: aload #22
    //   1703: getfield zzjui : [Lcom/google/android/gms/internal/zzcoc;
    //   1706: aload #22
    //   1708: getfield zzjui : [Lcom/google/android/gms/internal/zzcoc;
    //   1711: arraylength
    //   1712: iconst_1
    //   1713: iadd
    //   1714: invokestatic copyOf : ([Ljava/lang/Object;I)[Ljava/lang/Object;
    //   1717: checkcast [Lcom/google/android/gms/internal/zzcoc;
    //   1720: astore_1
    //   1721: new com/google/android/gms/internal/zzcoc
    //   1724: dup
    //   1725: invokespecial <init> : ()V
    //   1728: astore #17
    //   1730: aload #17
    //   1732: ldc_w '_r'
    //   1735: putfield name : Ljava/lang/String;
    //   1738: aload #17
    //   1740: lconst_1
    //   1741: invokestatic valueOf : (J)Ljava/lang/Long;
    //   1744: putfield zzjum : Ljava/lang/Long;
    //   1747: aload_1
    //   1748: aload_1
    //   1749: arraylength
    //   1750: iconst_1
    //   1751: isub
    //   1752: aload #17
    //   1754: aastore
    //   1755: aload #22
    //   1757: aload_1
    //   1758: putfield zzjui : [Lcom/google/android/gms/internal/zzcoc;
    //   1761: aload_0
    //   1762: invokevirtual zzayj : ()Lcom/google/android/gms/internal/zzcil;
    //   1765: aload_0
    //   1766: invokespecial zzbbx : ()J
    //   1769: aload #20
    //   1771: getfield zzjpe : Lcom/google/android/gms/internal/zzcoe;
    //   1774: getfield zzcm : Ljava/lang/String;
    //   1777: iconst_0
    //   1778: iconst_0
    //   1779: iconst_0
    //   1780: iconst_0
    //   1781: iconst_1
    //   1782: invokevirtual zza : (JLjava/lang/String;ZZZZZ)Lcom/google/android/gms/internal/zzcim;
    //   1785: getfield zzjhi : J
    //   1788: aload_0
    //   1789: getfield zzjns : Lcom/google/android/gms/internal/zzcik;
    //   1792: aload #20
    //   1794: getfield zzjpe : Lcom/google/android/gms/internal/zzcoe;
    //   1797: getfield zzcm : Ljava/lang/String;
    //   1800: invokevirtual zzje : (Ljava/lang/String;)I
    //   1803: i2l
    //   1804: lcmp
    //   1805: ifle -> 4330
    //   1808: iconst_0
    //   1809: istore #6
    //   1811: iload #6
    //   1813: aload #22
    //   1815: getfield zzjui : [Lcom/google/android/gms/internal/zzcoc;
    //   1818: arraylength
    //   1819: if_icmpge -> 4327
    //   1822: ldc_w '_r'
    //   1825: aload #22
    //   1827: getfield zzjui : [Lcom/google/android/gms/internal/zzcoc;
    //   1830: iload #6
    //   1832: aaload
    //   1833: getfield name : Ljava/lang/String;
    //   1836: invokevirtual equals : (Ljava/lang/Object;)Z
    //   1839: ifeq -> 4318
    //   1842: aload #22
    //   1844: getfield zzjui : [Lcom/google/android/gms/internal/zzcoc;
    //   1847: arraylength
    //   1848: iconst_1
    //   1849: isub
    //   1850: anewarray com/google/android/gms/internal/zzcoc
    //   1853: astore_1
    //   1854: iload #6
    //   1856: ifle -> 1872
    //   1859: aload #22
    //   1861: getfield zzjui : [Lcom/google/android/gms/internal/zzcoc;
    //   1864: iconst_0
    //   1865: aload_1
    //   1866: iconst_0
    //   1867: iload #6
    //   1869: invokestatic arraycopy : (Ljava/lang/Object;ILjava/lang/Object;II)V
    //   1872: iload #6
    //   1874: aload_1
    //   1875: arraylength
    //   1876: if_icmpge -> 4315
    //   1879: aload #22
    //   1881: getfield zzjui : [Lcom/google/android/gms/internal/zzcoc;
    //   1884: iload #6
    //   1886: iconst_1
    //   1887: iadd
    //   1888: aload_1
    //   1889: iload #6
    //   1891: aload_1
    //   1892: arraylength
    //   1893: iload #6
    //   1895: isub
    //   1896: invokestatic arraycopy : (Ljava/lang/Object;ILjava/lang/Object;II)V
    //   1899: goto -> 1902
    //   1902: aload #22
    //   1904: aload_1
    //   1905: putfield zzjui : [Lcom/google/android/gms/internal/zzcoc;
    //   1908: goto -> 4327
    //   1911: iload #13
    //   1913: istore #14
    //   1915: aload #22
    //   1917: getfield name : Ljava/lang/String;
    //   1920: invokestatic zzkh : (Ljava/lang/String;)Z
    //   1923: ifeq -> 4295
    //   1926: iload #13
    //   1928: istore #14
    //   1930: iload #16
    //   1932: ifeq -> 4295
    //   1935: iload #13
    //   1937: istore #14
    //   1939: aload_0
    //   1940: invokevirtual zzayj : ()Lcom/google/android/gms/internal/zzcil;
    //   1943: aload_0
    //   1944: invokespecial zzbbx : ()J
    //   1947: aload #20
    //   1949: getfield zzjpe : Lcom/google/android/gms/internal/zzcoe;
    //   1952: getfield zzcm : Ljava/lang/String;
    //   1955: iconst_0
    //   1956: iconst_0
    //   1957: iconst_1
    //   1958: iconst_0
    //   1959: iconst_0
    //   1960: invokevirtual zza : (JLjava/lang/String;ZZZZZ)Lcom/google/android/gms/internal/zzcim;
    //   1963: getfield zzjhg : J
    //   1966: aload_0
    //   1967: getfield zzjns : Lcom/google/android/gms/internal/zzcik;
    //   1970: aload #20
    //   1972: getfield zzjpe : Lcom/google/android/gms/internal/zzcoe;
    //   1975: getfield zzcm : Ljava/lang/String;
    //   1978: getstatic com/google/android/gms/internal/zzciz.zzjja : Lcom/google/android/gms/internal/zzcja;
    //   1981: invokevirtual zzb : (Ljava/lang/String;Lcom/google/android/gms/internal/zzcja;)I
    //   1984: i2l
    //   1985: lcmp
    //   1986: ifle -> 4295
    //   1989: aload_0
    //   1990: invokevirtual zzayp : ()Lcom/google/android/gms/internal/zzcjj;
    //   1993: invokevirtual zzbaw : ()Lcom/google/android/gms/internal/zzcjl;
    //   1996: ldc_w 'Too many conversions. Not logging as conversion. appId'
    //   1999: aload #20
    //   2001: getfield zzjpe : Lcom/google/android/gms/internal/zzcoe;
    //   2004: getfield zzcm : Ljava/lang/String;
    //   2007: invokestatic zzjs : (Ljava/lang/String;)Ljava/lang/Object;
    //   2010: invokevirtual zzj : (Ljava/lang/String;Ljava/lang/Object;)V
    //   2013: aload #22
    //   2015: getfield zzjui : [Lcom/google/android/gms/internal/zzcoc;
    //   2018: astore_1
    //   2019: aload_1
    //   2020: arraylength
    //   2021: istore #6
    //   2023: iconst_0
    //   2024: istore #7
    //   2026: iconst_0
    //   2027: istore #8
    //   2029: aconst_null
    //   2030: astore #17
    //   2032: iload #7
    //   2034: iload #6
    //   2036: if_icmpge -> 2094
    //   2039: aload_1
    //   2040: iload #7
    //   2042: aaload
    //   2043: astore #19
    //   2045: ldc_w '_c'
    //   2048: aload #19
    //   2050: getfield name : Ljava/lang/String;
    //   2053: invokevirtual equals : (Ljava/lang/Object;)Z
    //   2056: ifeq -> 2066
    //   2059: aload #19
    //   2061: astore #18
    //   2063: goto -> 4336
    //   2066: aload #17
    //   2068: astore #18
    //   2070: ldc_w '_err'
    //   2073: aload #19
    //   2075: getfield name : Ljava/lang/String;
    //   2078: invokevirtual equals : (Ljava/lang/Object;)Z
    //   2081: ifeq -> 4336
    //   2084: iconst_1
    //   2085: istore #8
    //   2087: aload #17
    //   2089: astore #18
    //   2091: goto -> 4336
    //   2094: iload #8
    //   2096: ifeq -> 2132
    //   2099: aload #17
    //   2101: ifnull -> 2132
    //   2104: aload #22
    //   2106: aload #22
    //   2108: getfield zzjui : [Lcom/google/android/gms/internal/zzcoc;
    //   2111: iconst_1
    //   2112: anewarray com/google/android/gms/internal/zzcoc
    //   2115: dup
    //   2116: iconst_0
    //   2117: aload #17
    //   2119: aastore
    //   2120: invokestatic zza : ([Ljava/lang/Object;[Ljava/lang/Object;)[Ljava/lang/Object;
    //   2123: checkcast [Lcom/google/android/gms/internal/zzcoc;
    //   2126: putfield zzjui : [Lcom/google/android/gms/internal/zzcoc;
    //   2129: goto -> 2183
    //   2132: aload #17
    //   2134: ifnull -> 2159
    //   2137: aload #17
    //   2139: ldc_w '_err'
    //   2142: putfield name : Ljava/lang/String;
    //   2145: aload #17
    //   2147: ldc2_w 10
    //   2150: invokestatic valueOf : (J)Ljava/lang/Long;
    //   2153: putfield zzjum : Ljava/lang/Long;
    //   2156: goto -> 2183
    //   2159: aload_0
    //   2160: invokevirtual zzayp : ()Lcom/google/android/gms/internal/zzcjj;
    //   2163: invokevirtual zzbau : ()Lcom/google/android/gms/internal/zzcjl;
    //   2166: ldc_w 'Did not find conversion parameter. appId'
    //   2169: aload #20
    //   2171: getfield zzjpe : Lcom/google/android/gms/internal/zzcoe;
    //   2174: getfield zzcm : Ljava/lang/String;
    //   2177: invokestatic zzjs : (Ljava/lang/String;)Ljava/lang/Object;
    //   2180: invokevirtual zzj : (Ljava/lang/String;Ljava/lang/Object;)V
    //   2183: lload_2
    //   2184: lstore #11
    //   2186: iload #15
    //   2188: ifeq -> 2329
    //   2191: lload_2
    //   2192: lstore #11
    //   2194: ldc_w '_e'
    //   2197: aload #22
    //   2199: getfield name : Ljava/lang/String;
    //   2202: invokevirtual equals : (Ljava/lang/Object;)Z
    //   2205: ifeq -> 2329
    //   2208: aload #22
    //   2210: getfield zzjui : [Lcom/google/android/gms/internal/zzcoc;
    //   2213: ifnull -> 2300
    //   2216: aload #22
    //   2218: getfield zzjui : [Lcom/google/android/gms/internal/zzcoc;
    //   2221: arraylength
    //   2222: ifne -> 2228
    //   2225: goto -> 2300
    //   2228: aload_0
    //   2229: invokevirtual zzayl : ()Lcom/google/android/gms/internal/zzcno;
    //   2232: pop
    //   2233: aload #22
    //   2235: ldc_w '_et'
    //   2238: invokestatic zzb : (Lcom/google/android/gms/internal/zzcob;Ljava/lang/String;)Ljava/lang/Object;
    //   2241: checkcast java/lang/Long
    //   2244: astore_1
    //   2245: aload_1
    //   2246: ifnonnull -> 2289
    //   2249: aload_0
    //   2250: invokevirtual zzayp : ()Lcom/google/android/gms/internal/zzcjj;
    //   2253: invokevirtual zzbaw : ()Lcom/google/android/gms/internal/zzcjl;
    //   2256: astore_1
    //   2257: ldc_w 'Engagement event does not include duration. appId'
    //   2260: astore #17
    //   2262: aload #20
    //   2264: getfield zzjpe : Lcom/google/android/gms/internal/zzcoe;
    //   2267: getfield zzcm : Ljava/lang/String;
    //   2270: invokestatic zzjs : (Ljava/lang/String;)Ljava/lang/Object;
    //   2273: astore #18
    //   2275: aload_1
    //   2276: aload #17
    //   2278: aload #18
    //   2280: invokevirtual zzj : (Ljava/lang/String;Ljava/lang/Object;)V
    //   2283: lload_2
    //   2284: lstore #11
    //   2286: goto -> 2329
    //   2289: lload_2
    //   2290: aload_1
    //   2291: invokevirtual longValue : ()J
    //   2294: ladd
    //   2295: lstore #11
    //   2297: goto -> 2329
    //   2300: aload_0
    //   2301: invokevirtual zzayp : ()Lcom/google/android/gms/internal/zzcjj;
    //   2304: invokevirtual zzbaw : ()Lcom/google/android/gms/internal/zzcjl;
    //   2307: astore_1
    //   2308: ldc_w 'Engagement event does not contain any parameters. appId'
    //   2311: astore #17
    //   2313: aload #20
    //   2315: getfield zzjpe : Lcom/google/android/gms/internal/zzcoe;
    //   2318: getfield zzcm : Ljava/lang/String;
    //   2321: invokestatic zzjs : (Ljava/lang/String;)Ljava/lang/Object;
    //   2324: astore #18
    //   2326: goto -> 2275
    //   2329: aload #21
    //   2331: getfield zzjuq : [Lcom/google/android/gms/internal/zzcob;
    //   2334: iload #5
    //   2336: aload #22
    //   2338: aastore
    //   2339: iload #5
    //   2341: iconst_1
    //   2342: iadd
    //   2343: istore #5
    //   2345: lload #11
    //   2347: lstore_2
    //   2348: goto -> 4349
    //   2351: iload #5
    //   2353: aload #20
    //   2355: getfield zzaoz : Ljava/util/List;
    //   2358: invokeinterface size : ()I
    //   2363: if_icmpge -> 2384
    //   2366: aload #21
    //   2368: aload #21
    //   2370: getfield zzjuq : [Lcom/google/android/gms/internal/zzcob;
    //   2373: iload #5
    //   2375: invokestatic copyOf : ([Ljava/lang/Object;I)[Ljava/lang/Object;
    //   2378: checkcast [Lcom/google/android/gms/internal/zzcob;
    //   2381: putfield zzjuq : [Lcom/google/android/gms/internal/zzcob;
    //   2384: iload #15
    //   2386: ifeq -> 2673
    //   2389: aload_0
    //   2390: invokevirtual zzayj : ()Lcom/google/android/gms/internal/zzcil;
    //   2393: aload #21
    //   2395: getfield zzcm : Ljava/lang/String;
    //   2398: ldc_w '_lte'
    //   2401: invokevirtual zzag : (Ljava/lang/String;Ljava/lang/String;)Lcom/google/android/gms/internal/zzcnn;
    //   2404: astore_1
    //   2405: aload_1
    //   2406: ifnull -> 2465
    //   2409: aload_1
    //   2410: getfield value : Ljava/lang/Object;
    //   2413: ifnonnull -> 2419
    //   2416: goto -> 2465
    //   2419: new com/google/android/gms/internal/zzcnn
    //   2422: dup
    //   2423: aload #21
    //   2425: getfield zzcm : Ljava/lang/String;
    //   2428: ldc_w 'auto'
    //   2431: ldc_w '_lte'
    //   2434: aload_0
    //   2435: getfield zzdir : Lcom/google/android/gms/common/util/zze;
    //   2438: invokeinterface currentTimeMillis : ()J
    //   2443: aload_1
    //   2444: getfield value : Ljava/lang/Object;
    //   2447: checkcast java/lang/Long
    //   2450: invokevirtual longValue : ()J
    //   2453: lload_2
    //   2454: ladd
    //   2455: invokestatic valueOf : (J)Ljava/lang/Long;
    //   2458: invokespecial <init> : (Ljava/lang/String;Ljava/lang/String;Ljava/lang/String;JLjava/lang/Object;)V
    //   2461: astore_1
    //   2462: goto -> 2497
    //   2465: new com/google/android/gms/internal/zzcnn
    //   2468: dup
    //   2469: aload #21
    //   2471: getfield zzcm : Ljava/lang/String;
    //   2474: ldc_w 'auto'
    //   2477: ldc_w '_lte'
    //   2480: aload_0
    //   2481: getfield zzdir : Lcom/google/android/gms/common/util/zze;
    //   2484: invokeinterface currentTimeMillis : ()J
    //   2489: lload_2
    //   2490: invokestatic valueOf : (J)Ljava/lang/Long;
    //   2493: invokespecial <init> : (Ljava/lang/String;Ljava/lang/String;Ljava/lang/String;JLjava/lang/Object;)V
    //   2496: astore_1
    //   2497: new com/google/android/gms/internal/zzcog
    //   2500: dup
    //   2501: invokespecial <init> : ()V
    //   2504: astore #17
    //   2506: aload #17
    //   2508: ldc_w '_lte'
    //   2511: putfield name : Ljava/lang/String;
    //   2514: aload #17
    //   2516: aload_0
    //   2517: getfield zzdir : Lcom/google/android/gms/common/util/zze;
    //   2520: invokeinterface currentTimeMillis : ()J
    //   2525: invokestatic valueOf : (J)Ljava/lang/Long;
    //   2528: putfield zzjvr : Ljava/lang/Long;
    //   2531: aload #17
    //   2533: aload_1
    //   2534: getfield value : Ljava/lang/Object;
    //   2537: checkcast java/lang/Long
    //   2540: putfield zzjum : Ljava/lang/Long;
    //   2543: iconst_0
    //   2544: istore #4
    //   2546: iload #4
    //   2548: aload #21
    //   2550: getfield zzjur : [Lcom/google/android/gms/internal/zzcog;
    //   2553: arraylength
    //   2554: if_icmpge -> 4367
    //   2557: ldc_w '_lte'
    //   2560: aload #21
    //   2562: getfield zzjur : [Lcom/google/android/gms/internal/zzcog;
    //   2565: iload #4
    //   2567: aaload
    //   2568: getfield name : Ljava/lang/String;
    //   2571: invokevirtual equals : (Ljava/lang/Object;)Z
    //   2574: ifeq -> 4358
    //   2577: aload #21
    //   2579: getfield zzjur : [Lcom/google/android/gms/internal/zzcog;
    //   2582: iload #4
    //   2584: aload #17
    //   2586: aastore
    //   2587: iconst_1
    //   2588: istore #4
    //   2590: goto -> 2593
    //   2593: iload #4
    //   2595: ifne -> 2641
    //   2598: aload #21
    //   2600: aload #21
    //   2602: getfield zzjur : [Lcom/google/android/gms/internal/zzcog;
    //   2605: aload #21
    //   2607: getfield zzjur : [Lcom/google/android/gms/internal/zzcog;
    //   2610: arraylength
    //   2611: iconst_1
    //   2612: iadd
    //   2613: invokestatic copyOf : ([Ljava/lang/Object;I)[Ljava/lang/Object;
    //   2616: checkcast [Lcom/google/android/gms/internal/zzcog;
    //   2619: putfield zzjur : [Lcom/google/android/gms/internal/zzcog;
    //   2622: aload #21
    //   2624: getfield zzjur : [Lcom/google/android/gms/internal/zzcog;
    //   2627: aload #20
    //   2629: getfield zzjpe : Lcom/google/android/gms/internal/zzcoe;
    //   2632: getfield zzjur : [Lcom/google/android/gms/internal/zzcog;
    //   2635: arraylength
    //   2636: iconst_1
    //   2637: isub
    //   2638: aload #17
    //   2640: aastore
    //   2641: lload_2
    //   2642: lconst_0
    //   2643: lcmp
    //   2644: ifle -> 2673
    //   2647: aload_0
    //   2648: invokevirtual zzayj : ()Lcom/google/android/gms/internal/zzcil;
    //   2651: aload_1
    //   2652: invokevirtual zza : (Lcom/google/android/gms/internal/zzcnn;)Z
    //   2655: pop
    //   2656: aload_0
    //   2657: invokevirtual zzayp : ()Lcom/google/android/gms/internal/zzcjj;
    //   2660: invokevirtual zzbaz : ()Lcom/google/android/gms/internal/zzcjl;
    //   2663: ldc_w 'Updated lifetime engagement user property with value. Value'
    //   2666: aload_1
    //   2667: getfield value : Ljava/lang/Object;
    //   2670: invokevirtual zzj : (Ljava/lang/String;Ljava/lang/Object;)V
    //   2673: aload #21
    //   2675: aload_0
    //   2676: aload #21
    //   2678: getfield zzcm : Ljava/lang/String;
    //   2681: aload #21
    //   2683: getfield zzjur : [Lcom/google/android/gms/internal/zzcog;
    //   2686: aload #21
    //   2688: getfield zzjuq : [Lcom/google/android/gms/internal/zzcob;
    //   2691: invokespecial zza : (Ljava/lang/String;[Lcom/google/android/gms/internal/zzcog;[Lcom/google/android/gms/internal/zzcob;)[Lcom/google/android/gms/internal/zzcoa;
    //   2694: putfield zzjvh : [Lcom/google/android/gms/internal/zzcoa;
    //   2697: getstatic com/google/android/gms/internal/zzciz.zzjim : Lcom/google/android/gms/internal/zzcja;
    //   2700: invokevirtual get : ()Ljava/lang/Object;
    //   2703: checkcast java/lang/Boolean
    //   2706: invokevirtual booleanValue : ()Z
    //   2709: ifeq -> 4429
    //   2712: aload_0
    //   2713: getfield zzjns : Lcom/google/android/gms/internal/zzcik;
    //   2716: astore_1
    //   2717: aload #20
    //   2719: getfield zzjpe : Lcom/google/android/gms/internal/zzcoe;
    //   2722: getfield zzcm : Ljava/lang/String;
    //   2725: astore #17
    //   2727: ldc_w '1'
    //   2730: aload_1
    //   2731: invokevirtual zzaym : ()Lcom/google/android/gms/internal/zzckd;
    //   2734: aload #17
    //   2736: ldc_w 'measurement.event_sampling_enabled'
    //   2739: invokevirtual zzam : (Ljava/lang/String;Ljava/lang/String;)Ljava/lang/String;
    //   2742: invokevirtual equals : (Ljava/lang/Object;)Z
    //   2745: ifeq -> 4429
    //   2748: new java/util/HashMap
    //   2751: dup
    //   2752: invokespecial <init> : ()V
    //   2755: astore #22
    //   2757: aload #21
    //   2759: getfield zzjuq : [Lcom/google/android/gms/internal/zzcob;
    //   2762: arraylength
    //   2763: anewarray com/google/android/gms/internal/zzcob
    //   2766: astore #23
    //   2768: aload_0
    //   2769: invokevirtual zzayl : ()Lcom/google/android/gms/internal/zzcno;
    //   2772: invokevirtual zzbcr : ()Ljava/security/SecureRandom;
    //   2775: astore #19
    //   2777: aload #21
    //   2779: getfield zzjuq : [Lcom/google/android/gms/internal/zzcob;
    //   2782: astore #18
    //   2784: aload #18
    //   2786: arraylength
    //   2787: istore #7
    //   2789: iconst_0
    //   2790: istore #6
    //   2792: iconst_0
    //   2793: istore #4
    //   2795: aload #20
    //   2797: astore #17
    //   2799: iload #6
    //   2801: iload #7
    //   2803: if_icmpge -> 3609
    //   2806: aload #18
    //   2808: iload #6
    //   2810: aaload
    //   2811: astore #24
    //   2813: aload #24
    //   2815: getfield name : Ljava/lang/String;
    //   2818: ldc_w '_ep'
    //   2821: invokevirtual equals : (Ljava/lang/Object;)Z
    //   2824: ifeq -> 2989
    //   2827: aload_0
    //   2828: invokevirtual zzayl : ()Lcom/google/android/gms/internal/zzcno;
    //   2831: pop
    //   2832: aload #24
    //   2834: ldc_w '_en'
    //   2837: invokestatic zzb : (Lcom/google/android/gms/internal/zzcob;Ljava/lang/String;)Ljava/lang/Object;
    //   2840: checkcast java/lang/String
    //   2843: astore #25
    //   2845: aload #22
    //   2847: aload #25
    //   2849: invokeinterface get : (Ljava/lang/Object;)Ljava/lang/Object;
    //   2854: checkcast com/google/android/gms/internal/zzcit
    //   2857: astore #20
    //   2859: aload #20
    //   2861: astore_1
    //   2862: aload #20
    //   2864: ifnonnull -> 2896
    //   2867: aload_0
    //   2868: invokevirtual zzayj : ()Lcom/google/android/gms/internal/zzcil;
    //   2871: aload #17
    //   2873: getfield zzjpe : Lcom/google/android/gms/internal/zzcoe;
    //   2876: getfield zzcm : Ljava/lang/String;
    //   2879: aload #25
    //   2881: invokevirtual zzae : (Ljava/lang/String;Ljava/lang/String;)Lcom/google/android/gms/internal/zzcit;
    //   2884: astore_1
    //   2885: aload #22
    //   2887: aload #25
    //   2889: aload_1
    //   2890: invokeinterface put : (Ljava/lang/Object;Ljava/lang/Object;)Ljava/lang/Object;
    //   2895: pop
    //   2896: iload #4
    //   2898: istore #5
    //   2900: aload_1
    //   2901: getfield zzjhw : Ljava/lang/Long;
    //   2904: ifnonnull -> 4403
    //   2907: aload_1
    //   2908: getfield zzjhx : Ljava/lang/Long;
    //   2911: invokevirtual longValue : ()J
    //   2914: lconst_1
    //   2915: lcmp
    //   2916: ifle -> 2944
    //   2919: aload_0
    //   2920: invokevirtual zzayl : ()Lcom/google/android/gms/internal/zzcno;
    //   2923: pop
    //   2924: aload #24
    //   2926: aload #24
    //   2928: getfield zzjui : [Lcom/google/android/gms/internal/zzcoc;
    //   2931: ldc_w '_sr'
    //   2934: aload_1
    //   2935: getfield zzjhx : Ljava/lang/Long;
    //   2938: invokestatic zza : ([Lcom/google/android/gms/internal/zzcoc;Ljava/lang/String;Ljava/lang/Object;)[Lcom/google/android/gms/internal/zzcoc;
    //   2941: putfield zzjui : [Lcom/google/android/gms/internal/zzcoc;
    //   2944: aload_1
    //   2945: getfield zzjhy : Ljava/lang/Boolean;
    //   2948: ifnull -> 4373
    //   2951: aload_1
    //   2952: getfield zzjhy : Ljava/lang/Boolean;
    //   2955: invokevirtual booleanValue : ()Z
    //   2958: ifeq -> 4373
    //   2961: aload_0
    //   2962: invokevirtual zzayl : ()Lcom/google/android/gms/internal/zzcno;
    //   2965: pop
    //   2966: aload #24
    //   2968: aload #24
    //   2970: getfield zzjui : [Lcom/google/android/gms/internal/zzcoc;
    //   2973: ldc_w '_efs'
    //   2976: lconst_1
    //   2977: invokestatic valueOf : (J)Ljava/lang/Long;
    //   2980: invokestatic zza : ([Lcom/google/android/gms/internal/zzcoc;Ljava/lang/String;Ljava/lang/Object;)[Lcom/google/android/gms/internal/zzcoc;
    //   2983: putfield zzjui : [Lcom/google/android/gms/internal/zzcoc;
    //   2986: goto -> 4373
    //   2989: aload #24
    //   2991: ldc_w '_dbg'
    //   2994: lconst_1
    //   2995: invokestatic valueOf : (J)Ljava/lang/Long;
    //   2998: invokestatic zza : (Lcom/google/android/gms/internal/zzcob;Ljava/lang/String;Ljava/lang/Object;)Z
    //   3001: ifne -> 4393
    //   3004: aload_0
    //   3005: invokevirtual zzaym : ()Lcom/google/android/gms/internal/zzckd;
    //   3008: aload #17
    //   3010: getfield zzjpe : Lcom/google/android/gms/internal/zzcoe;
    //   3013: getfield zzcm : Ljava/lang/String;
    //   3016: aload #24
    //   3018: getfield name : Ljava/lang/String;
    //   3021: invokevirtual zzap : (Ljava/lang/String;Ljava/lang/String;)I
    //   3024: istore #5
    //   3026: goto -> 3029
    //   3029: iload #5
    //   3031: ifgt -> 3077
    //   3034: aload_0
    //   3035: invokevirtual zzayp : ()Lcom/google/android/gms/internal/zzcjj;
    //   3038: invokevirtual zzbaw : ()Lcom/google/android/gms/internal/zzcjl;
    //   3041: ldc_w 'Sample rate must be positive. event, rate'
    //   3044: aload #24
    //   3046: getfield name : Ljava/lang/String;
    //   3049: iload #5
    //   3051: invokestatic valueOf : (I)Ljava/lang/Integer;
    //   3054: invokevirtual zze : (Ljava/lang/String;Ljava/lang/Object;Ljava/lang/Object;)V
    //   3057: iload #4
    //   3059: iconst_1
    //   3060: iadd
    //   3061: istore #5
    //   3063: aload #23
    //   3065: iload #4
    //   3067: aload #24
    //   3069: aastore
    //   3070: iload #5
    //   3072: istore #4
    //   3074: goto -> 4399
    //   3077: aload #22
    //   3079: aload #24
    //   3081: getfield name : Ljava/lang/String;
    //   3084: invokeinterface get : (Ljava/lang/Object;)Ljava/lang/Object;
    //   3089: checkcast com/google/android/gms/internal/zzcit
    //   3092: astore #20
    //   3094: aload #20
    //   3096: astore_1
    //   3097: aload #20
    //   3099: ifnonnull -> 3193
    //   3102: aload_0
    //   3103: invokevirtual zzayj : ()Lcom/google/android/gms/internal/zzcil;
    //   3106: aload #17
    //   3108: getfield zzjpe : Lcom/google/android/gms/internal/zzcoe;
    //   3111: getfield zzcm : Ljava/lang/String;
    //   3114: aload #24
    //   3116: getfield name : Ljava/lang/String;
    //   3119: invokevirtual zzae : (Ljava/lang/String;Ljava/lang/String;)Lcom/google/android/gms/internal/zzcit;
    //   3122: astore #20
    //   3124: aload #20
    //   3126: astore_1
    //   3127: aload #20
    //   3129: ifnonnull -> 3193
    //   3132: aload_0
    //   3133: invokevirtual zzayp : ()Lcom/google/android/gms/internal/zzcjj;
    //   3136: invokevirtual zzbaw : ()Lcom/google/android/gms/internal/zzcjl;
    //   3139: ldc_w 'Event being bundled has no eventAggregate. appId, eventName'
    //   3142: aload #17
    //   3144: getfield zzjpe : Lcom/google/android/gms/internal/zzcoe;
    //   3147: getfield zzcm : Ljava/lang/String;
    //   3150: aload #24
    //   3152: getfield name : Ljava/lang/String;
    //   3155: invokevirtual zze : (Ljava/lang/String;Ljava/lang/Object;Ljava/lang/Object;)V
    //   3158: new com/google/android/gms/internal/zzcit
    //   3161: dup
    //   3162: aload #17
    //   3164: getfield zzjpe : Lcom/google/android/gms/internal/zzcoe;
    //   3167: getfield zzcm : Ljava/lang/String;
    //   3170: aload #24
    //   3172: getfield name : Ljava/lang/String;
    //   3175: lconst_1
    //   3176: lconst_1
    //   3177: aload #24
    //   3179: getfield zzjuj : Ljava/lang/Long;
    //   3182: invokevirtual longValue : ()J
    //   3185: lconst_0
    //   3186: aconst_null
    //   3187: aconst_null
    //   3188: aconst_null
    //   3189: invokespecial <init> : (Ljava/lang/String;Ljava/lang/String;JJJJLjava/lang/Long;Ljava/lang/Long;Ljava/lang/Boolean;)V
    //   3192: astore_1
    //   3193: aload_0
    //   3194: invokevirtual zzayl : ()Lcom/google/android/gms/internal/zzcno;
    //   3197: pop
    //   3198: aload #24
    //   3200: ldc_w '_eid'
    //   3203: invokestatic zzb : (Lcom/google/android/gms/internal/zzcob;Ljava/lang/String;)Ljava/lang/Object;
    //   3206: checkcast java/lang/Long
    //   3209: astore #20
    //   3211: aload #20
    //   3213: ifnull -> 4410
    //   3216: iconst_1
    //   3217: istore #14
    //   3219: goto -> 3222
    //   3222: iload #14
    //   3224: invokestatic valueOf : (Z)Ljava/lang/Boolean;
    //   3227: astore #25
    //   3229: iload #5
    //   3231: iconst_1
    //   3232: if_icmpne -> 3314
    //   3235: iload #4
    //   3237: iconst_1
    //   3238: iadd
    //   3239: istore #5
    //   3241: aload #23
    //   3243: iload #4
    //   3245: aload #24
    //   3247: aastore
    //   3248: iload #5
    //   3250: istore #4
    //   3252: aload #25
    //   3254: invokevirtual booleanValue : ()Z
    //   3257: ifeq -> 4399
    //   3260: aload_1
    //   3261: getfield zzjhw : Ljava/lang/Long;
    //   3264: ifnonnull -> 3285
    //   3267: aload_1
    //   3268: getfield zzjhx : Ljava/lang/Long;
    //   3271: ifnonnull -> 3285
    //   3274: iload #5
    //   3276: istore #4
    //   3278: aload_1
    //   3279: getfield zzjhy : Ljava/lang/Boolean;
    //   3282: ifnull -> 4399
    //   3285: aload_1
    //   3286: aconst_null
    //   3287: aconst_null
    //   3288: aconst_null
    //   3289: invokevirtual zza : (Ljava/lang/Long;Ljava/lang/Long;Ljava/lang/Boolean;)Lcom/google/android/gms/internal/zzcit;
    //   3292: astore_1
    //   3293: aload #22
    //   3295: aload #24
    //   3297: getfield name : Ljava/lang/String;
    //   3300: aload_1
    //   3301: invokeinterface put : (Ljava/lang/Object;Ljava/lang/Object;)Ljava/lang/Object;
    //   3306: pop
    //   3307: iload #5
    //   3309: istore #4
    //   3311: goto -> 4399
    //   3314: aload #19
    //   3316: iload #5
    //   3318: invokevirtual nextInt : (I)I
    //   3321: ifne -> 3422
    //   3324: aload_0
    //   3325: invokevirtual zzayl : ()Lcom/google/android/gms/internal/zzcno;
    //   3328: pop
    //   3329: aload #24
    //   3331: getfield zzjui : [Lcom/google/android/gms/internal/zzcoc;
    //   3334: astore #20
    //   3336: iload #5
    //   3338: i2l
    //   3339: lstore_2
    //   3340: aload #24
    //   3342: aload #20
    //   3344: ldc_w '_sr'
    //   3347: lload_2
    //   3348: invokestatic valueOf : (J)Ljava/lang/Long;
    //   3351: invokestatic zza : ([Lcom/google/android/gms/internal/zzcoc;Ljava/lang/String;Ljava/lang/Object;)[Lcom/google/android/gms/internal/zzcoc;
    //   3354: putfield zzjui : [Lcom/google/android/gms/internal/zzcoc;
    //   3357: aload #23
    //   3359: iload #4
    //   3361: aload #24
    //   3363: aastore
    //   3364: aload_1
    //   3365: astore #20
    //   3367: aload #25
    //   3369: invokevirtual booleanValue : ()Z
    //   3372: ifeq -> 3387
    //   3375: aload_1
    //   3376: aconst_null
    //   3377: lload_2
    //   3378: invokestatic valueOf : (J)Ljava/lang/Long;
    //   3381: aconst_null
    //   3382: invokevirtual zza : (Ljava/lang/Long;Ljava/lang/Long;Ljava/lang/Boolean;)Lcom/google/android/gms/internal/zzcit;
    //   3385: astore #20
    //   3387: aload #22
    //   3389: aload #24
    //   3391: getfield name : Ljava/lang/String;
    //   3394: aload #20
    //   3396: aload #24
    //   3398: getfield zzjuj : Ljava/lang/Long;
    //   3401: invokevirtual longValue : ()J
    //   3404: invokevirtual zzbc : (J)Lcom/google/android/gms/internal/zzcit;
    //   3407: invokeinterface put : (Ljava/lang/Object;Ljava/lang/Object;)Ljava/lang/Object;
    //   3412: pop
    //   3413: iload #4
    //   3415: iconst_1
    //   3416: iadd
    //   3417: istore #4
    //   3419: goto -> 4407
    //   3422: aload_1
    //   3423: getfield zzjhv : J
    //   3426: lstore_2
    //   3427: aload #24
    //   3429: getfield zzjuj : Ljava/lang/Long;
    //   3432: invokevirtual longValue : ()J
    //   3435: lload_2
    //   3436: lsub
    //   3437: invokestatic abs : (J)J
    //   3440: ldc2_w 86400000
    //   3443: lcmp
    //   3444: iflt -> 3573
    //   3447: aload_0
    //   3448: invokevirtual zzayl : ()Lcom/google/android/gms/internal/zzcno;
    //   3451: pop
    //   3452: aload #24
    //   3454: aload #24
    //   3456: getfield zzjui : [Lcom/google/android/gms/internal/zzcoc;
    //   3459: ldc_w '_efs'
    //   3462: lconst_1
    //   3463: invokestatic valueOf : (J)Ljava/lang/Long;
    //   3466: invokestatic zza : ([Lcom/google/android/gms/internal/zzcoc;Ljava/lang/String;Ljava/lang/Object;)[Lcom/google/android/gms/internal/zzcoc;
    //   3469: putfield zzjui : [Lcom/google/android/gms/internal/zzcoc;
    //   3472: aload_0
    //   3473: invokevirtual zzayl : ()Lcom/google/android/gms/internal/zzcno;
    //   3476: pop
    //   3477: aload #24
    //   3479: getfield zzjui : [Lcom/google/android/gms/internal/zzcoc;
    //   3482: astore #20
    //   3484: iload #5
    //   3486: i2l
    //   3487: lstore_2
    //   3488: aload #24
    //   3490: aload #20
    //   3492: ldc_w '_sr'
    //   3495: lload_2
    //   3496: invokestatic valueOf : (J)Ljava/lang/Long;
    //   3499: invokestatic zza : ([Lcom/google/android/gms/internal/zzcoc;Ljava/lang/String;Ljava/lang/Object;)[Lcom/google/android/gms/internal/zzcoc;
    //   3502: putfield zzjui : [Lcom/google/android/gms/internal/zzcoc;
    //   3505: aload #23
    //   3507: iload #4
    //   3509: aload #24
    //   3511: aastore
    //   3512: aload_1
    //   3513: astore #20
    //   3515: aload #25
    //   3517: invokevirtual booleanValue : ()Z
    //   3520: ifeq -> 3538
    //   3523: aload_1
    //   3524: aconst_null
    //   3525: lload_2
    //   3526: invokestatic valueOf : (J)Ljava/lang/Long;
    //   3529: iconst_1
    //   3530: invokestatic valueOf : (Z)Ljava/lang/Boolean;
    //   3533: invokevirtual zza : (Ljava/lang/Long;Ljava/lang/Long;Ljava/lang/Boolean;)Lcom/google/android/gms/internal/zzcit;
    //   3536: astore #20
    //   3538: aload #22
    //   3540: aload #24
    //   3542: getfield name : Ljava/lang/String;
    //   3545: aload #20
    //   3547: aload #24
    //   3549: getfield zzjuj : Ljava/lang/Long;
    //   3552: invokevirtual longValue : ()J
    //   3555: invokevirtual zzbc : (J)Lcom/google/android/gms/internal/zzcit;
    //   3558: invokeinterface put : (Ljava/lang/Object;Ljava/lang/Object;)Ljava/lang/Object;
    //   3563: pop
    //   3564: iload #4
    //   3566: iconst_1
    //   3567: iadd
    //   3568: istore #5
    //   3570: goto -> 4416
    //   3573: iload #4
    //   3575: istore #5
    //   3577: aload #25
    //   3579: invokevirtual booleanValue : ()Z
    //   3582: ifeq -> 4416
    //   3585: aload #22
    //   3587: aload #24
    //   3589: getfield name : Ljava/lang/String;
    //   3592: aload_1
    //   3593: aload #20
    //   3595: aconst_null
    //   3596: aconst_null
    //   3597: invokevirtual zza : (Ljava/lang/Long;Ljava/lang/Long;Ljava/lang/Boolean;)Lcom/google/android/gms/internal/zzcit;
    //   3600: invokeinterface put : (Ljava/lang/Object;Ljava/lang/Object;)Ljava/lang/Object;
    //   3605: pop
    //   3606: goto -> 4420
    //   3609: iload #4
    //   3611: aload #21
    //   3613: getfield zzjuq : [Lcom/google/android/gms/internal/zzcob;
    //   3616: arraylength
    //   3617: if_icmpge -> 3635
    //   3620: aload #21
    //   3622: aload #23
    //   3624: iload #4
    //   3626: invokestatic copyOf : ([Ljava/lang/Object;I)[Ljava/lang/Object;
    //   3629: checkcast [Lcom/google/android/gms/internal/zzcob;
    //   3632: putfield zzjuq : [Lcom/google/android/gms/internal/zzcob;
    //   3635: aload #22
    //   3637: invokeinterface entrySet : ()Ljava/util/Set;
    //   3642: invokeinterface iterator : ()Ljava/util/Iterator;
    //   3647: astore #18
    //   3649: aload #17
    //   3651: astore_1
    //   3652: aload #18
    //   3654: invokeinterface hasNext : ()Z
    //   3659: ifeq -> 3692
    //   3662: aload #18
    //   3664: invokeinterface next : ()Ljava/lang/Object;
    //   3669: checkcast java/util/Map$Entry
    //   3672: astore_1
    //   3673: aload_0
    //   3674: invokevirtual zzayj : ()Lcom/google/android/gms/internal/zzcil;
    //   3677: aload_1
    //   3678: invokeinterface getValue : ()Ljava/lang/Object;
    //   3683: checkcast com/google/android/gms/internal/zzcit
    //   3686: invokevirtual zza : (Lcom/google/android/gms/internal/zzcit;)V
    //   3689: goto -> 3649
    //   3692: aconst_null
    //   3693: astore #18
    //   3695: aload #21
    //   3697: ldc2_w 9223372036854775807
    //   3700: invokestatic valueOf : (J)Ljava/lang/Long;
    //   3703: putfield zzjut : Ljava/lang/Long;
    //   3706: aload #21
    //   3708: ldc2_w -9223372036854775808
    //   3711: invokestatic valueOf : (J)Ljava/lang/Long;
    //   3714: putfield zzjuu : Ljava/lang/Long;
    //   3717: iconst_0
    //   3718: istore #4
    //   3720: iload #4
    //   3722: aload #21
    //   3724: getfield zzjuq : [Lcom/google/android/gms/internal/zzcob;
    //   3727: arraylength
    //   3728: if_icmpge -> 3804
    //   3731: aload #21
    //   3733: getfield zzjuq : [Lcom/google/android/gms/internal/zzcob;
    //   3736: iload #4
    //   3738: aaload
    //   3739: astore #17
    //   3741: aload #17
    //   3743: getfield zzjuj : Ljava/lang/Long;
    //   3746: invokevirtual longValue : ()J
    //   3749: aload #21
    //   3751: getfield zzjut : Ljava/lang/Long;
    //   3754: invokevirtual longValue : ()J
    //   3757: lcmp
    //   3758: ifge -> 3771
    //   3761: aload #21
    //   3763: aload #17
    //   3765: getfield zzjuj : Ljava/lang/Long;
    //   3768: putfield zzjut : Ljava/lang/Long;
    //   3771: aload #17
    //   3773: getfield zzjuj : Ljava/lang/Long;
    //   3776: invokevirtual longValue : ()J
    //   3779: aload #21
    //   3781: getfield zzjuu : Ljava/lang/Long;
    //   3784: invokevirtual longValue : ()J
    //   3787: lcmp
    //   3788: ifle -> 4435
    //   3791: aload #21
    //   3793: aload #17
    //   3795: getfield zzjuj : Ljava/lang/Long;
    //   3798: putfield zzjuu : Ljava/lang/Long;
    //   3801: goto -> 4435
    //   3804: aload_1
    //   3805: getfield zzjpe : Lcom/google/android/gms/internal/zzcoe;
    //   3808: getfield zzcm : Ljava/lang/String;
    //   3811: astore #19
    //   3813: aload_0
    //   3814: invokevirtual zzayj : ()Lcom/google/android/gms/internal/zzcil;
    //   3817: aload #19
    //   3819: invokevirtual zzjj : (Ljava/lang/String;)Lcom/google/android/gms/internal/zzcie;
    //   3822: astore #20
    //   3824: aload #20
    //   3826: ifnonnull -> 3855
    //   3829: aload_0
    //   3830: invokevirtual zzayp : ()Lcom/google/android/gms/internal/zzcjj;
    //   3833: invokevirtual zzbau : ()Lcom/google/android/gms/internal/zzcjl;
    //   3836: ldc_w 'Bundling raw events w/o app info. appId'
    //   3839: aload_1
    //   3840: getfield zzjpe : Lcom/google/android/gms/internal/zzcoe;
    //   3843: getfield zzcm : Ljava/lang/String;
    //   3846: invokestatic zzjs : (Ljava/lang/String;)Ljava/lang/Object;
    //   3849: invokevirtual zzj : (Ljava/lang/String;Ljava/lang/Object;)V
    //   3852: goto -> 3996
    //   3855: aload #21
    //   3857: getfield zzjuq : [Lcom/google/android/gms/internal/zzcob;
    //   3860: arraylength
    //   3861: ifle -> 3996
    //   3864: aload #20
    //   3866: invokevirtual zzayw : ()J
    //   3869: lstore_2
    //   3870: lload_2
    //   3871: lconst_0
    //   3872: lcmp
    //   3873: ifeq -> 4444
    //   3876: lload_2
    //   3877: invokestatic valueOf : (J)Ljava/lang/Long;
    //   3880: astore #17
    //   3882: goto -> 3885
    //   3885: aload #21
    //   3887: aload #17
    //   3889: putfield zzjuw : Ljava/lang/Long;
    //   3892: aload #20
    //   3894: invokevirtual zzayv : ()J
    //   3897: lstore #11
    //   3899: lload #11
    //   3901: lconst_0
    //   3902: lcmp
    //   3903: ifne -> 4450
    //   3906: goto -> 3909
    //   3909: aload #18
    //   3911: astore #17
    //   3913: lload_2
    //   3914: lconst_0
    //   3915: lcmp
    //   3916: ifeq -> 3925
    //   3919: lload_2
    //   3920: invokestatic valueOf : (J)Ljava/lang/Long;
    //   3923: astore #17
    //   3925: aload #21
    //   3927: aload #17
    //   3929: putfield zzjuv : Ljava/lang/Long;
    //   3932: aload #20
    //   3934: invokevirtual zzazf : ()V
    //   3937: aload #21
    //   3939: aload #20
    //   3941: invokevirtual zzazc : ()J
    //   3944: l2i
    //   3945: invokestatic valueOf : (I)Ljava/lang/Integer;
    //   3948: putfield zzjvf : Ljava/lang/Integer;
    //   3951: aload #20
    //   3953: aload #21
    //   3955: getfield zzjut : Ljava/lang/Long;
    //   3958: invokevirtual longValue : ()J
    //   3961: invokevirtual zzal : (J)V
    //   3964: aload #20
    //   3966: aload #21
    //   3968: getfield zzjuu : Ljava/lang/Long;
    //   3971: invokevirtual longValue : ()J
    //   3974: invokevirtual zzam : (J)V
    //   3977: aload #21
    //   3979: aload #20
    //   3981: invokevirtual zzazn : ()Ljava/lang/String;
    //   3984: putfield zzjgi : Ljava/lang/String;
    //   3987: aload_0
    //   3988: invokevirtual zzayj : ()Lcom/google/android/gms/internal/zzcil;
    //   3991: aload #20
    //   3993: invokevirtual zza : (Lcom/google/android/gms/internal/zzcie;)V
    //   3996: aload #21
    //   3998: getfield zzjuq : [Lcom/google/android/gms/internal/zzcob;
    //   4001: arraylength
    //   4002: ifle -> 4113
    //   4005: aload_0
    //   4006: invokevirtual zzaym : ()Lcom/google/android/gms/internal/zzckd;
    //   4009: aload_1
    //   4010: getfield zzjpe : Lcom/google/android/gms/internal/zzcoe;
    //   4013: getfield zzcm : Ljava/lang/String;
    //   4016: invokevirtual zzka : (Ljava/lang/String;)Lcom/google/android/gms/internal/zzcny;
    //   4019: astore #17
    //   4021: aload #17
    //   4023: ifnull -> 4054
    //   4026: aload #17
    //   4028: getfield zzjtx : Ljava/lang/Long;
    //   4031: ifnonnull -> 4037
    //   4034: goto -> 4054
    //   4037: aload #17
    //   4039: getfield zzjtx : Ljava/lang/Long;
    //   4042: astore #17
    //   4044: aload #21
    //   4046: aload #17
    //   4048: putfield zzjvm : Ljava/lang/Long;
    //   4051: goto -> 4101
    //   4054: aload_1
    //   4055: getfield zzjpe : Lcom/google/android/gms/internal/zzcoe;
    //   4058: getfield zzjfl : Ljava/lang/String;
    //   4061: invokestatic isEmpty : (Ljava/lang/CharSequence;)Z
    //   4064: ifeq -> 4078
    //   4067: ldc2_w -1
    //   4070: invokestatic valueOf : (J)Ljava/lang/Long;
    //   4073: astore #17
    //   4075: goto -> 4044
    //   4078: aload_0
    //   4079: invokevirtual zzayp : ()Lcom/google/android/gms/internal/zzcjj;
    //   4082: invokevirtual zzbaw : ()Lcom/google/android/gms/internal/zzcjl;
    //   4085: ldc_w 'Did not find measurement config or missing version info. appId'
    //   4088: aload_1
    //   4089: getfield zzjpe : Lcom/google/android/gms/internal/zzcoe;
    //   4092: getfield zzcm : Ljava/lang/String;
    //   4095: invokestatic zzjs : (Ljava/lang/String;)Ljava/lang/Object;
    //   4098: invokevirtual zzj : (Ljava/lang/String;Ljava/lang/Object;)V
    //   4101: aload_0
    //   4102: invokevirtual zzayj : ()Lcom/google/android/gms/internal/zzcil;
    //   4105: aload #21
    //   4107: iload #13
    //   4109: invokevirtual zza : (Lcom/google/android/gms/internal/zzcoe;Z)Z
    //   4112: pop
    //   4113: aload_0
    //   4114: invokevirtual zzayj : ()Lcom/google/android/gms/internal/zzcil;
    //   4117: aload_1
    //   4118: getfield zzjpf : Ljava/util/List;
    //   4121: invokevirtual zzai : (Ljava/util/List;)V
    //   4124: aload_0
    //   4125: invokevirtual zzayj : ()Lcom/google/android/gms/internal/zzcil;
    //   4128: astore_1
    //   4129: aload_1
    //   4130: invokevirtual getWritableDatabase : ()Landroid/database/sqlite/SQLiteDatabase;
    //   4133: astore #17
    //   4135: aload #17
    //   4137: ldc_w 'delete from raw_events_metadata where app_id=? and metadata_fingerprint not in (select distinct metadata_fingerprint from raw_events where app_id=?)'
    //   4140: iconst_2
    //   4141: anewarray java/lang/String
    //   4144: dup
    //   4145: iconst_0
    //   4146: aload #19
    //   4148: aastore
    //   4149: dup
    //   4150: iconst_1
    //   4151: aload #19
    //   4153: aastore
    //   4154: invokevirtual execSQL : (Ljava/lang/String;[Ljava/lang/Object;)V
    //   4157: goto -> 4182
    //   4160: astore #17
    //   4162: aload_1
    //   4163: invokevirtual zzayp : ()Lcom/google/android/gms/internal/zzcjj;
    //   4166: invokevirtual zzbau : ()Lcom/google/android/gms/internal/zzcjl;
    //   4169: ldc_w 'Failed to remove unused event metadata. appId'
    //   4172: aload #19
    //   4174: invokestatic zzjs : (Ljava/lang/String;)Ljava/lang/Object;
    //   4177: aload #17
    //   4179: invokevirtual zze : (Ljava/lang/String;Ljava/lang/Object;Ljava/lang/Object;)V
    //   4182: aload_0
    //   4183: invokevirtual zzayj : ()Lcom/google/android/gms/internal/zzcil;
    //   4186: invokevirtual setTransactionSuccessful : ()V
    //   4189: aload_0
    //   4190: invokevirtual zzayj : ()Lcom/google/android/gms/internal/zzcil;
    //   4193: invokevirtual endTransaction : ()V
    //   4196: iconst_1
    //   4197: ireturn
    //   4198: aload_0
    //   4199: invokevirtual zzayj : ()Lcom/google/android/gms/internal/zzcil;
    //   4202: invokevirtual setTransactionSuccessful : ()V
    //   4205: aload_0
    //   4206: invokevirtual zzayj : ()Lcom/google/android/gms/internal/zzcil;
    //   4209: invokevirtual endTransaction : ()V
    //   4212: iconst_0
    //   4213: ireturn
    //   4214: astore_1
    //   4215: aload #18
    //   4217: astore #17
    //   4219: aload #17
    //   4221: ifnull -> 4231
    //   4224: aload #17
    //   4226: invokeinterface close : ()V
    //   4231: aload_1
    //   4232: athrow
    //   4233: astore_1
    //   4234: aload_0
    //   4235: invokevirtual zzayj : ()Lcom/google/android/gms/internal/zzcil;
    //   4238: invokevirtual endTransaction : ()V
    //   4241: aload_1
    //   4242: athrow
    //   4243: iload #4
    //   4245: ifeq -> 4256
    //   4248: ldc_w ' and rowid <= ?'
    //   4251: astore #17
    //   4253: goto -> 366
    //   4256: ldc_w ''
    //   4259: astore #17
    //   4261: goto -> 366
    //   4264: iconst_0
    //   4265: istore #4
    //   4267: goto -> 1182
    //   4270: iconst_1
    //   4271: istore #4
    //   4273: goto -> 1182
    //   4276: iconst_0
    //   4277: istore #6
    //   4279: goto -> 1367
    //   4282: iconst_1
    //   4283: istore #6
    //   4285: goto -> 1367
    //   4288: goto -> 4349
    //   4291: iload #13
    //   4293: istore #14
    //   4295: iload #14
    //   4297: istore #13
    //   4299: goto -> 2183
    //   4302: iload #7
    //   4304: iconst_1
    //   4305: iadd
    //   4306: istore #7
    //   4308: iload #10
    //   4310: istore #8
    //   4312: goto -> 1497
    //   4315: goto -> 1902
    //   4318: iload #6
    //   4320: iconst_1
    //   4321: iadd
    //   4322: istore #6
    //   4324: goto -> 1811
    //   4327: goto -> 1911
    //   4330: iconst_1
    //   4331: istore #13
    //   4333: goto -> 1911
    //   4336: iload #7
    //   4338: iconst_1
    //   4339: iadd
    //   4340: istore #7
    //   4342: aload #18
    //   4344: astore #17
    //   4346: goto -> 2032
    //   4349: iload #4
    //   4351: iconst_1
    //   4352: iadd
    //   4353: istore #4
    //   4355: goto -> 1237
    //   4358: iload #4
    //   4360: iconst_1
    //   4361: iadd
    //   4362: istore #4
    //   4364: goto -> 2546
    //   4367: iconst_0
    //   4368: istore #4
    //   4370: goto -> 2593
    //   4373: iload #4
    //   4375: iconst_1
    //   4376: iadd
    //   4377: istore #5
    //   4379: aload #23
    //   4381: iload #4
    //   4383: aload #24
    //   4385: aastore
    //   4386: iload #5
    //   4388: istore #4
    //   4390: goto -> 4399
    //   4393: iconst_1
    //   4394: istore #5
    //   4396: goto -> 3029
    //   4399: iload #4
    //   4401: istore #5
    //   4403: iload #5
    //   4405: istore #4
    //   4407: goto -> 4420
    //   4410: iconst_0
    //   4411: istore #14
    //   4413: goto -> 3222
    //   4416: iload #5
    //   4418: istore #4
    //   4420: iload #6
    //   4422: iconst_1
    //   4423: iadd
    //   4424: istore #6
    //   4426: goto -> 2799
    //   4429: aload #20
    //   4431: astore_1
    //   4432: goto -> 3692
    //   4435: iload #4
    //   4437: iconst_1
    //   4438: iadd
    //   4439: istore #4
    //   4441: goto -> 3720
    //   4444: aconst_null
    //   4445: astore #17
    //   4447: goto -> 3885
    //   4450: lload #11
    //   4452: lstore_2
    //   4453: goto -> 3909
    // Exception table:
    //   from	to	target	type
    //   9	48	4233	finally
    //   48	61	1119	android/database/sqlite/SQLiteException
    //   48	61	1112	finally
    //   82	88	121	android/database/sqlite/SQLiteException
    //   82	88	117	finally
    //   91	100	121	android/database/sqlite/SQLiteException
    //   91	100	117	finally
    //   103	111	121	android/database/sqlite/SQLiteException
    //   103	111	117	finally
    //   136	148	1119	android/database/sqlite/SQLiteException
    //   136	148	1112	finally
    //   166	225	1119	android/database/sqlite/SQLiteException
    //   166	225	1112	finally
    //   231	239	1101	android/database/sqlite/SQLiteException
    //   231	239	117	finally
    //   248	254	4233	finally
    //   263	272	1101	android/database/sqlite/SQLiteException
    //   263	272	117	finally
    //   275	284	306	android/database/sqlite/SQLiteException
    //   275	284	117	finally
    //   287	293	306	android/database/sqlite/SQLiteException
    //   287	293	117	finally
    //   334	339	1119	android/database/sqlite/SQLiteException
    //   334	339	1112	finally
    //   343	351	1119	android/database/sqlite/SQLiteException
    //   343	351	1112	finally
    //   354	363	1119	android/database/sqlite/SQLiteException
    //   354	363	1112	finally
    //   366	424	1119	android/database/sqlite/SQLiteException
    //   366	424	1112	finally
    //   430	439	1101	android/database/sqlite/SQLiteException
    //   430	439	117	finally
    //   452	461	1101	android/database/sqlite/SQLiteException
    //   452	461	117	finally
    //   467	473	1101	android/database/sqlite/SQLiteException
    //   467	473	117	finally
    //   482	526	1082	android/database/sqlite/SQLiteException
    //   482	526	1074	finally
    //   526	535	1059	android/database/sqlite/SQLiteException
    //   526	535	1055	finally
    //   540	558	577	android/database/sqlite/SQLiteException
    //   540	558	573	finally
    //   563	570	4233	finally
    //   588	618	1059	android/database/sqlite/SQLiteException
    //   588	618	1055	finally
    //   618	626	1001	java/io/IOException
    //   618	626	1059	android/database/sqlite/SQLiteException
    //   618	626	1055	finally
    //   626	635	1059	android/database/sqlite/SQLiteException
    //   626	635	1055	finally
    //   640	658	577	android/database/sqlite/SQLiteException
    //   640	658	573	finally
    //   658	674	1059	android/database/sqlite/SQLiteException
    //   658	674	1055	finally
    //   723	738	1059	android/database/sqlite/SQLiteException
    //   723	738	1055	finally
    //   746	794	1050	android/database/sqlite/SQLiteException
    //   746	794	4214	finally
    //   794	822	986	android/database/sqlite/SQLiteException
    //   794	822	978	finally
    //   827	834	4233	finally
    //   837	876	986	android/database/sqlite/SQLiteException
    //   837	876	978	finally
    //   876	884	934	java/io/IOException
    //   876	884	986	android/database/sqlite/SQLiteException
    //   876	884	978	finally
    //   884	926	986	android/database/sqlite/SQLiteException
    //   884	926	978	finally
    //   936	956	986	android/database/sqlite/SQLiteException
    //   936	956	978	finally
    //   956	965	986	android/database/sqlite/SQLiteException
    //   956	965	978	finally
    //   1011	1031	1050	android/database/sqlite/SQLiteException
    //   1011	1031	4214	finally
    //   1040	1047	4233	finally
    //   1130	1150	4214	finally
    //   1158	1179	4233	finally
    //   1187	1226	4233	finally
    //   1237	1364	4233	finally
    //   1372	1412	4233	finally
    //   1415	1437	4233	finally
    //   1442	1458	4233	finally
    //   1461	1478	4233	finally
    //   1478	1488	4233	finally
    //   1510	1533	4233	finally
    //   1543	1566	4233	finally
    //   1586	1671	4233	finally
    //   1676	1761	4233	finally
    //   1761	1808	4233	finally
    //   1811	1854	4233	finally
    //   1859	1872	4233	finally
    //   1872	1899	4233	finally
    //   1902	1908	4233	finally
    //   1915	1926	4233	finally
    //   1939	2023	4233	finally
    //   2045	2059	4233	finally
    //   2070	2084	4233	finally
    //   2104	2129	4233	finally
    //   2137	2156	4233	finally
    //   2159	2183	4233	finally
    //   2194	2225	4233	finally
    //   2228	2245	4233	finally
    //   2249	2257	4233	finally
    //   2262	2275	4233	finally
    //   2275	2283	4233	finally
    //   2289	2297	4233	finally
    //   2300	2308	4233	finally
    //   2313	2326	4233	finally
    //   2329	2339	4233	finally
    //   2351	2384	4233	finally
    //   2389	2405	4233	finally
    //   2409	2416	4233	finally
    //   2419	2462	4233	finally
    //   2465	2497	4233	finally
    //   2497	2543	4233	finally
    //   2546	2587	4233	finally
    //   2598	2641	4233	finally
    //   2647	2673	4233	finally
    //   2673	2789	4233	finally
    //   2813	2859	4233	finally
    //   2867	2896	4233	finally
    //   2900	2944	4233	finally
    //   2944	2986	4233	finally
    //   2989	3026	4233	finally
    //   3034	3057	4233	finally
    //   3077	3094	4233	finally
    //   3102	3124	4233	finally
    //   3132	3193	4233	finally
    //   3193	3211	4233	finally
    //   3222	3229	4233	finally
    //   3252	3274	4233	finally
    //   3278	3285	4233	finally
    //   3285	3307	4233	finally
    //   3314	3336	4233	finally
    //   3340	3357	4233	finally
    //   3367	3387	4233	finally
    //   3387	3413	4233	finally
    //   3422	3484	4233	finally
    //   3488	3505	4233	finally
    //   3515	3538	4233	finally
    //   3538	3564	4233	finally
    //   3577	3606	4233	finally
    //   3609	3635	4233	finally
    //   3635	3649	4233	finally
    //   3652	3689	4233	finally
    //   3695	3717	4233	finally
    //   3720	3771	4233	finally
    //   3771	3801	4233	finally
    //   3804	3824	4233	finally
    //   3829	3852	4233	finally
    //   3855	3870	4233	finally
    //   3876	3882	4233	finally
    //   3885	3899	4233	finally
    //   3919	3925	4233	finally
    //   3925	3996	4233	finally
    //   3996	4021	4233	finally
    //   4026	4034	4233	finally
    //   4037	4044	4233	finally
    //   4044	4051	4233	finally
    //   4054	4075	4233	finally
    //   4078	4101	4233	finally
    //   4101	4113	4233	finally
    //   4113	4135	4233	finally
    //   4135	4157	4160	android/database/sqlite/SQLiteException
    //   4135	4157	4233	finally
    //   4162	4182	4233	finally
    //   4182	4189	4233	finally
    //   4198	4205	4233	finally
    //   4224	4231	4233	finally
    //   4231	4233	4233	finally
  }
  
  private final zzcif zzke(String paramString) {
    zzcjl zzcjl;
    String str2;
    String str1 = paramString;
    zzcie zzcie = zzayj().zzjj(str1);
    if (zzcie == null || TextUtils.isEmpty(zzcie.zzwo())) {
      zzcjl = zzayp().zzbaz();
      str2 = "No app data available; dropping";
      zzcjl.zzj(str2, str1);
      return null;
    } 
    Boolean bool = zzc((zzcie)str2);
    if (bool != null && !bool.booleanValue()) {
      zzcjl zzcjl1 = zzayp().zzbau();
      str2 = "App version does not match; dropping. appId";
      Object object2 = zzcjj.zzjs((String)zzcjl);
      zzcjl = zzcjl1;
      Object object1 = object2;
      zzcjl.zzj(str2, object1);
      return null;
    } 
    return new zzcif((String)zzcjl, str2.getGmpAppId(), str2.zzwo(), str2.zzayx(), str2.zzayy(), str2.zzayz(), str2.zzaza(), null, str2.zzazb(), false, str2.zzayu(), str2.zzazo(), 0L, 0, str2.zzazp());
  }
  
  public final Context getContext() {
    return this.zzaiq;
  }
  
  public final boolean isEnabled() {
    zzayo().zzwj();
    zzyk();
    boolean bool2 = this.zzjns.zzazr();
    boolean bool1 = false;
    if (bool2)
      return false; 
    Boolean bool = this.zzjns.zzjf("firebase_analytics_collection_enabled");
    if (bool != null) {
      bool1 = bool.booleanValue();
    } else if (!zzbz.zzakr()) {
      bool1 = true;
    } 
    return zzayq().zzbs(bool1);
  }
  
  protected final void start() {
    zzayo().zzwj();
    zzayj().zzazy();
    if ((zzayq()).zzjln.get() == 0L)
      (zzayq()).zzjln.set(this.zzdir.currentTimeMillis()); 
    if (Long.valueOf((zzayq()).zzjls.get()).longValue() == 0L) {
      zzayp().zzbba().zzj("Persisting first open", Long.valueOf(this.zzjgk));
      (zzayq()).zzjls.set(this.zzjgk);
    } 
    if (!zzbbn()) {
      if (isEnabled()) {
        if (!zzayl().zzeh("android.permission.INTERNET"))
          zzayp().zzbau().log("App is missing INTERNET permission"); 
        if (!zzayl().zzeh("android.permission.ACCESS_NETWORK_STATE"))
          zzayp().zzbau().log("App is missing ACCESS_NETWORK_STATE permission"); 
        if (!zzbih.zzdd(this.zzaiq).zzaoe()) {
          if (!zzcka.zzbj(this.zzaiq))
            zzayp().zzbau().log("AppMeasurementReceiver not registered/enabled"); 
          if (!zzcmy.zzg(this.zzaiq, false))
            zzayp().zzbau().log("AppMeasurementService not registered/enabled"); 
        } 
        zzayp().zzbau().log("Uploading is not possible. App measurement disabled");
      } 
    } else {
      if (!TextUtils.isEmpty(zzaye().getGmpAppId())) {
        String str = zzayq().zzbbe();
        if (str == null) {
          zzayq().zzjw(zzaye().getGmpAppId());
        } else if (!str.equals(zzaye().getGmpAppId())) {
          zzayp().zzbay().log("Rechecking which service to use due to a GMP App Id change");
          zzayq().zzbbh();
          this.zzjoi.disconnect();
          this.zzjoi.zzzh();
          zzayq().zzjw(zzaye().getGmpAppId());
          (zzayq()).zzjls.set(this.zzjgk);
          (zzayq()).zzjlt.zzjy(null);
        } 
      } 
      zzayd().zzjx((zzayq()).zzjlt.zzbbj());
      if (!TextUtils.isEmpty(zzaye().getGmpAppId())) {
        zzclk zzclk1 = zzayd();
        zzclk1.zzwj();
        zzclk1.zzyk();
        if (zzclk1.zzjev.zzbbn()) {
          zzclk1.zzayg().zzbcj();
          String str = zzclk1.zzayq().zzbbi();
          if (!TextUtils.isEmpty(str)) {
            zzclk1.zzayf().zzyk();
            if (!str.equals(Build.VERSION.RELEASE)) {
              Bundle bundle = new Bundle();
              bundle.putString("_po", str);
              zzclk1.zzd("auto", "_ou", bundle);
            } 
          } 
        } 
        zzayg().zza(new AtomicReference<String>());
      } 
    } 
    zzbca();
  }
  
  protected final void zza(int paramInt, Throwable paramThrowable, byte[] paramArrayOfbyte) {
    // Byte code:
    //   0: aload_0
    //   1: invokevirtual zzayo : ()Lcom/google/android/gms/internal/zzcke;
    //   4: invokevirtual zzwj : ()V
    //   7: aload_0
    //   8: invokevirtual zzyk : ()V
    //   11: aload_3
    //   12: astore #8
    //   14: aload_3
    //   15: ifnonnull -> 23
    //   18: iconst_0
    //   19: newarray byte
    //   21: astore #8
    //   23: aload_0
    //   24: getfield zzjot : Ljava/util/List;
    //   27: astore_3
    //   28: aload_0
    //   29: aconst_null
    //   30: putfield zzjot : Ljava/util/List;
    //   33: iconst_1
    //   34: istore #5
    //   36: iload_1
    //   37: sipush #200
    //   40: if_icmpeq -> 50
    //   43: iload_1
    //   44: sipush #204
    //   47: if_icmpne -> 347
    //   50: aload_2
    //   51: ifnonnull -> 347
    //   54: aload_0
    //   55: invokevirtual zzayq : ()Lcom/google/android/gms/internal/zzcju;
    //   58: getfield zzjln : Lcom/google/android/gms/internal/zzcjx;
    //   61: aload_0
    //   62: getfield zzdir : Lcom/google/android/gms/common/util/zze;
    //   65: invokeinterface currentTimeMillis : ()J
    //   70: invokevirtual set : (J)V
    //   73: aload_0
    //   74: invokevirtual zzayq : ()Lcom/google/android/gms/internal/zzcju;
    //   77: getfield zzjlo : Lcom/google/android/gms/internal/zzcjx;
    //   80: lconst_0
    //   81: invokevirtual set : (J)V
    //   84: aload_0
    //   85: invokespecial zzbca : ()V
    //   88: aload_0
    //   89: invokevirtual zzayp : ()Lcom/google/android/gms/internal/zzcjj;
    //   92: invokevirtual zzbba : ()Lcom/google/android/gms/internal/zzcjl;
    //   95: ldc_w 'Successful upload. Got network response. code, size'
    //   98: iload_1
    //   99: invokestatic valueOf : (I)Ljava/lang/Integer;
    //   102: aload #8
    //   104: arraylength
    //   105: invokestatic valueOf : (I)Ljava/lang/Integer;
    //   108: invokevirtual zze : (Ljava/lang/String;Ljava/lang/Object;Ljava/lang/Object;)V
    //   111: aload_0
    //   112: invokevirtual zzayj : ()Lcom/google/android/gms/internal/zzcil;
    //   115: invokevirtual beginTransaction : ()V
    //   118: aload_3
    //   119: invokeinterface iterator : ()Ljava/util/Iterator;
    //   124: astore_3
    //   125: aload_3
    //   126: invokeinterface hasNext : ()Z
    //   131: ifeq -> 229
    //   134: aload_3
    //   135: invokeinterface next : ()Ljava/lang/Object;
    //   140: checkcast java/lang/Long
    //   143: astore #8
    //   145: aload_0
    //   146: invokevirtual zzayj : ()Lcom/google/android/gms/internal/zzcil;
    //   149: astore_2
    //   150: aload #8
    //   152: invokevirtual longValue : ()J
    //   155: lstore #6
    //   157: aload_2
    //   158: invokevirtual zzwj : ()V
    //   161: aload_2
    //   162: invokevirtual zzyk : ()V
    //   165: aload_2
    //   166: invokevirtual getWritableDatabase : ()Landroid/database/sqlite/SQLiteDatabase;
    //   169: astore #8
    //   171: aload #8
    //   173: ldc_w 'queue'
    //   176: ldc_w 'rowid=?'
    //   179: iconst_1
    //   180: anewarray java/lang/String
    //   183: dup
    //   184: iconst_0
    //   185: lload #6
    //   187: invokestatic valueOf : (J)Ljava/lang/String;
    //   190: aastore
    //   191: invokevirtual delete : (Ljava/lang/String;Ljava/lang/String;[Ljava/lang/String;)I
    //   194: iconst_1
    //   195: if_icmpne -> 201
    //   198: goto -> 125
    //   201: new android/database/sqlite/SQLiteException
    //   204: dup
    //   205: ldc_w 'Deleted fewer rows from queue than expected'
    //   208: invokespecial <init> : (Ljava/lang/String;)V
    //   211: athrow
    //   212: astore_3
    //   213: aload_2
    //   214: invokevirtual zzayp : ()Lcom/google/android/gms/internal/zzcjj;
    //   217: invokevirtual zzbau : ()Lcom/google/android/gms/internal/zzcjl;
    //   220: ldc_w 'Failed to delete a bundle in a queue table'
    //   223: aload_3
    //   224: invokevirtual zzj : (Ljava/lang/String;Ljava/lang/Object;)V
    //   227: aload_3
    //   228: athrow
    //   229: aload_0
    //   230: invokevirtual zzayj : ()Lcom/google/android/gms/internal/zzcil;
    //   233: invokevirtual setTransactionSuccessful : ()V
    //   236: aload_0
    //   237: invokevirtual zzayj : ()Lcom/google/android/gms/internal/zzcil;
    //   240: invokevirtual endTransaction : ()V
    //   243: aload_0
    //   244: invokevirtual zzbbs : ()Lcom/google/android/gms/internal/zzcjn;
    //   247: invokevirtual zzaax : ()Z
    //   250: ifeq -> 267
    //   253: aload_0
    //   254: invokespecial zzbbz : ()Z
    //   257: ifeq -> 267
    //   260: aload_0
    //   261: invokevirtual zzbby : ()V
    //   264: goto -> 278
    //   267: aload_0
    //   268: ldc2_w -1
    //   271: putfield zzjox : J
    //   274: aload_0
    //   275: invokespecial zzbca : ()V
    //   278: aload_0
    //   279: lconst_0
    //   280: putfield zzjoy : J
    //   283: goto -> 437
    //   286: astore_2
    //   287: aload_0
    //   288: invokevirtual zzayj : ()Lcom/google/android/gms/internal/zzcil;
    //   291: invokevirtual endTransaction : ()V
    //   294: aload_2
    //   295: athrow
    //   296: astore_2
    //   297: aload_0
    //   298: invokevirtual zzayp : ()Lcom/google/android/gms/internal/zzcjj;
    //   301: invokevirtual zzbau : ()Lcom/google/android/gms/internal/zzcjl;
    //   304: ldc_w 'Database error while trying to delete uploaded bundles'
    //   307: aload_2
    //   308: invokevirtual zzj : (Ljava/lang/String;Ljava/lang/Object;)V
    //   311: aload_0
    //   312: aload_0
    //   313: getfield zzdir : Lcom/google/android/gms/common/util/zze;
    //   316: invokeinterface elapsedRealtime : ()J
    //   321: putfield zzjoy : J
    //   324: aload_0
    //   325: invokevirtual zzayp : ()Lcom/google/android/gms/internal/zzcjj;
    //   328: invokevirtual zzbba : ()Lcom/google/android/gms/internal/zzcjl;
    //   331: ldc_w 'Disable upload, time'
    //   334: aload_0
    //   335: getfield zzjoy : J
    //   338: invokestatic valueOf : (J)Ljava/lang/Long;
    //   341: invokevirtual zzj : (Ljava/lang/String;Ljava/lang/Object;)V
    //   344: goto -> 437
    //   347: aload_0
    //   348: invokevirtual zzayp : ()Lcom/google/android/gms/internal/zzcjj;
    //   351: invokevirtual zzbba : ()Lcom/google/android/gms/internal/zzcjl;
    //   354: ldc_w 'Network upload failed. Will retry later. code, error'
    //   357: iload_1
    //   358: invokestatic valueOf : (I)Ljava/lang/Integer;
    //   361: aload_2
    //   362: invokevirtual zze : (Ljava/lang/String;Ljava/lang/Object;Ljava/lang/Object;)V
    //   365: aload_0
    //   366: invokevirtual zzayq : ()Lcom/google/android/gms/internal/zzcju;
    //   369: getfield zzjlo : Lcom/google/android/gms/internal/zzcjx;
    //   372: aload_0
    //   373: getfield zzdir : Lcom/google/android/gms/common/util/zze;
    //   376: invokeinterface currentTimeMillis : ()J
    //   381: invokevirtual set : (J)V
    //   384: iload #5
    //   386: istore #4
    //   388: iload_1
    //   389: sipush #503
    //   392: if_icmpeq -> 409
    //   395: iload_1
    //   396: sipush #429
    //   399: if_icmpne -> 459
    //   402: iload #5
    //   404: istore #4
    //   406: goto -> 409
    //   409: iload #4
    //   411: ifeq -> 433
    //   414: aload_0
    //   415: invokevirtual zzayq : ()Lcom/google/android/gms/internal/zzcju;
    //   418: getfield zzjlp : Lcom/google/android/gms/internal/zzcjx;
    //   421: aload_0
    //   422: getfield zzdir : Lcom/google/android/gms/common/util/zze;
    //   425: invokeinterface currentTimeMillis : ()J
    //   430: invokevirtual set : (J)V
    //   433: aload_0
    //   434: invokespecial zzbca : ()V
    //   437: aload_0
    //   438: iconst_0
    //   439: putfield zzjpa : Z
    //   442: aload_0
    //   443: invokespecial zzbce : ()V
    //   446: return
    //   447: astore_2
    //   448: aload_0
    //   449: iconst_0
    //   450: putfield zzjpa : Z
    //   453: aload_0
    //   454: invokespecial zzbce : ()V
    //   457: aload_2
    //   458: athrow
    //   459: iconst_0
    //   460: istore #4
    //   462: goto -> 409
    // Exception table:
    //   from	to	target	type
    //   18	23	447	finally
    //   23	33	447	finally
    //   54	118	296	android/database/sqlite/SQLiteException
    //   54	118	447	finally
    //   118	125	286	finally
    //   125	171	286	finally
    //   171	198	212	android/database/sqlite/SQLiteException
    //   171	198	286	finally
    //   201	212	212	android/database/sqlite/SQLiteException
    //   201	212	286	finally
    //   213	229	286	finally
    //   229	236	286	finally
    //   236	264	296	android/database/sqlite/SQLiteException
    //   236	264	447	finally
    //   267	278	296	android/database/sqlite/SQLiteException
    //   267	278	447	finally
    //   278	283	296	android/database/sqlite/SQLiteException
    //   278	283	447	finally
    //   287	296	296	android/database/sqlite/SQLiteException
    //   287	296	447	finally
    //   297	344	447	finally
    //   347	384	447	finally
    //   414	433	447	finally
    //   433	437	447	finally
  }
  
  public final byte[] zza(zzcix paramzzcix, String paramString) {
    zzyk();
    zzayo().zzwj();
    zzaxz();
    zzbq.checkNotNull(paramzzcix);
    zzbq.zzgv(paramString);
    zzcod zzcod = new zzcod();
    zzayj().beginTransaction();
    try {
      zzcie zzcie = zzayj().zzjj(paramString);
      if (zzcie == null) {
        zzayp().zzbaz().zzj("Log and bundle not available. package_name", paramString);
        zzayj().endTransaction();
        return new byte[0];
      } 
      if (!zzcie.zzazb()) {
        zzayp().zzbaz().zzj("Log and bundle disabled. package_name", paramString);
        zzayj().endTransaction();
        return new byte[0];
      } 
      if (("_iap".equals(paramzzcix.name) || "ecommerce_purchase".equals(paramzzcix.name)) && !zza(paramString, paramzzcix))
        zzayp().zzbaw().zzj("Failed to handle purchase event at single event bundle creation. appId", zzcjj.zzjs(paramString)); 
      boolean bool = this.zzjns.zzjh(paramString);
      Long long_2 = Long.valueOf(0L);
      Long long_1 = long_2;
      if (bool) {
        long_1 = long_2;
        if ("_e".equals(paramzzcix.name)) {
          zzcjl zzcjl;
          Object object;
          if (paramzzcix.zzjhr == null || paramzzcix.zzjhr.size() == 0) {
            zzcjl = zzayp().zzbaw();
            String str = "The engagement event does not contain any parameters. appId";
            object = zzcjj.zzjs(paramString);
          } else if (paramzzcix.zzjhr.getLong("_et") == null) {
            zzcjl = zzayp().zzbaw();
            String str = "The engagement event does not include duration. appId";
            object = zzcjj.zzjs(paramString);
          } else {
            long_1 = paramzzcix.zzjhr.getLong("_et");
            zzcoe zzcoe1 = new zzcoe();
            zzcod.zzjun = new zzcoe[] { zzcoe1 };
            zzcoe1.zzjup = Integer.valueOf(1);
            zzcoe1.zzjux = "android";
            zzcoe1.zzcm = zzcie.getAppId();
            zzcoe1.zzjfs = zzcie.zzayy();
            zzcoe1.zzina = zzcie.zzwo();
            long l1 = zzcie.zzayx();
          } 
          zzcjl.zzj((String)long_1, object);
          long_1 = long_2;
        } 
      } 
      zzcoe zzcoe = new zzcoe();
      zzcod.zzjun = new zzcoe[] { zzcoe };
      zzcoe.zzjup = Integer.valueOf(1);
      zzcoe.zzjux = "android";
      zzcoe.zzcm = zzcie.getAppId();
      zzcoe.zzjfs = zzcie.zzayy();
      zzcoe.zzina = zzcie.zzwo();
      long l = zzcie.zzayx();
    } finally {}
    zzayj().endTransaction();
    throw paramzzcix;
  }
  
  public final zzcia zzayb() {
    zza(this.zzjof);
    return this.zzjof;
  }
  
  public final zzcih zzayc() {
    zza(this.zzjon);
    return this.zzjon;
  }
  
  public final zzclk zzayd() {
    zza(this.zzjoe);
    return this.zzjoe;
  }
  
  public final zzcje zzaye() {
    zza(this.zzjok);
    return this.zzjok;
  }
  
  public final zzcir zzayf() {
    zza(this.zzjoj);
    return this.zzjoj;
  }
  
  public final zzcme zzayg() {
    zza(this.zzjoi);
    return this.zzjoi;
  }
  
  public final zzcma zzayh() {
    zza(this.zzjod);
    return this.zzjod;
  }
  
  public final zzcjf zzayi() {
    zza(this.zzjoh);
    return this.zzjoh;
  }
  
  public final zzcil zzayj() {
    zza(this.zzjog);
    return this.zzjog;
  }
  
  public final zzcjh zzayk() {
    zza(this.zzjob);
    return this.zzjob;
  }
  
  public final zzcno zzayl() {
    zza(this.zzjoa);
    return this.zzjoa;
  }
  
  public final zzckd zzaym() {
    zza(this.zzjnx);
    return this.zzjnx;
  }
  
  public final zzcnd zzayn() {
    zza(this.zzjnw);
    return this.zzjnw;
  }
  
  public final zzcke zzayo() {
    zza(this.zzjnv);
    return this.zzjnv;
  }
  
  public final zzcjj zzayp() {
    zza(this.zzjnu);
    return this.zzjnu;
  }
  
  public final zzcju zzayq() {
    zza(this.zzjnt);
    return this.zzjnt;
  }
  
  public final zzcik zzayr() {
    return this.zzjns;
  }
  
  final void zzb(zzcii paramzzcii, zzcif paramzzcif) {
    zzbq.checkNotNull(paramzzcii);
    zzbq.zzgv(paramzzcii.packageName);
    zzbq.checkNotNull(paramzzcii.zzjgm);
    zzbq.checkNotNull(paramzzcii.zzjgn);
    zzbq.zzgv(paramzzcii.zzjgn.name);
    zzayo().zzwj();
    zzyk();
    if (TextUtils.isEmpty(paramzzcif.zzjfl))
      return; 
    if (!paramzzcif.zzjfv) {
      zzg(paramzzcif);
      return;
    } 
    zzcii zzcii1 = new zzcii(paramzzcii);
    boolean bool = false;
    zzcii1.zzjgp = false;
    zzayj().beginTransaction();
    try {
      Object object1;
      Object object2;
      String str1;
      Object object3;
      String str2;
      paramzzcii = zzayj().zzah(zzcii1.packageName, zzcii1.zzjgn.name);
      if (paramzzcii != null && !paramzzcii.zzjgm.equals(zzcii1.zzjgm))
        zzayp().zzbaw().zzd("Updating a conditional user property with different origin. name, origin, origin (from DB)", zzayk().zzjr(zzcii1.zzjgn.name), zzcii1.zzjgm, paramzzcii.zzjgm); 
      if (paramzzcii != null && paramzzcii.zzjgp) {
        zzcii1.zzjgm = paramzzcii.zzjgm;
        zzcii1.zzjgo = paramzzcii.zzjgo;
        zzcii1.zzjgs = paramzzcii.zzjgs;
        zzcii1.zzjgq = paramzzcii.zzjgq;
        zzcii1.zzjgt = paramzzcii.zzjgt;
        zzcii1.zzjgp = paramzzcii.zzjgp;
        zzcii1.zzjgn = new zzcnl(zzcii1.zzjgn.name, paramzzcii.zzjgn.zzjsi, zzcii1.zzjgn.getValue(), paramzzcii.zzjgn.zzjgm);
      } else if (TextUtils.isEmpty(zzcii1.zzjgq)) {
        zzcii1.zzjgn = new zzcnl(zzcii1.zzjgn.name, zzcii1.zzjgo, zzcii1.zzjgn.getValue(), zzcii1.zzjgn.zzjgm);
        zzcii1.zzjgp = true;
        bool = true;
      } 
      if (zzcii1.zzjgp) {
        zzcnl zzcnl = zzcii1.zzjgn;
        Object object = new zzcnn(zzcii1.packageName, zzcii1.zzjgm, zzcnl.name, zzcnl.zzjsi, zzcnl.getValue());
        if (zzayj().zza((zzcnn)object)) {
          object1 = zzayp().zzbaz();
          str1 = "User property updated immediately";
          object3 = zzcii1.packageName;
          str2 = zzayk().zzjr(((zzcnn)object).name);
          object = ((zzcnn)object).value;
        } else {
          object1 = zzayp().zzbau();
          str1 = "(2)Too many active user properties, ignoring";
          object3 = zzcjj.zzjs(zzcii1.packageName);
          str2 = zzayk().zzjr(((zzcnn)object).name);
          object = ((zzcnn)object).value;
        } 
        object1.zzd(str1, object3, str2, object);
        if (bool && zzcii1.zzjgt != null)
          zzc(new zzcix(zzcii1.zzjgt, zzcii1.zzjgo), paramzzcif); 
      } 
      if (zzayj().zza(zzcii1)) {
        object3 = zzayp().zzbaz();
        str2 = "Conditional property added";
        object2 = zzcii1.packageName;
        str1 = zzayk().zzjr(zzcii1.zzjgn.name);
        object1 = zzcii1.zzjgn.getValue();
      } else {
        object3 = zzayp().zzbau();
        str2 = "Too many conditional properties, ignoring";
        object2 = zzcjj.zzjs(zzcii1.packageName);
        str1 = zzayk().zzjr(zzcii1.zzjgn.name);
        object1 = zzcii1.zzjgn.getValue();
      } 
      object3.zzd(str2, object2, str1, object1);
      zzayj().setTransactionSuccessful();
      return;
    } finally {
      zzayj().endTransaction();
    } 
  }
  
  final void zzb(zzcix paramzzcix, zzcif paramzzcif) {
    zzbq.checkNotNull(paramzzcif);
    zzbq.zzgv(paramzzcif.packageName);
    zzayo().zzwj();
    zzyk();
    String str = paramzzcif.packageName;
    long l = paramzzcix.zzjib;
    zzayl();
    if (!zzcno.zzd(paramzzcix, paramzzcif))
      return; 
    if (!paramzzcif.zzjfv) {
      zzg(paramzzcif);
      return;
    } 
    zzayj().beginTransaction();
    try {
      List<?> list3;
      List<?> list1;
      zzcil zzcil3 = zzayj();
      zzbq.zzgv(str);
      zzcil3.zzwj();
      zzcil3.zzyk();
      int j = l cmp 0L;
      if (j < 0) {
        zzcil3.zzayp().zzbaw().zze("Invalid time querying timed out conditional properties", zzcjj.zzjs(str), Long.valueOf(l));
        list3 = Collections.emptyList();
      } else {
        list3 = list3.zzd("active=0 and app_id=? and abs(? - creation_timestamp) > trigger_timeout", new String[] { str, String.valueOf(l) });
      } 
      for (zzcii zzcii : list3) {
        if (zzcii != null) {
          zzayp().zzbaz().zzd("User property timed out", zzcii.packageName, zzayk().zzjr(zzcii.zzjgn.name), zzcii.zzjgn.getValue());
          if (zzcii.zzjgr != null)
            zzc(new zzcix(zzcii.zzjgr, l), paramzzcif); 
          zzayj().zzai(str, zzcii.zzjgn.name);
        } 
      } 
      zzcil zzcil2 = zzayj();
      zzbq.zzgv(str);
      zzcil2.zzwj();
      zzcil2.zzyk();
      if (j < 0) {
        zzcil2.zzayp().zzbaw().zze("Invalid time querying expired conditional properties", zzcjj.zzjs(str), Long.valueOf(l));
        list2 = Collections.emptyList();
      } else {
        list2 = list2.zzd("active<>0 and app_id=? and abs(? - triggered_timestamp) > time_to_live", new String[] { str, String.valueOf(l) });
      } 
      ArrayList<zzcix> arrayList2 = new ArrayList(list2.size());
      for (zzcii zzcii : list2) {
        if (zzcii != null) {
          zzayp().zzbaz().zzd("User property expired", zzcii.packageName, zzayk().zzjr(zzcii.zzjgn.name), zzcii.zzjgn.getValue());
          zzayj().zzaf(str, zzcii.zzjgn.name);
          if (zzcii.zzjgv != null)
            arrayList2.add(zzcii.zzjgv); 
          zzayj().zzai(str, zzcii.zzjgn.name);
        } 
      } 
      List<?> list2 = arrayList2;
      int k = list2.size();
      int i = 0;
      while (i < k) {
        arrayList2 = (ArrayList<zzcix>)list2.get(i);
        i++;
        zzc(new zzcix((zzcix)arrayList2, l), paramzzcif);
      } 
      zzcil zzcil1 = zzayj();
      String str1 = paramzzcix.name;
      zzbq.zzgv(str);
      zzbq.zzgv(str1);
      zzcil1.zzwj();
      zzcil1.zzyk();
      if (j < 0) {
        zzcil1.zzayp().zzbaw().zzd("Invalid time querying triggered conditional properties", zzcjj.zzjs(str), zzcil1.zzayk().zzjp(str1), Long.valueOf(l));
        list1 = Collections.emptyList();
      } else {
        list1 = list1.zzd("active=0 and app_id=? and trigger_event_name=? and abs(? - creation_timestamp) <= trigger_timeout", new String[] { str, str1, String.valueOf(l) });
      } 
      ArrayList<zzcix> arrayList3 = new ArrayList(list1.size());
      for (zzcii zzcii : list1) {
        if (zzcii != null) {
          zzcjl zzcjl;
          Object object1;
          String str2;
          Object object2;
          zzcnl zzcnl = zzcii.zzjgn;
          zzcnn zzcnn = new zzcnn(zzcii.packageName, zzcii.zzjgm, zzcnl.name, l, zzcnl.getValue());
          if (zzayj().zza(zzcnn)) {
            zzcjl = zzayp().zzbaz();
            str = "User property triggered";
            str1 = zzcii.packageName;
            str2 = zzayk().zzjr(zzcnn.name);
            object2 = zzcnn.value;
          } else {
            zzcjl = zzayp().zzbau();
            str = "Too many active user properties, ignoring";
            object1 = zzcjj.zzjs(zzcii.packageName);
            str2 = zzayk().zzjr(zzcnn.name);
            object2 = zzcnn.value;
          } 
          zzcjl.zzd(str, object1, str2, object2);
          if (zzcii.zzjgt != null)
            arrayList3.add(zzcii.zzjgt); 
          zzcii.zzjgn = new zzcnl(zzcnn);
          zzcii.zzjgp = true;
          zzayj().zza(zzcii);
        } 
      } 
      zzc(paramzzcix, paramzzcif);
      ArrayList<zzcix> arrayList1 = arrayList3;
      j = arrayList1.size();
      i = 0;
      while (i < j) {
        list1 = (List<?>)arrayList1.get(i);
        i++;
        zzc(new zzcix((zzcix)list1, l), paramzzcif);
      } 
      zzayj().setTransactionSuccessful();
      return;
    } finally {
      zzayj().endTransaction();
    } 
  }
  
  final void zzb(zzcix paramzzcix, String paramString) {
    zzcie zzcie = zzayj().zzjj(paramString);
    if (zzcie == null || TextUtils.isEmpty(zzcie.zzwo())) {
      zzayp().zzbaz().zzj("No app data available; dropping event", paramString);
      return;
    } 
    Boolean bool = zzc(zzcie);
    if (bool == null) {
      if (!"_ui".equals(paramzzcix.name))
        zzayp().zzbaw().zzj("Could not find package. appId", zzcjj.zzjs(paramString)); 
    } else if (!bool.booleanValue()) {
      zzayp().zzbau().zzj("App version does not match; dropping event. appId", zzcjj.zzjs(paramString));
      return;
    } 
    zzb(paramzzcix, new zzcif(paramString, zzcie.getGmpAppId(), zzcie.zzwo(), zzcie.zzayx(), zzcie.zzayy(), zzcie.zzayz(), zzcie.zzaza(), null, zzcie.zzazb(), false, zzcie.zzayu(), zzcie.zzazo(), 0L, 0, zzcie.zzazp()));
  }
  
  final void zzb(zzcli paramzzcli) {
    this.zzjov++;
  }
  
  final void zzb(zzcnl paramzzcnl, zzcif paramzzcif) {
    zzayo().zzwj();
    zzyk();
    if (TextUtils.isEmpty(paramzzcif.zzjfl))
      return; 
    if (!paramzzcif.zzjfv) {
      zzg(paramzzcif);
      return;
    } 
    int i = zzayl().zzkk(paramzzcnl.name);
    if (i != 0) {
      boolean bool;
      zzayl();
      String str = zzcno.zza(paramzzcnl.name, 24, true);
      if (paramzzcnl.name != null) {
        bool = paramzzcnl.name.length();
      } else {
        bool = false;
      } 
      zzayl().zza(paramzzcif.packageName, i, "_ev", str, bool);
      return;
    } 
    i = zzayl().zzl(paramzzcnl.name, paramzzcnl.getValue());
    if (i != 0) {
      boolean bool;
      zzayl();
      String str = zzcno.zza(paramzzcnl.name, 24, true);
      null = paramzzcnl.getValue();
      if (null != null && (null instanceof String || null instanceof CharSequence)) {
        bool = String.valueOf(null).length();
      } else {
        bool = false;
      } 
      zzayl().zza(paramzzcif.packageName, i, "_ev", str, bool);
      return;
    } 
    Object object = zzayl().zzm(((zzcnl)null).name, null.getValue());
    if (object == null)
      return; 
    null = new zzcnn(paramzzcif.packageName, ((zzcnl)null).zzjgm, ((zzcnl)null).name, ((zzcnl)null).zzjsi, object);
    zzayp().zzbaz().zze("Setting user property", zzayk().zzjr(((zzcnn)null).name), object);
    zzayj().beginTransaction();
    try {
      zzg(paramzzcif);
      boolean bool = zzayj().zza((zzcnn)null);
      zzayj().setTransactionSuccessful();
      if (bool) {
        zzayp().zzbaz().zze("User property set", zzayk().zzjr(((zzcnn)null).name), ((zzcnn)null).value);
      } else {
        zzayp().zzbau().zze("Too many unique user properties are set. Ignoring user property", zzayk().zzjr(((zzcnn)null).name), ((zzcnn)null).value);
        zzayl().zza(paramzzcif.packageName, 9, (String)null, (String)null, 0);
      } 
      return;
    } finally {
      zzayj().endTransaction();
    } 
  }
  
  final void zzb(String paramString, int paramInt, Throwable paramThrowable, byte[] paramArrayOfbyte, Map<String, List<String>> paramMap) {
    // Byte code:
    //   0: aload_0
    //   1: invokevirtual zzayo : ()Lcom/google/android/gms/internal/zzcke;
    //   4: invokevirtual zzwj : ()V
    //   7: aload_0
    //   8: invokevirtual zzyk : ()V
    //   11: aload_1
    //   12: invokestatic zzgv : (Ljava/lang/String;)Ljava/lang/String;
    //   15: pop
    //   16: aload #4
    //   18: astore #9
    //   20: aload #4
    //   22: ifnonnull -> 30
    //   25: iconst_0
    //   26: newarray byte
    //   28: astore #9
    //   30: aload_0
    //   31: invokevirtual zzayp : ()Lcom/google/android/gms/internal/zzcjj;
    //   34: invokevirtual zzbba : ()Lcom/google/android/gms/internal/zzcjl;
    //   37: ldc_w 'onConfigFetched. Response size'
    //   40: aload #9
    //   42: arraylength
    //   43: invokestatic valueOf : (I)Ljava/lang/Integer;
    //   46: invokevirtual zzj : (Ljava/lang/String;Ljava/lang/Object;)V
    //   49: aload_0
    //   50: invokevirtual zzayj : ()Lcom/google/android/gms/internal/zzcil;
    //   53: invokevirtual beginTransaction : ()V
    //   56: aload_0
    //   57: invokevirtual zzayj : ()Lcom/google/android/gms/internal/zzcil;
    //   60: aload_1
    //   61: invokevirtual zzjj : (Ljava/lang/String;)Lcom/google/android/gms/internal/zzcie;
    //   64: astore #4
    //   66: iconst_1
    //   67: istore #7
    //   69: iload_2
    //   70: sipush #200
    //   73: if_icmpeq -> 492
    //   76: iload_2
    //   77: sipush #204
    //   80: if_icmpeq -> 492
    //   83: iload_2
    //   84: sipush #304
    //   87: if_icmpne -> 502
    //   90: goto -> 492
    //   93: aload #4
    //   95: ifnonnull -> 508
    //   98: aload_0
    //   99: invokevirtual zzayp : ()Lcom/google/android/gms/internal/zzcjj;
    //   102: invokevirtual zzbaw : ()Lcom/google/android/gms/internal/zzcjl;
    //   105: ldc_w 'App does not exist in onConfigFetched. appId'
    //   108: aload_1
    //   109: invokestatic zzjs : (Ljava/lang/String;)Ljava/lang/Object;
    //   112: invokevirtual zzj : (Ljava/lang/String;Ljava/lang/Object;)V
    //   115: goto -> 455
    //   118: aload #4
    //   120: aload_0
    //   121: getfield zzdir : Lcom/google/android/gms/common/util/zze;
    //   124: invokeinterface currentTimeMillis : ()J
    //   129: invokevirtual zzas : (J)V
    //   132: aload_0
    //   133: invokevirtual zzayj : ()Lcom/google/android/gms/internal/zzcil;
    //   136: aload #4
    //   138: invokevirtual zza : (Lcom/google/android/gms/internal/zzcie;)V
    //   141: aload_0
    //   142: invokevirtual zzayp : ()Lcom/google/android/gms/internal/zzcjj;
    //   145: invokevirtual zzbba : ()Lcom/google/android/gms/internal/zzcjl;
    //   148: ldc_w 'Fetching config failed. code, error'
    //   151: iload_2
    //   152: invokestatic valueOf : (I)Ljava/lang/Integer;
    //   155: aload_3
    //   156: invokevirtual zze : (Ljava/lang/String;Ljava/lang/Object;Ljava/lang/Object;)V
    //   159: aload_0
    //   160: invokevirtual zzaym : ()Lcom/google/android/gms/internal/zzckd;
    //   163: aload_1
    //   164: invokevirtual zzkc : (Ljava/lang/String;)V
    //   167: aload_0
    //   168: invokevirtual zzayq : ()Lcom/google/android/gms/internal/zzcju;
    //   171: getfield zzjlo : Lcom/google/android/gms/internal/zzcjx;
    //   174: aload_0
    //   175: getfield zzdir : Lcom/google/android/gms/common/util/zze;
    //   178: invokeinterface currentTimeMillis : ()J
    //   183: invokevirtual set : (J)V
    //   186: iload #7
    //   188: istore #6
    //   190: iload_2
    //   191: sipush #503
    //   194: if_icmpeq -> 211
    //   197: iload_2
    //   198: sipush #429
    //   201: if_icmpne -> 523
    //   204: iload #7
    //   206: istore #6
    //   208: goto -> 211
    //   211: iload #6
    //   213: ifeq -> 235
    //   216: aload_0
    //   217: invokevirtual zzayq : ()Lcom/google/android/gms/internal/zzcju;
    //   220: getfield zzjlp : Lcom/google/android/gms/internal/zzcjx;
    //   223: aload_0
    //   224: getfield zzdir : Lcom/google/android/gms/common/util/zze;
    //   227: invokeinterface currentTimeMillis : ()J
    //   232: invokevirtual set : (J)V
    //   235: aload_0
    //   236: invokespecial zzbca : ()V
    //   239: goto -> 455
    //   242: aload #5
    //   244: ifnull -> 529
    //   247: aload #5
    //   249: ldc_w 'Last-Modified'
    //   252: invokeinterface get : (Ljava/lang/Object;)Ljava/lang/Object;
    //   257: checkcast java/util/List
    //   260: astore_3
    //   261: goto -> 264
    //   264: aload_3
    //   265: ifnull -> 534
    //   268: aload_3
    //   269: invokeinterface size : ()I
    //   274: ifle -> 534
    //   277: aload_3
    //   278: iconst_0
    //   279: invokeinterface get : (I)Ljava/lang/Object;
    //   284: checkcast java/lang/String
    //   287: astore_3
    //   288: goto -> 536
    //   291: aload_0
    //   292: invokevirtual zzaym : ()Lcom/google/android/gms/internal/zzckd;
    //   295: aload_1
    //   296: aload #9
    //   298: aload_3
    //   299: invokevirtual zzb : (Ljava/lang/String;[BLjava/lang/String;)Z
    //   302: istore #8
    //   304: iload #8
    //   306: ifne -> 364
    //   309: aload_0
    //   310: invokevirtual zzayj : ()Lcom/google/android/gms/internal/zzcil;
    //   313: astore_1
    //   314: aload_1
    //   315: invokevirtual endTransaction : ()V
    //   318: aload_0
    //   319: iconst_0
    //   320: putfield zzjoz : Z
    //   323: aload_0
    //   324: invokespecial zzbce : ()V
    //   327: return
    //   328: aload_0
    //   329: invokevirtual zzaym : ()Lcom/google/android/gms/internal/zzckd;
    //   332: aload_1
    //   333: invokevirtual zzka : (Ljava/lang/String;)Lcom/google/android/gms/internal/zzcny;
    //   336: ifnonnull -> 364
    //   339: aload_0
    //   340: invokevirtual zzaym : ()Lcom/google/android/gms/internal/zzckd;
    //   343: aload_1
    //   344: aconst_null
    //   345: aconst_null
    //   346: invokevirtual zzb : (Ljava/lang/String;[BLjava/lang/String;)Z
    //   349: istore #8
    //   351: iload #8
    //   353: ifne -> 364
    //   356: aload_0
    //   357: invokevirtual zzayj : ()Lcom/google/android/gms/internal/zzcil;
    //   360: astore_1
    //   361: goto -> 314
    //   364: aload #4
    //   366: aload_0
    //   367: getfield zzdir : Lcom/google/android/gms/common/util/zze;
    //   370: invokeinterface currentTimeMillis : ()J
    //   375: invokevirtual zzar : (J)V
    //   378: aload_0
    //   379: invokevirtual zzayj : ()Lcom/google/android/gms/internal/zzcil;
    //   382: aload #4
    //   384: invokevirtual zza : (Lcom/google/android/gms/internal/zzcie;)V
    //   387: iload_2
    //   388: sipush #404
    //   391: if_icmpne -> 411
    //   394: aload_0
    //   395: invokevirtual zzayp : ()Lcom/google/android/gms/internal/zzcjj;
    //   398: invokevirtual zzbax : ()Lcom/google/android/gms/internal/zzcjl;
    //   401: ldc_w 'Config not found. Using empty config. appId'
    //   404: aload_1
    //   405: invokevirtual zzj : (Ljava/lang/String;Ljava/lang/Object;)V
    //   408: goto -> 434
    //   411: aload_0
    //   412: invokevirtual zzayp : ()Lcom/google/android/gms/internal/zzcjj;
    //   415: invokevirtual zzbba : ()Lcom/google/android/gms/internal/zzcjl;
    //   418: ldc_w 'Successfully fetched config. Got network response. code, size'
    //   421: iload_2
    //   422: invokestatic valueOf : (I)Ljava/lang/Integer;
    //   425: aload #9
    //   427: arraylength
    //   428: invokestatic valueOf : (I)Ljava/lang/Integer;
    //   431: invokevirtual zze : (Ljava/lang/String;Ljava/lang/Object;Ljava/lang/Object;)V
    //   434: aload_0
    //   435: invokevirtual zzbbs : ()Lcom/google/android/gms/internal/zzcjn;
    //   438: invokevirtual zzaax : ()Z
    //   441: ifeq -> 235
    //   444: aload_0
    //   445: invokespecial zzbbz : ()Z
    //   448: ifeq -> 235
    //   451: aload_0
    //   452: invokevirtual zzbby : ()V
    //   455: aload_0
    //   456: invokevirtual zzayj : ()Lcom/google/android/gms/internal/zzcil;
    //   459: invokevirtual setTransactionSuccessful : ()V
    //   462: aload_0
    //   463: invokevirtual zzayj : ()Lcom/google/android/gms/internal/zzcil;
    //   466: astore_1
    //   467: goto -> 314
    //   470: astore_1
    //   471: aload_0
    //   472: invokevirtual zzayj : ()Lcom/google/android/gms/internal/zzcil;
    //   475: invokevirtual endTransaction : ()V
    //   478: aload_1
    //   479: athrow
    //   480: astore_1
    //   481: aload_0
    //   482: iconst_0
    //   483: putfield zzjoz : Z
    //   486: aload_0
    //   487: invokespecial zzbce : ()V
    //   490: aload_1
    //   491: athrow
    //   492: aload_3
    //   493: ifnonnull -> 502
    //   496: iconst_1
    //   497: istore #6
    //   499: goto -> 93
    //   502: iconst_0
    //   503: istore #6
    //   505: goto -> 93
    //   508: iload #6
    //   510: ifne -> 242
    //   513: iload_2
    //   514: sipush #404
    //   517: if_icmpne -> 118
    //   520: goto -> 242
    //   523: iconst_0
    //   524: istore #6
    //   526: goto -> 211
    //   529: aconst_null
    //   530: astore_3
    //   531: goto -> 264
    //   534: aconst_null
    //   535: astore_3
    //   536: iload_2
    //   537: sipush #404
    //   540: if_icmpeq -> 328
    //   543: iload_2
    //   544: sipush #304
    //   547: if_icmpne -> 291
    //   550: goto -> 328
    // Exception table:
    //   from	to	target	type
    //   25	30	480	finally
    //   30	56	480	finally
    //   56	66	470	finally
    //   98	115	470	finally
    //   118	186	470	finally
    //   216	235	470	finally
    //   235	239	470	finally
    //   247	261	470	finally
    //   268	288	470	finally
    //   291	304	470	finally
    //   309	314	480	finally
    //   314	318	480	finally
    //   328	351	470	finally
    //   356	361	480	finally
    //   364	387	470	finally
    //   394	408	470	finally
    //   411	434	470	finally
    //   434	455	470	finally
    //   455	462	470	finally
    //   462	467	480	finally
    //   471	480	480	finally
  }
  
  protected final boolean zzbbn() {
    // Byte code:
    //   0: aload_0
    //   1: invokevirtual zzyk : ()V
    //   4: aload_0
    //   5: invokevirtual zzayo : ()Lcom/google/android/gms/internal/zzcke;
    //   8: invokevirtual zzwj : ()V
    //   11: aload_0
    //   12: getfield zzjop : Ljava/lang/Boolean;
    //   15: astore #4
    //   17: aload #4
    //   19: ifnull -> 68
    //   22: aload_0
    //   23: getfield zzjoq : J
    //   26: lconst_0
    //   27: lcmp
    //   28: ifeq -> 68
    //   31: aload #4
    //   33: ifnull -> 194
    //   36: aload #4
    //   38: invokevirtual booleanValue : ()Z
    //   41: ifne -> 194
    //   44: aload_0
    //   45: getfield zzdir : Lcom/google/android/gms/common/util/zze;
    //   48: invokeinterface elapsedRealtime : ()J
    //   53: aload_0
    //   54: getfield zzjoq : J
    //   57: lsub
    //   58: invokestatic abs : (J)J
    //   61: ldc2_w 1000
    //   64: lcmp
    //   65: ifle -> 194
    //   68: aload_0
    //   69: aload_0
    //   70: getfield zzdir : Lcom/google/android/gms/common/util/zze;
    //   73: invokeinterface elapsedRealtime : ()J
    //   78: putfield zzjoq : J
    //   81: aload_0
    //   82: invokevirtual zzayl : ()Lcom/google/android/gms/internal/zzcno;
    //   85: ldc_w 'android.permission.INTERNET'
    //   88: invokevirtual zzeh : (Ljava/lang/String;)Z
    //   91: istore_3
    //   92: iconst_0
    //   93: istore_2
    //   94: iload_2
    //   95: istore_1
    //   96: iload_3
    //   97: ifeq -> 155
    //   100: iload_2
    //   101: istore_1
    //   102: aload_0
    //   103: invokevirtual zzayl : ()Lcom/google/android/gms/internal/zzcno;
    //   106: ldc_w 'android.permission.ACCESS_NETWORK_STATE'
    //   109: invokevirtual zzeh : (Ljava/lang/String;)Z
    //   112: ifeq -> 155
    //   115: aload_0
    //   116: getfield zzaiq : Landroid/content/Context;
    //   119: invokestatic zzdd : (Landroid/content/Context;)Lcom/google/android/gms/internal/zzbig;
    //   122: invokevirtual zzaoe : ()Z
    //   125: ifne -> 153
    //   128: iload_2
    //   129: istore_1
    //   130: aload_0
    //   131: getfield zzaiq : Landroid/content/Context;
    //   134: invokestatic zzbj : (Landroid/content/Context;)Z
    //   137: ifeq -> 155
    //   140: iload_2
    //   141: istore_1
    //   142: aload_0
    //   143: getfield zzaiq : Landroid/content/Context;
    //   146: iconst_0
    //   147: invokestatic zzg : (Landroid/content/Context;Z)Z
    //   150: ifeq -> 155
    //   153: iconst_1
    //   154: istore_1
    //   155: aload_0
    //   156: iload_1
    //   157: invokestatic valueOf : (Z)Ljava/lang/Boolean;
    //   160: putfield zzjop : Ljava/lang/Boolean;
    //   163: aload_0
    //   164: getfield zzjop : Ljava/lang/Boolean;
    //   167: invokevirtual booleanValue : ()Z
    //   170: ifeq -> 194
    //   173: aload_0
    //   174: aload_0
    //   175: invokevirtual zzayl : ()Lcom/google/android/gms/internal/zzcno;
    //   178: aload_0
    //   179: invokevirtual zzaye : ()Lcom/google/android/gms/internal/zzcje;
    //   182: invokevirtual getGmpAppId : ()Ljava/lang/String;
    //   185: invokevirtual zzkn : (Ljava/lang/String;)Z
    //   188: invokestatic valueOf : (Z)Ljava/lang/Boolean;
    //   191: putfield zzjop : Ljava/lang/Boolean;
    //   194: aload_0
    //   195: getfield zzjop : Ljava/lang/Boolean;
    //   198: invokevirtual booleanValue : ()Z
    //   201: ireturn
  }
  
  public final zzcjj zzbbo() {
    zzcjj zzcjj1 = this.zzjnu;
    return (zzcjj1 != null && zzcjj1.isInitialized()) ? this.zzjnu : null;
  }
  
  final zzcke zzbbp() {
    return this.zzjnv;
  }
  
  public final AppMeasurement zzbbq() {
    return this.zzjny;
  }
  
  public final FirebaseAnalytics zzbbr() {
    return this.zzjnz;
  }
  
  public final zzcjn zzbbs() {
    zza(this.zzjoc);
    return this.zzjoc;
  }
  
  final long zzbbw() {
    Long long_ = Long.valueOf((zzayq()).zzjls.get());
    return (long_.longValue() == 0L) ? this.zzjgk : Math.min(this.zzjgk, long_.longValue());
  }
  
  public final void zzbby() {
    // Byte code:
    //   0: aload_0
    //   1: invokevirtual zzayo : ()Lcom/google/android/gms/internal/zzcke;
    //   4: invokevirtual zzwj : ()V
    //   7: aload_0
    //   8: invokevirtual zzyk : ()V
    //   11: aload_0
    //   12: iconst_1
    //   13: putfield zzjpb : Z
    //   16: aload_0
    //   17: invokevirtual zzayg : ()Lcom/google/android/gms/internal/zzcme;
    //   20: invokevirtual zzbck : ()Ljava/lang/Boolean;
    //   23: astore #8
    //   25: aload #8
    //   27: ifnonnull -> 61
    //   30: aload_0
    //   31: invokevirtual zzayp : ()Lcom/google/android/gms/internal/zzcjj;
    //   34: invokevirtual zzbaw : ()Lcom/google/android/gms/internal/zzcjl;
    //   37: astore #8
    //   39: ldc_w 'Upload data called on the client side before use of service was decided'
    //   42: astore #9
    //   44: aload #8
    //   46: aload #9
    //   48: invokevirtual log : (Ljava/lang/String;)V
    //   51: aload_0
    //   52: iconst_0
    //   53: putfield zzjpb : Z
    //   56: aload_0
    //   57: invokespecial zzbce : ()V
    //   60: return
    //   61: aload #8
    //   63: invokevirtual booleanValue : ()Z
    //   66: ifeq -> 86
    //   69: aload_0
    //   70: invokevirtual zzayp : ()Lcom/google/android/gms/internal/zzcjj;
    //   73: invokevirtual zzbau : ()Lcom/google/android/gms/internal/zzcjl;
    //   76: astore #8
    //   78: ldc_w 'Upload called in the client side when service should be used'
    //   81: astore #9
    //   83: goto -> 44
    //   86: aload_0
    //   87: getfield zzjoy : J
    //   90: lconst_0
    //   91: lcmp
    //   92: ifle -> 102
    //   95: aload_0
    //   96: invokespecial zzbca : ()V
    //   99: goto -> 51
    //   102: aload_0
    //   103: invokevirtual zzayo : ()Lcom/google/android/gms/internal/zzcke;
    //   106: invokevirtual zzwj : ()V
    //   109: aload_0
    //   110: getfield zzjot : Ljava/util/List;
    //   113: ifnull -> 994
    //   116: iconst_1
    //   117: istore_1
    //   118: goto -> 121
    //   121: iload_1
    //   122: ifeq -> 142
    //   125: aload_0
    //   126: invokevirtual zzayp : ()Lcom/google/android/gms/internal/zzcjj;
    //   129: invokevirtual zzbba : ()Lcom/google/android/gms/internal/zzcjl;
    //   132: astore #8
    //   134: ldc_w 'Uploading requested multiple times'
    //   137: astore #9
    //   139: goto -> 44
    //   142: aload_0
    //   143: invokevirtual zzbbs : ()Lcom/google/android/gms/internal/zzcjn;
    //   146: invokevirtual zzaax : ()Z
    //   149: ifne -> 168
    //   152: aload_0
    //   153: invokevirtual zzayp : ()Lcom/google/android/gms/internal/zzcjj;
    //   156: invokevirtual zzbba : ()Lcom/google/android/gms/internal/zzcjl;
    //   159: ldc_w 'Network not connected, ignoring upload request'
    //   162: invokevirtual log : (Ljava/lang/String;)V
    //   165: goto -> 95
    //   168: aload_0
    //   169: getfield zzdir : Lcom/google/android/gms/common/util/zze;
    //   172: invokeinterface currentTimeMillis : ()J
    //   177: lstore_3
    //   178: invokestatic zzazt : ()J
    //   181: lstore #5
    //   183: aconst_null
    //   184: astore #10
    //   186: aload_0
    //   187: aconst_null
    //   188: lload_3
    //   189: lload #5
    //   191: lsub
    //   192: invokespecial zzg : (Ljava/lang/String;J)Z
    //   195: pop
    //   196: aload_0
    //   197: invokevirtual zzayq : ()Lcom/google/android/gms/internal/zzcju;
    //   200: getfield zzjln : Lcom/google/android/gms/internal/zzcjx;
    //   203: invokevirtual get : ()J
    //   206: lstore #5
    //   208: lload #5
    //   210: lconst_0
    //   211: lcmp
    //   212: ifeq -> 238
    //   215: aload_0
    //   216: invokevirtual zzayp : ()Lcom/google/android/gms/internal/zzcjj;
    //   219: invokevirtual zzbaz : ()Lcom/google/android/gms/internal/zzcjl;
    //   222: ldc_w 'Uploading events. Elapsed time since last upload attempt (ms)'
    //   225: lload_3
    //   226: lload #5
    //   228: lsub
    //   229: invokestatic abs : (J)J
    //   232: invokestatic valueOf : (J)Ljava/lang/Long;
    //   235: invokevirtual zzj : (Ljava/lang/String;Ljava/lang/Object;)V
    //   238: aload_0
    //   239: invokevirtual zzayj : ()Lcom/google/android/gms/internal/zzcil;
    //   242: invokevirtual zzazw : ()Ljava/lang/String;
    //   245: astore #12
    //   247: aload #12
    //   249: invokestatic isEmpty : (Ljava/lang/CharSequence;)Z
    //   252: ifne -> 921
    //   255: aload_0
    //   256: getfield zzjox : J
    //   259: ldc2_w -1
    //   262: lcmp
    //   263: ifne -> 277
    //   266: aload_0
    //   267: aload_0
    //   268: invokevirtual zzayj : ()Lcom/google/android/gms/internal/zzcil;
    //   271: invokevirtual zzbad : ()J
    //   274: putfield zzjox : J
    //   277: aload_0
    //   278: getfield zzjns : Lcom/google/android/gms/internal/zzcik;
    //   281: aload #12
    //   283: getstatic com/google/android/gms/internal/zzciz.zzjit : Lcom/google/android/gms/internal/zzcja;
    //   286: invokevirtual zzb : (Ljava/lang/String;Lcom/google/android/gms/internal/zzcja;)I
    //   289: istore_1
    //   290: iconst_0
    //   291: aload_0
    //   292: getfield zzjns : Lcom/google/android/gms/internal/zzcik;
    //   295: aload #12
    //   297: getstatic com/google/android/gms/internal/zzciz.zzjiu : Lcom/google/android/gms/internal/zzcja;
    //   300: invokevirtual zzb : (Ljava/lang/String;Lcom/google/android/gms/internal/zzcja;)I
    //   303: invokestatic max : (II)I
    //   306: istore_2
    //   307: aload_0
    //   308: invokevirtual zzayj : ()Lcom/google/android/gms/internal/zzcil;
    //   311: aload #12
    //   313: iload_1
    //   314: iload_2
    //   315: invokevirtual zzl : (Ljava/lang/String;II)Ljava/util/List;
    //   318: astore #11
    //   320: aload #11
    //   322: invokeinterface isEmpty : ()Z
    //   327: ifne -> 51
    //   330: aload #11
    //   332: invokeinterface iterator : ()Ljava/util/Iterator;
    //   337: astore #8
    //   339: aload #8
    //   341: invokeinterface hasNext : ()Z
    //   346: ifeq -> 999
    //   349: aload #8
    //   351: invokeinterface next : ()Ljava/lang/Object;
    //   356: checkcast android/util/Pair
    //   359: getfield first : Ljava/lang/Object;
    //   362: checkcast com/google/android/gms/internal/zzcoe
    //   365: astore #9
    //   367: aload #9
    //   369: getfield zzjvc : Ljava/lang/String;
    //   372: invokestatic isEmpty : (Ljava/lang/CharSequence;)Z
    //   375: ifne -> 339
    //   378: aload #9
    //   380: getfield zzjvc : Ljava/lang/String;
    //   383: astore #9
    //   385: goto -> 1002
    //   388: aload #11
    //   390: astore #8
    //   392: iload_1
    //   393: aload #11
    //   395: invokeinterface size : ()I
    //   400: if_icmpge -> 460
    //   403: aload #11
    //   405: iload_1
    //   406: invokeinterface get : (I)Ljava/lang/Object;
    //   411: checkcast android/util/Pair
    //   414: getfield first : Ljava/lang/Object;
    //   417: checkcast com/google/android/gms/internal/zzcoe
    //   420: astore #8
    //   422: aload #8
    //   424: getfield zzjvc : Ljava/lang/String;
    //   427: invokestatic isEmpty : (Ljava/lang/CharSequence;)Z
    //   430: ifne -> 1016
    //   433: aload #8
    //   435: getfield zzjvc : Ljava/lang/String;
    //   438: aload #9
    //   440: invokevirtual equals : (Ljava/lang/Object;)Z
    //   443: ifne -> 1016
    //   446: aload #11
    //   448: iconst_0
    //   449: iload_1
    //   450: invokeinterface subList : (II)Ljava/util/List;
    //   455: astore #8
    //   457: goto -> 460
    //   460: new com/google/android/gms/internal/zzcod
    //   463: dup
    //   464: invokespecial <init> : ()V
    //   467: astore #11
    //   469: aload #11
    //   471: aload #8
    //   473: invokeinterface size : ()I
    //   478: anewarray com/google/android/gms/internal/zzcoe
    //   481: putfield zzjun : [Lcom/google/android/gms/internal/zzcoe;
    //   484: new java/util/ArrayList
    //   487: dup
    //   488: aload #8
    //   490: invokeinterface size : ()I
    //   495: invokespecial <init> : (I)V
    //   498: astore #9
    //   500: invokestatic zzazv : ()Z
    //   503: ifeq -> 1023
    //   506: aload_0
    //   507: getfield zzjns : Lcom/google/android/gms/internal/zzcik;
    //   510: aload #12
    //   512: invokevirtual zzjg : (Ljava/lang/String;)Z
    //   515: ifeq -> 1023
    //   518: iconst_1
    //   519: istore_1
    //   520: goto -> 1025
    //   523: iload_2
    //   524: aload #11
    //   526: getfield zzjun : [Lcom/google/android/gms/internal/zzcoe;
    //   529: arraylength
    //   530: if_icmpge -> 644
    //   533: aload #11
    //   535: getfield zzjun : [Lcom/google/android/gms/internal/zzcoe;
    //   538: iload_2
    //   539: aload #8
    //   541: iload_2
    //   542: invokeinterface get : (I)Ljava/lang/Object;
    //   547: checkcast android/util/Pair
    //   550: getfield first : Ljava/lang/Object;
    //   553: checkcast com/google/android/gms/internal/zzcoe
    //   556: aastore
    //   557: aload #9
    //   559: aload #8
    //   561: iload_2
    //   562: invokeinterface get : (I)Ljava/lang/Object;
    //   567: checkcast android/util/Pair
    //   570: getfield second : Ljava/lang/Object;
    //   573: checkcast java/lang/Long
    //   576: invokeinterface add : (Ljava/lang/Object;)Z
    //   581: pop
    //   582: aload #11
    //   584: getfield zzjun : [Lcom/google/android/gms/internal/zzcoe;
    //   587: iload_2
    //   588: aaload
    //   589: ldc2_w 12211
    //   592: invokestatic valueOf : (J)Ljava/lang/Long;
    //   595: putfield zzjvb : Ljava/lang/Long;
    //   598: aload #11
    //   600: getfield zzjun : [Lcom/google/android/gms/internal/zzcoe;
    //   603: iload_2
    //   604: aaload
    //   605: lload_3
    //   606: invokestatic valueOf : (J)Ljava/lang/Long;
    //   609: putfield zzjus : Ljava/lang/Long;
    //   612: aload #11
    //   614: getfield zzjun : [Lcom/google/android/gms/internal/zzcoe;
    //   617: iload_2
    //   618: aaload
    //   619: iconst_0
    //   620: invokestatic valueOf : (Z)Ljava/lang/Boolean;
    //   623: putfield zzjvg : Ljava/lang/Boolean;
    //   626: iload_1
    //   627: ifne -> 1030
    //   630: aload #11
    //   632: getfield zzjun : [Lcom/google/android/gms/internal/zzcoe;
    //   635: iload_2
    //   636: aaload
    //   637: aconst_null
    //   638: putfield zzjvn : Ljava/lang/String;
    //   641: goto -> 1030
    //   644: aload #10
    //   646: astore #8
    //   648: aload_0
    //   649: invokevirtual zzayp : ()Lcom/google/android/gms/internal/zzcjj;
    //   652: iconst_2
    //   653: invokevirtual zzae : (I)Z
    //   656: ifeq -> 670
    //   659: aload_0
    //   660: invokevirtual zzayk : ()Lcom/google/android/gms/internal/zzcjh;
    //   663: aload #11
    //   665: invokevirtual zza : (Lcom/google/android/gms/internal/zzcod;)Ljava/lang/String;
    //   668: astore #8
    //   670: aload_0
    //   671: invokevirtual zzayl : ()Lcom/google/android/gms/internal/zzcno;
    //   674: aload #11
    //   676: invokevirtual zzb : (Lcom/google/android/gms/internal/zzcod;)[B
    //   679: astore #13
    //   681: getstatic com/google/android/gms/internal/zzciz.zzjjd : Lcom/google/android/gms/internal/zzcja;
    //   684: invokevirtual get : ()Ljava/lang/Object;
    //   687: checkcast java/lang/String
    //   690: astore #10
    //   692: new java/net/URL
    //   695: dup
    //   696: aload #10
    //   698: invokespecial <init> : (Ljava/lang/String;)V
    //   701: astore #14
    //   703: aload #9
    //   705: invokeinterface isEmpty : ()Z
    //   710: ifne -> 1037
    //   713: iconst_1
    //   714: istore #7
    //   716: goto -> 719
    //   719: iload #7
    //   721: invokestatic checkArgument : (Z)V
    //   724: aload_0
    //   725: getfield zzjot : Ljava/util/List;
    //   728: ifnull -> 747
    //   731: aload_0
    //   732: invokevirtual zzayp : ()Lcom/google/android/gms/internal/zzcjj;
    //   735: invokevirtual zzbau : ()Lcom/google/android/gms/internal/zzcjl;
    //   738: ldc_w 'Set uploading progress before finishing the previous upload'
    //   741: invokevirtual log : (Ljava/lang/String;)V
    //   744: goto -> 760
    //   747: aload_0
    //   748: new java/util/ArrayList
    //   751: dup
    //   752: aload #9
    //   754: invokespecial <init> : (Ljava/util/Collection;)V
    //   757: putfield zzjot : Ljava/util/List;
    //   760: aload_0
    //   761: invokevirtual zzayq : ()Lcom/google/android/gms/internal/zzcju;
    //   764: getfield zzjlo : Lcom/google/android/gms/internal/zzcjx;
    //   767: lload_3
    //   768: invokevirtual set : (J)V
    //   771: ldc_w '?'
    //   774: astore #9
    //   776: aload #11
    //   778: getfield zzjun : [Lcom/google/android/gms/internal/zzcoe;
    //   781: arraylength
    //   782: ifle -> 797
    //   785: aload #11
    //   787: getfield zzjun : [Lcom/google/android/gms/internal/zzcoe;
    //   790: iconst_0
    //   791: aaload
    //   792: getfield zzcm : Ljava/lang/String;
    //   795: astore #9
    //   797: aload_0
    //   798: invokevirtual zzayp : ()Lcom/google/android/gms/internal/zzcjj;
    //   801: invokevirtual zzbba : ()Lcom/google/android/gms/internal/zzcjl;
    //   804: ldc_w 'Uploading data. app, uncompressed size, data'
    //   807: aload #9
    //   809: aload #13
    //   811: arraylength
    //   812: invokestatic valueOf : (I)Ljava/lang/Integer;
    //   815: aload #8
    //   817: invokevirtual zzd : (Ljava/lang/String;Ljava/lang/Object;Ljava/lang/Object;Ljava/lang/Object;)V
    //   820: aload_0
    //   821: iconst_1
    //   822: putfield zzjpa : Z
    //   825: aload_0
    //   826: invokevirtual zzbbs : ()Lcom/google/android/gms/internal/zzcjn;
    //   829: astore #8
    //   831: new com/google/android/gms/internal/zzckm
    //   834: dup
    //   835: aload_0
    //   836: invokespecial <init> : (Lcom/google/android/gms/internal/zzckj;)V
    //   839: astore #9
    //   841: aload #8
    //   843: invokevirtual zzwj : ()V
    //   846: aload #8
    //   848: invokevirtual zzyk : ()V
    //   851: aload #14
    //   853: invokestatic checkNotNull : (Ljava/lang/Object;)Ljava/lang/Object;
    //   856: pop
    //   857: aload #13
    //   859: invokestatic checkNotNull : (Ljava/lang/Object;)Ljava/lang/Object;
    //   862: pop
    //   863: aload #9
    //   865: invokestatic checkNotNull : (Ljava/lang/Object;)Ljava/lang/Object;
    //   868: pop
    //   869: aload #8
    //   871: invokevirtual zzayo : ()Lcom/google/android/gms/internal/zzcke;
    //   874: new com/google/android/gms/internal/zzcjr
    //   877: dup
    //   878: aload #8
    //   880: aload #12
    //   882: aload #14
    //   884: aload #13
    //   886: aconst_null
    //   887: aload #9
    //   889: invokespecial <init> : (Lcom/google/android/gms/internal/zzcjn;Ljava/lang/String;Ljava/net/URL;[BLjava/util/Map;Lcom/google/android/gms/internal/zzcjp;)V
    //   892: invokevirtual zzi : (Ljava/lang/Runnable;)V
    //   895: goto -> 51
    //   898: aload_0
    //   899: invokevirtual zzayp : ()Lcom/google/android/gms/internal/zzcjj;
    //   902: invokevirtual zzbau : ()Lcom/google/android/gms/internal/zzcjl;
    //   905: ldc_w 'Failed to parse upload URL. Not uploading. appId'
    //   908: aload #12
    //   910: invokestatic zzjs : (Ljava/lang/String;)Ljava/lang/Object;
    //   913: aload #10
    //   915: invokevirtual zze : (Ljava/lang/String;Ljava/lang/Object;Ljava/lang/Object;)V
    //   918: goto -> 51
    //   921: aload_0
    //   922: ldc2_w -1
    //   925: putfield zzjox : J
    //   928: aload_0
    //   929: invokevirtual zzayj : ()Lcom/google/android/gms/internal/zzcil;
    //   932: lload_3
    //   933: invokestatic zzazt : ()J
    //   936: lsub
    //   937: invokevirtual zzba : (J)Ljava/lang/String;
    //   940: astore #8
    //   942: aload #8
    //   944: invokestatic isEmpty : (Ljava/lang/CharSequence;)Z
    //   947: ifne -> 51
    //   950: aload_0
    //   951: invokevirtual zzayj : ()Lcom/google/android/gms/internal/zzcil;
    //   954: aload #8
    //   956: invokevirtual zzjj : (Ljava/lang/String;)Lcom/google/android/gms/internal/zzcie;
    //   959: astore #8
    //   961: aload #8
    //   963: ifnull -> 51
    //   966: aload_0
    //   967: aload #8
    //   969: invokespecial zzb : (Lcom/google/android/gms/internal/zzcie;)V
    //   972: goto -> 51
    //   975: astore #8
    //   977: aload_0
    //   978: iconst_0
    //   979: putfield zzjpb : Z
    //   982: aload_0
    //   983: invokespecial zzbce : ()V
    //   986: aload #8
    //   988: athrow
    //   989: astore #8
    //   991: goto -> 898
    //   994: iconst_0
    //   995: istore_1
    //   996: goto -> 121
    //   999: aconst_null
    //   1000: astore #9
    //   1002: aload #11
    //   1004: astore #8
    //   1006: aload #9
    //   1008: ifnull -> 460
    //   1011: iconst_0
    //   1012: istore_1
    //   1013: goto -> 388
    //   1016: iload_1
    //   1017: iconst_1
    //   1018: iadd
    //   1019: istore_1
    //   1020: goto -> 388
    //   1023: iconst_0
    //   1024: istore_1
    //   1025: iconst_0
    //   1026: istore_2
    //   1027: goto -> 523
    //   1030: iload_2
    //   1031: iconst_1
    //   1032: iadd
    //   1033: istore_2
    //   1034: goto -> 523
    //   1037: iconst_0
    //   1038: istore #7
    //   1040: goto -> 719
    // Exception table:
    //   from	to	target	type
    //   16	25	975	finally
    //   30	39	975	finally
    //   44	51	975	finally
    //   61	78	975	finally
    //   86	95	975	finally
    //   95	99	975	finally
    //   102	116	975	finally
    //   125	134	975	finally
    //   142	165	975	finally
    //   168	183	975	finally
    //   186	208	975	finally
    //   215	238	975	finally
    //   238	277	975	finally
    //   277	339	975	finally
    //   339	385	975	finally
    //   392	457	975	finally
    //   460	518	975	finally
    //   523	626	975	finally
    //   630	641	975	finally
    //   648	670	975	finally
    //   670	692	975	finally
    //   692	713	989	java/net/MalformedURLException
    //   692	713	975	finally
    //   719	744	989	java/net/MalformedURLException
    //   719	744	975	finally
    //   747	760	989	java/net/MalformedURLException
    //   747	760	975	finally
    //   760	771	989	java/net/MalformedURLException
    //   760	771	975	finally
    //   776	797	989	java/net/MalformedURLException
    //   776	797	975	finally
    //   797	895	989	java/net/MalformedURLException
    //   797	895	975	finally
    //   898	918	975	finally
    //   921	961	975	finally
    //   966	972	975	finally
  }
  
  final void zzbcb() {
    this.zzjow++;
  }
  
  final void zzbcc() {
    // Byte code:
    //   0: aload_0
    //   1: invokevirtual zzayo : ()Lcom/google/android/gms/internal/zzcke;
    //   4: invokevirtual zzwj : ()V
    //   7: aload_0
    //   8: invokevirtual zzyk : ()V
    //   11: aload_0
    //   12: getfield zzjoo : Z
    //   15: ifne -> 173
    //   18: aload_0
    //   19: invokevirtual zzayp : ()Lcom/google/android/gms/internal/zzcjj;
    //   22: invokevirtual zzbay : ()Lcom/google/android/gms/internal/zzcjl;
    //   25: ldc_w 'This instance being marked as an uploader'
    //   28: invokevirtual log : (Ljava/lang/String;)V
    //   31: aload_0
    //   32: invokevirtual zzayo : ()Lcom/google/android/gms/internal/zzcke;
    //   35: invokevirtual zzwj : ()V
    //   38: aload_0
    //   39: invokevirtual zzyk : ()V
    //   42: aload_0
    //   43: invokespecial zzbcd : ()Z
    //   46: ifeq -> 164
    //   49: aload_0
    //   50: invokespecial zzbbv : ()Z
    //   53: ifeq -> 164
    //   56: aload_0
    //   57: aload_0
    //   58: getfield zzjos : Ljava/nio/channels/FileChannel;
    //   61: invokespecial zza : (Ljava/nio/channels/FileChannel;)I
    //   64: istore_1
    //   65: aload_0
    //   66: invokevirtual zzaye : ()Lcom/google/android/gms/internal/zzcje;
    //   69: invokevirtual zzbar : ()I
    //   72: istore_2
    //   73: aload_0
    //   74: invokevirtual zzayo : ()Lcom/google/android/gms/internal/zzcke;
    //   77: invokevirtual zzwj : ()V
    //   80: iload_1
    //   81: iload_2
    //   82: if_icmple -> 115
    //   85: aload_0
    //   86: invokevirtual zzayp : ()Lcom/google/android/gms/internal/zzcjj;
    //   89: invokevirtual zzbau : ()Lcom/google/android/gms/internal/zzcjl;
    //   92: astore_3
    //   93: ldc_w 'Panic: can't downgrade version. Previous, current version'
    //   96: astore #4
    //   98: aload_3
    //   99: aload #4
    //   101: iload_1
    //   102: invokestatic valueOf : (I)Ljava/lang/Integer;
    //   105: iload_2
    //   106: invokestatic valueOf : (I)Ljava/lang/Integer;
    //   109: invokevirtual zze : (Ljava/lang/String;Ljava/lang/Object;Ljava/lang/Object;)V
    //   112: goto -> 164
    //   115: iload_1
    //   116: iload_2
    //   117: if_icmpge -> 164
    //   120: aload_0
    //   121: iload_2
    //   122: aload_0
    //   123: getfield zzjos : Ljava/nio/channels/FileChannel;
    //   126: invokespecial zza : (ILjava/nio/channels/FileChannel;)Z
    //   129: ifeq -> 148
    //   132: aload_0
    //   133: invokevirtual zzayp : ()Lcom/google/android/gms/internal/zzcjj;
    //   136: invokevirtual zzbba : ()Lcom/google/android/gms/internal/zzcjl;
    //   139: astore_3
    //   140: ldc_w 'Storage version upgraded. Previous, current version'
    //   143: astore #4
    //   145: goto -> 98
    //   148: aload_0
    //   149: invokevirtual zzayp : ()Lcom/google/android/gms/internal/zzcjj;
    //   152: invokevirtual zzbau : ()Lcom/google/android/gms/internal/zzcjl;
    //   155: astore_3
    //   156: ldc_w 'Storage version upgrade failed. Previous, current version'
    //   159: astore #4
    //   161: goto -> 98
    //   164: aload_0
    //   165: iconst_1
    //   166: putfield zzjoo : Z
    //   169: aload_0
    //   170: invokespecial zzbca : ()V
    //   173: return
  }
  
  public final void zzbt(boolean paramBoolean) {
    zzbca();
  }
  
  final void zzc(zzcii paramzzcii, zzcif paramzzcif) {
    zzbq.checkNotNull(paramzzcii);
    zzbq.zzgv(paramzzcii.packageName);
    zzbq.checkNotNull(paramzzcii.zzjgn);
    zzbq.zzgv(paramzzcii.zzjgn.name);
    zzayo().zzwj();
    zzyk();
    if (TextUtils.isEmpty(paramzzcif.zzjfl))
      return; 
    if (!paramzzcif.zzjfv) {
      zzg(paramzzcif);
      return;
    } 
    zzayj().beginTransaction();
    try {
      zzg(paramzzcif);
      zzcii zzcii1 = zzayj().zzah(paramzzcii.packageName, paramzzcii.zzjgn.name);
      if (zzcii1 != null) {
        zzayp().zzbaz().zze("Removing conditional user property", paramzzcii.packageName, zzayk().zzjr(paramzzcii.zzjgn.name));
        zzayj().zzai(paramzzcii.packageName, paramzzcii.zzjgn.name);
        if (zzcii1.zzjgp)
          zzayj().zzaf(paramzzcii.packageName, paramzzcii.zzjgn.name); 
        if (paramzzcii.zzjgv != null) {
          Bundle bundle = null;
          if (paramzzcii.zzjgv.zzjhr != null)
            bundle = paramzzcii.zzjgv.zzjhr.zzbao(); 
          zzc(zzayl().zza(paramzzcii.zzjgv.name, bundle, zzcii1.zzjgm, paramzzcii.zzjgv.zzjib, true, false), paramzzcif);
        } 
      } else {
        zzayp().zzbaw().zze("Conditional user property doesn't exist", zzcjj.zzjs(paramzzcii.packageName), zzayk().zzjr(paramzzcii.zzjgn.name));
      } 
      zzayj().setTransactionSuccessful();
      return;
    } finally {
      zzayj().endTransaction();
    } 
  }
  
  final void zzc(zzcnl paramzzcnl, zzcif paramzzcif) {
    zzayo().zzwj();
    zzyk();
    if (TextUtils.isEmpty(paramzzcif.zzjfl))
      return; 
    if (!paramzzcif.zzjfv) {
      zzg(paramzzcif);
      return;
    } 
    zzayp().zzbaz().zzj("Removing user property", zzayk().zzjr(paramzzcnl.name));
    zzayj().beginTransaction();
    try {
      zzg(paramzzcif);
      zzayj().zzaf(paramzzcif.packageName, paramzzcnl.name);
      zzayj().setTransactionSuccessful();
      zzayp().zzbaz().zzj("User property removed", zzayk().zzjr(paramzzcnl.name));
      return;
    } finally {
      zzayj().endTransaction();
    } 
  }
  
  final void zzd(zzcif paramzzcif) {
    zzayj().zzjj(paramzzcif.packageName);
    zzcil zzcil1 = zzayj();
    String str = paramzzcif.packageName;
    zzbq.zzgv(str);
    zzcil1.zzwj();
    zzcil1.zzyk();
    try {
      SQLiteDatabase sQLiteDatabase = zzcil1.getWritableDatabase();
      String[] arrayOfString = new String[1];
      arrayOfString[0] = str;
      int i = sQLiteDatabase.delete("apps", "app_id=?", arrayOfString) + 0 + sQLiteDatabase.delete("events", "app_id=?", arrayOfString) + sQLiteDatabase.delete("user_attributes", "app_id=?", arrayOfString) + sQLiteDatabase.delete("conditional_properties", "app_id=?", arrayOfString) + sQLiteDatabase.delete("raw_events", "app_id=?", arrayOfString) + sQLiteDatabase.delete("raw_events_metadata", "app_id=?", arrayOfString) + sQLiteDatabase.delete("queue", "app_id=?", arrayOfString) + sQLiteDatabase.delete("audience_filter_values", "app_id=?", arrayOfString) + sQLiteDatabase.delete("main_event_params", "app_id=?", arrayOfString);
      if (i > 0)
        zzcil1.zzayp().zzbba().zze("Reset analytics data. app, records", str, Integer.valueOf(i)); 
    } catch (SQLiteException sQLiteException) {
      zzcil1.zzayp().zzbau().zze("Error resetting analytics data. appId, error", zzcjj.zzjs(str), sQLiteException);
    } 
    zzf(zza(this.zzaiq, paramzzcif.packageName, paramzzcif.zzjfl, paramzzcif.zzjfv, paramzzcif.zzjfx));
  }
  
  final void zzd(zzcii paramzzcii) {
    zzcif zzcif = zzke(paramzzcii.packageName);
    if (zzcif != null)
      zzb(paramzzcii, zzcif); 
  }
  
  final void zze(zzcif paramzzcif) {
    zzayo().zzwj();
    zzyk();
    zzbq.zzgv(paramzzcif.packageName);
    zzg(paramzzcif);
  }
  
  final void zze(zzcii paramzzcii) {
    zzcif zzcif = zzke(paramzzcii.packageName);
    if (zzcif != null)
      zzc(paramzzcii, zzcif); 
  }
  
  public final void zzf(zzcif paramzzcif) {
    // Byte code:
    //   0: aload_0
    //   1: invokevirtual zzayo : ()Lcom/google/android/gms/internal/zzcke;
    //   4: invokevirtual zzwj : ()V
    //   7: aload_0
    //   8: invokevirtual zzyk : ()V
    //   11: aload_1
    //   12: invokestatic checkNotNull : (Ljava/lang/Object;)Ljava/lang/Object;
    //   15: pop
    //   16: aload_1
    //   17: getfield packageName : Ljava/lang/String;
    //   20: invokestatic zzgv : (Ljava/lang/String;)Ljava/lang/String;
    //   23: pop
    //   24: aload_1
    //   25: getfield zzjfl : Ljava/lang/String;
    //   28: invokestatic isEmpty : (Ljava/lang/CharSequence;)Z
    //   31: ifeq -> 35
    //   34: return
    //   35: aload_0
    //   36: invokevirtual zzayj : ()Lcom/google/android/gms/internal/zzcil;
    //   39: aload_1
    //   40: getfield packageName : Ljava/lang/String;
    //   43: invokevirtual zzjj : (Ljava/lang/String;)Lcom/google/android/gms/internal/zzcie;
    //   46: astore #10
    //   48: aload #10
    //   50: ifnull -> 100
    //   53: aload #10
    //   55: invokevirtual getGmpAppId : ()Ljava/lang/String;
    //   58: invokestatic isEmpty : (Ljava/lang/CharSequence;)Z
    //   61: ifeq -> 100
    //   64: aload_1
    //   65: getfield zzjfl : Ljava/lang/String;
    //   68: invokestatic isEmpty : (Ljava/lang/CharSequence;)Z
    //   71: ifne -> 100
    //   74: aload #10
    //   76: lconst_0
    //   77: invokevirtual zzar : (J)V
    //   80: aload_0
    //   81: invokevirtual zzayj : ()Lcom/google/android/gms/internal/zzcil;
    //   84: aload #10
    //   86: invokevirtual zza : (Lcom/google/android/gms/internal/zzcie;)V
    //   89: aload_0
    //   90: invokevirtual zzaym : ()Lcom/google/android/gms/internal/zzckd;
    //   93: aload_1
    //   94: getfield packageName : Ljava/lang/String;
    //   97: invokevirtual zzkd : (Ljava/lang/String;)V
    //   100: aload_1
    //   101: getfield zzjfv : Z
    //   104: ifne -> 113
    //   107: aload_0
    //   108: aload_1
    //   109: invokespecial zzg : (Lcom/google/android/gms/internal/zzcif;)V
    //   112: return
    //   113: aload_1
    //   114: getfield zzjgk : J
    //   117: lstore #6
    //   119: lload #6
    //   121: lstore #4
    //   123: lload #6
    //   125: lconst_0
    //   126: lcmp
    //   127: ifne -> 141
    //   130: aload_0
    //   131: getfield zzdir : Lcom/google/android/gms/common/util/zze;
    //   134: invokeinterface currentTimeMillis : ()J
    //   139: lstore #4
    //   141: aload_1
    //   142: getfield zzjgl : I
    //   145: istore_2
    //   146: iload_2
    //   147: ifeq -> 184
    //   150: iload_2
    //   151: iconst_1
    //   152: if_icmpeq -> 184
    //   155: aload_0
    //   156: invokevirtual zzayp : ()Lcom/google/android/gms/internal/zzcjj;
    //   159: invokevirtual zzbaw : ()Lcom/google/android/gms/internal/zzcjl;
    //   162: ldc_w 'Incorrect app type, assuming installed app. appId, appType'
    //   165: aload_1
    //   166: getfield packageName : Ljava/lang/String;
    //   169: invokestatic zzjs : (Ljava/lang/String;)Ljava/lang/Object;
    //   172: iload_2
    //   173: invokestatic valueOf : (I)Ljava/lang/Integer;
    //   176: invokevirtual zze : (Ljava/lang/String;Ljava/lang/Object;Ljava/lang/Object;)V
    //   179: iconst_0
    //   180: istore_2
    //   181: goto -> 184
    //   184: aload_0
    //   185: invokevirtual zzayj : ()Lcom/google/android/gms/internal/zzcil;
    //   188: invokevirtual beginTransaction : ()V
    //   191: aload_0
    //   192: invokevirtual zzayj : ()Lcom/google/android/gms/internal/zzcil;
    //   195: aload_1
    //   196: getfield packageName : Ljava/lang/String;
    //   199: invokevirtual zzjj : (Ljava/lang/String;)Lcom/google/android/gms/internal/zzcie;
    //   202: astore #11
    //   204: aconst_null
    //   205: astore #13
    //   207: aload #11
    //   209: astore #10
    //   211: aload #11
    //   213: ifnull -> 497
    //   216: aload #11
    //   218: astore #10
    //   220: aload #11
    //   222: invokevirtual getGmpAppId : ()Ljava/lang/String;
    //   225: ifnull -> 497
    //   228: aload #11
    //   230: astore #10
    //   232: aload #11
    //   234: invokevirtual getGmpAppId : ()Ljava/lang/String;
    //   237: aload_1
    //   238: getfield zzjfl : Ljava/lang/String;
    //   241: invokevirtual equals : (Ljava/lang/Object;)Z
    //   244: ifne -> 497
    //   247: aload_0
    //   248: invokevirtual zzayp : ()Lcom/google/android/gms/internal/zzcjj;
    //   251: invokevirtual zzbaw : ()Lcom/google/android/gms/internal/zzcjl;
    //   254: ldc_w 'New GMP App Id passed in. Removing cached database data. appId'
    //   257: aload #11
    //   259: invokevirtual getAppId : ()Ljava/lang/String;
    //   262: invokestatic zzjs : (Ljava/lang/String;)Ljava/lang/Object;
    //   265: invokevirtual zzj : (Ljava/lang/String;Ljava/lang/Object;)V
    //   268: aload_0
    //   269: invokevirtual zzayj : ()Lcom/google/android/gms/internal/zzcil;
    //   272: astore #10
    //   274: aload #11
    //   276: invokevirtual getAppId : ()Ljava/lang/String;
    //   279: astore #11
    //   281: aload #10
    //   283: invokevirtual zzyk : ()V
    //   286: aload #10
    //   288: invokevirtual zzwj : ()V
    //   291: aload #11
    //   293: invokestatic zzgv : (Ljava/lang/String;)Ljava/lang/String;
    //   296: pop
    //   297: aload #10
    //   299: invokevirtual getWritableDatabase : ()Landroid/database/sqlite/SQLiteDatabase;
    //   302: astore #12
    //   304: iconst_1
    //   305: anewarray java/lang/String
    //   308: astore #14
    //   310: aload #14
    //   312: iconst_0
    //   313: aload #11
    //   315: aastore
    //   316: aload #12
    //   318: ldc_w 'events'
    //   321: ldc_w 'app_id=?'
    //   324: aload #14
    //   326: invokevirtual delete : (Ljava/lang/String;Ljava/lang/String;[Ljava/lang/String;)I
    //   329: iconst_0
    //   330: iadd
    //   331: aload #12
    //   333: ldc_w 'user_attributes'
    //   336: ldc_w 'app_id=?'
    //   339: aload #14
    //   341: invokevirtual delete : (Ljava/lang/String;Ljava/lang/String;[Ljava/lang/String;)I
    //   344: iadd
    //   345: aload #12
    //   347: ldc_w 'conditional_properties'
    //   350: ldc_w 'app_id=?'
    //   353: aload #14
    //   355: invokevirtual delete : (Ljava/lang/String;Ljava/lang/String;[Ljava/lang/String;)I
    //   358: iadd
    //   359: aload #12
    //   361: ldc_w 'apps'
    //   364: ldc_w 'app_id=?'
    //   367: aload #14
    //   369: invokevirtual delete : (Ljava/lang/String;Ljava/lang/String;[Ljava/lang/String;)I
    //   372: iadd
    //   373: aload #12
    //   375: ldc_w 'raw_events'
    //   378: ldc_w 'app_id=?'
    //   381: aload #14
    //   383: invokevirtual delete : (Ljava/lang/String;Ljava/lang/String;[Ljava/lang/String;)I
    //   386: iadd
    //   387: aload #12
    //   389: ldc_w 'raw_events_metadata'
    //   392: ldc_w 'app_id=?'
    //   395: aload #14
    //   397: invokevirtual delete : (Ljava/lang/String;Ljava/lang/String;[Ljava/lang/String;)I
    //   400: iadd
    //   401: aload #12
    //   403: ldc_w 'event_filters'
    //   406: ldc_w 'app_id=?'
    //   409: aload #14
    //   411: invokevirtual delete : (Ljava/lang/String;Ljava/lang/String;[Ljava/lang/String;)I
    //   414: iadd
    //   415: aload #12
    //   417: ldc_w 'property_filters'
    //   420: ldc_w 'app_id=?'
    //   423: aload #14
    //   425: invokevirtual delete : (Ljava/lang/String;Ljava/lang/String;[Ljava/lang/String;)I
    //   428: iadd
    //   429: aload #12
    //   431: ldc_w 'audience_filter_values'
    //   434: ldc_w 'app_id=?'
    //   437: aload #14
    //   439: invokevirtual delete : (Ljava/lang/String;Ljava/lang/String;[Ljava/lang/String;)I
    //   442: iadd
    //   443: istore_3
    //   444: iload_3
    //   445: ifle -> 1420
    //   448: aload #10
    //   450: invokevirtual zzayp : ()Lcom/google/android/gms/internal/zzcjj;
    //   453: invokevirtual zzbba : ()Lcom/google/android/gms/internal/zzcjl;
    //   456: ldc_w 'Deleted application data. app, records'
    //   459: aload #11
    //   461: iload_3
    //   462: invokestatic valueOf : (I)Ljava/lang/Integer;
    //   465: invokevirtual zze : (Ljava/lang/String;Ljava/lang/Object;Ljava/lang/Object;)V
    //   468: goto -> 1420
    //   471: astore #12
    //   473: aload #10
    //   475: invokevirtual zzayp : ()Lcom/google/android/gms/internal/zzcjj;
    //   478: invokevirtual zzbau : ()Lcom/google/android/gms/internal/zzcjl;
    //   481: ldc_w 'Error deleting application data. appId, error'
    //   484: aload #11
    //   486: invokestatic zzjs : (Ljava/lang/String;)Ljava/lang/Object;
    //   489: aload #12
    //   491: invokevirtual zze : (Ljava/lang/String;Ljava/lang/Object;Ljava/lang/Object;)V
    //   494: goto -> 1420
    //   497: aload #10
    //   499: ifnull -> 659
    //   502: aload #10
    //   504: invokevirtual zzayx : ()J
    //   507: ldc2_w -2147483648
    //   510: lcmp
    //   511: ifeq -> 585
    //   514: aload #10
    //   516: invokevirtual zzayx : ()J
    //   519: aload_1
    //   520: getfield zzjfr : J
    //   523: lcmp
    //   524: ifeq -> 659
    //   527: new android/os/Bundle
    //   530: dup
    //   531: invokespecial <init> : ()V
    //   534: astore #11
    //   536: aload #11
    //   538: ldc_w '_pv'
    //   541: aload #10
    //   543: invokevirtual zzwo : ()Ljava/lang/String;
    //   546: invokevirtual putString : (Ljava/lang/String;Ljava/lang/String;)V
    //   549: new com/google/android/gms/internal/zzcix
    //   552: dup
    //   553: ldc_w '_au'
    //   556: new com/google/android/gms/internal/zzciu
    //   559: dup
    //   560: aload #11
    //   562: invokespecial <init> : (Landroid/os/Bundle;)V
    //   565: ldc_w 'auto'
    //   568: lload #4
    //   570: invokespecial <init> : (Ljava/lang/String;Lcom/google/android/gms/internal/zzciu;Ljava/lang/String;J)V
    //   573: astore #10
    //   575: aload_0
    //   576: aload #10
    //   578: aload_1
    //   579: invokevirtual zzb : (Lcom/google/android/gms/internal/zzcix;Lcom/google/android/gms/internal/zzcif;)V
    //   582: goto -> 659
    //   585: aload #10
    //   587: invokevirtual zzwo : ()Ljava/lang/String;
    //   590: ifnull -> 659
    //   593: aload #10
    //   595: invokevirtual zzwo : ()Ljava/lang/String;
    //   598: aload_1
    //   599: getfield zzina : Ljava/lang/String;
    //   602: invokevirtual equals : (Ljava/lang/Object;)Z
    //   605: ifne -> 659
    //   608: new android/os/Bundle
    //   611: dup
    //   612: invokespecial <init> : ()V
    //   615: astore #11
    //   617: aload #11
    //   619: ldc_w '_pv'
    //   622: aload #10
    //   624: invokevirtual zzwo : ()Ljava/lang/String;
    //   627: invokevirtual putString : (Ljava/lang/String;Ljava/lang/String;)V
    //   630: new com/google/android/gms/internal/zzcix
    //   633: dup
    //   634: ldc_w '_au'
    //   637: new com/google/android/gms/internal/zzciu
    //   640: dup
    //   641: aload #11
    //   643: invokespecial <init> : (Landroid/os/Bundle;)V
    //   646: ldc_w 'auto'
    //   649: lload #4
    //   651: invokespecial <init> : (Ljava/lang/String;Lcom/google/android/gms/internal/zzciu;Ljava/lang/String;J)V
    //   654: astore #10
    //   656: goto -> 575
    //   659: aload_0
    //   660: aload_1
    //   661: invokespecial zzg : (Lcom/google/android/gms/internal/zzcif;)V
    //   664: iload_2
    //   665: ifne -> 699
    //   668: aload_0
    //   669: invokevirtual zzayj : ()Lcom/google/android/gms/internal/zzcil;
    //   672: astore #10
    //   674: aload_1
    //   675: getfield packageName : Ljava/lang/String;
    //   678: astore #11
    //   680: ldc_w '_f'
    //   683: astore #12
    //   685: aload #10
    //   687: aload #11
    //   689: aload #12
    //   691: invokevirtual zzae : (Ljava/lang/String;Ljava/lang/String;)Lcom/google/android/gms/internal/zzcit;
    //   694: astore #10
    //   696: goto -> 724
    //   699: iload_2
    //   700: iconst_1
    //   701: if_icmpne -> 1426
    //   704: aload_0
    //   705: invokevirtual zzayj : ()Lcom/google/android/gms/internal/zzcil;
    //   708: astore #10
    //   710: aload_1
    //   711: getfield packageName : Ljava/lang/String;
    //   714: astore #11
    //   716: ldc_w '_v'
    //   719: astore #12
    //   721: goto -> 685
    //   724: aload #10
    //   726: ifnonnull -> 1354
    //   729: lload #4
    //   731: ldc2_w 3600000
    //   734: ldiv
    //   735: lconst_1
    //   736: ladd
    //   737: ldc2_w 3600000
    //   740: lmul
    //   741: lstore #6
    //   743: iload_2
    //   744: ifne -> 1198
    //   747: lconst_1
    //   748: lstore #8
    //   750: aload_0
    //   751: new com/google/android/gms/internal/zzcnl
    //   754: dup
    //   755: ldc_w '_fot'
    //   758: lload #4
    //   760: lload #6
    //   762: invokestatic valueOf : (J)Ljava/lang/Long;
    //   765: ldc_w 'auto'
    //   768: invokespecial <init> : (Ljava/lang/String;JLjava/lang/Object;Ljava/lang/String;)V
    //   771: aload_1
    //   772: invokevirtual zzb : (Lcom/google/android/gms/internal/zzcnl;Lcom/google/android/gms/internal/zzcif;)V
    //   775: aload_0
    //   776: invokevirtual zzayo : ()Lcom/google/android/gms/internal/zzcke;
    //   779: invokevirtual zzwj : ()V
    //   782: aload_0
    //   783: invokevirtual zzyk : ()V
    //   786: new android/os/Bundle
    //   789: dup
    //   790: invokespecial <init> : ()V
    //   793: astore #11
    //   795: aload #11
    //   797: ldc_w '_c'
    //   800: lload #8
    //   802: invokevirtual putLong : (Ljava/lang/String;J)V
    //   805: aload #11
    //   807: ldc_w '_r'
    //   810: lload #8
    //   812: invokevirtual putLong : (Ljava/lang/String;J)V
    //   815: aload #11
    //   817: ldc_w '_uwa'
    //   820: lconst_0
    //   821: invokevirtual putLong : (Ljava/lang/String;J)V
    //   824: aload #11
    //   826: ldc_w '_pfo'
    //   829: lconst_0
    //   830: invokevirtual putLong : (Ljava/lang/String;J)V
    //   833: aload #11
    //   835: ldc_w '_sys'
    //   838: lconst_0
    //   839: invokevirtual putLong : (Ljava/lang/String;J)V
    //   842: aload #11
    //   844: ldc_w '_sysu'
    //   847: lconst_0
    //   848: invokevirtual putLong : (Ljava/lang/String;J)V
    //   851: aload_0
    //   852: getfield zzaiq : Landroid/content/Context;
    //   855: invokevirtual getPackageManager : ()Landroid/content/pm/PackageManager;
    //   858: ifnonnull -> 884
    //   861: aload_0
    //   862: invokevirtual zzayp : ()Lcom/google/android/gms/internal/zzcjj;
    //   865: invokevirtual zzbau : ()Lcom/google/android/gms/internal/zzcjl;
    //   868: ldc_w 'PackageManager is null, first open report might be inaccurate. appId'
    //   871: aload_1
    //   872: getfield packageName : Ljava/lang/String;
    //   875: invokestatic zzjs : (Ljava/lang/String;)Ljava/lang/Object;
    //   878: invokevirtual zzj : (Ljava/lang/String;Ljava/lang/Object;)V
    //   881: goto -> 1109
    //   884: aload_0
    //   885: getfield zzaiq : Landroid/content/Context;
    //   888: invokestatic zzdd : (Landroid/content/Context;)Lcom/google/android/gms/internal/zzbig;
    //   891: aload_1
    //   892: getfield packageName : Ljava/lang/String;
    //   895: iconst_0
    //   896: invokevirtual getPackageInfo : (Ljava/lang/String;I)Landroid/content/pm/PackageInfo;
    //   899: astore #10
    //   901: goto -> 931
    //   904: astore #10
    //   906: aload_0
    //   907: invokevirtual zzayp : ()Lcom/google/android/gms/internal/zzcjj;
    //   910: invokevirtual zzbau : ()Lcom/google/android/gms/internal/zzcjl;
    //   913: ldc_w 'Package info is null, first open report might be inaccurate. appId'
    //   916: aload_1
    //   917: getfield packageName : Ljava/lang/String;
    //   920: invokestatic zzjs : (Ljava/lang/String;)Ljava/lang/Object;
    //   923: aload #10
    //   925: invokevirtual zze : (Ljava/lang/String;Ljava/lang/Object;Ljava/lang/Object;)V
    //   928: aconst_null
    //   929: astore #10
    //   931: aload #10
    //   933: ifnull -> 1011
    //   936: aload #10
    //   938: getfield firstInstallTime : J
    //   941: lconst_0
    //   942: lcmp
    //   943: ifeq -> 1011
    //   946: aload #10
    //   948: getfield firstInstallTime : J
    //   951: aload #10
    //   953: getfield lastUpdateTime : J
    //   956: lcmp
    //   957: ifeq -> 1432
    //   960: aload #11
    //   962: ldc_w '_uwa'
    //   965: lload #8
    //   967: invokevirtual putLong : (Ljava/lang/String;J)V
    //   970: iconst_0
    //   971: istore_2
    //   972: goto -> 975
    //   975: iload_2
    //   976: ifeq -> 1437
    //   979: lload #8
    //   981: lstore #6
    //   983: goto -> 986
    //   986: aload_0
    //   987: new com/google/android/gms/internal/zzcnl
    //   990: dup
    //   991: ldc_w '_fi'
    //   994: lload #4
    //   996: lload #6
    //   998: invokestatic valueOf : (J)Ljava/lang/Long;
    //   1001: ldc_w 'auto'
    //   1004: invokespecial <init> : (Ljava/lang/String;JLjava/lang/Object;Ljava/lang/String;)V
    //   1007: aload_1
    //   1008: invokevirtual zzb : (Lcom/google/android/gms/internal/zzcnl;Lcom/google/android/gms/internal/zzcif;)V
    //   1011: aload_0
    //   1012: getfield zzaiq : Landroid/content/Context;
    //   1015: invokestatic zzdd : (Landroid/content/Context;)Lcom/google/android/gms/internal/zzbig;
    //   1018: aload_1
    //   1019: getfield packageName : Ljava/lang/String;
    //   1022: iconst_0
    //   1023: invokevirtual getApplicationInfo : (Ljava/lang/String;I)Landroid/content/pm/ApplicationInfo;
    //   1026: astore #10
    //   1028: goto -> 1062
    //   1031: astore #10
    //   1033: aload_0
    //   1034: invokevirtual zzayp : ()Lcom/google/android/gms/internal/zzcjj;
    //   1037: invokevirtual zzbau : ()Lcom/google/android/gms/internal/zzcjl;
    //   1040: ldc_w 'Application info is null, first open report might be inaccurate. appId'
    //   1043: aload_1
    //   1044: getfield packageName : Ljava/lang/String;
    //   1047: invokestatic zzjs : (Ljava/lang/String;)Ljava/lang/Object;
    //   1050: aload #10
    //   1052: invokevirtual zze : (Ljava/lang/String;Ljava/lang/Object;Ljava/lang/Object;)V
    //   1055: aload #13
    //   1057: astore #10
    //   1059: goto -> 1028
    //   1062: aload #10
    //   1064: ifnull -> 1109
    //   1067: aload #10
    //   1069: getfield flags : I
    //   1072: iconst_1
    //   1073: iand
    //   1074: ifeq -> 1087
    //   1077: aload #11
    //   1079: ldc_w '_sys'
    //   1082: lload #8
    //   1084: invokevirtual putLong : (Ljava/lang/String;J)V
    //   1087: aload #10
    //   1089: getfield flags : I
    //   1092: sipush #128
    //   1095: iand
    //   1096: ifeq -> 1109
    //   1099: aload #11
    //   1101: ldc_w '_sysu'
    //   1104: lload #8
    //   1106: invokevirtual putLong : (Ljava/lang/String;J)V
    //   1109: aload_0
    //   1110: invokevirtual zzayj : ()Lcom/google/android/gms/internal/zzcil;
    //   1113: astore #10
    //   1115: aload_1
    //   1116: getfield packageName : Ljava/lang/String;
    //   1119: astore #12
    //   1121: aload #12
    //   1123: invokestatic zzgv : (Ljava/lang/String;)Ljava/lang/String;
    //   1126: pop
    //   1127: aload #10
    //   1129: invokevirtual zzwj : ()V
    //   1132: aload #10
    //   1134: invokevirtual zzyk : ()V
    //   1137: aload #10
    //   1139: aload #12
    //   1141: ldc_w 'first_open_count'
    //   1144: invokevirtual zzal : (Ljava/lang/String;Ljava/lang/String;)J
    //   1147: lstore #6
    //   1149: lload #6
    //   1151: lconst_0
    //   1152: lcmp
    //   1153: iflt -> 1166
    //   1156: aload #11
    //   1158: ldc_w '_pfo'
    //   1161: lload #6
    //   1163: invokevirtual putLong : (Ljava/lang/String;J)V
    //   1166: aload_0
    //   1167: new com/google/android/gms/internal/zzcix
    //   1170: dup
    //   1171: ldc_w '_f'
    //   1174: new com/google/android/gms/internal/zzciu
    //   1177: dup
    //   1178: aload #11
    //   1180: invokespecial <init> : (Landroid/os/Bundle;)V
    //   1183: ldc_w 'auto'
    //   1186: lload #4
    //   1188: invokespecial <init> : (Ljava/lang/String;Lcom/google/android/gms/internal/zzciu;Ljava/lang/String;J)V
    //   1191: aload_1
    //   1192: invokevirtual zzb : (Lcom/google/android/gms/internal/zzcix;Lcom/google/android/gms/internal/zzcif;)V
    //   1195: goto -> 1300
    //   1198: lconst_1
    //   1199: lstore #8
    //   1201: iload_2
    //   1202: iconst_1
    //   1203: if_icmpne -> 1300
    //   1206: aload_0
    //   1207: new com/google/android/gms/internal/zzcnl
    //   1210: dup
    //   1211: ldc_w '_fvt'
    //   1214: lload #4
    //   1216: lload #6
    //   1218: invokestatic valueOf : (J)Ljava/lang/Long;
    //   1221: ldc_w 'auto'
    //   1224: invokespecial <init> : (Ljava/lang/String;JLjava/lang/Object;Ljava/lang/String;)V
    //   1227: aload_1
    //   1228: invokevirtual zzb : (Lcom/google/android/gms/internal/zzcnl;Lcom/google/android/gms/internal/zzcif;)V
    //   1231: aload_0
    //   1232: invokevirtual zzayo : ()Lcom/google/android/gms/internal/zzcke;
    //   1235: invokevirtual zzwj : ()V
    //   1238: aload_0
    //   1239: invokevirtual zzyk : ()V
    //   1242: new android/os/Bundle
    //   1245: dup
    //   1246: invokespecial <init> : ()V
    //   1249: astore #10
    //   1251: aload #10
    //   1253: ldc_w '_c'
    //   1256: lload #8
    //   1258: invokevirtual putLong : (Ljava/lang/String;J)V
    //   1261: aload #10
    //   1263: ldc_w '_r'
    //   1266: lload #8
    //   1268: invokevirtual putLong : (Ljava/lang/String;J)V
    //   1271: aload_0
    //   1272: new com/google/android/gms/internal/zzcix
    //   1275: dup
    //   1276: ldc_w '_v'
    //   1279: new com/google/android/gms/internal/zzciu
    //   1282: dup
    //   1283: aload #10
    //   1285: invokespecial <init> : (Landroid/os/Bundle;)V
    //   1288: ldc_w 'auto'
    //   1291: lload #4
    //   1293: invokespecial <init> : (Ljava/lang/String;Lcom/google/android/gms/internal/zzciu;Ljava/lang/String;J)V
    //   1296: aload_1
    //   1297: invokevirtual zzb : (Lcom/google/android/gms/internal/zzcix;Lcom/google/android/gms/internal/zzcif;)V
    //   1300: new android/os/Bundle
    //   1303: dup
    //   1304: invokespecial <init> : ()V
    //   1307: astore #10
    //   1309: aload #10
    //   1311: ldc_w '_et'
    //   1314: lconst_1
    //   1315: invokevirtual putLong : (Ljava/lang/String;J)V
    //   1318: new com/google/android/gms/internal/zzcix
    //   1321: dup
    //   1322: ldc_w '_e'
    //   1325: new com/google/android/gms/internal/zzciu
    //   1328: dup
    //   1329: aload #10
    //   1331: invokespecial <init> : (Landroid/os/Bundle;)V
    //   1334: ldc_w 'auto'
    //   1337: lload #4
    //   1339: invokespecial <init> : (Ljava/lang/String;Lcom/google/android/gms/internal/zzciu;Ljava/lang/String;J)V
    //   1342: astore #10
    //   1344: aload_0
    //   1345: aload #10
    //   1347: aload_1
    //   1348: invokevirtual zzb : (Lcom/google/android/gms/internal/zzcix;Lcom/google/android/gms/internal/zzcif;)V
    //   1351: goto -> 1395
    //   1354: aload_1
    //   1355: getfield zzjgj : Z
    //   1358: ifeq -> 1395
    //   1361: new com/google/android/gms/internal/zzcix
    //   1364: dup
    //   1365: ldc_w '_cd'
    //   1368: new com/google/android/gms/internal/zzciu
    //   1371: dup
    //   1372: new android/os/Bundle
    //   1375: dup
    //   1376: invokespecial <init> : ()V
    //   1379: invokespecial <init> : (Landroid/os/Bundle;)V
    //   1382: ldc_w 'auto'
    //   1385: lload #4
    //   1387: invokespecial <init> : (Ljava/lang/String;Lcom/google/android/gms/internal/zzciu;Ljava/lang/String;J)V
    //   1390: astore #10
    //   1392: goto -> 1344
    //   1395: aload_0
    //   1396: invokevirtual zzayj : ()Lcom/google/android/gms/internal/zzcil;
    //   1399: invokevirtual setTransactionSuccessful : ()V
    //   1402: aload_0
    //   1403: invokevirtual zzayj : ()Lcom/google/android/gms/internal/zzcil;
    //   1406: invokevirtual endTransaction : ()V
    //   1409: return
    //   1410: astore_1
    //   1411: aload_0
    //   1412: invokevirtual zzayj : ()Lcom/google/android/gms/internal/zzcil;
    //   1415: invokevirtual endTransaction : ()V
    //   1418: aload_1
    //   1419: athrow
    //   1420: aconst_null
    //   1421: astore #10
    //   1423: goto -> 497
    //   1426: aconst_null
    //   1427: astore #10
    //   1429: goto -> 724
    //   1432: iconst_1
    //   1433: istore_2
    //   1434: goto -> 975
    //   1437: lconst_0
    //   1438: lstore #6
    //   1440: goto -> 986
    // Exception table:
    //   from	to	target	type
    //   191	204	1410	finally
    //   220	228	1410	finally
    //   232	297	1410	finally
    //   297	310	471	android/database/sqlite/SQLiteException
    //   297	310	1410	finally
    //   316	444	471	android/database/sqlite/SQLiteException
    //   316	444	1410	finally
    //   448	468	471	android/database/sqlite/SQLiteException
    //   448	468	1410	finally
    //   473	494	1410	finally
    //   502	575	1410	finally
    //   575	582	1410	finally
    //   585	656	1410	finally
    //   659	664	1410	finally
    //   668	680	1410	finally
    //   685	696	1410	finally
    //   704	716	1410	finally
    //   729	743	1410	finally
    //   750	881	1410	finally
    //   884	901	904	android/content/pm/PackageManager$NameNotFoundException
    //   884	901	1410	finally
    //   906	928	1410	finally
    //   936	970	1410	finally
    //   986	1011	1410	finally
    //   1011	1028	1031	android/content/pm/PackageManager$NameNotFoundException
    //   1011	1028	1410	finally
    //   1033	1055	1410	finally
    //   1067	1087	1410	finally
    //   1087	1109	1410	finally
    //   1109	1149	1410	finally
    //   1156	1166	1410	finally
    //   1166	1195	1410	finally
    //   1206	1300	1410	finally
    //   1300	1344	1410	finally
    //   1344	1351	1410	finally
    //   1354	1392	1410	finally
    //   1395	1402	1410	finally
  }
  
  final void zzj(Runnable paramRunnable) {
    zzayo().zzwj();
    if (this.zzjou == null)
      this.zzjou = new ArrayList<Runnable>(); 
    this.zzjou.add(paramRunnable);
  }
  
  public final String zzkf(String paramString) {
    Future<?> future = zzayo().zzc(new zzckl(this, paramString));
    try {
      return (String)future.get(30000L, TimeUnit.MILLISECONDS);
    } catch (TimeoutException timeoutException) {
    
    } catch (InterruptedException interruptedException) {
    
    } catch (ExecutionException executionException) {}
    zzayp().zzbau().zze("Failed to get app instance id. appId", zzcjj.zzjs(paramString), executionException);
    return null;
  }
  
  public final zze zzxx() {
    return this.zzdir;
  }
  
  final void zzyk() {
    if (this.initialized)
      return; 
    throw new IllegalStateException("AppMeasurement is not initialized");
  }
  
  final class zza implements zzcin {
    List<zzcob> zzaoz;
    
    zzcoe zzjpe;
    
    List<Long> zzjpf;
    
    private long zzjpg;
    
    private zza(zzckj this$0) {}
    
    private static long zza(zzcob param1zzcob) {
      return param1zzcob.zzjuj.longValue() / 1000L / 60L / 60L;
    }
    
    public final boolean zza(long param1Long, zzcob param1zzcob) {
      zzbq.checkNotNull(param1zzcob);
      if (this.zzaoz == null)
        this.zzaoz = new ArrayList<zzcob>(); 
      if (this.zzjpf == null)
        this.zzjpf = new ArrayList<Long>(); 
      if (this.zzaoz.size() > 0 && zza(this.zzaoz.get(0)) != zza(param1zzcob))
        return false; 
      long l = this.zzjpg + param1zzcob.zzhs();
      if (l >= Math.max(0, ((Integer)zzciz.zzjiv.get()).intValue()))
        return false; 
      this.zzjpg = l;
      this.zzaoz.add(param1zzcob);
      this.zzjpf.add(Long.valueOf(param1Long));
      return !(this.zzaoz.size() >= Math.max(1, ((Integer)zzciz.zzjiw.get()).intValue()));
    }
    
    public final void zzb(zzcoe param1zzcoe) {
      zzbq.checkNotNull(param1zzcoe);
      this.zzjpe = param1zzcoe;
    }
  }
}


/* Location:              /home/egaebel/Programs/sony-headphones-hack/base-dex2jar.jar!/com/google/android/gms/internal/zzckj.class
 * Java compiler version: 6 (50.0)
 * JD-Core Version:       1.1.3
 */