package com.google.android.gms.internal;

import java.util.concurrent.atomic.AtomicReference;

final class zzcmo implements Runnable {
  zzcmo(zzcme paramzzcme, AtomicReference paramAtomicReference, String paramString1, String paramString2, String paramString3, zzcif paramzzcif) {}
  
  public final void run() {
    // Byte code:
    //   0: aload_0
    //   1: getfield zzjrj : Ljava/util/concurrent/atomic/AtomicReference;
    //   4: astore_3
    //   5: aload_3
    //   6: monitorenter
    //   7: aload_0
    //   8: getfield zzjri : Lcom/google/android/gms/internal/zzcme;
    //   11: invokestatic zzd : (Lcom/google/android/gms/internal/zzcme;)Lcom/google/android/gms/internal/zzcjb;
    //   14: astore_1
    //   15: aload_1
    //   16: ifnonnull -> 69
    //   19: aload_0
    //   20: getfield zzjri : Lcom/google/android/gms/internal/zzcme;
    //   23: invokevirtual zzayp : ()Lcom/google/android/gms/internal/zzcjj;
    //   26: invokevirtual zzbau : ()Lcom/google/android/gms/internal/zzcjl;
    //   29: ldc 'Failed to get conditional properties'
    //   31: aload_0
    //   32: getfield zziuw : Ljava/lang/String;
    //   35: invokestatic zzjs : (Ljava/lang/String;)Ljava/lang/Object;
    //   38: aload_0
    //   39: getfield zzjpm : Ljava/lang/String;
    //   42: aload_0
    //   43: getfield zzjpn : Ljava/lang/String;
    //   46: invokevirtual zzd : (Ljava/lang/String;Ljava/lang/Object;Ljava/lang/Object;Ljava/lang/Object;)V
    //   49: aload_0
    //   50: getfield zzjrj : Ljava/util/concurrent/atomic/AtomicReference;
    //   53: invokestatic emptyList : ()Ljava/util/List;
    //   56: invokevirtual set : (Ljava/lang/Object;)V
    //   59: aload_0
    //   60: getfield zzjrj : Ljava/util/concurrent/atomic/AtomicReference;
    //   63: invokevirtual notify : ()V
    //   66: aload_3
    //   67: monitorexit
    //   68: return
    //   69: aload_0
    //   70: getfield zziuw : Ljava/lang/String;
    //   73: invokestatic isEmpty : (Ljava/lang/CharSequence;)Z
    //   76: ifeq -> 111
    //   79: aload_0
    //   80: getfield zzjrj : Ljava/util/concurrent/atomic/AtomicReference;
    //   83: astore_2
    //   84: aload_1
    //   85: aload_0
    //   86: getfield zzjpm : Ljava/lang/String;
    //   89: aload_0
    //   90: getfield zzjpn : Ljava/lang/String;
    //   93: aload_0
    //   94: getfield zzjpj : Lcom/google/android/gms/internal/zzcif;
    //   97: invokeinterface zza : (Ljava/lang/String;Ljava/lang/String;Lcom/google/android/gms/internal/zzcif;)Ljava/util/List;
    //   102: astore_1
    //   103: aload_2
    //   104: aload_1
    //   105: invokevirtual set : (Ljava/lang/Object;)V
    //   108: goto -> 138
    //   111: aload_0
    //   112: getfield zzjrj : Ljava/util/concurrent/atomic/AtomicReference;
    //   115: astore_2
    //   116: aload_1
    //   117: aload_0
    //   118: getfield zziuw : Ljava/lang/String;
    //   121: aload_0
    //   122: getfield zzjpm : Ljava/lang/String;
    //   125: aload_0
    //   126: getfield zzjpn : Ljava/lang/String;
    //   129: invokeinterface zzk : (Ljava/lang/String;Ljava/lang/String;Ljava/lang/String;)Ljava/util/List;
    //   134: astore_1
    //   135: goto -> 103
    //   138: aload_0
    //   139: getfield zzjri : Lcom/google/android/gms/internal/zzcme;
    //   142: invokestatic zze : (Lcom/google/android/gms/internal/zzcme;)V
    //   145: aload_0
    //   146: getfield zzjrj : Ljava/util/concurrent/atomic/AtomicReference;
    //   149: astore_1
    //   150: aload_1
    //   151: invokevirtual notify : ()V
    //   154: goto -> 207
    //   157: astore_1
    //   158: goto -> 210
    //   161: astore_1
    //   162: aload_0
    //   163: getfield zzjri : Lcom/google/android/gms/internal/zzcme;
    //   166: invokevirtual zzayp : ()Lcom/google/android/gms/internal/zzcjj;
    //   169: invokevirtual zzbau : ()Lcom/google/android/gms/internal/zzcjl;
    //   172: ldc 'Failed to get conditional properties'
    //   174: aload_0
    //   175: getfield zziuw : Ljava/lang/String;
    //   178: invokestatic zzjs : (Ljava/lang/String;)Ljava/lang/Object;
    //   181: aload_0
    //   182: getfield zzjpm : Ljava/lang/String;
    //   185: aload_1
    //   186: invokevirtual zzd : (Ljava/lang/String;Ljava/lang/Object;Ljava/lang/Object;Ljava/lang/Object;)V
    //   189: aload_0
    //   190: getfield zzjrj : Ljava/util/concurrent/atomic/AtomicReference;
    //   193: invokestatic emptyList : ()Ljava/util/List;
    //   196: invokevirtual set : (Ljava/lang/Object;)V
    //   199: aload_0
    //   200: getfield zzjrj : Ljava/util/concurrent/atomic/AtomicReference;
    //   203: astore_1
    //   204: goto -> 150
    //   207: aload_3
    //   208: monitorexit
    //   209: return
    //   210: aload_0
    //   211: getfield zzjrj : Ljava/util/concurrent/atomic/AtomicReference;
    //   214: invokevirtual notify : ()V
    //   217: aload_1
    //   218: athrow
    //   219: astore_1
    //   220: aload_3
    //   221: monitorexit
    //   222: aload_1
    //   223: athrow
    // Exception table:
    //   from	to	target	type
    //   7	15	161	android/os/RemoteException
    //   7	15	157	finally
    //   19	59	161	android/os/RemoteException
    //   19	59	157	finally
    //   59	68	219	finally
    //   69	103	161	android/os/RemoteException
    //   69	103	157	finally
    //   103	108	161	android/os/RemoteException
    //   103	108	157	finally
    //   111	135	161	android/os/RemoteException
    //   111	135	157	finally
    //   138	145	161	android/os/RemoteException
    //   138	145	157	finally
    //   145	150	219	finally
    //   150	154	219	finally
    //   162	199	157	finally
    //   199	204	219	finally
    //   207	209	219	finally
    //   210	219	219	finally
    //   220	222	219	finally
  }
}


/* Location:              /home/egaebel/Programs/sony-headphones-hack/base-dex2jar.jar!/com/google/android/gms/internal/zzcmo.class
 * Java compiler version: 6 (50.0)
 * JD-Core Version:       1.1.3
 */