package com.google.android.gms.internal;

import java.util.concurrent.atomic.AtomicReference;

final class zzcmr implements Runnable {
  zzcmr(zzcme paramzzcme, AtomicReference paramAtomicReference, zzcif paramzzcif, boolean paramBoolean) {}
  
  public final void run() {
    // Byte code:
    //   0: aload_0
    //   1: getfield zzjrj : Ljava/util/concurrent/atomic/AtomicReference;
    //   4: astore_2
    //   5: aload_2
    //   6: monitorenter
    //   7: aload_0
    //   8: getfield zzjri : Lcom/google/android/gms/internal/zzcme;
    //   11: invokestatic zzd : (Lcom/google/android/gms/internal/zzcme;)Lcom/google/android/gms/internal/zzcjb;
    //   14: astore_1
    //   15: aload_1
    //   16: ifnonnull -> 44
    //   19: aload_0
    //   20: getfield zzjri : Lcom/google/android/gms/internal/zzcme;
    //   23: invokevirtual zzayp : ()Lcom/google/android/gms/internal/zzcjj;
    //   26: invokevirtual zzbau : ()Lcom/google/android/gms/internal/zzcjl;
    //   29: ldc 'Failed to get user properties'
    //   31: invokevirtual log : (Ljava/lang/String;)V
    //   34: aload_0
    //   35: getfield zzjrj : Ljava/util/concurrent/atomic/AtomicReference;
    //   38: invokevirtual notify : ()V
    //   41: aload_2
    //   42: monitorexit
    //   43: return
    //   44: aload_0
    //   45: getfield zzjrj : Ljava/util/concurrent/atomic/AtomicReference;
    //   48: aload_1
    //   49: aload_0
    //   50: getfield zzjpj : Lcom/google/android/gms/internal/zzcif;
    //   53: aload_0
    //   54: getfield zzjqb : Z
    //   57: invokeinterface zza : (Lcom/google/android/gms/internal/zzcif;Z)Ljava/util/List;
    //   62: invokevirtual set : (Ljava/lang/Object;)V
    //   65: aload_0
    //   66: getfield zzjri : Lcom/google/android/gms/internal/zzcme;
    //   69: invokestatic zze : (Lcom/google/android/gms/internal/zzcme;)V
    //   72: aload_0
    //   73: getfield zzjrj : Ljava/util/concurrent/atomic/AtomicReference;
    //   76: astore_1
    //   77: aload_1
    //   78: invokevirtual notify : ()V
    //   81: goto -> 113
    //   84: astore_1
    //   85: goto -> 116
    //   88: astore_1
    //   89: aload_0
    //   90: getfield zzjri : Lcom/google/android/gms/internal/zzcme;
    //   93: invokevirtual zzayp : ()Lcom/google/android/gms/internal/zzcjj;
    //   96: invokevirtual zzbau : ()Lcom/google/android/gms/internal/zzcjl;
    //   99: ldc 'Failed to get user properties'
    //   101: aload_1
    //   102: invokevirtual zzj : (Ljava/lang/String;Ljava/lang/Object;)V
    //   105: aload_0
    //   106: getfield zzjrj : Ljava/util/concurrent/atomic/AtomicReference;
    //   109: astore_1
    //   110: goto -> 77
    //   113: aload_2
    //   114: monitorexit
    //   115: return
    //   116: aload_0
    //   117: getfield zzjrj : Ljava/util/concurrent/atomic/AtomicReference;
    //   120: invokevirtual notify : ()V
    //   123: aload_1
    //   124: athrow
    //   125: astore_1
    //   126: aload_2
    //   127: monitorexit
    //   128: aload_1
    //   129: athrow
    // Exception table:
    //   from	to	target	type
    //   7	15	88	android/os/RemoteException
    //   7	15	84	finally
    //   19	34	88	android/os/RemoteException
    //   19	34	84	finally
    //   34	43	125	finally
    //   44	72	88	android/os/RemoteException
    //   44	72	84	finally
    //   72	77	125	finally
    //   77	81	125	finally
    //   89	105	84	finally
    //   105	110	125	finally
    //   113	115	125	finally
    //   116	125	125	finally
    //   126	128	125	finally
  }
}


/* Location:              /home/egaebel/Programs/sony-headphones-hack/base-dex2jar.jar!/com/google/android/gms/internal/zzcmr.class
 * Java compiler version: 6 (50.0)
 * JD-Core Version:       1.1.3
 */