package com.google.android.gms.internal;

import java.util.concurrent.atomic.AtomicReference;

final class zzcmh implements Runnable {
  zzcmh(zzcme paramzzcme, AtomicReference paramAtomicReference, zzcif paramzzcif) {}
  
  public final void run() {
    // Byte code:
    //   0: aload_0
    //   1: getfield zzjrj : Ljava/util/concurrent/atomic/AtomicReference;
    //   4: astore_2
    //   5: aload_2
    //   6: monitorenter
    //   7: aload_0
    //   8: getfield zzjri : Lcom/google/android/gms/internal/zzcme;
    //   11: invokestatic zzd : (Lcom/google/android/gms/internal/zzcme;)Lcom/google/android/gms/internal/zzcjb;
    //   14: astore_1
    //   15: aload_1
    //   16: ifnonnull -> 44
    //   19: aload_0
    //   20: getfield zzjri : Lcom/google/android/gms/internal/zzcme;
    //   23: invokevirtual zzayp : ()Lcom/google/android/gms/internal/zzcjj;
    //   26: invokevirtual zzbau : ()Lcom/google/android/gms/internal/zzcjl;
    //   29: ldc 'Failed to get app instance id'
    //   31: invokevirtual log : (Ljava/lang/String;)V
    //   34: aload_0
    //   35: getfield zzjrj : Ljava/util/concurrent/atomic/AtomicReference;
    //   38: invokevirtual notify : ()V
    //   41: aload_2
    //   42: monitorexit
    //   43: return
    //   44: aload_0
    //   45: getfield zzjrj : Ljava/util/concurrent/atomic/AtomicReference;
    //   48: aload_1
    //   49: aload_0
    //   50: getfield zzjpj : Lcom/google/android/gms/internal/zzcif;
    //   53: invokeinterface zzc : (Lcom/google/android/gms/internal/zzcif;)Ljava/lang/String;
    //   58: invokevirtual set : (Ljava/lang/Object;)V
    //   61: aload_0
    //   62: getfield zzjrj : Ljava/util/concurrent/atomic/AtomicReference;
    //   65: invokevirtual get : ()Ljava/lang/Object;
    //   68: checkcast java/lang/String
    //   71: astore_1
    //   72: aload_1
    //   73: ifnull -> 101
    //   76: aload_0
    //   77: getfield zzjri : Lcom/google/android/gms/internal/zzcme;
    //   80: invokevirtual zzayd : ()Lcom/google/android/gms/internal/zzclk;
    //   83: aload_1
    //   84: invokevirtual zzjx : (Ljava/lang/String;)V
    //   87: aload_0
    //   88: getfield zzjri : Lcom/google/android/gms/internal/zzcme;
    //   91: invokevirtual zzayq : ()Lcom/google/android/gms/internal/zzcju;
    //   94: getfield zzjlt : Lcom/google/android/gms/internal/zzcjz;
    //   97: aload_1
    //   98: invokevirtual zzjy : (Ljava/lang/String;)V
    //   101: aload_0
    //   102: getfield zzjri : Lcom/google/android/gms/internal/zzcme;
    //   105: invokestatic zze : (Lcom/google/android/gms/internal/zzcme;)V
    //   108: aload_0
    //   109: getfield zzjrj : Ljava/util/concurrent/atomic/AtomicReference;
    //   112: astore_1
    //   113: aload_1
    //   114: invokevirtual notify : ()V
    //   117: goto -> 149
    //   120: astore_1
    //   121: goto -> 152
    //   124: astore_1
    //   125: aload_0
    //   126: getfield zzjri : Lcom/google/android/gms/internal/zzcme;
    //   129: invokevirtual zzayp : ()Lcom/google/android/gms/internal/zzcjj;
    //   132: invokevirtual zzbau : ()Lcom/google/android/gms/internal/zzcjl;
    //   135: ldc 'Failed to get app instance id'
    //   137: aload_1
    //   138: invokevirtual zzj : (Ljava/lang/String;Ljava/lang/Object;)V
    //   141: aload_0
    //   142: getfield zzjrj : Ljava/util/concurrent/atomic/AtomicReference;
    //   145: astore_1
    //   146: goto -> 113
    //   149: aload_2
    //   150: monitorexit
    //   151: return
    //   152: aload_0
    //   153: getfield zzjrj : Ljava/util/concurrent/atomic/AtomicReference;
    //   156: invokevirtual notify : ()V
    //   159: aload_1
    //   160: athrow
    //   161: astore_1
    //   162: aload_2
    //   163: monitorexit
    //   164: aload_1
    //   165: athrow
    // Exception table:
    //   from	to	target	type
    //   7	15	124	android/os/RemoteException
    //   7	15	120	finally
    //   19	34	124	android/os/RemoteException
    //   19	34	120	finally
    //   34	43	161	finally
    //   44	72	124	android/os/RemoteException
    //   44	72	120	finally
    //   76	101	124	android/os/RemoteException
    //   76	101	120	finally
    //   101	108	124	android/os/RemoteException
    //   101	108	120	finally
    //   108	113	161	finally
    //   113	117	161	finally
    //   125	141	120	finally
    //   141	146	161	finally
    //   149	151	161	finally
    //   152	161	161	finally
    //   162	164	161	finally
  }
}


/* Location:              /home/egaebel/Programs/sony-headphones-hack/base-dex2jar.jar!/com/google/android/gms/internal/zzcmh.class
 * Java compiler version: 6 (50.0)
 * JD-Core Version:       1.1.3
 */