package com.google.android.gms.internal;

import java.util.concurrent.atomic.AtomicReference;

final class zzcmp implements Runnable {
  zzcmp(zzcme paramzzcme, AtomicReference paramAtomicReference, String paramString1, String paramString2, String paramString3, boolean paramBoolean, zzcif paramzzcif) {}
  
  public final void run() {
    // Byte code:
    //   0: aload_0
    //   1: getfield zzjrj : Ljava/util/concurrent/atomic/AtomicReference;
    //   4: astore_3
    //   5: aload_3
    //   6: monitorenter
    //   7: aload_0
    //   8: getfield zzjri : Lcom/google/android/gms/internal/zzcme;
    //   11: invokestatic zzd : (Lcom/google/android/gms/internal/zzcme;)Lcom/google/android/gms/internal/zzcjb;
    //   14: astore_1
    //   15: aload_1
    //   16: ifnonnull -> 69
    //   19: aload_0
    //   20: getfield zzjri : Lcom/google/android/gms/internal/zzcme;
    //   23: invokevirtual zzayp : ()Lcom/google/android/gms/internal/zzcjj;
    //   26: invokevirtual zzbau : ()Lcom/google/android/gms/internal/zzcjl;
    //   29: ldc 'Failed to get user properties'
    //   31: aload_0
    //   32: getfield zziuw : Ljava/lang/String;
    //   35: invokestatic zzjs : (Ljava/lang/String;)Ljava/lang/Object;
    //   38: aload_0
    //   39: getfield zzjpm : Ljava/lang/String;
    //   42: aload_0
    //   43: getfield zzjpn : Ljava/lang/String;
    //   46: invokevirtual zzd : (Ljava/lang/String;Ljava/lang/Object;Ljava/lang/Object;Ljava/lang/Object;)V
    //   49: aload_0
    //   50: getfield zzjrj : Ljava/util/concurrent/atomic/AtomicReference;
    //   53: invokestatic emptyList : ()Ljava/util/List;
    //   56: invokevirtual set : (Ljava/lang/Object;)V
    //   59: aload_0
    //   60: getfield zzjrj : Ljava/util/concurrent/atomic/AtomicReference;
    //   63: invokevirtual notify : ()V
    //   66: aload_3
    //   67: monitorexit
    //   68: return
    //   69: aload_0
    //   70: getfield zziuw : Ljava/lang/String;
    //   73: invokestatic isEmpty : (Ljava/lang/CharSequence;)Z
    //   76: ifeq -> 115
    //   79: aload_0
    //   80: getfield zzjrj : Ljava/util/concurrent/atomic/AtomicReference;
    //   83: astore_2
    //   84: aload_1
    //   85: aload_0
    //   86: getfield zzjpm : Ljava/lang/String;
    //   89: aload_0
    //   90: getfield zzjpn : Ljava/lang/String;
    //   93: aload_0
    //   94: getfield zzjqb : Z
    //   97: aload_0
    //   98: getfield zzjpj : Lcom/google/android/gms/internal/zzcif;
    //   101: invokeinterface zza : (Ljava/lang/String;Ljava/lang/String;ZLcom/google/android/gms/internal/zzcif;)Ljava/util/List;
    //   106: astore_1
    //   107: aload_2
    //   108: aload_1
    //   109: invokevirtual set : (Ljava/lang/Object;)V
    //   112: goto -> 146
    //   115: aload_0
    //   116: getfield zzjrj : Ljava/util/concurrent/atomic/AtomicReference;
    //   119: astore_2
    //   120: aload_1
    //   121: aload_0
    //   122: getfield zziuw : Ljava/lang/String;
    //   125: aload_0
    //   126: getfield zzjpm : Ljava/lang/String;
    //   129: aload_0
    //   130: getfield zzjpn : Ljava/lang/String;
    //   133: aload_0
    //   134: getfield zzjqb : Z
    //   137: invokeinterface zza : (Ljava/lang/String;Ljava/lang/String;Ljava/lang/String;Z)Ljava/util/List;
    //   142: astore_1
    //   143: goto -> 107
    //   146: aload_0
    //   147: getfield zzjri : Lcom/google/android/gms/internal/zzcme;
    //   150: invokestatic zze : (Lcom/google/android/gms/internal/zzcme;)V
    //   153: aload_0
    //   154: getfield zzjrj : Ljava/util/concurrent/atomic/AtomicReference;
    //   157: astore_1
    //   158: aload_1
    //   159: invokevirtual notify : ()V
    //   162: goto -> 215
    //   165: astore_1
    //   166: goto -> 218
    //   169: astore_1
    //   170: aload_0
    //   171: getfield zzjri : Lcom/google/android/gms/internal/zzcme;
    //   174: invokevirtual zzayp : ()Lcom/google/android/gms/internal/zzcjj;
    //   177: invokevirtual zzbau : ()Lcom/google/android/gms/internal/zzcjl;
    //   180: ldc 'Failed to get user properties'
    //   182: aload_0
    //   183: getfield zziuw : Ljava/lang/String;
    //   186: invokestatic zzjs : (Ljava/lang/String;)Ljava/lang/Object;
    //   189: aload_0
    //   190: getfield zzjpm : Ljava/lang/String;
    //   193: aload_1
    //   194: invokevirtual zzd : (Ljava/lang/String;Ljava/lang/Object;Ljava/lang/Object;Ljava/lang/Object;)V
    //   197: aload_0
    //   198: getfield zzjrj : Ljava/util/concurrent/atomic/AtomicReference;
    //   201: invokestatic emptyList : ()Ljava/util/List;
    //   204: invokevirtual set : (Ljava/lang/Object;)V
    //   207: aload_0
    //   208: getfield zzjrj : Ljava/util/concurrent/atomic/AtomicReference;
    //   211: astore_1
    //   212: goto -> 158
    //   215: aload_3
    //   216: monitorexit
    //   217: return
    //   218: aload_0
    //   219: getfield zzjrj : Ljava/util/concurrent/atomic/AtomicReference;
    //   222: invokevirtual notify : ()V
    //   225: aload_1
    //   226: athrow
    //   227: astore_1
    //   228: aload_3
    //   229: monitorexit
    //   230: aload_1
    //   231: athrow
    // Exception table:
    //   from	to	target	type
    //   7	15	169	android/os/RemoteException
    //   7	15	165	finally
    //   19	59	169	android/os/RemoteException
    //   19	59	165	finally
    //   59	68	227	finally
    //   69	107	169	android/os/RemoteException
    //   69	107	165	finally
    //   107	112	169	android/os/RemoteException
    //   107	112	165	finally
    //   115	143	169	android/os/RemoteException
    //   115	143	165	finally
    //   146	153	169	android/os/RemoteException
    //   146	153	165	finally
    //   153	158	227	finally
    //   158	162	227	finally
    //   170	207	165	finally
    //   207	212	227	finally
    //   215	217	227	finally
    //   218	227	227	finally
    //   228	230	227	finally
  }
}


/* Location:              /home/egaebel/Programs/sony-headphones-hack/base-dex2jar.jar!/com/google/android/gms/internal/zzcmp.class
 * Java compiler version: 6 (50.0)
 * JD-Core Version:       1.1.3
 */