package com.google.android.gms.internal;

public final class zzea extends zzeu {
  private static final Object zzakj = new Object();
  
  private static volatile zzbw zzakk;
  
  private zzax zzakl = null;
  
  public zzea(zzdm paramzzdm, String paramString1, String paramString2, zzba paramzzba, int paramInt1, int paramInt2, zzax paramzzax) {
    super(paramzzdm, paramString1, paramString2, paramzzba, paramInt1, 27);
    this.zzakl = paramzzax;
  }
  
  private final String zzax() {
    try {
      if (this.zzagq.zzan() != null)
        this.zzagq.zzan().get(); 
      zzba zzba = this.zzagq.zzam();
      if (zzba != null && zzba.zzcv != null)
        return zzba.zzcv; 
    } catch (InterruptedException|java.util.concurrent.ExecutionException interruptedException) {}
    return null;
  }
  
  protected final void zzaw() {
    // Byte code:
    //   0: getstatic com/google/android/gms/internal/zzea.zzakk : Lcom/google/android/gms/internal/zzbw;
    //   3: astore_3
    //   4: iconst_0
    //   5: istore_2
    //   6: aload_3
    //   7: ifnull -> 58
    //   10: getstatic com/google/android/gms/internal/zzea.zzakk : Lcom/google/android/gms/internal/zzbw;
    //   13: getfield zzcv : Ljava/lang/String;
    //   16: invokestatic zzo : (Ljava/lang/String;)Z
    //   19: ifne -> 58
    //   22: getstatic com/google/android/gms/internal/zzea.zzakk : Lcom/google/android/gms/internal/zzbw;
    //   25: getfield zzcv : Ljava/lang/String;
    //   28: ldc 'E'
    //   30: invokevirtual equals : (Ljava/lang/Object;)Z
    //   33: ifne -> 58
    //   36: getstatic com/google/android/gms/internal/zzea.zzakk : Lcom/google/android/gms/internal/zzbw;
    //   39: getfield zzcv : Ljava/lang/String;
    //   42: ldc '0000000000000000000000000000000000000000000000000000000000000000'
    //   44: invokevirtual equals : (Ljava/lang/Object;)Z
    //   47: ifeq -> 53
    //   50: goto -> 58
    //   53: iconst_0
    //   54: istore_1
    //   55: goto -> 60
    //   58: iconst_1
    //   59: istore_1
    //   60: iload_1
    //   61: ifeq -> 320
    //   64: getstatic com/google/android/gms/internal/zzea.zzakj : Ljava/lang/Object;
    //   67: astore_3
    //   68: aload_3
    //   69: monitorenter
    //   70: aload_0
    //   71: getfield zzakl : Lcom/google/android/gms/internal/zzax;
    //   74: astore #4
    //   76: aconst_null
    //   77: invokestatic zzo : (Ljava/lang/String;)Z
    //   80: ifne -> 88
    //   83: iconst_4
    //   84: istore_1
    //   85: goto -> 168
    //   88: aload_0
    //   89: getfield zzakl : Lcom/google/android/gms/internal/zzax;
    //   92: astore #4
    //   94: aconst_null
    //   95: invokestatic zzo : (Ljava/lang/String;)Z
    //   98: pop
    //   99: iconst_0
    //   100: invokestatic valueOf : (Z)Ljava/lang/Boolean;
    //   103: invokevirtual booleanValue : ()Z
    //   106: ifeq -> 424
    //   109: aload_0
    //   110: getfield zzagq : Lcom/google/android/gms/internal/zzdm;
    //   113: invokevirtual zzak : ()Z
    //   116: ifeq -> 413
    //   119: getstatic com/google/android/gms/internal/zzoi.zzbru : Lcom/google/android/gms/internal/zzny;
    //   122: astore #4
    //   124: invokestatic zzio : ()Lcom/google/android/gms/internal/zzog;
    //   127: aload #4
    //   129: invokevirtual zzd : (Lcom/google/android/gms/internal/zzny;)Ljava/lang/Object;
    //   132: checkcast java/lang/Boolean
    //   135: invokevirtual booleanValue : ()Z
    //   138: ifeq -> 413
    //   141: getstatic com/google/android/gms/internal/zzoi.zzbrv : Lcom/google/android/gms/internal/zzny;
    //   144: astore #4
    //   146: invokestatic zzio : ()Lcom/google/android/gms/internal/zzog;
    //   149: aload #4
    //   151: invokevirtual zzd : (Lcom/google/android/gms/internal/zzny;)Ljava/lang/Object;
    //   154: checkcast java/lang/Boolean
    //   157: invokevirtual booleanValue : ()Z
    //   160: ifeq -> 413
    //   163: iconst_1
    //   164: istore_1
    //   165: goto -> 415
    //   168: aload_0
    //   169: getfield zzaku : Ljava/lang/reflect/Method;
    //   172: astore #5
    //   174: aload_0
    //   175: getfield zzagq : Lcom/google/android/gms/internal/zzdm;
    //   178: invokevirtual getContext : ()Landroid/content/Context;
    //   181: astore #4
    //   183: iload_1
    //   184: iconst_2
    //   185: if_icmpne -> 190
    //   188: iconst_1
    //   189: istore_2
    //   190: getstatic com/google/android/gms/internal/zzoi.zzbrn : Lcom/google/android/gms/internal/zzny;
    //   193: astore #6
    //   195: new com/google/android/gms/internal/zzbw
    //   198: dup
    //   199: aload #5
    //   201: aconst_null
    //   202: iconst_3
    //   203: anewarray java/lang/Object
    //   206: dup
    //   207: iconst_0
    //   208: aload #4
    //   210: aastore
    //   211: dup
    //   212: iconst_1
    //   213: iload_2
    //   214: invokestatic valueOf : (Z)Ljava/lang/Boolean;
    //   217: aastore
    //   218: dup
    //   219: iconst_2
    //   220: invokestatic zzio : ()Lcom/google/android/gms/internal/zzog;
    //   223: aload #6
    //   225: invokevirtual zzd : (Lcom/google/android/gms/internal/zzny;)Ljava/lang/Object;
    //   228: aastore
    //   229: invokevirtual invoke : (Ljava/lang/Object;[Ljava/lang/Object;)Ljava/lang/Object;
    //   232: checkcast java/lang/String
    //   235: invokespecial <init> : (Ljava/lang/String;)V
    //   238: astore #4
    //   240: aload #4
    //   242: putstatic com/google/android/gms/internal/zzea.zzakk : Lcom/google/android/gms/internal/zzbw;
    //   245: aload #4
    //   247: getfield zzcv : Ljava/lang/String;
    //   250: invokestatic zzo : (Ljava/lang/String;)Z
    //   253: ifne -> 429
    //   256: getstatic com/google/android/gms/internal/zzea.zzakk : Lcom/google/android/gms/internal/zzbw;
    //   259: getfield zzcv : Ljava/lang/String;
    //   262: ldc 'E'
    //   264: invokevirtual equals : (Ljava/lang/Object;)Z
    //   267: ifeq -> 308
    //   270: goto -> 429
    //   273: getstatic com/google/android/gms/internal/zzea.zzakk : Lcom/google/android/gms/internal/zzbw;
    //   276: astore #4
    //   278: new java/lang/NullPointerException
    //   281: dup
    //   282: invokespecial <init> : ()V
    //   285: athrow
    //   286: aload_0
    //   287: invokespecial zzax : ()Ljava/lang/String;
    //   290: astore #4
    //   292: aload #4
    //   294: invokestatic zzo : (Ljava/lang/String;)Z
    //   297: ifne -> 308
    //   300: getstatic com/google/android/gms/internal/zzea.zzakk : Lcom/google/android/gms/internal/zzbw;
    //   303: aload #4
    //   305: putfield zzcv : Ljava/lang/String;
    //   308: aload_3
    //   309: monitorexit
    //   310: goto -> 320
    //   313: astore #4
    //   315: aload_3
    //   316: monitorexit
    //   317: aload #4
    //   319: athrow
    //   320: aload_0
    //   321: getfield zzakm : Lcom/google/android/gms/internal/zzba;
    //   324: astore #4
    //   326: aload #4
    //   328: monitorenter
    //   329: getstatic com/google/android/gms/internal/zzea.zzakk : Lcom/google/android/gms/internal/zzbw;
    //   332: ifnull -> 403
    //   335: aload_0
    //   336: getfield zzakm : Lcom/google/android/gms/internal/zzba;
    //   339: getstatic com/google/android/gms/internal/zzea.zzakk : Lcom/google/android/gms/internal/zzbw;
    //   342: getfield zzcv : Ljava/lang/String;
    //   345: putfield zzcv : Ljava/lang/String;
    //   348: aload_0
    //   349: getfield zzakm : Lcom/google/android/gms/internal/zzba;
    //   352: getstatic com/google/android/gms/internal/zzea.zzakk : Lcom/google/android/gms/internal/zzbw;
    //   355: getfield zzyv : J
    //   358: invokestatic valueOf : (J)Ljava/lang/Long;
    //   361: putfield zzdz : Ljava/lang/Long;
    //   364: aload_0
    //   365: getfield zzakm : Lcom/google/android/gms/internal/zzba;
    //   368: getstatic com/google/android/gms/internal/zzea.zzakk : Lcom/google/android/gms/internal/zzbw;
    //   371: getfield zzcx : Ljava/lang/String;
    //   374: putfield zzcx : Ljava/lang/String;
    //   377: aload_0
    //   378: getfield zzakm : Lcom/google/android/gms/internal/zzba;
    //   381: getstatic com/google/android/gms/internal/zzea.zzakk : Lcom/google/android/gms/internal/zzbw;
    //   384: getfield zzcy : Ljava/lang/String;
    //   387: putfield zzcy : Ljava/lang/String;
    //   390: aload_0
    //   391: getfield zzakm : Lcom/google/android/gms/internal/zzba;
    //   394: getstatic com/google/android/gms/internal/zzea.zzakk : Lcom/google/android/gms/internal/zzbw;
    //   397: getfield zzcz : Ljava/lang/String;
    //   400: putfield zzcz : Ljava/lang/String;
    //   403: aload #4
    //   405: monitorexit
    //   406: return
    //   407: astore_3
    //   408: aload #4
    //   410: monitorexit
    //   411: aload_3
    //   412: athrow
    //   413: iconst_0
    //   414: istore_1
    //   415: iload_1
    //   416: ifeq -> 424
    //   419: iconst_3
    //   420: istore_1
    //   421: goto -> 168
    //   424: iconst_2
    //   425: istore_1
    //   426: goto -> 168
    //   429: iload_1
    //   430: tableswitch default -> 452, 3 -> 286, 4 -> 273
    //   452: goto -> 308
    // Exception table:
    //   from	to	target	type
    //   70	83	313	finally
    //   88	163	313	finally
    //   168	183	313	finally
    //   190	270	313	finally
    //   273	286	313	finally
    //   286	308	313	finally
    //   308	310	313	finally
    //   315	317	313	finally
    //   329	403	407	finally
    //   403	406	407	finally
    //   408	411	407	finally
  }
}


/* Location:              /home/egaebel/Programs/sony-headphones-hack/base-dex2jar.jar!/com/google/android/gms/internal/zzea.class
 * Java compiler version: 6 (50.0)
 * JD-Core Version:       1.1.3
 */