package com.google.android.gms.internal;

public final class zzeq extends zzeu {
  public zzeq(zzdm paramzzdm, String paramString1, String paramString2, zzba paramzzba, int paramInt1, int paramInt2) {
    super(paramzzdm, paramString1, paramString2, paramzzba, paramInt1, 48);
  }
  
  protected final void zzaw() {
    // Byte code:
    //   0: aload_0
    //   1: getfield zzakm : Lcom/google/android/gms/internal/zzba;
    //   4: iconst_2
    //   5: invokestatic valueOf : (I)Ljava/lang/Integer;
    //   8: putfield zzej : Ljava/lang/Integer;
    //   11: aload_0
    //   12: getfield zzaku : Ljava/lang/reflect/Method;
    //   15: aconst_null
    //   16: iconst_1
    //   17: anewarray java/lang/Object
    //   20: dup
    //   21: iconst_0
    //   22: aload_0
    //   23: getfield zzagq : Lcom/google/android/gms/internal/zzdm;
    //   26: invokevirtual getContext : ()Landroid/content/Context;
    //   29: aastore
    //   30: invokevirtual invoke : (Ljava/lang/Object;[Ljava/lang/Object;)Ljava/lang/Object;
    //   33: checkcast java/lang/Boolean
    //   36: invokevirtual booleanValue : ()Z
    //   39: istore_1
    //   40: aload_0
    //   41: getfield zzakm : Lcom/google/android/gms/internal/zzba;
    //   44: astore #4
    //   46: aload #4
    //   48: monitorenter
    //   49: iload_1
    //   50: iconst_1
    //   51: if_icmpne -> 72
    //   54: aload_0
    //   55: getfield zzakm : Lcom/google/android/gms/internal/zzba;
    //   58: astore_2
    //   59: iconst_1
    //   60: invokestatic valueOf : (I)Ljava/lang/Integer;
    //   63: astore_3
    //   64: aload_2
    //   65: aload_3
    //   66: putfield zzej : Ljava/lang/Integer;
    //   69: goto -> 85
    //   72: aload_0
    //   73: getfield zzakm : Lcom/google/android/gms/internal/zzba;
    //   76: astore_2
    //   77: iconst_0
    //   78: invokestatic valueOf : (I)Ljava/lang/Integer;
    //   81: astore_3
    //   82: goto -> 64
    //   85: aload #4
    //   87: monitorexit
    //   88: return
    //   89: astore_2
    //   90: aload #4
    //   92: monitorexit
    //   93: aload_2
    //   94: athrow
    // Exception table:
    //   from	to	target	type
    //   54	64	89	finally
    //   64	69	89	finally
    //   72	82	89	finally
    //   85	88	89	finally
    //   90	93	89	finally
  }
}


/* Location:              /home/egaebel/Programs/sony-headphones-hack/base-dex2jar.jar!/com/google/android/gms/internal/zzeq.class
 * Java compiler version: 6 (50.0)
 * JD-Core Version:       1.1.3
 */