package com.sony.snc.ad.plugin.sncadvoci.b;

import android.graphics.Bitmap;
import java.net.URL;
import kotlin.jvm.a.q;
import kotlin.jvm.internal.h;
import kotlin.l;

public final class ae implements bk {
  private Integer a;
  
  public Integer a() {
    return this.a;
  }
  
  public void a(URL paramURL, q<? super String, ? super Integer, ? super String, l> paramq) {
    h.b(paramURL, "url");
    h.b(paramq, "completionHandler");
    (new Thread(new a(this, paramURL, paramq))).start();
  }
  
  public void b(URL paramURL, q<? super Bitmap, ? super Integer, ? super String, l> paramq) {
    h.b(paramURL, "imageUrl");
    h.b(paramq, "completionHandler");
    (new Thread(new b(this, paramURL, paramq))).start();
  }
  
  static final class a implements Runnable {
    a(ae param1ae, URL param1URL, q param1q) {}
    
    public final void run() {
      // Byte code:
      //   0: aload_0
      //   1: getfield b : Ljava/net/URL;
      //   4: invokevirtual openConnection : ()Ljava/net/URLConnection;
      //   7: astore_3
      //   8: aload_3
      //   9: astore_2
      //   10: aload_3
      //   11: instanceof java/net/HttpURLConnection
      //   14: ifne -> 19
      //   17: aconst_null
      //   18: astore_2
      //   19: aload_2
      //   20: checkcast java/net/HttpURLConnection
      //   23: astore_3
      //   24: aload_3
      //   25: ifnull -> 229
      //   28: aload_3
      //   29: astore_2
      //   30: aload_0
      //   31: getfield a : Lcom/sony/snc/ad/plugin/sncadvoci/b/ae;
      //   34: invokevirtual a : ()Ljava/lang/Integer;
      //   37: astore #4
      //   39: aload #4
      //   41: ifnull -> 66
      //   44: aload_3
      //   45: astore_2
      //   46: aload #4
      //   48: invokevirtual intValue : ()I
      //   51: istore_1
      //   52: aload_3
      //   53: astore_2
      //   54: aload_3
      //   55: iload_1
      //   56: invokevirtual setConnectTimeout : (I)V
      //   59: aload_3
      //   60: astore_2
      //   61: aload_3
      //   62: iload_1
      //   63: invokevirtual setReadTimeout : (I)V
      //   66: aload_3
      //   67: astore_2
      //   68: aload_3
      //   69: iconst_0
      //   70: invokevirtual setUseCaches : (Z)V
      //   73: aload_3
      //   74: astore_2
      //   75: aload_3
      //   76: ldc 'GET'
      //   78: invokevirtual setRequestMethod : (Ljava/lang/String;)V
      //   81: aload_3
      //   82: astore_2
      //   83: aload_3
      //   84: invokevirtual connect : ()V
      //   87: aload_3
      //   88: astore_2
      //   89: aload_3
      //   90: invokevirtual getResponseCode : ()I
      //   93: istore_1
      //   94: aload_3
      //   95: astore_2
      //   96: aload_3
      //   97: invokevirtual getResponseMessage : ()Ljava/lang/String;
      //   100: astore #4
      //   102: aload_3
      //   103: astore_2
      //   104: new java/lang/StringBuilder
      //   107: dup
      //   108: invokespecial <init> : ()V
      //   111: astore #5
      //   113: iload_1
      //   114: sipush #200
      //   117: if_icmpne -> 199
      //   120: aload_3
      //   121: astore_2
      //   122: new java/io/BufferedReader
      //   125: dup
      //   126: new java/io/InputStreamReader
      //   129: dup
      //   130: aload_3
      //   131: invokevirtual getInputStream : ()Ljava/io/InputStream;
      //   134: invokespecial <init> : (Ljava/io/InputStream;)V
      //   137: invokespecial <init> : (Ljava/io/Reader;)V
      //   140: astore #4
      //   142: aload_3
      //   143: astore_2
      //   144: aload #4
      //   146: invokestatic a : (Ljava/io/Reader;)Ljava/util/List;
      //   149: invokeinterface iterator : ()Ljava/util/Iterator;
      //   154: astore #6
      //   156: aload_3
      //   157: astore_2
      //   158: aload #6
      //   160: invokeinterface hasNext : ()Z
      //   165: ifeq -> 189
      //   168: aload_3
      //   169: astore_2
      //   170: aload #5
      //   172: aload #6
      //   174: invokeinterface next : ()Ljava/lang/Object;
      //   179: checkcast java/lang/String
      //   182: invokevirtual append : (Ljava/lang/String;)Ljava/lang/StringBuilder;
      //   185: pop
      //   186: goto -> 156
      //   189: aload_3
      //   190: astore_2
      //   191: aload #4
      //   193: invokevirtual close : ()V
      //   196: aconst_null
      //   197: astore #4
      //   199: aload_3
      //   200: astore_2
      //   201: aload_0
      //   202: getfield c : Lkotlin/jvm/a/q;
      //   205: aload #5
      //   207: invokevirtual toString : ()Ljava/lang/String;
      //   210: iload_1
      //   211: invokestatic valueOf : (I)Ljava/lang/Integer;
      //   214: aload #4
      //   216: invokeinterface invoke : (Ljava/lang/Object;Ljava/lang/Object;Ljava/lang/Object;)Ljava/lang/Object;
      //   221: pop
      //   222: aload_3
      //   223: ifnull -> 435
      //   226: goto -> 431
      //   229: aload_3
      //   230: astore_2
      //   231: aload_0
      //   232: getfield c : Lkotlin/jvm/a/q;
      //   235: astore #4
      //   237: aload_3
      //   238: astore_2
      //   239: new java/lang/StringBuilder
      //   242: dup
      //   243: invokespecial <init> : ()V
      //   246: astore #5
      //   248: aload_3
      //   249: astore_2
      //   250: aload #5
      //   252: ldc 'Failed to create connection : '
      //   254: invokevirtual append : (Ljava/lang/String;)Ljava/lang/StringBuilder;
      //   257: pop
      //   258: aload_3
      //   259: astore_2
      //   260: aload #5
      //   262: aload_0
      //   263: getfield b : Ljava/net/URL;
      //   266: invokevirtual append : (Ljava/lang/Object;)Ljava/lang/StringBuilder;
      //   269: pop
      //   270: aload_3
      //   271: astore_2
      //   272: aload #4
      //   274: aconst_null
      //   275: aconst_null
      //   276: aload #5
      //   278: invokevirtual toString : ()Ljava/lang/String;
      //   281: invokeinterface invoke : (Ljava/lang/Object;Ljava/lang/Object;Ljava/lang/Object;)Ljava/lang/Object;
      //   286: pop
      //   287: aload_3
      //   288: ifnull -> 295
      //   291: aload_3
      //   292: invokevirtual disconnect : ()V
      //   295: return
      //   296: astore_2
      //   297: aconst_null
      //   298: astore_3
      //   299: goto -> 443
      //   302: aconst_null
      //   303: astore_3
      //   304: aload_3
      //   305: astore_2
      //   306: aload_0
      //   307: getfield c : Lkotlin/jvm/a/q;
      //   310: astore #4
      //   312: aload_3
      //   313: astore_2
      //   314: new java/lang/StringBuilder
      //   317: dup
      //   318: invokespecial <init> : ()V
      //   321: astore #5
      //   323: aload_3
      //   324: astore_2
      //   325: aload #5
      //   327: ldc 'Failed to connect : '
      //   329: invokevirtual append : (Ljava/lang/String;)Ljava/lang/StringBuilder;
      //   332: pop
      //   333: aload_3
      //   334: astore_2
      //   335: aload #5
      //   337: aload_0
      //   338: getfield b : Ljava/net/URL;
      //   341: invokevirtual append : (Ljava/lang/Object;)Ljava/lang/StringBuilder;
      //   344: pop
      //   345: aload_3
      //   346: astore_2
      //   347: aload #4
      //   349: aconst_null
      //   350: aconst_null
      //   351: aload #5
      //   353: invokevirtual toString : ()Ljava/lang/String;
      //   356: invokeinterface invoke : (Ljava/lang/Object;Ljava/lang/Object;Ljava/lang/Object;)Ljava/lang/Object;
      //   361: pop
      //   362: aload_3
      //   363: ifnull -> 435
      //   366: goto -> 431
      //   369: aload_3
      //   370: astore_2
      //   371: aload_0
      //   372: getfield c : Lkotlin/jvm/a/q;
      //   375: astore #4
      //   377: aload_3
      //   378: astore_2
      //   379: new java/lang/StringBuilder
      //   382: dup
      //   383: invokespecial <init> : ()V
      //   386: astore #5
      //   388: aload_3
      //   389: astore_2
      //   390: aload #5
      //   392: ldc 'Connection timeout error : '
      //   394: invokevirtual append : (Ljava/lang/String;)Ljava/lang/StringBuilder;
      //   397: pop
      //   398: aload_3
      //   399: astore_2
      //   400: aload #5
      //   402: aload_0
      //   403: getfield b : Ljava/net/URL;
      //   406: invokevirtual append : (Ljava/lang/Object;)Ljava/lang/StringBuilder;
      //   409: pop
      //   410: aload_3
      //   411: astore_2
      //   412: aload #4
      //   414: aconst_null
      //   415: aconst_null
      //   416: aload #5
      //   418: invokevirtual toString : ()Ljava/lang/String;
      //   421: invokeinterface invoke : (Ljava/lang/Object;Ljava/lang/Object;Ljava/lang/Object;)Ljava/lang/Object;
      //   426: pop
      //   427: aload_3
      //   428: ifnull -> 435
      //   431: aload_3
      //   432: invokevirtual disconnect : ()V
      //   435: return
      //   436: astore #4
      //   438: aload_2
      //   439: astore_3
      //   440: aload #4
      //   442: astore_2
      //   443: aload_3
      //   444: ifnull -> 451
      //   447: aload_3
      //   448: invokevirtual disconnect : ()V
      //   451: aload_2
      //   452: athrow
      //   453: astore_2
      //   454: goto -> 469
      //   457: astore_2
      //   458: goto -> 302
      //   461: astore_2
      //   462: goto -> 369
      //   465: astore_2
      //   466: goto -> 304
      //   469: aconst_null
      //   470: astore_3
      //   471: goto -> 369
      // Exception table:
      //   from	to	target	type
      //   0	8	453	java/net/SocketTimeoutException
      //   0	8	457	java/io/IOException
      //   0	8	296	finally
      //   10	17	453	java/net/SocketTimeoutException
      //   10	17	457	java/io/IOException
      //   10	17	296	finally
      //   19	24	453	java/net/SocketTimeoutException
      //   19	24	457	java/io/IOException
      //   19	24	296	finally
      //   30	39	461	java/net/SocketTimeoutException
      //   30	39	465	java/io/IOException
      //   30	39	436	finally
      //   46	52	461	java/net/SocketTimeoutException
      //   46	52	465	java/io/IOException
      //   46	52	436	finally
      //   54	59	461	java/net/SocketTimeoutException
      //   54	59	465	java/io/IOException
      //   54	59	436	finally
      //   61	66	461	java/net/SocketTimeoutException
      //   61	66	465	java/io/IOException
      //   61	66	436	finally
      //   68	73	461	java/net/SocketTimeoutException
      //   68	73	465	java/io/IOException
      //   68	73	436	finally
      //   75	81	461	java/net/SocketTimeoutException
      //   75	81	465	java/io/IOException
      //   75	81	436	finally
      //   83	87	461	java/net/SocketTimeoutException
      //   83	87	465	java/io/IOException
      //   83	87	436	finally
      //   89	94	461	java/net/SocketTimeoutException
      //   89	94	465	java/io/IOException
      //   89	94	436	finally
      //   96	102	461	java/net/SocketTimeoutException
      //   96	102	465	java/io/IOException
      //   96	102	436	finally
      //   104	113	461	java/net/SocketTimeoutException
      //   104	113	465	java/io/IOException
      //   104	113	436	finally
      //   122	142	461	java/net/SocketTimeoutException
      //   122	142	465	java/io/IOException
      //   122	142	436	finally
      //   144	156	461	java/net/SocketTimeoutException
      //   144	156	465	java/io/IOException
      //   144	156	436	finally
      //   158	168	461	java/net/SocketTimeoutException
      //   158	168	465	java/io/IOException
      //   158	168	436	finally
      //   170	186	461	java/net/SocketTimeoutException
      //   170	186	465	java/io/IOException
      //   170	186	436	finally
      //   191	196	461	java/net/SocketTimeoutException
      //   191	196	465	java/io/IOException
      //   191	196	436	finally
      //   201	222	461	java/net/SocketTimeoutException
      //   201	222	465	java/io/IOException
      //   201	222	436	finally
      //   231	237	461	java/net/SocketTimeoutException
      //   231	237	465	java/io/IOException
      //   231	237	436	finally
      //   239	248	461	java/net/SocketTimeoutException
      //   239	248	465	java/io/IOException
      //   239	248	436	finally
      //   250	258	461	java/net/SocketTimeoutException
      //   250	258	465	java/io/IOException
      //   250	258	436	finally
      //   260	270	461	java/net/SocketTimeoutException
      //   260	270	465	java/io/IOException
      //   260	270	436	finally
      //   272	287	461	java/net/SocketTimeoutException
      //   272	287	465	java/io/IOException
      //   272	287	436	finally
      //   306	312	436	finally
      //   314	323	436	finally
      //   325	333	436	finally
      //   335	345	436	finally
      //   347	362	436	finally
      //   371	377	436	finally
      //   379	388	436	finally
      //   390	398	436	finally
      //   400	410	436	finally
      //   412	427	436	finally
    }
  }
  
  static final class b implements Runnable {
    b(ae param1ae, URL param1URL, q param1q) {}
    
    public final void run() {
      // Byte code:
      //   0: aload_0
      //   1: getfield b : Ljava/net/URL;
      //   4: invokevirtual openConnection : ()Ljava/net/URLConnection;
      //   7: astore_3
      //   8: aload_3
      //   9: astore_2
      //   10: aload_3
      //   11: instanceof java/net/HttpURLConnection
      //   14: ifne -> 19
      //   17: aconst_null
      //   18: astore_2
      //   19: aload_2
      //   20: checkcast java/net/HttpURLConnection
      //   23: astore_3
      //   24: aload_3
      //   25: ifnull -> 195
      //   28: aload_3
      //   29: astore_2
      //   30: aload_0
      //   31: getfield a : Lcom/sony/snc/ad/plugin/sncadvoci/b/ae;
      //   34: invokevirtual a : ()Ljava/lang/Integer;
      //   37: astore #4
      //   39: aload #4
      //   41: ifnull -> 66
      //   44: aload_3
      //   45: astore_2
      //   46: aload #4
      //   48: invokevirtual intValue : ()I
      //   51: istore_1
      //   52: aload_3
      //   53: astore_2
      //   54: aload_3
      //   55: iload_1
      //   56: invokevirtual setConnectTimeout : (I)V
      //   59: aload_3
      //   60: astore_2
      //   61: aload_3
      //   62: iload_1
      //   63: invokevirtual setReadTimeout : (I)V
      //   66: aload_3
      //   67: astore_2
      //   68: aload_3
      //   69: iconst_0
      //   70: invokevirtual setUseCaches : (Z)V
      //   73: aload_3
      //   74: astore_2
      //   75: aload_3
      //   76: ldc 'GET'
      //   78: invokevirtual setRequestMethod : (Ljava/lang/String;)V
      //   81: aload_3
      //   82: astore_2
      //   83: aload_3
      //   84: invokevirtual connect : ()V
      //   87: aload_3
      //   88: astore_2
      //   89: aload_3
      //   90: invokevirtual getResponseCode : ()I
      //   93: invokestatic valueOf : (I)Ljava/lang/Integer;
      //   96: astore #6
      //   98: aload_3
      //   99: astore_2
      //   100: aload_3
      //   101: invokevirtual getResponseMessage : ()Ljava/lang/String;
      //   104: astore #5
      //   106: aload_3
      //   107: astore_2
      //   108: aload #6
      //   110: invokevirtual intValue : ()I
      //   113: sipush #200
      //   116: if_icmpne -> 167
      //   119: aload_3
      //   120: astore_2
      //   121: aload_3
      //   122: invokevirtual getInputStream : ()Ljava/io/InputStream;
      //   125: invokestatic decodeStream : (Ljava/io/InputStream;)Landroid/graphics/Bitmap;
      //   128: astore #4
      //   130: aload #4
      //   132: ifnull -> 141
      //   135: aconst_null
      //   136: astore #5
      //   138: goto -> 170
      //   141: aload_3
      //   142: astore_2
      //   143: aload_0
      //   144: getfield c : Lkotlin/jvm/a/q;
      //   147: aconst_null
      //   148: aload #6
      //   150: ldc 'Bitmap decoding failed'
      //   152: invokeinterface invoke : (Ljava/lang/Object;Ljava/lang/Object;Ljava/lang/Object;)Ljava/lang/Object;
      //   157: pop
      //   158: aload_3
      //   159: ifnull -> 166
      //   162: aload_3
      //   163: invokevirtual disconnect : ()V
      //   166: return
      //   167: aconst_null
      //   168: astore #4
      //   170: aload_3
      //   171: astore_2
      //   172: aload_0
      //   173: getfield c : Lkotlin/jvm/a/q;
      //   176: aload #4
      //   178: aload #6
      //   180: aload #5
      //   182: invokeinterface invoke : (Ljava/lang/Object;Ljava/lang/Object;Ljava/lang/Object;)Ljava/lang/Object;
      //   187: pop
      //   188: aload_3
      //   189: ifnull -> 401
      //   192: goto -> 397
      //   195: aload_3
      //   196: astore_2
      //   197: aload_0
      //   198: getfield c : Lkotlin/jvm/a/q;
      //   201: astore #4
      //   203: aload_3
      //   204: astore_2
      //   205: new java/lang/StringBuilder
      //   208: dup
      //   209: invokespecial <init> : ()V
      //   212: astore #5
      //   214: aload_3
      //   215: astore_2
      //   216: aload #5
      //   218: ldc 'Failed to create connection : '
      //   220: invokevirtual append : (Ljava/lang/String;)Ljava/lang/StringBuilder;
      //   223: pop
      //   224: aload_3
      //   225: astore_2
      //   226: aload #5
      //   228: aload_0
      //   229: getfield b : Ljava/net/URL;
      //   232: invokevirtual append : (Ljava/lang/Object;)Ljava/lang/StringBuilder;
      //   235: pop
      //   236: aload_3
      //   237: astore_2
      //   238: aload #4
      //   240: aconst_null
      //   241: aconst_null
      //   242: aload #5
      //   244: invokevirtual toString : ()Ljava/lang/String;
      //   247: invokeinterface invoke : (Ljava/lang/Object;Ljava/lang/Object;Ljava/lang/Object;)Ljava/lang/Object;
      //   252: pop
      //   253: aload_3
      //   254: ifnull -> 261
      //   257: aload_3
      //   258: invokevirtual disconnect : ()V
      //   261: return
      //   262: astore_2
      //   263: aconst_null
      //   264: astore_3
      //   265: goto -> 409
      //   268: aconst_null
      //   269: astore_3
      //   270: aload_3
      //   271: astore_2
      //   272: aload_0
      //   273: getfield c : Lkotlin/jvm/a/q;
      //   276: astore #4
      //   278: aload_3
      //   279: astore_2
      //   280: new java/lang/StringBuilder
      //   283: dup
      //   284: invokespecial <init> : ()V
      //   287: astore #5
      //   289: aload_3
      //   290: astore_2
      //   291: aload #5
      //   293: ldc 'Failed to connect : '
      //   295: invokevirtual append : (Ljava/lang/String;)Ljava/lang/StringBuilder;
      //   298: pop
      //   299: aload_3
      //   300: astore_2
      //   301: aload #5
      //   303: aload_0
      //   304: getfield b : Ljava/net/URL;
      //   307: invokevirtual append : (Ljava/lang/Object;)Ljava/lang/StringBuilder;
      //   310: pop
      //   311: aload_3
      //   312: astore_2
      //   313: aload #4
      //   315: aconst_null
      //   316: aconst_null
      //   317: aload #5
      //   319: invokevirtual toString : ()Ljava/lang/String;
      //   322: invokeinterface invoke : (Ljava/lang/Object;Ljava/lang/Object;Ljava/lang/Object;)Ljava/lang/Object;
      //   327: pop
      //   328: aload_3
      //   329: ifnull -> 401
      //   332: goto -> 397
      //   335: aload_3
      //   336: astore_2
      //   337: aload_0
      //   338: getfield c : Lkotlin/jvm/a/q;
      //   341: astore #4
      //   343: aload_3
      //   344: astore_2
      //   345: new java/lang/StringBuilder
      //   348: dup
      //   349: invokespecial <init> : ()V
      //   352: astore #5
      //   354: aload_3
      //   355: astore_2
      //   356: aload #5
      //   358: ldc 'Connection timeout error : '
      //   360: invokevirtual append : (Ljava/lang/String;)Ljava/lang/StringBuilder;
      //   363: pop
      //   364: aload_3
      //   365: astore_2
      //   366: aload #5
      //   368: aload_0
      //   369: getfield b : Ljava/net/URL;
      //   372: invokevirtual append : (Ljava/lang/Object;)Ljava/lang/StringBuilder;
      //   375: pop
      //   376: aload_3
      //   377: astore_2
      //   378: aload #4
      //   380: aconst_null
      //   381: aconst_null
      //   382: aload #5
      //   384: invokevirtual toString : ()Ljava/lang/String;
      //   387: invokeinterface invoke : (Ljava/lang/Object;Ljava/lang/Object;Ljava/lang/Object;)Ljava/lang/Object;
      //   392: pop
      //   393: aload_3
      //   394: ifnull -> 401
      //   397: aload_3
      //   398: invokevirtual disconnect : ()V
      //   401: return
      //   402: astore #4
      //   404: aload_2
      //   405: astore_3
      //   406: aload #4
      //   408: astore_2
      //   409: aload_3
      //   410: ifnull -> 417
      //   413: aload_3
      //   414: invokevirtual disconnect : ()V
      //   417: aload_2
      //   418: athrow
      //   419: astore_2
      //   420: goto -> 435
      //   423: astore_2
      //   424: goto -> 268
      //   427: astore_2
      //   428: goto -> 335
      //   431: astore_2
      //   432: goto -> 270
      //   435: aconst_null
      //   436: astore_3
      //   437: goto -> 335
      // Exception table:
      //   from	to	target	type
      //   0	8	419	java/net/SocketTimeoutException
      //   0	8	423	java/io/IOException
      //   0	8	262	finally
      //   10	17	419	java/net/SocketTimeoutException
      //   10	17	423	java/io/IOException
      //   10	17	262	finally
      //   19	24	419	java/net/SocketTimeoutException
      //   19	24	423	java/io/IOException
      //   19	24	262	finally
      //   30	39	427	java/net/SocketTimeoutException
      //   30	39	431	java/io/IOException
      //   30	39	402	finally
      //   46	52	427	java/net/SocketTimeoutException
      //   46	52	431	java/io/IOException
      //   46	52	402	finally
      //   54	59	427	java/net/SocketTimeoutException
      //   54	59	431	java/io/IOException
      //   54	59	402	finally
      //   61	66	427	java/net/SocketTimeoutException
      //   61	66	431	java/io/IOException
      //   61	66	402	finally
      //   68	73	427	java/net/SocketTimeoutException
      //   68	73	431	java/io/IOException
      //   68	73	402	finally
      //   75	81	427	java/net/SocketTimeoutException
      //   75	81	431	java/io/IOException
      //   75	81	402	finally
      //   83	87	427	java/net/SocketTimeoutException
      //   83	87	431	java/io/IOException
      //   83	87	402	finally
      //   89	98	427	java/net/SocketTimeoutException
      //   89	98	431	java/io/IOException
      //   89	98	402	finally
      //   100	106	427	java/net/SocketTimeoutException
      //   100	106	431	java/io/IOException
      //   100	106	402	finally
      //   108	119	427	java/net/SocketTimeoutException
      //   108	119	431	java/io/IOException
      //   108	119	402	finally
      //   121	130	427	java/net/SocketTimeoutException
      //   121	130	431	java/io/IOException
      //   121	130	402	finally
      //   143	158	427	java/net/SocketTimeoutException
      //   143	158	431	java/io/IOException
      //   143	158	402	finally
      //   172	188	427	java/net/SocketTimeoutException
      //   172	188	431	java/io/IOException
      //   172	188	402	finally
      //   197	203	427	java/net/SocketTimeoutException
      //   197	203	431	java/io/IOException
      //   197	203	402	finally
      //   205	214	427	java/net/SocketTimeoutException
      //   205	214	431	java/io/IOException
      //   205	214	402	finally
      //   216	224	427	java/net/SocketTimeoutException
      //   216	224	431	java/io/IOException
      //   216	224	402	finally
      //   226	236	427	java/net/SocketTimeoutException
      //   226	236	431	java/io/IOException
      //   226	236	402	finally
      //   238	253	427	java/net/SocketTimeoutException
      //   238	253	431	java/io/IOException
      //   238	253	402	finally
      //   272	278	402	finally
      //   280	289	402	finally
      //   291	299	402	finally
      //   301	311	402	finally
      //   313	328	402	finally
      //   337	343	402	finally
      //   345	354	402	finally
      //   356	364	402	finally
      //   366	376	402	finally
      //   378	393	402	finally
    }
  }
}


/* Location:              /home/egaebel/Programs/sony-headphones-hack/base-dex2jar.jar!/com/sony/snc/ad/plugin/sncadvoci/b/ae.class
 * Java compiler version: 6 (50.0)
 * JD-Core Version:       1.1.3
 */