package androidx.constraintlayout.solver.widgets;

import androidx.constraintlayout.solver.e;

class c {
  static void a(e parame, e parame1, int paramInt) {
    byte b;
    int i;
    d[] arrayOfD;
    int j = 0;
    if (paramInt == 0) {
      i = parame.an;
      arrayOfD = parame.aq;
      b = 0;
    } else {
      b = 2;
      i = parame.ao;
      arrayOfD = parame.ap;
    } 
    while (j < i) {
      d d = arrayOfD[j];
      d.a();
      if (parame.u(4)) {
        if (!i.a(parame, parame1, paramInt, b, d))
          a(parame, parame1, paramInt, b, d); 
      } else {
        a(parame, parame1, paramInt, b, d);
      } 
      j++;
    } 
  }
  
  static void a(e parame, e parame1, int paramInt1, int paramInt2, d paramd) {
    // Byte code:
    //   0: aload #4
    //   2: getfield a : Landroidx/constraintlayout/solver/widgets/ConstraintWidget;
    //   5: astore #19
    //   7: aload #4
    //   9: getfield c : Landroidx/constraintlayout/solver/widgets/ConstraintWidget;
    //   12: astore #22
    //   14: aload #4
    //   16: getfield b : Landroidx/constraintlayout/solver/widgets/ConstraintWidget;
    //   19: astore #18
    //   21: aload #4
    //   23: getfield d : Landroidx/constraintlayout/solver/widgets/ConstraintWidget;
    //   26: astore #23
    //   28: aload #4
    //   30: getfield e : Landroidx/constraintlayout/solver/widgets/ConstraintWidget;
    //   33: astore #17
    //   35: aload #4
    //   37: getfield k : F
    //   40: fstore #5
    //   42: aload #4
    //   44: getfield f : Landroidx/constraintlayout/solver/widgets/ConstraintWidget;
    //   47: astore #15
    //   49: aload #4
    //   51: getfield g : Landroidx/constraintlayout/solver/widgets/ConstraintWidget;
    //   54: astore #15
    //   56: aload_0
    //   57: getfield C : [Landroidx/constraintlayout/solver/widgets/ConstraintWidget$DimensionBehaviour;
    //   60: iload_2
    //   61: aaload
    //   62: getstatic androidx/constraintlayout/solver/widgets/ConstraintWidget$DimensionBehaviour.WRAP_CONTENT : Landroidx/constraintlayout/solver/widgets/ConstraintWidget$DimensionBehaviour;
    //   65: if_acmpne -> 74
    //   68: iconst_1
    //   69: istore #12
    //   71: goto -> 77
    //   74: iconst_0
    //   75: istore #12
    //   77: iload_2
    //   78: ifne -> 164
    //   81: aload #17
    //   83: getfield Z : I
    //   86: ifne -> 95
    //   89: iconst_1
    //   90: istore #8
    //   92: goto -> 98
    //   95: iconst_0
    //   96: istore #8
    //   98: aload #17
    //   100: getfield Z : I
    //   103: iconst_1
    //   104: if_icmpne -> 113
    //   107: iconst_1
    //   108: istore #9
    //   110: goto -> 116
    //   113: iconst_0
    //   114: istore #9
    //   116: aload #17
    //   118: getfield Z : I
    //   121: iconst_2
    //   122: if_icmpne -> 131
    //   125: iconst_1
    //   126: istore #10
    //   128: goto -> 134
    //   131: iconst_0
    //   132: istore #10
    //   134: iload #8
    //   136: istore #11
    //   138: aload #19
    //   140: astore #15
    //   142: iload #9
    //   144: istore #14
    //   146: iconst_0
    //   147: istore #8
    //   149: iload #10
    //   151: istore #13
    //   153: iload #11
    //   155: istore #9
    //   157: iload #14
    //   159: istore #11
    //   161: goto -> 240
    //   164: aload #17
    //   166: getfield aa : I
    //   169: ifne -> 178
    //   172: iconst_1
    //   173: istore #8
    //   175: goto -> 181
    //   178: iconst_0
    //   179: istore #8
    //   181: aload #17
    //   183: getfield aa : I
    //   186: iconst_1
    //   187: if_icmpne -> 196
    //   190: iconst_1
    //   191: istore #9
    //   193: goto -> 199
    //   196: iconst_0
    //   197: istore #9
    //   199: aload #17
    //   201: getfield aa : I
    //   204: iconst_2
    //   205: if_icmpne -> 214
    //   208: iconst_1
    //   209: istore #10
    //   211: goto -> 217
    //   214: iconst_0
    //   215: istore #10
    //   217: aload #19
    //   219: astore #15
    //   221: iconst_0
    //   222: istore #14
    //   224: iload #9
    //   226: istore #11
    //   228: iload #8
    //   230: istore #9
    //   232: iload #10
    //   234: istore #13
    //   236: iload #14
    //   238: istore #8
    //   240: aconst_null
    //   241: astore #20
    //   243: iload #8
    //   245: ifne -> 622
    //   248: aload #15
    //   250: getfield A : [Landroidx/constraintlayout/solver/widgets/ConstraintAnchor;
    //   253: iload_3
    //   254: aaload
    //   255: astore #16
    //   257: iload #12
    //   259: ifne -> 276
    //   262: iload #13
    //   264: ifeq -> 270
    //   267: goto -> 276
    //   270: iconst_4
    //   271: istore #10
    //   273: goto -> 279
    //   276: iconst_1
    //   277: istore #10
    //   279: aload #16
    //   281: invokevirtual e : ()I
    //   284: istore #14
    //   286: aload #16
    //   288: getfield c : Landroidx/constraintlayout/solver/widgets/ConstraintAnchor;
    //   291: ifnull -> 317
    //   294: aload #15
    //   296: aload #19
    //   298: if_acmpeq -> 317
    //   301: iload #14
    //   303: aload #16
    //   305: getfield c : Landroidx/constraintlayout/solver/widgets/ConstraintAnchor;
    //   308: invokevirtual e : ()I
    //   311: iadd
    //   312: istore #14
    //   314: goto -> 317
    //   317: iload #13
    //   319: ifeq -> 343
    //   322: aload #15
    //   324: aload #19
    //   326: if_acmpeq -> 343
    //   329: aload #15
    //   331: aload #18
    //   333: if_acmpeq -> 343
    //   336: bipush #6
    //   338: istore #10
    //   340: goto -> 359
    //   343: iload #9
    //   345: ifeq -> 359
    //   348: iload #12
    //   350: ifeq -> 359
    //   353: iconst_4
    //   354: istore #10
    //   356: goto -> 359
    //   359: aload #16
    //   361: getfield c : Landroidx/constraintlayout/solver/widgets/ConstraintAnchor;
    //   364: ifnull -> 443
    //   367: aload #15
    //   369: aload #18
    //   371: if_acmpne -> 397
    //   374: aload_1
    //   375: aload #16
    //   377: getfield f : Landroidx/constraintlayout/solver/SolverVariable;
    //   380: aload #16
    //   382: getfield c : Landroidx/constraintlayout/solver/widgets/ConstraintAnchor;
    //   385: getfield f : Landroidx/constraintlayout/solver/SolverVariable;
    //   388: iload #14
    //   390: iconst_5
    //   391: invokevirtual a : (Landroidx/constraintlayout/solver/SolverVariable;Landroidx/constraintlayout/solver/SolverVariable;II)V
    //   394: goto -> 418
    //   397: aload_1
    //   398: aload #16
    //   400: getfield f : Landroidx/constraintlayout/solver/SolverVariable;
    //   403: aload #16
    //   405: getfield c : Landroidx/constraintlayout/solver/widgets/ConstraintAnchor;
    //   408: getfield f : Landroidx/constraintlayout/solver/SolverVariable;
    //   411: iload #14
    //   413: bipush #6
    //   415: invokevirtual a : (Landroidx/constraintlayout/solver/SolverVariable;Landroidx/constraintlayout/solver/SolverVariable;II)V
    //   418: aload_1
    //   419: aload #16
    //   421: getfield f : Landroidx/constraintlayout/solver/SolverVariable;
    //   424: aload #16
    //   426: getfield c : Landroidx/constraintlayout/solver/widgets/ConstraintAnchor;
    //   429: getfield f : Landroidx/constraintlayout/solver/SolverVariable;
    //   432: iload #14
    //   434: iload #10
    //   436: invokevirtual c : (Landroidx/constraintlayout/solver/SolverVariable;Landroidx/constraintlayout/solver/SolverVariable;II)Landroidx/constraintlayout/solver/b;
    //   439: pop
    //   440: goto -> 443
    //   443: iload #12
    //   445: ifeq -> 528
    //   448: aload #15
    //   450: invokevirtual l : ()I
    //   453: bipush #8
    //   455: if_icmpeq -> 502
    //   458: aload #15
    //   460: getfield C : [Landroidx/constraintlayout/solver/widgets/ConstraintWidget$DimensionBehaviour;
    //   463: iload_2
    //   464: aaload
    //   465: getstatic androidx/constraintlayout/solver/widgets/ConstraintWidget$DimensionBehaviour.MATCH_CONSTRAINT : Landroidx/constraintlayout/solver/widgets/ConstraintWidget$DimensionBehaviour;
    //   468: if_acmpne -> 502
    //   471: aload_1
    //   472: aload #15
    //   474: getfield A : [Landroidx/constraintlayout/solver/widgets/ConstraintAnchor;
    //   477: iload_3
    //   478: iconst_1
    //   479: iadd
    //   480: aaload
    //   481: getfield f : Landroidx/constraintlayout/solver/SolverVariable;
    //   484: aload #15
    //   486: getfield A : [Landroidx/constraintlayout/solver/widgets/ConstraintAnchor;
    //   489: iload_3
    //   490: aaload
    //   491: getfield f : Landroidx/constraintlayout/solver/SolverVariable;
    //   494: iconst_0
    //   495: iconst_5
    //   496: invokevirtual a : (Landroidx/constraintlayout/solver/SolverVariable;Landroidx/constraintlayout/solver/SolverVariable;II)V
    //   499: goto -> 502
    //   502: aload_1
    //   503: aload #15
    //   505: getfield A : [Landroidx/constraintlayout/solver/widgets/ConstraintAnchor;
    //   508: iload_3
    //   509: aaload
    //   510: getfield f : Landroidx/constraintlayout/solver/SolverVariable;
    //   513: aload_0
    //   514: getfield A : [Landroidx/constraintlayout/solver/widgets/ConstraintAnchor;
    //   517: iload_3
    //   518: aaload
    //   519: getfield f : Landroidx/constraintlayout/solver/SolverVariable;
    //   522: iconst_0
    //   523: bipush #6
    //   525: invokevirtual a : (Landroidx/constraintlayout/solver/SolverVariable;Landroidx/constraintlayout/solver/SolverVariable;II)V
    //   528: aload #15
    //   530: getfield A : [Landroidx/constraintlayout/solver/widgets/ConstraintAnchor;
    //   533: iload_3
    //   534: iconst_1
    //   535: iadd
    //   536: aaload
    //   537: getfield c : Landroidx/constraintlayout/solver/widgets/ConstraintAnchor;
    //   540: astore #21
    //   542: aload #20
    //   544: astore #16
    //   546: aload #21
    //   548: ifnull -> 604
    //   551: aload #21
    //   553: getfield a : Landroidx/constraintlayout/solver/widgets/ConstraintWidget;
    //   556: astore #21
    //   558: aload #20
    //   560: astore #16
    //   562: aload #21
    //   564: getfield A : [Landroidx/constraintlayout/solver/widgets/ConstraintAnchor;
    //   567: iload_3
    //   568: aaload
    //   569: getfield c : Landroidx/constraintlayout/solver/widgets/ConstraintAnchor;
    //   572: ifnull -> 604
    //   575: aload #21
    //   577: getfield A : [Landroidx/constraintlayout/solver/widgets/ConstraintAnchor;
    //   580: iload_3
    //   581: aaload
    //   582: getfield c : Landroidx/constraintlayout/solver/widgets/ConstraintAnchor;
    //   585: getfield a : Landroidx/constraintlayout/solver/widgets/ConstraintWidget;
    //   588: aload #15
    //   590: if_acmpeq -> 600
    //   593: aload #20
    //   595: astore #16
    //   597: goto -> 604
    //   600: aload #21
    //   602: astore #16
    //   604: aload #16
    //   606: ifnull -> 616
    //   609: aload #16
    //   611: astore #15
    //   613: goto -> 619
    //   616: iconst_1
    //   617: istore #8
    //   619: goto -> 240
    //   622: aload #23
    //   624: ifnull -> 693
    //   627: aload #22
    //   629: getfield A : [Landroidx/constraintlayout/solver/widgets/ConstraintAnchor;
    //   632: astore #15
    //   634: iload_3
    //   635: iconst_1
    //   636: iadd
    //   637: istore #8
    //   639: aload #15
    //   641: iload #8
    //   643: aaload
    //   644: getfield c : Landroidx/constraintlayout/solver/widgets/ConstraintAnchor;
    //   647: ifnull -> 693
    //   650: aload #23
    //   652: getfield A : [Landroidx/constraintlayout/solver/widgets/ConstraintAnchor;
    //   655: iload #8
    //   657: aaload
    //   658: astore #15
    //   660: aload_1
    //   661: aload #15
    //   663: getfield f : Landroidx/constraintlayout/solver/SolverVariable;
    //   666: aload #22
    //   668: getfield A : [Landroidx/constraintlayout/solver/widgets/ConstraintAnchor;
    //   671: iload #8
    //   673: aaload
    //   674: getfield c : Landroidx/constraintlayout/solver/widgets/ConstraintAnchor;
    //   677: getfield f : Landroidx/constraintlayout/solver/SolverVariable;
    //   680: aload #15
    //   682: invokevirtual e : ()I
    //   685: ineg
    //   686: iconst_5
    //   687: invokevirtual b : (Landroidx/constraintlayout/solver/SolverVariable;Landroidx/constraintlayout/solver/SolverVariable;II)V
    //   690: goto -> 693
    //   693: iload #12
    //   695: ifeq -> 743
    //   698: aload_0
    //   699: getfield A : [Landroidx/constraintlayout/solver/widgets/ConstraintAnchor;
    //   702: astore_0
    //   703: iload_3
    //   704: iconst_1
    //   705: iadd
    //   706: istore #8
    //   708: aload_1
    //   709: aload_0
    //   710: iload #8
    //   712: aaload
    //   713: getfield f : Landroidx/constraintlayout/solver/SolverVariable;
    //   716: aload #22
    //   718: getfield A : [Landroidx/constraintlayout/solver/widgets/ConstraintAnchor;
    //   721: iload #8
    //   723: aaload
    //   724: getfield f : Landroidx/constraintlayout/solver/SolverVariable;
    //   727: aload #22
    //   729: getfield A : [Landroidx/constraintlayout/solver/widgets/ConstraintAnchor;
    //   732: iload #8
    //   734: aaload
    //   735: invokevirtual e : ()I
    //   738: bipush #6
    //   740: invokevirtual a : (Landroidx/constraintlayout/solver/SolverVariable;Landroidx/constraintlayout/solver/SolverVariable;II)V
    //   743: aload #4
    //   745: getfield h : Ljava/util/ArrayList;
    //   748: astore_0
    //   749: aload_0
    //   750: ifnull -> 1045
    //   753: aload_0
    //   754: invokevirtual size : ()I
    //   757: istore #8
    //   759: iload #8
    //   761: iconst_1
    //   762: if_icmple -> 1045
    //   765: aload #4
    //   767: getfield l : Z
    //   770: ifeq -> 792
    //   773: aload #4
    //   775: getfield n : Z
    //   778: ifne -> 792
    //   781: aload #4
    //   783: getfield j : I
    //   786: i2f
    //   787: fstore #6
    //   789: goto -> 796
    //   792: fload #5
    //   794: fstore #6
    //   796: aconst_null
    //   797: astore #15
    //   799: iconst_0
    //   800: istore #10
    //   802: fconst_0
    //   803: fstore #7
    //   805: iload #10
    //   807: iload #8
    //   809: if_icmpge -> 1045
    //   812: aload_0
    //   813: iload #10
    //   815: invokevirtual get : (I)Ljava/lang/Object;
    //   818: checkcast androidx/constraintlayout/solver/widgets/ConstraintWidget
    //   821: astore #16
    //   823: aload #16
    //   825: getfield ad : [F
    //   828: iload_2
    //   829: faload
    //   830: fstore #5
    //   832: fload #5
    //   834: fconst_0
    //   835: fcmpg
    //   836: ifge -> 885
    //   839: aload #4
    //   841: getfield n : Z
    //   844: ifeq -> 879
    //   847: aload_1
    //   848: aload #16
    //   850: getfield A : [Landroidx/constraintlayout/solver/widgets/ConstraintAnchor;
    //   853: iload_3
    //   854: iconst_1
    //   855: iadd
    //   856: aaload
    //   857: getfield f : Landroidx/constraintlayout/solver/SolverVariable;
    //   860: aload #16
    //   862: getfield A : [Landroidx/constraintlayout/solver/widgets/ConstraintAnchor;
    //   865: iload_3
    //   866: aaload
    //   867: getfield f : Landroidx/constraintlayout/solver/SolverVariable;
    //   870: iconst_0
    //   871: iconst_4
    //   872: invokevirtual c : (Landroidx/constraintlayout/solver/SolverVariable;Landroidx/constraintlayout/solver/SolverVariable;II)Landroidx/constraintlayout/solver/b;
    //   875: pop
    //   876: goto -> 922
    //   879: fconst_1
    //   880: fstore #5
    //   882: goto -> 885
    //   885: fload #5
    //   887: fconst_0
    //   888: fcmpl
    //   889: ifne -> 929
    //   892: aload_1
    //   893: aload #16
    //   895: getfield A : [Landroidx/constraintlayout/solver/widgets/ConstraintAnchor;
    //   898: iload_3
    //   899: iconst_1
    //   900: iadd
    //   901: aaload
    //   902: getfield f : Landroidx/constraintlayout/solver/SolverVariable;
    //   905: aload #16
    //   907: getfield A : [Landroidx/constraintlayout/solver/widgets/ConstraintAnchor;
    //   910: iload_3
    //   911: aaload
    //   912: getfield f : Landroidx/constraintlayout/solver/SolverVariable;
    //   915: iconst_0
    //   916: bipush #6
    //   918: invokevirtual c : (Landroidx/constraintlayout/solver/SolverVariable;Landroidx/constraintlayout/solver/SolverVariable;II)Landroidx/constraintlayout/solver/b;
    //   921: pop
    //   922: fload #7
    //   924: fstore #5
    //   926: goto -> 1032
    //   929: aload #15
    //   931: ifnull -> 1028
    //   934: aload #15
    //   936: getfield A : [Landroidx/constraintlayout/solver/widgets/ConstraintAnchor;
    //   939: iload_3
    //   940: aaload
    //   941: getfield f : Landroidx/constraintlayout/solver/SolverVariable;
    //   944: astore #20
    //   946: aload #15
    //   948: getfield A : [Landroidx/constraintlayout/solver/widgets/ConstraintAnchor;
    //   951: astore #15
    //   953: iload_3
    //   954: iconst_1
    //   955: iadd
    //   956: istore #12
    //   958: aload #15
    //   960: iload #12
    //   962: aaload
    //   963: getfield f : Landroidx/constraintlayout/solver/SolverVariable;
    //   966: astore #15
    //   968: aload #16
    //   970: getfield A : [Landroidx/constraintlayout/solver/widgets/ConstraintAnchor;
    //   973: iload_3
    //   974: aaload
    //   975: getfield f : Landroidx/constraintlayout/solver/SolverVariable;
    //   978: astore #21
    //   980: aload #16
    //   982: getfield A : [Landroidx/constraintlayout/solver/widgets/ConstraintAnchor;
    //   985: iload #12
    //   987: aaload
    //   988: getfield f : Landroidx/constraintlayout/solver/SolverVariable;
    //   991: astore #24
    //   993: aload_1
    //   994: invokevirtual c : ()Landroidx/constraintlayout/solver/b;
    //   997: astore #25
    //   999: aload #25
    //   1001: fload #7
    //   1003: fload #6
    //   1005: fload #5
    //   1007: aload #20
    //   1009: aload #15
    //   1011: aload #21
    //   1013: aload #24
    //   1015: invokevirtual a : (FFFLandroidx/constraintlayout/solver/SolverVariable;Landroidx/constraintlayout/solver/SolverVariable;Landroidx/constraintlayout/solver/SolverVariable;Landroidx/constraintlayout/solver/SolverVariable;)Landroidx/constraintlayout/solver/b;
    //   1018: pop
    //   1019: aload_1
    //   1020: aload #25
    //   1022: invokevirtual a : (Landroidx/constraintlayout/solver/b;)V
    //   1025: goto -> 1028
    //   1028: aload #16
    //   1030: astore #15
    //   1032: iload #10
    //   1034: iconst_1
    //   1035: iadd
    //   1036: istore #10
    //   1038: fload #5
    //   1040: fstore #7
    //   1042: goto -> 805
    //   1045: aload #18
    //   1047: ifnull -> 1251
    //   1050: aload #18
    //   1052: aload #23
    //   1054: if_acmpeq -> 1062
    //   1057: iload #13
    //   1059: ifeq -> 1251
    //   1062: aload #19
    //   1064: getfield A : [Landroidx/constraintlayout/solver/widgets/ConstraintAnchor;
    //   1067: iload_3
    //   1068: aaload
    //   1069: astore #15
    //   1071: aload #22
    //   1073: getfield A : [Landroidx/constraintlayout/solver/widgets/ConstraintAnchor;
    //   1076: astore_0
    //   1077: iload_3
    //   1078: iconst_1
    //   1079: iadd
    //   1080: istore #8
    //   1082: aload_0
    //   1083: iload #8
    //   1085: aaload
    //   1086: astore #16
    //   1088: aload #19
    //   1090: getfield A : [Landroidx/constraintlayout/solver/widgets/ConstraintAnchor;
    //   1093: iload_3
    //   1094: aaload
    //   1095: getfield c : Landroidx/constraintlayout/solver/widgets/ConstraintAnchor;
    //   1098: ifnull -> 1118
    //   1101: aload #19
    //   1103: getfield A : [Landroidx/constraintlayout/solver/widgets/ConstraintAnchor;
    //   1106: iload_3
    //   1107: aaload
    //   1108: getfield c : Landroidx/constraintlayout/solver/widgets/ConstraintAnchor;
    //   1111: getfield f : Landroidx/constraintlayout/solver/SolverVariable;
    //   1114: astore_0
    //   1115: goto -> 1120
    //   1118: aconst_null
    //   1119: astore_0
    //   1120: aload #22
    //   1122: getfield A : [Landroidx/constraintlayout/solver/widgets/ConstraintAnchor;
    //   1125: iload #8
    //   1127: aaload
    //   1128: getfield c : Landroidx/constraintlayout/solver/widgets/ConstraintAnchor;
    //   1131: ifnull -> 1153
    //   1134: aload #22
    //   1136: getfield A : [Landroidx/constraintlayout/solver/widgets/ConstraintAnchor;
    //   1139: iload #8
    //   1141: aaload
    //   1142: getfield c : Landroidx/constraintlayout/solver/widgets/ConstraintAnchor;
    //   1145: getfield f : Landroidx/constraintlayout/solver/SolverVariable;
    //   1148: astore #4
    //   1150: goto -> 1156
    //   1153: aconst_null
    //   1154: astore #4
    //   1156: aload #18
    //   1158: aload #23
    //   1160: if_acmpne -> 1182
    //   1163: aload #18
    //   1165: getfield A : [Landroidx/constraintlayout/solver/widgets/ConstraintAnchor;
    //   1168: iload_3
    //   1169: aaload
    //   1170: astore #15
    //   1172: aload #18
    //   1174: getfield A : [Landroidx/constraintlayout/solver/widgets/ConstraintAnchor;
    //   1177: iload #8
    //   1179: aaload
    //   1180: astore #16
    //   1182: aload_0
    //   1183: ifnull -> 2334
    //   1186: aload #4
    //   1188: ifnull -> 2334
    //   1191: iload_2
    //   1192: ifne -> 1205
    //   1195: aload #17
    //   1197: getfield S : F
    //   1200: fstore #5
    //   1202: goto -> 1212
    //   1205: aload #17
    //   1207: getfield T : F
    //   1210: fstore #5
    //   1212: aload #15
    //   1214: invokevirtual e : ()I
    //   1217: istore_2
    //   1218: aload #16
    //   1220: invokevirtual e : ()I
    //   1223: istore #8
    //   1225: aload_1
    //   1226: aload #15
    //   1228: getfield f : Landroidx/constraintlayout/solver/SolverVariable;
    //   1231: aload_0
    //   1232: iload_2
    //   1233: fload #5
    //   1235: aload #4
    //   1237: aload #16
    //   1239: getfield f : Landroidx/constraintlayout/solver/SolverVariable;
    //   1242: iload #8
    //   1244: iconst_5
    //   1245: invokevirtual a : (Landroidx/constraintlayout/solver/SolverVariable;Landroidx/constraintlayout/solver/SolverVariable;IFLandroidx/constraintlayout/solver/SolverVariable;Landroidx/constraintlayout/solver/SolverVariable;II)V
    //   1248: goto -> 2334
    //   1251: iload #9
    //   1253: ifeq -> 1757
    //   1256: aload #18
    //   1258: ifnull -> 1757
    //   1261: aload #4
    //   1263: getfield j : I
    //   1266: ifle -> 1288
    //   1269: aload #4
    //   1271: getfield i : I
    //   1274: aload #4
    //   1276: getfield j : I
    //   1279: if_icmpne -> 1288
    //   1282: iconst_1
    //   1283: istore #12
    //   1285: goto -> 1291
    //   1288: iconst_0
    //   1289: istore #12
    //   1291: aload #18
    //   1293: astore #4
    //   1295: aload #4
    //   1297: astore #17
    //   1299: aload #4
    //   1301: ifnull -> 2334
    //   1304: aload #4
    //   1306: getfield af : [Landroidx/constraintlayout/solver/widgets/ConstraintWidget;
    //   1309: iload_2
    //   1310: aaload
    //   1311: astore #15
    //   1313: aload #15
    //   1315: ifnull -> 1340
    //   1318: aload #15
    //   1320: invokevirtual l : ()I
    //   1323: bipush #8
    //   1325: if_icmpne -> 1340
    //   1328: aload #15
    //   1330: getfield af : [Landroidx/constraintlayout/solver/widgets/ConstraintWidget;
    //   1333: iload_2
    //   1334: aaload
    //   1335: astore #15
    //   1337: goto -> 1313
    //   1340: aload #15
    //   1342: ifnonnull -> 1358
    //   1345: aload #4
    //   1347: aload #23
    //   1349: if_acmpne -> 1355
    //   1352: goto -> 1358
    //   1355: goto -> 1736
    //   1358: aload #4
    //   1360: getfield A : [Landroidx/constraintlayout/solver/widgets/ConstraintAnchor;
    //   1363: iload_3
    //   1364: aaload
    //   1365: astore #20
    //   1367: aload #20
    //   1369: getfield f : Landroidx/constraintlayout/solver/SolverVariable;
    //   1372: astore #25
    //   1374: aload #20
    //   1376: getfield c : Landroidx/constraintlayout/solver/widgets/ConstraintAnchor;
    //   1379: ifnull -> 1395
    //   1382: aload #20
    //   1384: getfield c : Landroidx/constraintlayout/solver/widgets/ConstraintAnchor;
    //   1387: getfield f : Landroidx/constraintlayout/solver/SolverVariable;
    //   1390: astore #16
    //   1392: goto -> 1398
    //   1395: aconst_null
    //   1396: astore #16
    //   1398: aload #17
    //   1400: aload #4
    //   1402: if_acmpeq -> 1421
    //   1405: aload #17
    //   1407: getfield A : [Landroidx/constraintlayout/solver/widgets/ConstraintAnchor;
    //   1410: iload_3
    //   1411: iconst_1
    //   1412: iadd
    //   1413: aaload
    //   1414: getfield f : Landroidx/constraintlayout/solver/SolverVariable;
    //   1417: astore_0
    //   1418: goto -> 1473
    //   1421: aload #16
    //   1423: astore_0
    //   1424: aload #4
    //   1426: aload #18
    //   1428: if_acmpne -> 1473
    //   1431: aload #16
    //   1433: astore_0
    //   1434: aload #17
    //   1436: aload #4
    //   1438: if_acmpne -> 1473
    //   1441: aload #19
    //   1443: getfield A : [Landroidx/constraintlayout/solver/widgets/ConstraintAnchor;
    //   1446: iload_3
    //   1447: aaload
    //   1448: getfield c : Landroidx/constraintlayout/solver/widgets/ConstraintAnchor;
    //   1451: ifnull -> 1471
    //   1454: aload #19
    //   1456: getfield A : [Landroidx/constraintlayout/solver/widgets/ConstraintAnchor;
    //   1459: iload_3
    //   1460: aaload
    //   1461: getfield c : Landroidx/constraintlayout/solver/widgets/ConstraintAnchor;
    //   1464: getfield f : Landroidx/constraintlayout/solver/SolverVariable;
    //   1467: astore_0
    //   1468: goto -> 1473
    //   1471: aconst_null
    //   1472: astore_0
    //   1473: aload #20
    //   1475: invokevirtual e : ()I
    //   1478: istore #13
    //   1480: aload #4
    //   1482: getfield A : [Landroidx/constraintlayout/solver/widgets/ConstraintAnchor;
    //   1485: astore #16
    //   1487: iload_3
    //   1488: iconst_1
    //   1489: iadd
    //   1490: istore #14
    //   1492: aload #16
    //   1494: iload #14
    //   1496: aaload
    //   1497: invokevirtual e : ()I
    //   1500: istore #10
    //   1502: aload #15
    //   1504: ifnull -> 1539
    //   1507: aload #15
    //   1509: getfield A : [Landroidx/constraintlayout/solver/widgets/ConstraintAnchor;
    //   1512: iload_3
    //   1513: aaload
    //   1514: astore #16
    //   1516: aload #16
    //   1518: getfield f : Landroidx/constraintlayout/solver/SolverVariable;
    //   1521: astore #20
    //   1523: aload #4
    //   1525: getfield A : [Landroidx/constraintlayout/solver/widgets/ConstraintAnchor;
    //   1528: iload #14
    //   1530: aaload
    //   1531: getfield f : Landroidx/constraintlayout/solver/SolverVariable;
    //   1534: astore #21
    //   1536: goto -> 1591
    //   1539: aload #22
    //   1541: getfield A : [Landroidx/constraintlayout/solver/widgets/ConstraintAnchor;
    //   1544: iload #14
    //   1546: aaload
    //   1547: getfield c : Landroidx/constraintlayout/solver/widgets/ConstraintAnchor;
    //   1550: astore #24
    //   1552: aload #24
    //   1554: ifnull -> 1567
    //   1557: aload #24
    //   1559: getfield f : Landroidx/constraintlayout/solver/SolverVariable;
    //   1562: astore #16
    //   1564: goto -> 1570
    //   1567: aconst_null
    //   1568: astore #16
    //   1570: aload #4
    //   1572: getfield A : [Landroidx/constraintlayout/solver/widgets/ConstraintAnchor;
    //   1575: iload #14
    //   1577: aaload
    //   1578: getfield f : Landroidx/constraintlayout/solver/SolverVariable;
    //   1581: astore #21
    //   1583: aload #16
    //   1585: astore #20
    //   1587: aload #24
    //   1589: astore #16
    //   1591: iload #10
    //   1593: istore #8
    //   1595: aload #16
    //   1597: ifnull -> 1610
    //   1600: iload #10
    //   1602: aload #16
    //   1604: invokevirtual e : ()I
    //   1607: iadd
    //   1608: istore #8
    //   1610: iload #13
    //   1612: istore #10
    //   1614: aload #17
    //   1616: ifnull -> 1635
    //   1619: iload #13
    //   1621: aload #17
    //   1623: getfield A : [Landroidx/constraintlayout/solver/widgets/ConstraintAnchor;
    //   1626: iload #14
    //   1628: aaload
    //   1629: invokevirtual e : ()I
    //   1632: iadd
    //   1633: istore #10
    //   1635: aload #25
    //   1637: ifnull -> 1736
    //   1640: aload_0
    //   1641: ifnull -> 1736
    //   1644: aload #20
    //   1646: ifnull -> 1736
    //   1649: aload #21
    //   1651: ifnull -> 1736
    //   1654: aload #4
    //   1656: aload #18
    //   1658: if_acmpne -> 1676
    //   1661: aload #18
    //   1663: getfield A : [Landroidx/constraintlayout/solver/widgets/ConstraintAnchor;
    //   1666: iload_3
    //   1667: aaload
    //   1668: invokevirtual e : ()I
    //   1671: istore #10
    //   1673: goto -> 1676
    //   1676: aload #4
    //   1678: aload #23
    //   1680: if_acmpne -> 1699
    //   1683: aload #23
    //   1685: getfield A : [Landroidx/constraintlayout/solver/widgets/ConstraintAnchor;
    //   1688: iload #14
    //   1690: aaload
    //   1691: invokevirtual e : ()I
    //   1694: istore #8
    //   1696: goto -> 1699
    //   1699: iload #12
    //   1701: ifeq -> 1711
    //   1704: bipush #6
    //   1706: istore #13
    //   1708: goto -> 1714
    //   1711: iconst_4
    //   1712: istore #13
    //   1714: aload_1
    //   1715: aload #25
    //   1717: aload_0
    //   1718: iload #10
    //   1720: ldc 0.5
    //   1722: aload #20
    //   1724: aload #21
    //   1726: iload #8
    //   1728: iload #13
    //   1730: invokevirtual a : (Landroidx/constraintlayout/solver/SolverVariable;Landroidx/constraintlayout/solver/SolverVariable;IFLandroidx/constraintlayout/solver/SolverVariable;Landroidx/constraintlayout/solver/SolverVariable;II)V
    //   1733: goto -> 1736
    //   1736: aload #4
    //   1738: invokevirtual l : ()I
    //   1741: bipush #8
    //   1743: if_icmpeq -> 1750
    //   1746: aload #4
    //   1748: astore #17
    //   1750: aload #15
    //   1752: astore #4
    //   1754: goto -> 1299
    //   1757: iload #11
    //   1759: ifeq -> 2334
    //   1762: aload #18
    //   1764: ifnull -> 2334
    //   1767: aload #4
    //   1769: getfield j : I
    //   1772: ifle -> 1794
    //   1775: aload #4
    //   1777: getfield i : I
    //   1780: aload #4
    //   1782: getfield j : I
    //   1785: if_icmpne -> 1794
    //   1788: iconst_1
    //   1789: istore #8
    //   1791: goto -> 1797
    //   1794: iconst_0
    //   1795: istore #8
    //   1797: aload #18
    //   1799: astore #4
    //   1801: aload #4
    //   1803: astore #15
    //   1805: aload #4
    //   1807: ifnull -> 2174
    //   1810: aload #4
    //   1812: getfield af : [Landroidx/constraintlayout/solver/widgets/ConstraintWidget;
    //   1815: iload_2
    //   1816: aaload
    //   1817: astore_0
    //   1818: aload_0
    //   1819: ifnull -> 1841
    //   1822: aload_0
    //   1823: invokevirtual l : ()I
    //   1826: bipush #8
    //   1828: if_icmpne -> 1841
    //   1831: aload_0
    //   1832: getfield af : [Landroidx/constraintlayout/solver/widgets/ConstraintWidget;
    //   1835: iload_2
    //   1836: aaload
    //   1837: astore_0
    //   1838: goto -> 1818
    //   1841: aload #4
    //   1843: aload #18
    //   1845: if_acmpeq -> 2147
    //   1848: aload #4
    //   1850: aload #23
    //   1852: if_acmpeq -> 2147
    //   1855: aload_0
    //   1856: ifnull -> 2147
    //   1859: aload_0
    //   1860: aload #23
    //   1862: if_acmpne -> 1870
    //   1865: aconst_null
    //   1866: astore_0
    //   1867: goto -> 1870
    //   1870: aload #4
    //   1872: getfield A : [Landroidx/constraintlayout/solver/widgets/ConstraintAnchor;
    //   1875: iload_3
    //   1876: aaload
    //   1877: astore #16
    //   1879: aload #16
    //   1881: getfield f : Landroidx/constraintlayout/solver/SolverVariable;
    //   1884: astore #24
    //   1886: aload #16
    //   1888: getfield c : Landroidx/constraintlayout/solver/widgets/ConstraintAnchor;
    //   1891: ifnull -> 1904
    //   1894: aload #16
    //   1896: getfield c : Landroidx/constraintlayout/solver/widgets/ConstraintAnchor;
    //   1899: getfield f : Landroidx/constraintlayout/solver/SolverVariable;
    //   1902: astore #17
    //   1904: aload #15
    //   1906: getfield A : [Landroidx/constraintlayout/solver/widgets/ConstraintAnchor;
    //   1909: astore #17
    //   1911: iload_3
    //   1912: iconst_1
    //   1913: iadd
    //   1914: istore #13
    //   1916: aload #17
    //   1918: iload #13
    //   1920: aaload
    //   1921: getfield f : Landroidx/constraintlayout/solver/SolverVariable;
    //   1924: astore #25
    //   1926: aload #16
    //   1928: invokevirtual e : ()I
    //   1931: istore #12
    //   1933: aload #4
    //   1935: getfield A : [Landroidx/constraintlayout/solver/widgets/ConstraintAnchor;
    //   1938: iload #13
    //   1940: aaload
    //   1941: invokevirtual e : ()I
    //   1944: istore #10
    //   1946: aload_0
    //   1947: ifnull -> 1992
    //   1950: aload_0
    //   1951: getfield A : [Landroidx/constraintlayout/solver/widgets/ConstraintAnchor;
    //   1954: iload_3
    //   1955: aaload
    //   1956: astore #17
    //   1958: aload #17
    //   1960: getfield f : Landroidx/constraintlayout/solver/SolverVariable;
    //   1963: astore #20
    //   1965: aload #17
    //   1967: getfield c : Landroidx/constraintlayout/solver/widgets/ConstraintAnchor;
    //   1970: ifnull -> 1986
    //   1973: aload #17
    //   1975: getfield c : Landroidx/constraintlayout/solver/widgets/ConstraintAnchor;
    //   1978: getfield f : Landroidx/constraintlayout/solver/SolverVariable;
    //   1981: astore #16
    //   1983: goto -> 2044
    //   1986: aconst_null
    //   1987: astore #16
    //   1989: goto -> 2044
    //   1992: aload #4
    //   1994: getfield A : [Landroidx/constraintlayout/solver/widgets/ConstraintAnchor;
    //   1997: iload #13
    //   1999: aaload
    //   2000: getfield c : Landroidx/constraintlayout/solver/widgets/ConstraintAnchor;
    //   2003: astore #21
    //   2005: aload #21
    //   2007: ifnull -> 2020
    //   2010: aload #21
    //   2012: getfield f : Landroidx/constraintlayout/solver/SolverVariable;
    //   2015: astore #17
    //   2017: goto -> 2023
    //   2020: aconst_null
    //   2021: astore #17
    //   2023: aload #4
    //   2025: getfield A : [Landroidx/constraintlayout/solver/widgets/ConstraintAnchor;
    //   2028: iload #13
    //   2030: aaload
    //   2031: getfield f : Landroidx/constraintlayout/solver/SolverVariable;
    //   2034: astore #16
    //   2036: aload #17
    //   2038: astore #20
    //   2040: aload #21
    //   2042: astore #17
    //   2044: aload #17
    //   2046: ifnull -> 2062
    //   2049: iload #10
    //   2051: aload #17
    //   2053: invokevirtual e : ()I
    //   2056: iadd
    //   2057: istore #10
    //   2059: goto -> 2062
    //   2062: aload #15
    //   2064: ifnull -> 2086
    //   2067: iload #12
    //   2069: aload #15
    //   2071: getfield A : [Landroidx/constraintlayout/solver/widgets/ConstraintAnchor;
    //   2074: iload #13
    //   2076: aaload
    //   2077: invokevirtual e : ()I
    //   2080: iadd
    //   2081: istore #12
    //   2083: goto -> 2086
    //   2086: iload #8
    //   2088: ifeq -> 2098
    //   2091: bipush #6
    //   2093: istore #13
    //   2095: goto -> 2101
    //   2098: iconst_4
    //   2099: istore #13
    //   2101: aload #24
    //   2103: ifnull -> 2144
    //   2106: aload #25
    //   2108: ifnull -> 2144
    //   2111: aload #20
    //   2113: ifnull -> 2144
    //   2116: aload #16
    //   2118: ifnull -> 2144
    //   2121: aload_1
    //   2122: aload #24
    //   2124: aload #25
    //   2126: iload #12
    //   2128: ldc 0.5
    //   2130: aload #20
    //   2132: aload #16
    //   2134: iload #10
    //   2136: iload #13
    //   2138: invokevirtual a : (Landroidx/constraintlayout/solver/SolverVariable;Landroidx/constraintlayout/solver/SolverVariable;IFLandroidx/constraintlayout/solver/SolverVariable;Landroidx/constraintlayout/solver/SolverVariable;II)V
    //   2141: goto -> 2144
    //   2144: goto -> 2147
    //   2147: aload #4
    //   2149: invokevirtual l : ()I
    //   2152: bipush #8
    //   2154: if_icmpeq -> 2160
    //   2157: goto -> 2164
    //   2160: aload #15
    //   2162: astore #4
    //   2164: aload #4
    //   2166: astore #15
    //   2168: aload_0
    //   2169: astore #4
    //   2171: goto -> 1805
    //   2174: aload #18
    //   2176: getfield A : [Landroidx/constraintlayout/solver/widgets/ConstraintAnchor;
    //   2179: iload_3
    //   2180: aaload
    //   2181: astore_0
    //   2182: aload #19
    //   2184: getfield A : [Landroidx/constraintlayout/solver/widgets/ConstraintAnchor;
    //   2187: iload_3
    //   2188: aaload
    //   2189: getfield c : Landroidx/constraintlayout/solver/widgets/ConstraintAnchor;
    //   2192: astore #4
    //   2194: aload #23
    //   2196: getfield A : [Landroidx/constraintlayout/solver/widgets/ConstraintAnchor;
    //   2199: astore #15
    //   2201: iload_3
    //   2202: iconst_1
    //   2203: iadd
    //   2204: istore_2
    //   2205: aload #15
    //   2207: iload_2
    //   2208: aaload
    //   2209: astore #15
    //   2211: aload #22
    //   2213: getfield A : [Landroidx/constraintlayout/solver/widgets/ConstraintAnchor;
    //   2216: iload_2
    //   2217: aaload
    //   2218: getfield c : Landroidx/constraintlayout/solver/widgets/ConstraintAnchor;
    //   2221: astore #16
    //   2223: aload #4
    //   2225: ifnull -> 2300
    //   2228: aload #18
    //   2230: aload #23
    //   2232: if_acmpeq -> 2257
    //   2235: aload_1
    //   2236: aload_0
    //   2237: getfield f : Landroidx/constraintlayout/solver/SolverVariable;
    //   2240: aload #4
    //   2242: getfield f : Landroidx/constraintlayout/solver/SolverVariable;
    //   2245: aload_0
    //   2246: invokevirtual e : ()I
    //   2249: iconst_5
    //   2250: invokevirtual c : (Landroidx/constraintlayout/solver/SolverVariable;Landroidx/constraintlayout/solver/SolverVariable;II)Landroidx/constraintlayout/solver/b;
    //   2253: pop
    //   2254: goto -> 2300
    //   2257: aload #16
    //   2259: ifnull -> 2300
    //   2262: aload_1
    //   2263: aload_0
    //   2264: getfield f : Landroidx/constraintlayout/solver/SolverVariable;
    //   2267: aload #4
    //   2269: getfield f : Landroidx/constraintlayout/solver/SolverVariable;
    //   2272: aload_0
    //   2273: invokevirtual e : ()I
    //   2276: ldc 0.5
    //   2278: aload #15
    //   2280: getfield f : Landroidx/constraintlayout/solver/SolverVariable;
    //   2283: aload #16
    //   2285: getfield f : Landroidx/constraintlayout/solver/SolverVariable;
    //   2288: aload #15
    //   2290: invokevirtual e : ()I
    //   2293: iconst_5
    //   2294: invokevirtual a : (Landroidx/constraintlayout/solver/SolverVariable;Landroidx/constraintlayout/solver/SolverVariable;IFLandroidx/constraintlayout/solver/SolverVariable;Landroidx/constraintlayout/solver/SolverVariable;II)V
    //   2297: goto -> 2300
    //   2300: aload #16
    //   2302: ifnull -> 2334
    //   2305: aload #18
    //   2307: aload #23
    //   2309: if_acmpeq -> 2334
    //   2312: aload_1
    //   2313: aload #15
    //   2315: getfield f : Landroidx/constraintlayout/solver/SolverVariable;
    //   2318: aload #16
    //   2320: getfield f : Landroidx/constraintlayout/solver/SolverVariable;
    //   2323: aload #15
    //   2325: invokevirtual e : ()I
    //   2328: ineg
    //   2329: iconst_5
    //   2330: invokevirtual c : (Landroidx/constraintlayout/solver/SolverVariable;Landroidx/constraintlayout/solver/SolverVariable;II)Landroidx/constraintlayout/solver/b;
    //   2333: pop
    //   2334: iload #9
    //   2336: ifne -> 2344
    //   2339: iload #11
    //   2341: ifeq -> 2546
    //   2344: aload #18
    //   2346: ifnull -> 2546
    //   2349: aload #18
    //   2351: getfield A : [Landroidx/constraintlayout/solver/widgets/ConstraintAnchor;
    //   2354: iload_3
    //   2355: aaload
    //   2356: astore #15
    //   2358: aload #23
    //   2360: getfield A : [Landroidx/constraintlayout/solver/widgets/ConstraintAnchor;
    //   2363: astore_0
    //   2364: iload_3
    //   2365: iconst_1
    //   2366: iadd
    //   2367: istore_2
    //   2368: aload_0
    //   2369: iload_2
    //   2370: aaload
    //   2371: astore #16
    //   2373: aload #15
    //   2375: getfield c : Landroidx/constraintlayout/solver/widgets/ConstraintAnchor;
    //   2378: ifnull -> 2394
    //   2381: aload #15
    //   2383: getfield c : Landroidx/constraintlayout/solver/widgets/ConstraintAnchor;
    //   2386: getfield f : Landroidx/constraintlayout/solver/SolverVariable;
    //   2389: astore #4
    //   2391: goto -> 2397
    //   2394: aconst_null
    //   2395: astore #4
    //   2397: aload #16
    //   2399: getfield c : Landroidx/constraintlayout/solver/widgets/ConstraintAnchor;
    //   2402: ifnull -> 2417
    //   2405: aload #16
    //   2407: getfield c : Landroidx/constraintlayout/solver/widgets/ConstraintAnchor;
    //   2410: getfield f : Landroidx/constraintlayout/solver/SolverVariable;
    //   2413: astore_0
    //   2414: goto -> 2419
    //   2417: aconst_null
    //   2418: astore_0
    //   2419: aload #22
    //   2421: aload #23
    //   2423: if_acmpeq -> 2457
    //   2426: aload #22
    //   2428: getfield A : [Landroidx/constraintlayout/solver/widgets/ConstraintAnchor;
    //   2431: iload_2
    //   2432: aaload
    //   2433: astore_0
    //   2434: aload_0
    //   2435: getfield c : Landroidx/constraintlayout/solver/widgets/ConstraintAnchor;
    //   2438: ifnull -> 2452
    //   2441: aload_0
    //   2442: getfield c : Landroidx/constraintlayout/solver/widgets/ConstraintAnchor;
    //   2445: getfield f : Landroidx/constraintlayout/solver/SolverVariable;
    //   2448: astore_0
    //   2449: goto -> 2454
    //   2452: aconst_null
    //   2453: astore_0
    //   2454: goto -> 2457
    //   2457: aload #18
    //   2459: aload #23
    //   2461: if_acmpne -> 2482
    //   2464: aload #18
    //   2466: getfield A : [Landroidx/constraintlayout/solver/widgets/ConstraintAnchor;
    //   2469: iload_3
    //   2470: aaload
    //   2471: astore #15
    //   2473: aload #18
    //   2475: getfield A : [Landroidx/constraintlayout/solver/widgets/ConstraintAnchor;
    //   2478: iload_2
    //   2479: aaload
    //   2480: astore #16
    //   2482: aload #4
    //   2484: ifnull -> 2546
    //   2487: aload_0
    //   2488: ifnull -> 2546
    //   2491: aload #15
    //   2493: invokevirtual e : ()I
    //   2496: istore_3
    //   2497: aload #23
    //   2499: ifnonnull -> 2509
    //   2502: aload #22
    //   2504: astore #17
    //   2506: goto -> 2513
    //   2509: aload #23
    //   2511: astore #17
    //   2513: aload #17
    //   2515: getfield A : [Landroidx/constraintlayout/solver/widgets/ConstraintAnchor;
    //   2518: iload_2
    //   2519: aaload
    //   2520: invokevirtual e : ()I
    //   2523: istore_2
    //   2524: aload_1
    //   2525: aload #15
    //   2527: getfield f : Landroidx/constraintlayout/solver/SolverVariable;
    //   2530: aload #4
    //   2532: iload_3
    //   2533: ldc 0.5
    //   2535: aload_0
    //   2536: aload #16
    //   2538: getfield f : Landroidx/constraintlayout/solver/SolverVariable;
    //   2541: iload_2
    //   2542: iconst_5
    //   2543: invokevirtual a : (Landroidx/constraintlayout/solver/SolverVariable;Landroidx/constraintlayout/solver/SolverVariable;IFLandroidx/constraintlayout/solver/SolverVariable;Landroidx/constraintlayout/solver/SolverVariable;II)V
    //   2546: return
  }
}


/* Location:              /home/egaebel/Programs/sony-headphones-hack/base-dex2jar.jar!/androidx/constraintlayout/solver/widgets/c.class
 * Java compiler version: 6 (50.0)
 * JD-Core Version:       1.1.3
 */