package com.google.android.gms.ads.internal;

import android.content.Context;
import android.content.pm.ApplicationInfo;
import android.content.pm.PackageInfo;
import android.content.pm.PackageManager;
import android.os.Bundle;
import android.os.RemoteException;
import android.util.DisplayMetrics;
import android.view.View;
import com.google.android.gms.ads.internal.overlay.zzn;
import com.google.android.gms.common.internal.Hide;
import com.google.android.gms.common.internal.zzbq;
import com.google.android.gms.internal.zzabh;
import com.google.android.gms.internal.zzabk;
import com.google.android.gms.internal.zzacg;
import com.google.android.gms.internal.zzada;
import com.google.android.gms.internal.zzahd;
import com.google.android.gms.internal.zzahf;
import com.google.android.gms.internal.zzahh;
import com.google.android.gms.internal.zzahs;
import com.google.android.gms.internal.zzahw;
import com.google.android.gms.internal.zzaid;
import com.google.android.gms.internal.zzaij;
import com.google.android.gms.internal.zzaip;
import com.google.android.gms.internal.zzala;
import com.google.android.gms.internal.zzalt;
import com.google.android.gms.internal.zzaly;
import com.google.android.gms.internal.zzaof;
import com.google.android.gms.internal.zzbih;
import com.google.android.gms.internal.zzhm;
import com.google.android.gms.internal.zziw;
import com.google.android.gms.internal.zziz;
import com.google.android.gms.internal.zzkk;
import com.google.android.gms.internal.zzko;
import com.google.android.gms.internal.zzlc;
import com.google.android.gms.internal.zzms;
import com.google.android.gms.internal.zzny;
import com.google.android.gms.internal.zzoi;
import com.google.android.gms.internal.zzov;
import com.google.android.gms.internal.zzqh;
import com.google.android.gms.internal.zzro;
import com.google.android.gms.internal.zzus;
import com.google.android.gms.internal.zzvq;
import com.google.android.gms.internal.zzvr;
import com.google.android.gms.internal.zzvy;
import com.google.android.gms.internal.zzwf;
import java.util.ArrayList;
import java.util.List;
import java.util.UUID;
import java.util.concurrent.Executor;
import java.util.concurrent.Future;
import org.json.JSONArray;
import org.json.JSONException;
import org.json.JSONObject;

@zzabh
@Hide
public abstract class zzd extends zza implements zzn, zzbm, zzvr {
  protected final zzwf zzanu;
  
  private transient boolean zzanv;
  
  public zzd(Context paramContext, zzko paramzzko, String paramString, zzwf paramzzwf, zzala paramzzala, zzv paramzzv) {
    this(new zzbu(paramContext, paramzzko, paramString, paramzzala), paramzzwf, (zzbj)null, paramzzv);
  }
  
  private zzd(zzbu paramzzbu, zzwf paramzzwf, zzbj paramzzbj, zzv paramzzv) {
    super(paramzzbu, null, paramzzv);
    this.zzanu = paramzzwf;
    this.zzanv = false;
  }
  
  private final zzacg zza(zzkk paramzzkk, Bundle paramBundle, zzahh paramzzahh, int paramInt) {
    Bundle bundle1;
    String str1;
    ApplicationInfo applicationInfo = this.zzanm.zzaiq.getApplicationInfo();
    zzh zzh2 = null;
    int j = 0;
    try {
      PackageInfo packageInfo = zzbih.zzdd(this.zzanm.zzaiq).getPackageInfo(applicationInfo.packageName, 0);
    } catch (android.content.pm.PackageManager.NameNotFoundException nameNotFoundException) {
      nameNotFoundException = null;
    } 
    DisplayMetrics displayMetrics = this.zzanm.zzaiq.getResources().getDisplayMetrics();
    if (this.zzanm.zzaua != null && this.zzanm.zzaua.getParent() != null) {
      int[] arrayOfInt = new int[2];
      this.zzanm.zzaua.getLocationOnScreen(arrayOfInt);
      int i1 = arrayOfInt[0];
      boolean bool = true;
      int i2 = arrayOfInt[1];
      int i3 = this.zzanm.zzaua.getWidth();
      int i4 = this.zzanm.zzaua.getHeight();
      if (!this.zzanm.zzaua.isShown() || i1 + i3 <= 0 || i2 + i4 <= 0 || i1 > displayMetrics.widthPixels || i2 > displayMetrics.heightPixels)
        bool = false; 
      bundle1 = new Bundle(5);
      bundle1.putInt("x", i1);
      bundle1.putInt("y", i2);
      bundle1.putInt("width", i3);
      bundle1.putInt("height", i4);
      bundle1.putInt("visible", bool);
    } else {
      bundle1 = null;
    } 
    String str2 = zzbt.zzep().zzpu().zzqg();
    this.zzanm.zzaug = new zzahf(str2, this.zzanm.zzatx);
    this.zzanm.zzaug.zzn(paramzzkk);
    zzbt.zzel();
    String str3 = zzaij.zza(this.zzanm.zzaiq, (View)this.zzanm.zzaua, this.zzanm.zzaud);
    long l2 = 0L;
    long l1 = l2;
    if (this.zzanm.zzauk != null)
      try {
        l1 = this.zzanm.zzauk.getValue();
      } catch (RemoteException remoteException) {
        zzahw.zzcz("Cannot get correlation id, default to 0.");
        l1 = l2;
      }  
    String str4 = UUID.randomUUID().toString();
    Bundle bundle2 = zzbt.zzeq().zza(this.zzanm.zzaiq, this, str2);
    ArrayList<String> arrayList1 = new ArrayList();
    ArrayList<String> arrayList2 = new ArrayList();
    int i;
    for (i = 0; i < this.zzanm.zzaup.size(); i++) {
      str1 = (String)this.zzanm.zzaup.b(i);
      arrayList1.add(str1);
      if (this.zzanm.zzauo.containsKey(str1) && this.zzanm.zzauo.get(str1) != null)
        arrayList2.add(str1); 
    } 
    zzg zzg = new zzg(this);
    zzalt zzalt1 = zzaid.zza(zzaid.zzdfi, zzg);
    zzh zzh1 = new zzh(this);
    zzalt zzalt2 = zzaid.zza(zzaid.zzdfi, zzh1);
    if (paramzzahh != null) {
      String str = paramzzahh.zzps();
    } else {
      paramzzahh = null;
    } 
    zzh1 = zzh2;
    if (this.zzanm.zzauy != null) {
      zzh1 = zzh2;
      if (this.zzanm.zzauy.size() > 0) {
        i = j;
        if (nameNotFoundException != null)
          i = ((PackageInfo)nameNotFoundException).versionCode; 
        if (i > zzbt.zzep().zzqe().zzqu()) {
          zzbt.zzep().zzqe().zzra();
          zzbt.zzep().zzqe().zzac(i);
          zzh1 = zzh2;
        } else {
          JSONObject jSONObject = zzbt.zzep().zzqe().zzqz();
          zzh1 = zzh2;
          if (jSONObject != null) {
            JSONArray jSONArray = jSONObject.optJSONArray(this.zzanm.zzatx);
            zzh1 = zzh2;
            if (jSONArray != null)
              str1 = jSONArray.toString(); 
          } 
        } 
      } 
    } 
    zzko zzko = this.zzanm.zzaud;
    String str5 = this.zzanm.zzatx;
    String str6 = zzlc.zzil();
    zzala zzala = this.zzanm.zzatz;
    List<String> list1 = this.zzanm.zzauy;
    boolean bool1 = zzbt.zzep().zzqe().zzqo();
    i = displayMetrics.widthPixels;
    j = displayMetrics.heightPixels;
    float f1 = displayMetrics.density;
    List list = zzoi.zzjf();
    String str7 = this.zzanm.zzatw;
    zzqh zzqh = this.zzanm.zzauq;
    String str8 = this.zzanm.zzfq();
    float f2 = zzbt.zzfj().zzdp();
    boolean bool2 = zzbt.zzfj().zzdq();
    zzbt.zzel();
    int k = zzaij.zzap(this.zzanm.zzaiq);
    zzbt.zzel();
    int m = zzaij.zzw((View)this.zzanm.zzaua);
    boolean bool3 = this.zzanm.zzaiq instanceof android.app.Activity;
    boolean bool4 = zzbt.zzep().zzqe().zzqt();
    boolean bool5 = zzbt.zzep().zzpx();
    int n = zzbt.zzff().zzts();
    zzbt.zzel();
    Bundle bundle3 = zzaij.zzrf();
    String str9 = zzbt.zzev().zzrq();
    zzms zzms = this.zzanm.zzaus;
    boolean bool6 = zzbt.zzev().zzrr();
    Bundle bundle4 = zzus.zzln().asBundle();
    boolean bool7 = zzbt.zzep().zzqe().zzcf(this.zzanm.zzatx);
    List<Integer> list2 = this.zzanm.zzauu;
    boolean bool8 = zzbih.zzdd(this.zzanm.zzaiq).zzaoe();
    boolean bool9 = zzbt.zzep().zzpy();
    zzbt.zzen();
    return new zzacg(bundle1, paramzzkk, zzko, str5, applicationInfo, (PackageInfo)nameNotFoundException, str2, str6, zzala, bundle2, list1, arrayList1, paramBundle, bool1, i, j, f1, str3, l1, str4, list, str7, zzqh, str8, f2, bool2, k, m, bool3, bool4, (Future)zzalt1, (String)paramzzahh, bool5, n, bundle3, str9, zzms, bool6, bundle4, bool7, (Future)zzalt2, list2, str1, arrayList2, paramInt, bool8, bool9, zzaip.zzrk());
  }
  
  static String zzc(zzahd paramzzahd) {
    boolean bool;
    if (paramzzahd == null)
      return null; 
    String str = paramzzahd.zzcjg;
    if ("com.google.android.gms.ads.mediation.customevent.CustomEventAdapter".equals(str) || "com.google.ads.mediation.customevent.CustomEventAdapter".equals(str)) {
      bool = true;
    } else {
      bool = false;
    } 
    if (bool && paramzzahd.zzcje != null) {
      String str1 = paramzzahd.zzcje.zzchk;
      try {
        return (new JSONObject(str1)).getString("class_name");
      } catch (JSONException|NullPointerException jSONException) {
        return str;
      } 
    } 
    return str;
  }
  
  public final String getMediationAdapterClassName() {
    return (this.zzanm.zzaue == null) ? null : this.zzanm.zzaue.zzcjg;
  }
  
  public void onAdClicked() {
    if (this.zzanm.zzaue == null) {
      zzahw.zzcz("Ad state was null when trying to ping click URLs.");
      return;
    } 
    if (this.zzanm.zzaue.zzdcj != null && this.zzanm.zzaue.zzdcj.zzchw != null) {
      zzbt.zzfd();
      zzvy.zza(this.zzanm.zzaiq, this.zzanm.zzatz.zzcu, this.zzanm.zzaue, this.zzanm.zzatx, false, zzc(this.zzanm.zzaue.zzdcj.zzchw));
    } 
    if (this.zzanm.zzaue.zzcje != null && this.zzanm.zzaue.zzcje.zzchg != null) {
      zzbt.zzfd();
      zzvy.zza(this.zzanm.zzaiq, this.zzanm.zzatz.zzcu, this.zzanm.zzaue, this.zzanm.zzatx, false, this.zzanm.zzaue.zzcje.zzchg);
    } 
    super.onAdClicked();
  }
  
  public final void onPause() {
    this.zzano.zzj(this.zzanm.zzaue);
  }
  
  public final void onResume() {
    this.zzano.zzk(this.zzanm.zzaue);
  }
  
  public void pause() {
    zzbq.zzgn("pause must be called on the main UI thread.");
    if (this.zzanm.zzaue != null && this.zzanm.zzaue.zzcnm != null && this.zzanm.zzfo()) {
      zzbt.zzen();
      zzaip.zzh(this.zzanm.zzaue.zzcnm);
    } 
    if (this.zzanm.zzaue != null && this.zzanm.zzaue.zzcjf != null)
      try {
        this.zzanm.zzaue.zzcjf.pause();
      } catch (RemoteException remoteException) {
        zzahw.zzcz("Could not pause mediation adapter.");
      }  
    this.zzano.zzj(this.zzanm.zzaue);
    this.zzanl.pause();
  }
  
  public final void recordImpression() {
    zza(this.zzanm.zzaue, false);
  }
  
  public void resume() {
    zzaof zzaof;
    zzbq.zzgn("resume must be called on the main UI thread.");
    if (this.zzanm.zzaue != null && this.zzanm.zzaue.zzcnm != null) {
      zzaof = this.zzanm.zzaue.zzcnm;
    } else {
      zzaof = null;
    } 
    if (zzaof != null && this.zzanm.zzfo()) {
      zzbt.zzen();
      zzaip.zzi(this.zzanm.zzaue.zzcnm);
    } 
    if (this.zzanm.zzaue != null && this.zzanm.zzaue.zzcjf != null)
      try {
        this.zzanm.zzaue.zzcjf.resume();
      } catch (RemoteException remoteException) {
        zzahw.zzcz("Could not resume mediation adapter.");
      }  
    if (zzaof == null || !zzaof.zzug())
      this.zzanl.resume(); 
    this.zzano.zzk(this.zzanm.zzaue);
  }
  
  public void showInterstitial() {
    zzahw.zzcz("showInterstitial is not supported for current ad type");
  }
  
  protected void zza(zzahd paramzzahd, boolean paramBoolean) {
    if (paramzzahd == null) {
      zzahw.zzcz("Ad state was null when trying to ping impression URLs.");
      return;
    } 
    if (paramzzahd == null) {
      zzahw.zzcz("Ad state was null when trying to ping impression URLs.");
    } else {
      zzahw.zzby("Pinging Impression URLs.");
      if (this.zzanm.zzaug != null)
        this.zzanm.zzaug.zzpk(); 
      paramzzahd.zzdcu.zza(zziw.zza.zzb.zzbbs);
      if (paramzzahd.zzchx != null && !paramzzahd.zzdcq) {
        zzbt.zzel();
        zzaij.zza(this.zzanm.zzaiq, this.zzanm.zzatz.zzcu, zzc(paramzzahd.zzchx));
        paramzzahd.zzdcq = true;
      } 
    } 
    if (paramzzahd.zzdcr && !paramBoolean)
      return; 
    if (paramzzahd.zzdcj != null && paramzzahd.zzdcj.zzchx != null) {
      zzbt.zzfd();
      zzvy.zza(this.zzanm.zzaiq, this.zzanm.zzatz.zzcu, paramzzahd, this.zzanm.zzatx, paramBoolean, zzc(paramzzahd.zzdcj.zzchx));
    } 
    if (paramzzahd.zzcje != null && paramzzahd.zzcje.zzchh != null) {
      zzbt.zzfd();
      zzvy.zza(this.zzanm.zzaiq, this.zzanm.zzatz.zzcu, paramzzahd, this.zzanm.zzatx, paramBoolean, paramzzahd.zzcje.zzchh);
    } 
    paramzzahd.zzdcr = true;
  }
  
  public final void zza(zzro paramzzro, String paramString) {
    // Byte code:
    //   0: aconst_null
    //   1: astore #5
    //   3: aload_1
    //   4: ifnull -> 89
    //   7: aload_1
    //   8: invokeinterface getCustomTemplateId : ()Ljava/lang/String;
    //   13: astore_3
    //   14: goto -> 17
    //   17: aload #5
    //   19: astore #4
    //   21: aload_0
    //   22: getfield zzanm : Lcom/google/android/gms/ads/internal/zzbu;
    //   25: getfield zzauo : Landroidx/b/g;
    //   28: ifnull -> 55
    //   31: aload #5
    //   33: astore #4
    //   35: aload_3
    //   36: ifnull -> 55
    //   39: aload_0
    //   40: getfield zzanm : Lcom/google/android/gms/ads/internal/zzbu;
    //   43: getfield zzauo : Landroidx/b/g;
    //   46: aload_3
    //   47: invokevirtual get : (Ljava/lang/Object;)Ljava/lang/Object;
    //   50: checkcast com/google/android/gms/internal/zzry
    //   53: astore #4
    //   55: aload #4
    //   57: ifnonnull -> 67
    //   60: ldc_w 'Mediation adapter invoked onCustomClick but no listeners were set.'
    //   63: invokestatic zzcz : (Ljava/lang/String;)V
    //   66: return
    //   67: aload #4
    //   69: aload_1
    //   70: aload_2
    //   71: invokeinterface zzb : (Lcom/google/android/gms/internal/zzro;Ljava/lang/String;)V
    //   76: return
    //   77: ldc_w 'Unable to call onCustomClick.'
    //   80: aload_1
    //   81: invokestatic zzc : (Ljava/lang/String;Ljava/lang/Throwable;)V
    //   84: return
    //   85: astore_1
    //   86: goto -> 77
    //   89: aconst_null
    //   90: astore_3
    //   91: goto -> 17
    // Exception table:
    //   from	to	target	type
    //   7	14	85	android/os/RemoteException
    //   21	31	85	android/os/RemoteException
    //   39	55	85	android/os/RemoteException
    //   60	66	85	android/os/RemoteException
    //   67	76	85	android/os/RemoteException
  }
  
  public final boolean zza(zzacg paramzzacg, zzov paramzzov) {
    zzada zzada;
    zzabk zzabk;
    this.zzanh = paramzzov;
    paramzzov.zzf("seq_num", paramzzacg.zzcry);
    paramzzov.zzf("request_id", paramzzacg.zzcsi);
    paramzzov.zzf("session_id", paramzzacg.zzcrz);
    if (paramzzacg.zzcrw != null)
      paramzzov.zzf("app_version", String.valueOf(paramzzacg.zzcrw.versionCode)); 
    zzbu zzbu = this.zzanm;
    zzbt.zzeh();
    Context context = this.zzanm.zzaiq;
    zziz zziz = this.zzanp.zzaon;
    if (paramzzacg.zzcrv.extras.getBundle("sdk_less_server_data") != null) {
      zzada = new zzada(context, paramzzacg, this, zziz);
    } else {
      zzabk = new zzabk(context, (zzacg)zzada, this, zziz);
    } 
    zzabk.zzqj();
    zzbu.zzaub = (zzahs)zzabk;
    return true;
  }
  
  final boolean zza(zzahd paramzzahd) {
    zzkk zzkk = this.zzann;
    boolean bool = false;
    if (zzkk != null) {
      zzkk = this.zzann;
      this.zzann = null;
    } else {
      zzkk zzkk1 = paramzzahd.zzcrv;
      zzkk = zzkk1;
      if (zzkk1.extras != null) {
        bool = zzkk1.extras.getBoolean("_noRefresh", false);
        zzkk = zzkk1;
      } 
    } 
    return zza(zzkk, paramzzahd, bool);
  }
  
  protected boolean zza(zzahd paramzzahd1, zzahd paramzzahd2) {
    boolean bool;
    if (paramzzahd1 != null && paramzzahd1.zzcjh != null)
      paramzzahd1.zzcjh.zza(null); 
    if (paramzzahd2.zzcjh != null)
      paramzzahd2.zzcjh.zza(this); 
    zzvq zzvq = paramzzahd2.zzdcj;
    int i = 0;
    if (zzvq != null) {
      i = paramzzahd2.zzdcj.zzcik;
      bool = paramzzahd2.zzdcj.zzcil;
    } else {
      bool = false;
    } 
    this.zzanm.zzauz.zze(i, bool);
    return true;
  }
  
  protected boolean zza(zzkk paramzzkk, zzahd paramzzahd, boolean paramBoolean) {
    if (!paramBoolean && this.zzanm.zzfo()) {
      zzbj zzbj;
      long l;
      if (paramzzahd.zzcic > 0L) {
        zzbj zzbj1 = this.zzanl;
        l = paramzzahd.zzcic;
        zzbj = zzbj1;
      } else if (((zzahd)zzbj).zzdcj != null && ((zzahd)zzbj).zzdcj.zzcic > 0L) {
        zzbj zzbj1 = this.zzanl;
        l = ((zzahd)zzbj).zzdcj.zzcic;
        zzbj = zzbj1;
      } else {
        if (!((zzahd)zzbj).zzcto && ((zzahd)zzbj).errorCode == 2)
          this.zzanl.zzg(paramzzkk); 
        return this.zzanl.zzea();
      } 
      zzbj.zza(paramzzkk, l);
    } 
    return this.zzanl.zzea();
  }
  
  public boolean zza(zzkk paramzzkk, zzov paramzzov) {
    return zza(paramzzkk, paramzzov, 1);
  }
  
  public final boolean zza(zzkk paramzzkk, zzov paramzzov, int paramInt) {
    Bundle bundle;
    if (!zzce())
      return false; 
    zzbt.zzel();
    Context context = this.zzanm.zzaiq;
    zzhm zzhm = zzbt.zzep().zzad(context);
    String str = null;
    if (zzhm == null) {
      zzhm = null;
    } else {
      bundle = zzaij.zza(zzhm);
    } 
    this.zzanl.cancel();
    this.zzanm.zzavb = 0;
    zzny zzny = zzoi.zzbti;
    if (((Boolean)zzlc.zzio().zzd(zzny)).booleanValue()) {
      zzahh zzahh2 = zzbt.zzep().zzqe().zzqv();
      zzac zzac = zzbt.zzet();
      Context context1 = this.zzanm.zzaiq;
      zzala zzala = this.zzanm.zzatz;
      String str1 = this.zzanm.zzatx;
      if (zzahh2 != null)
        str = zzahh2.getAppId(); 
      zzac.zza(context1, zzala, false, zzahh2, str, str1, null);
      zzahh zzahh1 = zzahh2;
    } else {
      str = null;
    } 
    return zza(zza(paramzzkk, bundle, (zzahh)str, paramInt), paramzzov);
  }
  
  public final void zzb(zzahd paramzzahd) {
    super.zzb(paramzzahd);
    if (paramzzahd.zzcje != null) {
      zzahw.zzby("Disable the debug gesture detector on the mediation ad frame.");
      if (this.zzanm.zzaua != null)
        this.zzanm.zzaua.zzfu(); 
      zzahw.zzby("Pinging network fill URLs.");
      zzbt.zzfd();
      zzvy.zza(this.zzanm.zzaiq, this.zzanm.zzatz.zzcu, paramzzahd, this.zzanm.zzatx, false, paramzzahd.zzcje.zzchj);
      if (paramzzahd.zzdcj != null && paramzzahd.zzdcj.zzchz != null && paramzzahd.zzdcj.zzchz.size() > 0) {
        zzahw.zzby("Pinging urls remotely");
        zzbt.zzel().zza(this.zzanm.zzaiq, paramzzahd.zzdcj.zzchz);
      } 
    } else {
      zzahw.zzby("Enable the debug gesture detector on the admob ad frame.");
      if (this.zzanm.zzaua != null)
        this.zzanm.zzaua.zzft(); 
    } 
    if (paramzzahd.errorCode == 3 && paramzzahd.zzdcj != null && paramzzahd.zzdcj.zzchy != null) {
      zzahw.zzby("Pinging no fill URLs.");
      zzbt.zzfd();
      zzvy.zza(this.zzanm.zzaiq, this.zzanm.zzatz.zzcu, paramzzahd, this.zzanm.zzatx, false, paramzzahd.zzdcj.zzchy);
    } 
  }
  
  public final void zzc(String paramString1, String paramString2) {
    onAppEvent(paramString1, paramString2);
  }
  
  protected final boolean zzc(zzkk paramzzkk) {
    return (super.zzc(paramzzkk) && !this.zzanv);
  }
  
  protected boolean zzce() {
    zzbt.zzel();
    if (zzaij.zzd(this.zzanm.zzaiq, this.zzanm.zzaiq.getPackageName(), "android.permission.INTERNET")) {
      zzbt.zzel();
      if (zzaij.zzag(this.zzanm.zzaiq))
        return true; 
    } 
    return false;
  }
  
  public void zzcf() {
    this.zzanv = false;
    zzbt();
    this.zzanm.zzaug.zzpm();
  }
  
  public void zzcg() {
    this.zzanv = true;
    zzbv();
  }
  
  public void zzch() {
    zzahw.zzcz("Mediated ad does not support onVideoEnd callback");
  }
  
  public void zzci() {
    super.onAdClicked();
  }
  
  public final void zzcj() {
    zzcf();
  }
  
  public final void zzck() {
    zzbu();
  }
  
  public final void zzcl() {
    zzcg();
  }
  
  public final void zzcm() {
    if (this.zzanm.zzaue != null) {
      String str = this.zzanm.zzaue.zzcjg;
      StringBuilder stringBuilder = new StringBuilder(String.valueOf(str).length() + 74);
      stringBuilder.append("Mediation adapter ");
      stringBuilder.append(str);
      stringBuilder.append(" refreshed, but mediation adapters should never refresh.");
      zzahw.zzcz(stringBuilder.toString());
    } 
    zza(this.zzanm.zzaue, true);
    zzbw();
  }
  
  public void zzcn() {
    recordImpression();
  }
  
  public final String zzco() {
    return (this.zzanm.zzaue == null) ? null : zzc(this.zzanm.zzaue);
  }
  
  public final void zzcp() {
    Executor executor = zzaly.zzdjt;
    zzbj zzbj = this.zzanl;
    zzbj.getClass();
    executor.execute(zze.zza(zzbj));
  }
  
  public final void zzcq() {
    Executor executor = zzaly.zzdjt;
    zzbj zzbj = this.zzanl;
    zzbj.getClass();
    executor.execute(zzf.zza(zzbj));
  }
}


/* Location:              /home/egaebel/Programs/sony-headphones-hack/base-dex2jar.jar!/com/google/android/gms/ads/internal/zzd.class
 * Java compiler version: 6 (50.0)
 * JD-Core Version:       1.1.3
 */