package com.sony.songpal.mdr.j2objc.tandem;

public class e {
  private static final String a = "e";
  
  private final com.sony.songpal.tandemfamily.mdr.e b;
  
  private boolean c = false;
  
  public e(com.sony.songpal.tandemfamily.mdr.e parame) {
    this.b = parame;
  }
  
  public void a() {
    // Byte code:
    //   0: aload_0
    //   1: monitorenter
    //   2: aload_0
    //   3: iconst_1
    //   4: putfield c : Z
    //   7: aload_0
    //   8: monitorexit
    //   9: return
    //   10: astore_1
    //   11: aload_0
    //   12: monitorexit
    //   13: aload_1
    //   14: athrow
    // Exception table:
    //   from	to	target	type
    //   2	7	10	finally
  }
}


/* Location:              /home/egaebel/Programs/sony-headphones-hack/base-dex2jar.jar!/com/sony/songpal/mdr/j2objc/tandem/e.class
 * Java compiler version: 6 (50.0)
 * JD-Core Version:       1.1.3
 */