package a.b.a.a.a;

public final class f implements Runnable {
  public f(e parame, String paramString, e.b paramb, int paramInt1, int paramInt2, boolean paramBoolean1, boolean paramBoolean2) {}
  
  public final void run() {
    // Byte code:
    //   0: new java/net/URL
    //   3: dup
    //   4: aload_0
    //   5: getfield b : Ljava/lang/String;
    //   8: invokespecial <init> : (Ljava/lang/String;)V
    //   11: invokevirtual openConnection : ()Ljava/net/URLConnection;
    //   14: astore_1
    //   15: aload_1
    //   16: ifnull -> 82
    //   19: aload_1
    //   20: checkcast java/net/HttpURLConnection
    //   23: astore_2
    //   24: aload_2
    //   25: astore_1
    //   26: aload_2
    //   27: ldc 'GET'
    //   29: invokevirtual setRequestMethod : (Ljava/lang/String;)V
    //   32: aload_2
    //   33: astore_1
    //   34: aload_0
    //   35: getfield c : La/b/a/a/a/e$b;
    //   38: aload_0
    //   39: getfield a : La/b/a/a/a/e;
    //   42: aload_2
    //   43: aload_0
    //   44: getfield d : I
    //   47: aload_0
    //   48: getfield e : I
    //   51: aload_0
    //   52: getfield f : Z
    //   55: aload_0
    //   56: getfield g : Z
    //   59: invokestatic a : (La/b/a/a/a/e;Ljava/net/HttpURLConnection;IIZZ)Ljava/lang/Object;
    //   62: invokeinterface a : (Ljava/lang/Object;)V
    //   67: goto -> 247
    //   70: astore_3
    //   71: goto -> 101
    //   74: astore_3
    //   75: goto -> 154
    //   78: astore_3
    //   79: goto -> 197
    //   82: new kotlin/TypeCastException
    //   85: dup
    //   86: ldc 'null cannot be cast to non-null type java.net.HttpURLConnection'
    //   88: invokespecial <init> : (Ljava/lang/String;)V
    //   91: athrow
    //   92: astore_1
    //   93: aconst_null
    //   94: astore_2
    //   95: goto -> 257
    //   98: astore_3
    //   99: aconst_null
    //   100: astore_2
    //   101: aload_2
    //   102: astore_1
    //   103: getstatic com/sony/snc/ad/common/d.e : Lcom/sony/snc/ad/common/d;
    //   106: astore #4
    //   108: aload_2
    //   109: astore_1
    //   110: aload #4
    //   112: ldc 'http Exception.'
    //   114: aload_3
    //   115: invokevirtual a : (Ljava/lang/String;Ljava/lang/Throwable;)V
    //   118: aload_2
    //   119: astore_1
    //   120: aload_0
    //   121: getfield c : La/b/a/a/a/e$b;
    //   124: new com/sony/snc/ad/param/e
    //   127: dup
    //   128: new com/sony/snc/ad/exception/AdException
    //   131: dup
    //   132: getstatic com/sony/snc/ad/exception/SNCAdError.SNCADERR_HTTP_GET_FAILURE : Lcom/sony/snc/ad/exception/SNCAdError;
    //   135: aload_3
    //   136: invokespecial <init> : (Lcom/sony/snc/ad/exception/SNCAdError;Ljava/lang/Throwable;)V
    //   139: invokespecial <init> : (Lcom/sony/snc/ad/exception/AdException;)V
    //   142: invokeinterface a : (Lcom/sony/snc/ad/param/e;)V
    //   147: aload_2
    //   148: ifnull -> 251
    //   151: goto -> 247
    //   154: aload_2
    //   155: astore_1
    //   156: getstatic com/sony/snc/ad/common/d.e : Lcom/sony/snc/ad/common/d;
    //   159: astore #4
    //   161: aload_2
    //   162: astore_1
    //   163: aload #4
    //   165: ldc 'http AdException.'
    //   167: aload_3
    //   168: invokevirtual a : (Ljava/lang/String;Ljava/lang/Throwable;)V
    //   171: aload_2
    //   172: astore_1
    //   173: aload_0
    //   174: getfield c : La/b/a/a/a/e$b;
    //   177: new com/sony/snc/ad/param/e
    //   180: dup
    //   181: aload_3
    //   182: invokespecial <init> : (Lcom/sony/snc/ad/exception/AdException;)V
    //   185: invokeinterface a : (Lcom/sony/snc/ad/param/e;)V
    //   190: aload_2
    //   191: ifnull -> 251
    //   194: goto -> 247
    //   197: aload_2
    //   198: astore_1
    //   199: getstatic com/sony/snc/ad/common/d.e : Lcom/sony/snc/ad/common/d;
    //   202: astore #4
    //   204: aload_2
    //   205: astore_1
    //   206: aload #4
    //   208: ldc 'http IOException.'
    //   210: aload_3
    //   211: invokevirtual a : (Ljava/lang/String;Ljava/lang/Throwable;)V
    //   214: aload_2
    //   215: astore_1
    //   216: aload_0
    //   217: getfield c : La/b/a/a/a/e$b;
    //   220: new com/sony/snc/ad/param/e
    //   223: dup
    //   224: new com/sony/snc/ad/exception/AdException
    //   227: dup
    //   228: getstatic com/sony/snc/ad/exception/SNCAdError.SNCADERR_HTTP_GET_IO_EXCEPTION : Lcom/sony/snc/ad/exception/SNCAdError;
    //   231: aload_3
    //   232: invokespecial <init> : (Lcom/sony/snc/ad/exception/SNCAdError;Ljava/lang/Throwable;)V
    //   235: invokespecial <init> : (Lcom/sony/snc/ad/exception/AdException;)V
    //   238: invokeinterface a : (Lcom/sony/snc/ad/param/e;)V
    //   243: aload_2
    //   244: ifnull -> 251
    //   247: aload_2
    //   248: invokevirtual disconnect : ()V
    //   251: return
    //   252: astore_3
    //   253: aload_1
    //   254: astore_2
    //   255: aload_3
    //   256: astore_1
    //   257: aload_2
    //   258: ifnull -> 265
    //   261: aload_2
    //   262: invokevirtual disconnect : ()V
    //   265: aload_1
    //   266: athrow
    //   267: astore_3
    //   268: aconst_null
    //   269: astore_2
    //   270: goto -> 154
    //   273: astore_3
    //   274: aconst_null
    //   275: astore_2
    //   276: goto -> 197
    // Exception table:
    //   from	to	target	type
    //   0	15	273	java/io/IOException
    //   0	15	267	com/sony/snc/ad/exception/AdException
    //   0	15	98	java/lang/Exception
    //   0	15	92	finally
    //   19	24	273	java/io/IOException
    //   19	24	267	com/sony/snc/ad/exception/AdException
    //   19	24	98	java/lang/Exception
    //   19	24	92	finally
    //   26	32	78	java/io/IOException
    //   26	32	74	com/sony/snc/ad/exception/AdException
    //   26	32	70	java/lang/Exception
    //   26	32	252	finally
    //   34	67	78	java/io/IOException
    //   34	67	74	com/sony/snc/ad/exception/AdException
    //   34	67	70	java/lang/Exception
    //   34	67	252	finally
    //   82	92	273	java/io/IOException
    //   82	92	267	com/sony/snc/ad/exception/AdException
    //   82	92	98	java/lang/Exception
    //   82	92	92	finally
    //   103	108	252	finally
    //   110	118	252	finally
    //   120	147	252	finally
    //   156	161	252	finally
    //   163	171	252	finally
    //   173	190	252	finally
    //   199	204	252	finally
    //   206	214	252	finally
    //   216	243	252	finally
  }
}


/* Location:              /home/egaebel/Programs/sony-headphones-hack/base-dex2jar.jar!/a/b/a/a/a/f.class
 * Java compiler version: 6 (50.0)
 * JD-Core Version:       1.1.3
 */